Workbook

Sheet rows
A1: row_id | B1: Filas
A2: pan_v02_q01_r0001 | B2: PANof001
A3: pan_v02_q01_r0002 | B3: PANof002
A4: pan_v02_q01_r0003 | B4: PANof003
A5: pan_v02_q01_r0004 | B5: PANof004
A6: pan_v02_q01_r0005 | B6: PANof005
A7: pan_v02_q01_r0006 | B7: PANof006
A8: pan_v02_q01_r0007 | B8: PANof007
A9: pan_v02_q01_r0008 | B9: PANof008
A10: pan_v02_q01_r0009 | B10: PANof009
A11: pan_v02_q01_r0010 | B11: PANof010
A12: pan_v02_q01_r0011 | B12: PANof011
... A189: pan_v02_q01_r0188 | B189: PANof188
A190: pan_v02_q01_r0189
A191: pan_v02_q01_r0190 | B191: PANof189
A192: pan_v02_q01_r0191
A193: pan_v02_q01_r0192 | B193: PANof190
A194: pan_v02_q01_r0193 | B194: PANof191
A195: pan_v02_q01_r0194 | B195: PANof192
A196: pan_v02_q01_r0195 | B196: PANof193
A197: pan_v02_q01_r0196
A198: pan_v02_q01_r0197
A199: pan_v02_q02_r0001 | B199: PANuf001
A200: pan_v02_q02_r0002 | B200: PANuf002
A201: pan_v02_q02_r0003 | B201: PANuf003
A202: pan_v02_q02_r0004 | B202: PANuf004
A203: pan_v02_q02_r0005 | B203: PANuf005
A204: pan_v02_q02_r0006 | B204: PANuf006
A205: pan_v02_q02_r0007 | B205: PANuf007
A206: pan_v02_q02_r0008 | B206: PANuf008
A207: pan_v02_q02_r0009 | B207: PANuf009
A208: pan_v02_q02_r0010 | B208: PANuf010
A209: pan_v02_q02_r0011 | B209: PANuf011
A210: pan_v02_q02_r0012 | B210: PANuf012
... A386: pan_v02_q02_r0188 | B386: PANuf188
A387: pan_v02_q02_r0189
A388: pan_v02_q02_r0190 | B388: PANuf189
A389: pan_v02_q02_r0191
A390: pan_v02_q02_r0192 | B390: PANuf190
A391: pan_v02_q02_r0193 | B391: PANuf191
A392: pan_v02_q02_r0194 | B392: PANuf192
A393: pan_v02_q02_r0195 | B393: PANuf193
A394: pan_v02_q02_r0196
A395: pan_v02_q02_r0197
A396: pan_v02_q03_r0001 | B396: PANvf001

Sheet columns
A1: col_id | B1: Columnas
A2: pan_v02_q01_c0001 | B2: PANoc001
A3: pan_v02_q01_c0002 | B3: PANoc002
A4: pan_v02_q01_c0003 | B4: PANoc003
A5: pan_v02_q01_c0004 | B5: PANoc004
A6: pan_v02_q01_c0005 | B6: PANoc005
A7: pan_v02_q01_c0006 | B7: PANoc006
A8: pan_v02_q01_c0007 | B8: PANoc007
A9: pan_v02_q01_c0008 | B9: PANoc008
A10: pan_v02_q01_c0009 | B10: PANoc009
A11: pan_v02_q01_c0010 | B11: PANoc010
A12: pan_v02_q01_c0011 | B12: PANoc011
... A92: pan_v02_q01_c0091 | B92: PANoc091
A93: pan_v02_q01_c0092
A94: pan_v02_q01_c0093
A95: pan_v02_q01_c0094 | B95: PANoc092
A96: pan_v02_q01_c0095 | B96: PANoc093
A97: pan_v02_q01_c0096 | B97: PANoc094
A98: pan_v02_q01_c0097 | B98: PANoc095
A99: pan_v02_q01_c0098 | B99: PANoc096
A100: pan_v02_q01_c0099 | B100: PANoc097
A101: pan_v02_q01_c0100 | B101: PANoc098
A102: pan_v02_q01_c0101 | B102: PANoc099
A103: pan_v02_q01_c0102 | B103: PANoc100
A104: pan_v02_q01_c0103 | B104: PANoc101
A105: pan_v02_q01_c0104 | B105: PANoc102
A106: pan_v02_q01_c0105 | B106: PANoc103
A107: pan_v02_q01_c0106 | B107: PANoc104
A108: pan_v02_q01_c0107
A109: pan_v02_q01_c0108
A110: pan_v02_q02_c0001 | B110: PANuc001
A111: pan_v02_q02_c0002 | B111: PANuc002
A112: pan_v02_q02_c0003 | B112: PANuc003
A113: pan_v02_q02_c0004 | B113: PANuc004
A114: pan_v02_q02_c0005 | B114: PANuc005
A115: pan_v02_q02_c0006 | B115: PANuc006
A116: pan_v02_q02_c0007 | B116: PANuc007
A117: pan_v02_q02_c0008 | B117: PANuc008
A118: pan_v02_q02_c0009 | B118: PANuc009
A119: pan_v02_q02_c0010 | B119: PANuc010
A120: pan_v02_q02_c0011 | B120: PANuc011
A121: pan_v02_q02_c0012 | B121: PANuc012
... A200: pan_v02_q02_c0091 | B200: PANuc091
A201: pan_v02_q02_c0092
A202: pan_v02_q02_c0093 | B202: PANuc092
A203: pan_v02_q02_c0094 | B203: PANuc093
A204: pan_v02_q02_c0095 | B204: PANuc094
A205: pan_v02_q02_c0096 | B205: PANuc095
A206: pan_v02_q02_c0097 | B206: PANuc096
A207: pan_v02_q02_c0098 | B207: PANuc097
A208: pan_v02_q02_c0099 | B208: PANuc098
A209: pan_v02_q02_c0100 | B209: PANuc099
A210: pan_v02_q02_c0101 | B210: PANuc100
A211: pan_v02_q02_c0102 | B211: PANuc101
A212: pan_v02_q02_c0103 | B212: PANuc102
A213: pan_v02_q02_c0104 | B213: PANuc103
... A216: pan_v02_q02_c0107 | B216: PANuc106
A217: pan_v02_q02_c0108
A218: pan_v02_q02_c0109
A219: pan_v02_q03_c0001 | B219: PANvc001
A220: pan_v02_q03_c0002 | B220: PANvc002
A221: pan_v02_q03_c0003 | B221: PANvc003
A222: pan_v02_q03_c0004 | B222: PANvc004
A223: pan_v02_q03_c0005 | B223: PANvc005
A224: pan_v02_q03_c0006 | B224: PANvc006
A225: pan_v02_q03_c0007 | B225: PANvc007
A226: pan_v02_q03_c0008 | B226: PANvc008
A227: pan_v02_q03_c0009 | B227: PANvc009
A228: pan_v02_q03_c0010 | B228: PANvc010
A229: pan_v02_q03_c0011 | B229: PANvc011
A230: pan_v02_q03_c0012 | B230: PANvc012
... A307: pan_v02_q03_c0089 | B307: PANvc089
A308: pan_v02_q03_c0090
A309: pan_v02_q03_c0091

Sheet quadrants
A1: quadrant_code | B1: quadrant | C1: target_table | D1: cell_range | E1: excl_rows | F1: excl_cols
A2: q01 | B2: OFERTA DE PRODUCTOS A PRECIOS DE COMPRADOR | C2: Supply | D2: C12:DF208 | E2: 189, 191, 196, 197 | F2: 75,79,90,91,92,93,96,98,103,107,108
A3: q02 | B3: UTILIZACIÓN DE PRODUCTOS A PRECIOS DE COMPRADOR | C3: Use | D3: C12:DG208 | E3: 189, 191, 196, 197 | F3: 75,79,90,91,92,95,99,102,103,108,109
A4: q03 | B4: VALOR AGREGADO BRUTO TOTAL/PIB | C4: Value Added | D4: D210:CQ210 | F4: 75,79,90,91,92

Sheet columnas
A1: Columnas | B1: Código Transacciones | C1: Área transaccional columnas No. | D1: Área transaccional | E1: Transacciones | F1: Correlativo Transacciones Agregadas | G1: Código Transacciones Agregadas | H1: Transacciones Agregadas | I1: Código Clasificación Actividades | J1: Descripción Actividades | K1: CIIU Secciones | L1: CIIU Secciones descripción | M1: CIIU Corto | N1: CIIU English | O1: Correlativo Bioeconomía Actividades | P1: Bioeconomía Actividades
A2: PANoc001 | B2: P11 | C2: =+VLOOKUP(B2,transacciones!$A$1:$I$39,2,FALSE()) -> ATC01 | D2: =+VLOOKUP(B2,transacciones!$A$1:$I$39,3,FALSE()) -> Producción / Consumo intermedio | E2: =+VLOOKUP($B2,transacciones!$A$1:$I$39,4,FALSE()) -> Producción de mercado | F2: =+VLOOKUP(B2,transacciones!$A$2:$I$39,5,FALSE()) -> 1 | G2: =+VLOOKUP(B2,transacciones!$A$2:$I$39,6,FALSE()) -> P1 | H2: =+VLOOKUP(B2,transacciones!$A$1:$I$39,7,FALSE()) -> Producción | I2: 01.1 | J2: Cultivo de cereales, legumbres y semillas oleaginosas | K2: A | L2: =+VLOOKUP(K2,'Correl CIIU'!$A$1:$F$26,2,FALSE()) -> Agricultura, ganadería, silvicultura y pesca | M2: =+VLOOKUP(K2,'Correl CIIU'!$A$1:$F$26,3,FALSE()) -> Agricultura | N2: =+VLOOKUP(K2,'Correl CIIU'!$A$1:$F$26,4,FALSE()) -> Agriculture, forestry and fishing | O2: 1 | P2: =+VLOOKUP(O2,bio!$A$2:$B$4,2,FALSE()) -> Bioeconomía
A3: PANoc002 | B3: P11 | C3: =+VLOOKUP(B3,transacciones!$A$1:$I$39,2,FALSE()) -> ATC01 | D3: =+VLOOKUP(B3,transacciones!$A$1:$I$39,3,FALSE()) -> Producción / Consumo intermedio | E3: =+VLOOKUP($B3,transacciones!$A$1:$I$39,4,FALSE()) -> Producción de mercado | F3: =+VLOOKUP(B3,transacciones!$A$2:$I$39,5,FALSE()) -> 1 | G3: =+VLOOKUP(B3,transacciones!$A$2:$I$39,6,FALSE()) -> P1 | H3: =+VLOOKUP(B3,transacciones!$A$1:$I$39,7,FALSE()) -> Producción | I3: 02.1 | J3: Cultivo de maiz | K3: A | L3: =+VLOOKUP(K3,'Correl CIIU'!$A$1:$F$26,2,FALSE()) -> Agricultura, ganadería, silvicultura y pesca | M3: =+VLOOKUP(K3,'Correl CIIU'!$A$1:$F$26,3,FALSE()) -> Agricultura | N3: =+VLOOKUP(K3,'Correl CIIU'!$A$1:$F$26,4,FALSE()) -> Agriculture, forestry and fishing | O3: 1 | P3: =+VLOOKUP(O3,bio!$A$2:$B$4,2,FALSE()) -> Bioeconomía
A4: PANoc003 | B4: P11 | C4: =+VLOOKUP(B4,transacciones!$A$1:$I$39,2,FALSE()) -> ATC01 | D4: =+VLOOKUP(B4,transacciones!$A$1:$I$39,3,FALSE()) -> Producción / Consumo intermedio | E4: =+VLOOKUP($B4,transacciones!$A$1:$I$39,4,FALSE()) -> Producción de mercado | F4: =+VLOOKUP(B4,transacciones!$A$2:$I$39,5,FALSE()) -> 1 | G4: =+VLOOKUP(B4,transacciones!$A$2:$I$39,6,FALSE()) -> P1 | H4: =+VLOOKUP(B4,transacciones!$A$1:$I$39,7,FALSE()) -> Producción | I4: 03.1 | J4: Cultivo de arroz | K4: A | L4: =+VLOOKUP(K4,'Correl CIIU'!$A$1:$F$26,2,FALSE()) -> Agricultura, ganadería, silvicultura y pesca | M4: =+VLOOKUP(K4,'Correl CIIU'!$A$1:$F$26,3,FALSE()) -> Agricultura | N4: =+VLOOKUP(K4,'Correl CIIU'!$A$1:$F$26,4,FALSE()) -> Agriculture, forestry and fishing | O4: 1 | P4: =+VLOOKUP(O4,bio!$A$2:$B$4,2,FALSE()) -> Bioeconomía
A5: PANoc004 | B5: P11 | C5: =+VLOOKUP(B5,transacciones!$A$1:$I$39,2,FALSE()) -> ATC01 | D5: =+VLOOKUP(B5,transacciones!$A$1:$I$39,3,FALSE()) -> Producción / Consumo intermedio | E5: =+VLOOKUP($B5,transacciones!$A$1:$I$39,4,FALSE()) -> Producción de mercado | F5: =+VLOOKUP(B5,transacciones!$A$2:$I$39,5,FALSE()) -> 1 | G5: =+VLOOKUP(B5,transacciones!$A$2:$I$39,6,FALSE()) -> P1 | H5: =+VLOOKUP(B5,transacciones!$A$1:$I$39,7,FALSE()) -> Producción | I5: 04.1 | J5: Cultivo de vegetales, raíces y tubérculos | K5: A | L5: =+VLOOKUP(K5,'Correl CIIU'!$A$1:$F$26,2,FALSE()) -> Agricultura, ganadería, silvicultura y pesca | M5: =+VLOOKUP(K5,'Correl CIIU'!$A$1:$F$26,3,FALSE()) -> Agricultura | N5: =+VLOOKUP(K5,'Correl CIIU'!$A$1:$F$26,4,FALSE()) -> Agriculture, forestry and fishing | O5: 1 | P5: =+VLOOKUP(O5,bio!$A$2:$B$4,2,FALSE()) -> Bioeconomía
A6: PANoc005 | B6: P11 | C6: =+VLOOKUP(B6,transacciones!$A$1:$I$39,2,FALSE()) -> ATC01 | D6: =+VLOOKUP($B6,transacciones!$A$1:$I$39,4,FALSE()) -> Producción de mercado | E6: =+VLOOKUP($B6,transacciones!$A$1:$I$39,4,FALSE()) -> Producción de mercado | F6: =+VLOOKUP(B6,transacciones!$A$2:$I$39,5,FALSE()) -> 1 | G6: =+VLOOKUP(B6,transacciones!$A$2:$I$39,6,FALSE()) -> P1 | H6: =+VLOOKUP(B6,transacciones!$A$1:$I$39,7,FALSE()) -> Producción | I6: 05.1 | J6: Cultivo de Banano | K6: A | L6: =+VLOOKUP(K6,'Correl CIIU'!$A$1:$F$26,2,FALSE()) -> Agricultura, ganadería, silvicultura y pesca | M6: =+VLOOKUP(K6,'Correl CIIU'!$A$1:$F$26,3,FALSE()) -> Agricultura | N6: =+VLOOKUP(K6,'Correl CIIU'!$A$1:$F$26,4,FALSE()) -> Agriculture, forestry and fishing | O6: 1 | P6: =+VLOOKUP(O6,bio!$A$2:$B$4,2,FALSE()) -> Bioeconomía
A7: PANoc006 | B7: P11 | C7: =+VLOOKUP(B7,transacciones!$A$1:$I$39,2,FALSE()) -> ATC01 | D7: =+VLOOKUP($B7,transacciones!$A$1:$I$39,4,FALSE()) -> Producción de mercado | E7: =+VLOOKUP($B7,transacciones!$A$1:$I$39,4,FALSE()) -> Producción de mercado | F7: =+VLOOKUP(B7,transacciones!$A$2:$I$39,5,FALSE()) -> 1 | G7: =+VLOOKUP(B7,transacciones!$A$2:$I$39,6,FALSE()) -> P1 | H7: =+VLOOKUP(B7,transacciones!$A$1:$I$39,7,FALSE()) -> Producción | I7: 06.1 | J7: Cultivo de otras frutas y nueces | K7: A | L7: =+VLOOKUP(K7,'Correl CIIU'!$A$1:$F$26,2,FALSE()) -> Agricultura, ganadería, silvicultura y pesca | M7: =+VLOOKUP(K7,'Correl CIIU'!$A$1:$F$26,3,FALSE()) -> Agricultura | N7: =+VLOOKUP(K7,'Correl CIIU'!$A$1:$F$26,4,FALSE()) -> Agriculture, forestry and fishing | O7: 1 | P7: =+VLOOKUP(O7,bio!$A$2:$B$4,2,FALSE()) -> Bioeconomía
A8: PANoc007 | B8: P11 | C8: =+VLOOKUP(B8,transacciones!$A$1:$I$39,2,FALSE()) -> ATC01 | D8: =+VLOOKUP($B8,transacciones!$A$1:$I$39,4,FALSE()) -> Producción de mercado | E8: =+VLOOKUP($B8,transacciones!$A$1:$I$39,4,FALSE()) -> Producción de mercado | F8: =+VLOOKUP(B8,transacciones!$A$2:$I$39,5,FALSE()) -> 1 | G8: =+VLOOKUP(B8,transacciones!$A$2:$I$39,6,FALSE()) -> P1 | H8: =+VLOOKUP(B8,transacciones!$A$1:$I$39,7,FALSE()) -> Producción | I8: 07.1 | J8: Otras actividades agrícolas | K8: A | L8: =+VLOOKUP(K8,'Correl CIIU'!$A$1:$F$26,2,FALSE()) -> Agricultura, ganadería, silvicultura y pesca | M8: =+VLOOKUP(K8,'Correl CIIU'!$A$1:$F$26,3,FALSE()) -> Agricultura | N8: =+VLOOKUP(K8,'Correl CIIU'!$A$1:$F$26,4,FALSE()) -> Agriculture, forestry and fishing | O8: 1 | P8: =+VLOOKUP(O8,bio!$A$2:$B$4,2,FALSE()) -> Bioeconomía
A9: PANoc008 | B9: P11 | C9: =+VLOOKUP(B9,transacciones!$A$1:$I$39,2,FALSE()) -> ATC01 | D9: =+VLOOKUP($B9,transacciones!$A$1:$I$39,4,FALSE()) -> Producción de mercado | E9: =+VLOOKUP($B9,transacciones!$A$1:$I$39,4,FALSE()) -> Producción de mercado | F9: =+VLOOKUP(B9,transacciones!$A$2:$I$39,5,FALSE()) -> 1 | G9: =+VLOOKUP(B9,transacciones!$A$2:$I$39,6,FALSE()) -> P1 | H9: =+VLOOKUP(B9,transacciones!$A$1:$I$39,7,FALSE()) -> Producción | I9: 08.1 | J9: Cría de ganado bovino (excluye búfalo) | K9: A | L9: =+VLOOKUP(K9,'Correl CIIU'!$A$1:$F$26,2,FALSE()) -> Agricultura, ganadería, silvicultura y pesca | M9: =+VLOOKUP(K9,'Correl CIIU'!$A$1:$F$26,3,FALSE()) -> Agricultura | N9: =+VLOOKUP(K9,'Correl CIIU'!$A$1:$F$26,4,FALSE()) -> Agriculture, forestry and fishing | O9: 1 | P9: =+VLOOKUP(O9,bio!$A$2:$B$4,2,FALSE()) -> Bioeconomía
A10: PANoc009 | B10: P11 | C10: =+VLOOKUP(B10,transacciones!$A$1:$I$39,2,FALSE()) -> ATC01 | D10: =+VLOOKUP($B10,transacciones!$A$1:$I$39,4,FALSE()) -> Producción de mercado | E10: =+VLOOKUP($B10,transacciones!$A$1:$I$39,4,FALSE()) -> Producción de mercado | F10: =+VLOOKUP(B10,transacciones!$A$2:$I$39,5,FALSE()) -> 1 | G10: =+VLOOKUP(B10,transacciones!$A$2:$I$39,6,FALSE()) -> P1 | H10: =+VLOOKUP(B10,transacciones!$A$1:$I$39,7,FALSE()) -> Producción | I10: 08.2 | J10: Cría de ganado porcino | K10: A | L10: =+VLOOKUP(K10,'Correl CIIU'!$A$1:$F$26,2,FALSE()) -> Agricultura, ganadería, silvicultura y pesca | M10: =+VLOOKUP(K10,'Correl CIIU'!$A$1:$F$26,3,FALSE()) -> Agricultura | N10: =+VLOOKUP(K10,'Correl CIIU'!$A$1:$F$26,4,FALSE()) -> Agriculture, forestry and fishing | O10: 1 | P10: =+VLOOKUP(O10,bio!$A$2:$B$4,2,FALSE()) -> Bioeconomía
A11: PANoc010 | B11: P11 | C11: =+VLOOKUP(B11,transacciones!$A$1:$I$39,2,FALSE()) -> ATC01 | D11: =+VLOOKUP($B11,transacciones!$A$1:$I$39,4,FALSE()) -> Producción de mercado | E11: =+VLOOKUP($B11,transacciones!$A$1:$I$39,4,FALSE()) -> Producción de mercado | F11: =+VLOOKUP(B11,transacciones!$A$2:$I$39,5,FALSE()) -> 1 | G11: =+VLOOKUP(B11,transacciones!$A$2:$I$39,6,FALSE()) -> P1 | H11: =+VLOOKUP(B11,transacciones!$A$1:$I$39,7,FALSE()) -> Producción | I11: 08.3 | J11: Cría de aves de corral | K11: A | L11: =+VLOOKUP(K11,'Correl CIIU'!$A$1:$F$26,2,FALSE()) -> Agricultura, ganadería, silvicultura y pesca | M11: =+VLOOKUP(K11,'Correl CIIU'!$A$1:$F$26,3,FALSE()) -> Agricultura | N11: =+VLOOKUP(K11,'Correl CIIU'!$A$1:$F$26,4,FALSE()) -> Agriculture, forestry and fishing | O11: 1 | P11: =+VLOOKUP(O11,bio!$A$2:$B$4,2,FALSE()) -> Bioeconomía
A12: PANoc011 | B12: P11 | C12: =+VLOOKUP(B12,transacciones!$A$1:$I$39,2,FALSE()) -> ATC01 | D12: =+VLOOKUP($B12,transacciones!$A$1:$I$39,4,FALSE()) -> Producción de mercado | E12: =+VLOOKUP($B12,transacciones!$A$1:$I$39,4,FALSE()) -> Producción de mercado | F12: =+VLOOKUP(B12,transacciones!$A$2:$I$39,5,FALSE()) -> 1 | G12: =+VLOOKUP(B12,transacciones!$A$2:$I$39,6,FALSE()) -> P1 | H12: =+VLOOKUP(B12,transacciones!$A$1:$I$39,7,FALSE()) -> Producción | I12: 08.4 | J12: Cría de otros animales y obtención de subproductos | K12: A | L12: =+VLOOKUP(K12,'Correl CIIU'!$A$1:$F$26,2,FALSE()) -> Agricultura, ganadería, silvicultura y pesca | M12: =+VLOOKUP(K12,'Correl CIIU'!$A$1:$F$26,3,FALSE()) -> Agricultura | N12: =+VLOOKUP(K12,'Correl CIIU'!$A$1:$F$26,4,FALSE()) -> Agriculture, forestry and fishing | O12: 1 | P12: =+VLOOKUP(O12,bio!$A$2:$B$4,2,FALSE()) -> Bioeconomía
A13: PANoc012 | B13: P11 | C13: =+VLOOKUP(B13,transacciones!$A$1:$I$39,2,FALSE()) -> ATC01 | D13: =+VLOOKUP($B13,transacciones!$A$1:$I$39,4,FALSE()) -> Producción de mercado | E13: =+VLOOKUP($B13,transacciones!$A$1:$I$39,4,FALSE()) -> Producción de mercado | F13: =+VLOOKUP(B13,transacciones!$A$2:$I$39,5,FALSE()) -> 1 | G13: =+VLOOKUP(B13,transacciones!$A$2:$I$39,6,FALSE()) -> P1 | H13: =+VLOOKUP(B13,transacciones!$A$1:$I$39,7,FALSE()) -> Producción | I13: 09.1 | J13: Actividades de apoyo agropecuario | K13: A | L13: =+VLOOKUP(K13,'Correl CIIU'!$A$1:$F$26,2,FALSE()) -> Agricultura, ganadería, silvicultura y pesca | M13: =+VLOOKUP(K13,'Correl CIIU'!$A$1:$F$26,3,FALSE()) -> Agricultura | N13: =+VLOOKUP(K13,'Correl CIIU'!$A$1:$F$26,4,FALSE()) -> Agriculture, forestry and fishing | O13: 1 | P13: =+VLOOKUP(O13,bio!$A$2:$B$4,2,FALSE()) -> Bioeconomía
A14: PANoc013 | B14: P11 | C14: =+VLOOKUP(B14,transacciones!$A$1:$I$39,2,FALSE()) -> ATC01 | D14: =+VLOOKUP($B14,transacciones!$A$1:$I$39,4,FALSE()) -> Producción de mercado | E14: =+VLOOKUP($B14,transacciones!$A$1:$I$39,4,FALSE()) -> Producción de mercado | F14: =+VLOOKUP(B14,transacciones!$A$2:$I$39,5,FALSE()) -> 1 | G14: =+VLOOKUP(B14,transacciones!$A$2:$I$39,6,FALSE()) -> P1 | H14: =+VLOOKUP(B14,transacciones!$A$1:$I$39,7,FALSE()) -> Producción | I14: 10.1 | J14: Silvicultura, extracción de madera y actividades conexas | K14: A | L14: =+VLOOKUP(K14,'Correl CIIU'!$A$1:$F$26,2,FALSE()) -> Agricultura, ganadería, silvicultura y pesca | M14: =+VLOOKUP(K14,'Correl CIIU'!$A$1:$F$26,3,FALSE()) -> Agricultura | N14: =+VLOOKUP(K14,'Correl CIIU'!$A$1:$F$26,4,FALSE()) -> Agriculture, forestry and fishing | O14: 1 | P14: =+VLOOKUP(O14,bio!$A$2:$B$4,2,FALSE()) -> Bioeconomía
A15: PANoc014 | B15: P11 | C15: =+VLOOKUP(B15,transacciones!$A$1:$I$39,2,FALSE()) -> ATC01 | D15: =+VLOOKUP(B15,transacciones!$A$1:$I$39,3,FALSE()) -> Producción / Consumo intermedio | E15: =+VLOOKUP($B15,transacciones!$A$1:$I$39,4,FALSE()) -> Producción de mercado | F15: =+VLOOKUP(B15,transacciones!$A$2:$I$39,5,FALSE()) -> 1 | G15: =+VLOOKUP(B15,transacciones!$A$2:$I$39,6,FALSE()) -> P1 | H15: =+VLOOKUP(B15,transacciones!$A$1:$I$39,7,FALSE()) -> Producción | I15: 11.1 | J15: Pesca | K15: A | L15: =+VLOOKUP(K15,'Correl CIIU'!$A$1:$F$26,2,FALSE()) -> Agricultura, ganadería, silvicultura y pesca | M15: =+VLOOKUP(K15,'Correl CIIU'!$A$1:$F$26,3,FALSE()) -> Agricultura | N15: =+VLOOKUP(K15,'Correl CIIU'!$A$1:$F$26,4,FALSE()) -> Agriculture, forestry and fishing | O15: 1 | P15: =+VLOOKUP(O15,bio!$A$2:$B$4,2,FALSE()) -> Bioeconomía
A16: PANoc015 | B16: P11 | C16: =+VLOOKUP(B16,transacciones!$A$1:$I$39,2,FALSE()) -> ATC01 | D16: =+VLOOKUP(B16,transacciones!$A$1:$I$39,3,FALSE()) -> Producción / Consumo intermedio | E16: =+VLOOKUP($B16,transacciones!$A$1:$I$39,4,FALSE()) -> Producción de mercado | F16: =+VLOOKUP(B16,transacciones!$A$2:$I$39,5,FALSE()) -> 1 | G16: =+VLOOKUP(B16,transacciones!$A$2:$I$39,6,FALSE()) -> P1 | H16: =+VLOOKUP(B16,transacciones!$A$1:$I$39,7,FALSE()) -> Producción | I16: 12.1 | J16: Acuicultura | K16: A | L16: =+VLOOKUP(K16,'Correl CIIU'!$A$1:$F$26,2,FALSE()) -> Agricultura, ganadería, silvicultura y pesca | M16: =+VLOOKUP(K16,'Correl CIIU'!$A$1:$F$26,3,FALSE()) -> Agricultura | N16: =+VLOOKUP(K16,'Correl CIIU'!$A$1:$F$26,4,FALSE()) -> Agriculture, forestry and fishing | O16: 1 | P16: =+VLOOKUP(O16,bio!$A$2:$B$4,2,FALSE()) -> Bioeconomía
A17: PANoc016 | B17: P11 | C17: =+VLOOKUP(B17,transacciones!$A$1:$I$39,2,FALSE()) -> ATC01 | D17: =+VLOOKUP(B17,transacciones!$A$1:$I$39,3,FALSE()) -> Producción / Consumo intermedio | E17: =+VLOOKUP($B17,transacciones!$A$1:$I$39,4,FALSE()) -> Producción de mercado | F17: =+VLOOKUP(B17,transacciones!$A$2:$I$39,5,FALSE()) -> 1 | G17: =+VLOOKUP(B17,transacciones!$A$2:$I$39,6,FALSE()) -> P1 | H17: =+VLOOKUP(B17,transacciones!$A$1:$I$39,7,FALSE()) -> Producción | I17: 13.1 | J17: Explotación minas y canteras | K17: B | L17: =+VLOOKUP(K17,'Correl CIIU'!$A$1:$F$26,2,FALSE()) -> Explotación de minas y canteras | M17: =+VLOOKUP(K17,'Correl CIIU'!$A$1:$F$26,3,FALSE()) -> Minería | N17: =+VLOOKUP(K17,'Correl CIIU'!$A$1:$F$26,4,FALSE()) -> Mining and quarrying | O17: 3 | P17: =+VLOOKUP(O17,bio!$A$2:$B$4,2,FALSE()) -> No bioeconomía
A18: PANoc017 | B18: P11 | C18: =+VLOOKUP(B18,transacciones!$A$1:$I$39,2,FALSE()) -> ATC01 | D18: =+VLOOKUP($B18,transacciones!$A$1:$I$39,4,FALSE()) -> Producción de mercado | E18: =+VLOOKUP($B18,transacciones!$A$1:$I$39,4,FALSE()) -> Producción de mercado | F18: =+VLOOKUP(B18,transacciones!$A$2:$I$39,5,FALSE()) -> 1 | G18: =+VLOOKUP(B18,transacciones!$A$2:$I$39,6,FALSE()) -> P1 | H18: =+VLOOKUP(B18,transacciones!$A$1:$I$39,7,FALSE()) -> Producción | I18: 14.1 | J18: Procesamiento y conservación de carne | K18: C | L18: =+VLOOKUP(K18,'Correl CIIU'!$A$1:$F$26,2,FALSE()) -> Industrias manufactureras | M18: =+VLOOKUP(K18,'Correl CIIU'!$A$1:$F$26,3,FALSE()) -> Manufacturas | N18: =+VLOOKUP(K18,'Correl CIIU'!$A$1:$F$26,4,FALSE()) -> Manufacturing | O18: 1 | P18: =+VLOOKUP(O18,bio!$A$2:$B$4,2,FALSE()) -> Bioeconomía
A19: PANoc018 | B19: P11 | C19: =+VLOOKUP(B19,transacciones!$A$1:$I$39,2,FALSE()) -> ATC01 | D19: =+VLOOKUP($B19,transacciones!$A$1:$I$39,4,FALSE()) -> Producción de mercado | E19: =+VLOOKUP($B19,transacciones!$A$1:$I$39,4,FALSE()) -> Producción de mercado | F19: =+VLOOKUP(B19,transacciones!$A$2:$I$39,5,FALSE()) -> 1 | G19: =+VLOOKUP(B19,transacciones!$A$2:$I$39,6,FALSE()) -> P1 | H19: =+VLOOKUP(B19,transacciones!$A$1:$I$39,7,FALSE()) -> Producción | I19: 15.1 | J19: Procesamiento y conservación de pescado, crustáceos y moluscos | K19: C | L19: =+VLOOKUP(K19,'Correl CIIU'!$A$1:$F$26,2,FALSE()) -> Industrias manufactureras | M19: =+VLOOKUP(K19,'Correl CIIU'!$A$1:$F$26,3,FALSE()) -> Manufacturas | N19: =+VLOOKUP(K19,'Correl CIIU'!$A$1:$F$26,4,FALSE()) -> Manufacturing | O19: 1 | P19: =+VLOOKUP(O19,bio!$A$2:$B$4,2,FALSE()) -> Bioeconomía
A20: PANoc019 | B20: P11 | C20: =+VLOOKUP(B20,transacciones!$A$1:$I$39,2,FALSE()) -> ATC01 | D20: =+VLOOKUP($B20,transacciones!$A$1:$I$39,4,FALSE()) -> Producción de mercado | E20: =+VLOOKUP($B20,transacciones!$A$1:$I$39,4,FALSE()) -> Producción de mercado | F20: =+VLOOKUP(B20,transacciones!$A$2:$I$39,5,FALSE()) -> 1 | G20: =+VLOOKUP(B20,transacciones!$A$2:$I$39,6,FALSE()) -> P1 | H20: =+VLOOKUP(B20,transacciones!$A$1:$I$39,7,FALSE()) -> Producción | I20: 16.1 | J20: Procesamiento y conservación de frutas y vegetales | K20: C | L20: =+VLOOKUP(K20,'Correl CIIU'!$A$1:$F$26,2,FALSE()) -> Industrias manufactureras | M20: =+VLOOKUP(K20,'Correl CIIU'!$A$1:$F$26,3,FALSE()) -> Manufacturas | N20: =+VLOOKUP(K20,'Correl CIIU'!$A$1:$F$26,4,FALSE()) -> Manufacturing | O20: 1 | P20: =+VLOOKUP(O20,bio!$A$2:$B$4,2,FALSE()) -> Bioeconomía
A21: PANoc020 | B21: P11 | C21: =+VLOOKUP(B21,transacciones!$A$1:$I$39,2,FALSE()) -> ATC01 | D21: =+VLOOKUP($B21,transacciones!$A$1:$I$39,4,FALSE()) -> Producción de mercado | E21: =+VLOOKUP($B21,transacciones!$A$1:$I$39,4,FALSE()) -> Producción de mercado | F21: =+VLOOKUP(B21,transacciones!$A$2:$I$39,5,FALSE()) -> 1 | G21: =+VLOOKUP(B21,transacciones!$A$2:$I$39,6,FALSE()) -> P1 | H21: =+VLOOKUP(B21,transacciones!$A$1:$I$39,7,FALSE()) -> Producción | I21: 17.1 | J21: Elaboración de aceites y grasas de origen vegetal y animal | K21: C | L21: =+VLOOKUP(K21,'Correl CIIU'!$A$1:$F$26,2,FALSE()) -> Industrias manufactureras | M21: =+VLOOKUP(K21,'Correl CIIU'!$A$1:$F$26,3,FALSE()) -> Manufacturas | N21: =+VLOOKUP(K21,'Correl CIIU'!$A$1:$F$26,4,FALSE()) -> Manufacturing | O21: 1 | P21: =+VLOOKUP(O21,bio!$A$2:$B$4,2,FALSE()) -> Bioeconomía
A22: PANoc021 | B22: P11 | C22: =+VLOOKUP(B22,transacciones!$A$1:$I$39,2,FALSE()) -> ATC01 | D22: =+VLOOKUP($B22,transacciones!$A$1:$I$39,4,FALSE()) -> Producción de mercado | E22: =+VLOOKUP($B22,transacciones!$A$1:$I$39,4,FALSE()) -> Producción de mercado | F22: =+VLOOKUP(B22,transacciones!$A$2:$I$39,5,FALSE()) -> 1 | G22: =+VLOOKUP(B22,transacciones!$A$2:$I$39,6,FALSE()) -> P1 | H22: =+VLOOKUP(B22,transacciones!$A$1:$I$39,7,FALSE()) -> Producción | I22: 18.1 | J22: Elaboración de productos lácteos | K22: C | L22: =+VLOOKUP(K22,'Correl CIIU'!$A$1:$F$26,2,FALSE()) -> Industrias manufactureras | M22: =+VLOOKUP(K22,'Correl CIIU'!$A$1:$F$26,3,FALSE()) -> Manufacturas | N22: =+VLOOKUP(K22,'Correl CIIU'!$A$1:$F$26,4,FALSE()) -> Manufacturing | O22: 1 | P22: =+VLOOKUP(O22,bio!$A$2:$B$4,2,FALSE()) -> Bioeconomía
A23: PANoc022 | B23: P11 | C23: =+VLOOKUP(B23,transacciones!$A$1:$I$39,2,FALSE()) -> ATC01 | D23: =+VLOOKUP($B23,transacciones!$A$1:$I$39,4,FALSE()) -> Producción de mercado | E23: =+VLOOKUP($B23,transacciones!$A$1:$I$39,4,FALSE()) -> Producción de mercado | F23: =+VLOOKUP(B23,transacciones!$A$2:$I$39,5,FALSE()) -> 1 | G23: =+VLOOKUP(B23,transacciones!$A$2:$I$39,6,FALSE()) -> P1 | H23: =+VLOOKUP(B23,transacciones!$A$1:$I$39,7,FALSE()) -> Producción | I23: 19.1 | J23: Elaboración de productos de molinería, almidones y productos derivados del almidón | K23: C | L23: =+VLOOKUP(K23,'Correl CIIU'!$A$1:$F$26,2,FALSE()) -> Industrias manufactureras | M23: =+VLOOKUP(K23,'Correl CIIU'!$A$1:$F$26,3,FALSE()) -> Manufacturas | N23: =+VLOOKUP(K23,'Correl CIIU'!$A$1:$F$26,4,FALSE()) -> Manufacturing | O23: 1 | P23: =+VLOOKUP(O23,bio!$A$2:$B$4,2,FALSE()) -> Bioeconomía
A24: PANoc023 | B24: P11 | C24: =+VLOOKUP(B24,transacciones!$A$1:$I$39,2,FALSE()) -> ATC01 | D24: =+VLOOKUP($B24,transacciones!$A$1:$I$39,4,FALSE()) -> Producción de mercado | E24: =+VLOOKUP($B24,transacciones!$A$1:$I$39,4,FALSE()) -> Producción de mercado | F24: =+VLOOKUP(B24,transacciones!$A$2:$I$39,5,FALSE()) -> 1 | G24: =+VLOOKUP(B24,transacciones!$A$2:$I$39,6,FALSE()) -> P1 | H24: =+VLOOKUP(B24,transacciones!$A$1:$I$39,7,FALSE()) -> Producción | I24: 19.2 | J24: Elaboración de otros productos alimenticios | K24: C | L24: =+VLOOKUP(K24,'Correl CIIU'!$A$1:$F$26,2,FALSE()) -> Industrias manufactureras | M24: =+VLOOKUP(K24,'Correl CIIU'!$A$1:$F$26,3,FALSE()) -> Manufacturas | N24: =+VLOOKUP(K24,'Correl CIIU'!$A$1:$F$26,4,FALSE()) -> Manufacturing | O24: 1 | P24: =+VLOOKUP(O24,bio!$A$2:$B$4,2,FALSE()) -> Bioeconomía
A25: PANoc024 | B25: P11 | C25: =+VLOOKUP(B25,transacciones!$A$1:$I$39,2,FALSE()) -> ATC01 | D25: =+VLOOKUP($B25,transacciones!$A$1:$I$39,4,FALSE()) -> Producción de mercado | E25: =+VLOOKUP($B25,transacciones!$A$1:$I$39,4,FALSE()) -> Producción de mercado | F25: =+VLOOKUP(B25,transacciones!$A$2:$I$39,5,FALSE()) -> 1 | G25: =+VLOOKUP(B25,transacciones!$A$2:$I$39,6,FALSE()) -> P1 | H25: =+VLOOKUP(B25,transacciones!$A$1:$I$39,7,FALSE()) -> Producción | I25: 20.1 | J25: Elaboración de bebidas y tabaco | K25: C | L25: =+VLOOKUP(K25,'Correl CIIU'!$A$1:$F$26,2,FALSE()) -> Industrias manufactureras | M25: =+VLOOKUP(K25,'Correl CIIU'!$A$1:$F$26,3,FALSE()) -> Manufacturas | N25: =+VLOOKUP(K25,'Correl CIIU'!$A$1:$F$26,4,FALSE()) -> Manufacturing | O25: 1 | P25: =+VLOOKUP(O25,bio!$A$2:$B$4,2,FALSE()) -> Bioeconomía
A26: PANoc025 | B26: P11 | C26: =+VLOOKUP(B26,transacciones!$A$1:$I$39,2,FALSE()) -> ATC01 | D26: =+VLOOKUP($B26,transacciones!$A$1:$I$39,4,FALSE()) -> Producción de mercado | E26: =+VLOOKUP($B26,transacciones!$A$1:$I$39,4,FALSE()) -> Producción de mercado | F26: =+VLOOKUP(B26,transacciones!$A$2:$I$39,5,FALSE()) -> 1 | G26: =+VLOOKUP(B26,transacciones!$A$2:$I$39,6,FALSE()) -> P1 | H26: =+VLOOKUP(B26,transacciones!$A$1:$I$39,7,FALSE()) -> Producción | I26: 21.1 | J26: Fabricación de productos textiles y prendas de vestir | K26: C | L26: =+VLOOKUP(K26,'Correl CIIU'!$A$1:$F$26,2,FALSE()) -> Industrias manufactureras | M26: =+VLOOKUP(K26,'Correl CIIU'!$A$1:$F$26,3,FALSE()) -> Manufacturas | N26: =+VLOOKUP(K26,'Correl CIIU'!$A$1:$F$26,4,FALSE()) -> Manufacturing | O26: 2 | P26: =+VLOOKUP(O26,bio!$A$2:$B$4,2,FALSE()) -> Bioeconomía extendida
A27: PANoc026 | B27: P11 | C27: =+VLOOKUP(B27,transacciones!$A$1:$I$39,2,FALSE()) -> ATC01 | D27: =+VLOOKUP(B27,transacciones!$A$1:$I$39,3,FALSE()) -> Producción / Consumo intermedio | E27: =+VLOOKUP($B27,transacciones!$A$1:$I$39,4,FALSE()) -> Producción de mercado | F27: =+VLOOKUP(B27,transacciones!$A$2:$I$39,5,FALSE()) -> 1 | G27: =+VLOOKUP(B27,transacciones!$A$2:$I$39,6,FALSE()) -> P1 | H27: =+VLOOKUP(B27,transacciones!$A$1:$I$39,7,FALSE()) -> Producción | I27: 22.1 | J27: Fabricación de cuero, productos conexos y calzado | K27: C | L27: =+VLOOKUP(K27,'Correl CIIU'!$A$1:$F$26,2,FALSE()) -> Industrias manufactureras | M27: =+VLOOKUP(K27,'Correl CIIU'!$A$1:$F$26,3,FALSE()) -> Manufacturas | N27: =+VLOOKUP(K27,'Correl CIIU'!$A$1:$F$26,4,FALSE()) -> Manufacturing | O27: 2 | P27: =+VLOOKUP(O27,bio!$A$2:$B$4,2,FALSE()) -> Bioeconomía extendida
A28: PANoc027 | B28: P11 | C28: =+VLOOKUP(B28,transacciones!$A$1:$I$39,2,FALSE()) -> ATC01 | D28: =+VLOOKUP(B28,transacciones!$A$1:$I$39,3,FALSE()) -> Producción / Consumo intermedio | E28: =+VLOOKUP($B28,transacciones!$A$1:$I$39,4,FALSE()) -> Producción de mercado | F28: =+VLOOKUP(B28,transacciones!$A$2:$I$39,5,FALSE()) -> 1 | G28: =+VLOOKUP(B28,transacciones!$A$2:$I$39,6,FALSE()) -> P1 | H28: =+VLOOKUP(B28,transacciones!$A$1:$I$39,7,FALSE()) -> Producción | I28: 23.1 | J28: Producción de madera y fabricación de productos de madera y corcho, excepto muebles; fabricación de artículos de paja y de materiales trenzables | K28: C | L28: =+VLOOKUP(K28,'Correl CIIU'!$A$1:$F$26,2,FALSE()) -> Industrias manufactureras | M28: =+VLOOKUP(K28,'Correl CIIU'!$A$1:$F$26,3,FALSE()) -> Manufacturas | N28: =+VLOOKUP(K28,'Correl CIIU'!$A$1:$F$26,4,FALSE()) -> Manufacturing | O28: 1 | P28: =+VLOOKUP(O28,bio!$A$2:$B$4,2,FALSE()) -> Bioeconomía
A29: PANoc028 | B29: P11 | C29: =+VLOOKUP(B29,transacciones!$A$1:$I$39,2,FALSE()) -> ATC01 | D29: =+VLOOKUP(B29,transacciones!$A$1:$I$39,3,FALSE()) -> Producción / Consumo intermedio | E29: =+VLOOKUP($B29,transacciones!$A$1:$I$39,4,FALSE()) -> Producción de mercado | F29: =+VLOOKUP(B29,transacciones!$A$2:$I$39,5,FALSE()) -> 1 | G29: =+VLOOKUP(B29,transacciones!$A$2:$I$39,6,FALSE()) -> P1 | H29: =+VLOOKUP(B29,transacciones!$A$1:$I$39,7,FALSE()) -> Producción | I29: 24.1 | J29: Fabricacion de papel y productos de papel | K29: C | L29: =+VLOOKUP(K29,'Correl CIIU'!$A$1:$F$26,2,FALSE()) -> Industrias manufactureras | M29: =+VLOOKUP(K29,'Correl CIIU'!$A$1:$F$26,3,FALSE()) -> Manufacturas | N29: =+VLOOKUP(K29,'Correl CIIU'!$A$1:$F$26,4,FALSE()) -> Manufacturing | O29: 1 | P29: =+VLOOKUP(O29,bio!$A$2:$B$4,2,FALSE()) -> Bioeconomía
A30: PANoc029 | B30: P11 | C30: =+VLOOKUP(B30,transacciones!$A$1:$I$39,2,FALSE()) -> ATC01 | D30: =+VLOOKUP($B30,transacciones!$A$1:$I$39,4,FALSE()) -> Producción de mercado | E30: =+VLOOKUP($B30,transacciones!$A$1:$I$39,4,FALSE()) -> Producción de mercado | F30: =+VLOOKUP(B30,transacciones!$A$2:$I$39,5,FALSE()) -> 1 | G30: =+VLOOKUP(B30,transacciones!$A$2:$I$39,6,FALSE()) -> P1 | H30: =+VLOOKUP(B30,transacciones!$A$1:$I$39,7,FALSE()) -> Producción | I30: 25.1 | J30: Actividades de impresión y servicios conexos | K30: C | L30: =+VLOOKUP(K30,'Correl CIIU'!$A$1:$F$26,2,FALSE()) -> Industrias manufactureras | M30: =+VLOOKUP(K30,'Correl CIIU'!$A$1:$F$26,3,FALSE()) -> Manufacturas | N30: =+VLOOKUP(K30,'Correl CIIU'!$A$1:$F$26,4,FALSE()) -> Manufacturing | O30: 2 | P30: =+VLOOKUP(O30,bio!$A$2:$B$4,2,FALSE()) -> Bioeconomía extendida
A31: PANoc030 | B31: P11 | C31: =+VLOOKUP(B31,transacciones!$A$1:$I$39,2,FALSE()) -> ATC01 | D31: =+VLOOKUP($B31,transacciones!$A$1:$I$39,4,FALSE()) -> Producción de mercado | E31: =+VLOOKUP($B31,transacciones!$A$1:$I$39,4,FALSE()) -> Producción de mercado | F31: =+VLOOKUP(B31,transacciones!$A$2:$I$39,5,FALSE()) -> 1 | G31: =+VLOOKUP(B31,transacciones!$A$2:$I$39,6,FALSE()) -> P1 | H31: =+VLOOKUP(B31,transacciones!$A$1:$I$39,7,FALSE()) -> Producción | I31: 26.1 | J31: Fabricación de sustancias y productos químicos | K31: C | L31: =+VLOOKUP(K31,'Correl CIIU'!$A$1:$F$26,2,FALSE()) -> Industrias manufactureras | M31: =+VLOOKUP(K31,'Correl CIIU'!$A$1:$F$26,3,FALSE()) -> Manufacturas | N31: =+VLOOKUP(K31,'Correl CIIU'!$A$1:$F$26,4,FALSE()) -> Manufacturing | O31: 2 | P31: =+VLOOKUP(O31,bio!$A$2:$B$4,2,FALSE()) -> Bioeconomía extendida
A32: PANoc031 | B32: P11 | C32: =+VLOOKUP(B32,transacciones!$A$1:$I$39,2,FALSE()) -> ATC01 | D32: =+VLOOKUP($B32,transacciones!$A$1:$I$39,4,FALSE()) -> Producción de mercado | E32: =+VLOOKUP($B32,transacciones!$A$1:$I$39,4,FALSE()) -> Producción de mercado | F32: =+VLOOKUP(B32,transacciones!$A$2:$I$39,5,FALSE()) -> 1 | G32: =+VLOOKUP(B32,transacciones!$A$2:$I$39,6,FALSE()) -> P1 | H32: =+VLOOKUP(B32,transacciones!$A$1:$I$39,7,FALSE()) -> Producción | I32: 27.1 | J32: Fabricación de productos farmacéuticos, sustancias químicas medicinales y de productos botánicos | K32: C | L32: =+VLOOKUP(K32,'Correl CIIU'!$A$1:$F$26,2,FALSE()) -> Industrias manufactureras | M32: =+VLOOKUP(K32,'Correl CIIU'!$A$1:$F$26,3,FALSE()) -> Manufacturas | N32: =+VLOOKUP(K32,'Correl CIIU'!$A$1:$F$26,4,FALSE()) -> Manufacturing | O32: 2 | P32: =+VLOOKUP(O32,bio!$A$2:$B$4,2,FALSE()) -> Bioeconomía extendida
A33: PANoc032 | B33: P11 | C33: =+VLOOKUP(B33,transacciones!$A$1:$I$39,2,FALSE()) -> ATC01 | D33: =+VLOOKUP($B33,transacciones!$A$1:$I$39,4,FALSE()) -> Producción de mercado | E33: =+VLOOKUP($B33,transacciones!$A$1:$I$39,4,FALSE()) -> Producción de mercado | F33: =+VLOOKUP(B33,transacciones!$A$2:$I$39,5,FALSE()) -> 1 | G33: =+VLOOKUP(B33,transacciones!$A$2:$I$39,6,FALSE()) -> P1 | H33: =+VLOOKUP(B33,transacciones!$A$1:$I$39,7,FALSE()) -> Producción | I33: 28.1 | J33: Fabricación de productos de caucho y plástico | K33: C | L33: =+VLOOKUP(K33,'Correl CIIU'!$A$1:$F$26,2,FALSE()) -> Industrias manufactureras | M33: =+VLOOKUP(K33,'Correl CIIU'!$A$1:$F$26,3,FALSE()) -> Manufacturas | N33: =+VLOOKUP(K33,'Correl CIIU'!$A$1:$F$26,4,FALSE()) -> Manufacturing | O33: 3 | P33: =+VLOOKUP(O33,bio!$A$2:$B$4,2,FALSE()) -> No bioeconomía
A34: PANoc033 | B34: P11 | C34: =+VLOOKUP(B34,transacciones!$A$1:$I$39,2,FALSE()) -> ATC01 | D34: =+VLOOKUP($B34,transacciones!$A$1:$I$39,4,FALSE()) -> Producción de mercado | E34: =+VLOOKUP($B34,transacciones!$A$1:$I$39,4,FALSE()) -> Producción de mercado | F34: =+VLOOKUP(B34,transacciones!$A$2:$I$39,5,FALSE()) -> 1 | G34: =+VLOOKUP(B34,transacciones!$A$2:$I$39,6,FALSE()) -> P1 | H34: =+VLOOKUP(B34,transacciones!$A$1:$I$39,7,FALSE()) -> Producción | I34: 29.1 | J34: Fabricación de cemento, cal y yeso | K34: C | L34: =+VLOOKUP(K34,'Correl CIIU'!$A$1:$F$26,2,FALSE()) -> Industrias manufactureras | M34: =+VLOOKUP(K34,'Correl CIIU'!$A$1:$F$26,3,FALSE()) -> Manufacturas | N34: =+VLOOKUP(K34,'Correl CIIU'!$A$1:$F$26,4,FALSE()) -> Manufacturing | O34: 3 | P34: =+VLOOKUP(O34,bio!$A$2:$B$4,2,FALSE()) -> No bioeconomía
A35: PANoc034 | B35: P11 | C35: =+VLOOKUP(B35,transacciones!$A$1:$I$39,2,FALSE()) -> ATC01 | D35: =+VLOOKUP($B35,transacciones!$A$1:$I$39,4,FALSE()) -> Producción de mercado | E35: =+VLOOKUP($B35,transacciones!$A$1:$I$39,4,FALSE()) -> Producción de mercado | F35: =+VLOOKUP(B35,transacciones!$A$2:$I$39,5,FALSE()) -> 1 | G35: =+VLOOKUP(B35,transacciones!$A$2:$I$39,6,FALSE()) -> P1 | H35: =+VLOOKUP(B35,transacciones!$A$1:$I$39,7,FALSE()) -> Producción | I35: 30.1 | J35: Fabricación de otros productos minerales no metálicos | K35: C | L35: =+VLOOKUP(K35,'Correl CIIU'!$A$1:$F$26,2,FALSE()) -> Industrias manufactureras | M35: =+VLOOKUP(K35,'Correl CIIU'!$A$1:$F$26,3,FALSE()) -> Manufacturas | N35: =+VLOOKUP(K35,'Correl CIIU'!$A$1:$F$26,4,FALSE()) -> Manufacturing | O35: 3 | P35: =+VLOOKUP(O35,bio!$A$2:$B$4,2,FALSE()) -> No bioeconomía
A36: PANoc035 | B36: P11 | C36: =+VLOOKUP(B36,transacciones!$A$1:$I$39,2,FALSE()) -> ATC01 | D36: =+VLOOKUP($B36,transacciones!$A$1:$I$39,4,FALSE()) -> Producción de mercado | E36: =+VLOOKUP($B36,transacciones!$A$1:$I$39,4,FALSE()) -> Producción de mercado | F36: =+VLOOKUP(B36,transacciones!$A$2:$I$39,5,FALSE()) -> 1 | G36: =+VLOOKUP(B36,transacciones!$A$2:$I$39,6,FALSE()) -> P1 | H36: =+VLOOKUP(B36,transacciones!$A$1:$I$39,7,FALSE()) -> Producción | I36: 31.1 | J36: Fabricación de metales comunes | K36: C | L36: =+VLOOKUP(K36,'Correl CIIU'!$A$1:$F$26,2,FALSE()) -> Industrias manufactureras | M36: =+VLOOKUP(K36,'Correl CIIU'!$A$1:$F$26,3,FALSE()) -> Manufacturas | N36: =+VLOOKUP(K36,'Correl CIIU'!$A$1:$F$26,4,FALSE()) -> Manufacturing | O36: 3 | P36: =+VLOOKUP(O36,bio!$A$2:$B$4,2,FALSE()) -> No bioeconomía
A37: PANoc036 | B37: P11 | C37: =+VLOOKUP(B37,transacciones!$A$1:$I$39,2,FALSE()) -> ATC01 | D37: =+VLOOKUP($B37,transacciones!$A$1:$I$39,4,FALSE()) -> Producción de mercado | E37: =+VLOOKUP($B37,transacciones!$A$1:$I$39,4,FALSE()) -> Producción de mercado | F37: =+VLOOKUP(B37,transacciones!$A$2:$I$39,5,FALSE()) -> 1 | G37: =+VLOOKUP(B37,transacciones!$A$2:$I$39,6,FALSE()) -> P1 | H37: =+VLOOKUP(B37,transacciones!$A$1:$I$39,7,FALSE()) -> Producción | I37: 31.2 | J37: Fabricación de productos metalicos elaborados, excepto maquinaria y equipo | K37: C | L37: =+VLOOKUP(K37,'Correl CIIU'!$A$1:$F$26,2,FALSE()) -> Industrias manufactureras | M37: =+VLOOKUP(K37,'Correl CIIU'!$A$1:$F$26,3,FALSE()) -> Manufacturas | N37: =+VLOOKUP(K37,'Correl CIIU'!$A$1:$F$26,4,FALSE()) -> Manufacturing | O37: 3 | P37: =+VLOOKUP(O37,bio!$A$2:$B$4,2,FALSE()) -> No bioeconomía
A38: PANoc037 | B38: P11 | C38: =+VLOOKUP(B38,transacciones!$A$1:$I$39,2,FALSE()) -> ATC01 | D38: =+VLOOKUP($B38,transacciones!$A$1:$I$39,4,FALSE()) -> Producción de mercado | E38: =+VLOOKUP($B38,transacciones!$A$1:$I$39,4,FALSE()) -> Producción de mercado | F38: =+VLOOKUP(B38,transacciones!$A$2:$I$39,5,FALSE()) -> 1 | G38: =+VLOOKUP(B38,transacciones!$A$2:$I$39,6,FALSE()) -> P1 | H38: =+VLOOKUP(B38,transacciones!$A$1:$I$39,7,FALSE()) -> Producción | I38: 32.1 | J38: Otras industrias manufactureras | K38: C | L38: =+VLOOKUP(K38,'Correl CIIU'!$A$1:$F$26,2,FALSE()) -> Industrias manufactureras | M38: =+VLOOKUP(K38,'Correl CIIU'!$A$1:$F$26,3,FALSE()) -> Manufacturas | N38: =+VLOOKUP(K38,'Correl CIIU'!$A$1:$F$26,4,FALSE()) -> Manufacturing | O38: 3 | P38: =+VLOOKUP(O38,bio!$A$2:$B$4,2,FALSE()) -> No bioeconomía
A39: PANoc038 | B39: P11 | C39: =+VLOOKUP(B39,transacciones!$A$1:$I$39,2,FALSE()) -> ATC01 | D39: =+VLOOKUP(B39,transacciones!$A$1:$I$39,3,FALSE()) -> Producción / Consumo intermedio | E39: =+VLOOKUP($B39,transacciones!$A$1:$I$39,4,FALSE()) -> Producción de mercado | F39: =+VLOOKUP(B39,transacciones!$A$2:$I$39,5,FALSE()) -> 1 | G39: =+VLOOKUP(B39,transacciones!$A$2:$I$39,6,FALSE()) -> P1 | H39: =+VLOOKUP(B39,transacciones!$A$1:$I$39,7,FALSE()) -> Producción | I39: 33.1 | J39: Reparación, mantenimiento e instalación de maquinaria y equipo comercial e industrial | K39: C | L39: =+VLOOKUP(K39,'Correl CIIU'!$A$1:$F$26,2,FALSE()) -> Industrias manufactureras | M39: =+VLOOKUP(K39,'Correl CIIU'!$A$1:$F$26,3,FALSE()) -> Manufacturas | N39: =+VLOOKUP(K39,'Correl CIIU'!$A$1:$F$26,4,FALSE()) -> Manufacturing | O39: 3 | P39: =+VLOOKUP(O39,bio!$A$2:$B$4,2,FALSE()) -> No bioeconomía
A40: PANoc039 | B40: P11 | C40: =+VLOOKUP(B40,transacciones!$A$1:$I$39,2,FALSE()) -> ATC01 | D40: =+VLOOKUP(B40,transacciones!$A$1:$I$39,3,FALSE()) -> Producción / Consumo intermedio | E40: =+VLOOKUP($B40,transacciones!$A$1:$I$39,4,FALSE()) -> Producción de mercado | F40: =+VLOOKUP(B40,transacciones!$A$2:$I$39,5,FALSE()) -> 1 | G40: =+VLOOKUP(B40,transacciones!$A$2:$I$39,6,FALSE()) -> P1 | H40: =+VLOOKUP(B40,transacciones!$A$1:$I$39,7,FALSE()) -> Producción | I40: 34.1 | J40: Suministro de electricidad, gas, vapor y aire acondicionado | K40: D | L40: =+VLOOKUP(K40,'Correl CIIU'!$A$1:$F$26,2,FALSE()) -> Suministro de electricidad, gas, vapor y aire acondicionado | M40: =+VLOOKUP(K40,'Correl CIIU'!$A$1:$F$26,3,FALSE()) -> Servicios básicos | N40: =+VLOOKUP(K40,'Correl CIIU'!$A$1:$F$26,4,FALSE()) -> Electricity, gas, steam and air conditioning supply | O40: 3 | P40: =+VLOOKUP(O40,bio!$A$2:$B$4,2,FALSE()) -> No bioeconomía
A41: PANoc040 | B41: P11 | C41: =+VLOOKUP(B41,transacciones!$A$1:$I$39,2,FALSE()) -> ATC01 | D41: =+VLOOKUP(B41,transacciones!$A$1:$I$39,3,FALSE()) -> Producción / Consumo intermedio | E41: =+VLOOKUP($B41,transacciones!$A$1:$I$39,4,FALSE()) -> Producción de mercado | F41: =+VLOOKUP(B41,transacciones!$A$2:$I$39,5,FALSE()) -> 1 | G41: =+VLOOKUP(B41,transacciones!$A$2:$I$39,6,FALSE()) -> P1 | H41: =+VLOOKUP(B41,transacciones!$A$1:$I$39,7,FALSE()) -> Producción | I41: 35.1 | J41: Captación, tratamiento y distribuciòn de agua | K41: E | L41: =+VLOOKUP(K41,'Correl CIIU'!$A$1:$F$26,2,FALSE()) -> Suministro de agua; evacuación de aguas residuales, gestión de desechos y descontaminación | M41: =+VLOOKUP(K41,'Correl CIIU'!$A$1:$F$26,3,FALSE()) -> Suministro de agua | N41: =+VLOOKUP(K41,'Correl CIIU'!$A$1:$F$26,4,FALSE()) -> Water supply; sewerage, waste management and remediation activities | O41: 3 | P41: =+VLOOKUP(O41,bio!$A$2:$B$4,2,FALSE()) -> No bioeconomía
A42: PANoc041 | B42: P11 | C42: =+VLOOKUP(B42,transacciones!$A$1:$I$39,2,FALSE()) -> ATC01 | D42: =+VLOOKUP($B42,transacciones!$A$1:$I$39,4,FALSE()) -> Producción de mercado | E42: =+VLOOKUP($B42,transacciones!$A$1:$I$39,4,FALSE()) -> Producción de mercado | F42: =+VLOOKUP(B42,transacciones!$A$2:$I$39,5,FALSE()) -> 1 | G42: =+VLOOKUP(B42,transacciones!$A$2:$I$39,6,FALSE()) -> P1 | H42: =+VLOOKUP(B42,transacciones!$A$1:$I$39,7,FALSE()) -> Producción | I42: 35.2 M | J42: Recogida, tratamiento y eliminación de desechos, recuperación de materiales y actividades de descontaminación y otros servicios de eliminación de desechos | K42: E | L42: =+VLOOKUP(K42,'Correl CIIU'!$A$1:$F$26,2,FALSE()) -> Suministro de agua; evacuación de aguas residuales, gestión de desechos y descontaminación | M42: =+VLOOKUP(K42,'Correl CIIU'!$A$1:$F$26,3,FALSE()) -> Suministro de agua | N42: =+VLOOKUP(K42,'Correl CIIU'!$A$1:$F$26,4,FALSE()) -> Water supply; sewerage, waste management and remediation activities | O42: 2 | P42: =+VLOOKUP(O42,bio!$A$2:$B$4,2,FALSE()) -> Bioeconomía extendida
A43: PANoc042 | B43: P11 | C43: =+VLOOKUP(B43,transacciones!$A$1:$I$39,2,FALSE()) -> ATC01 | D43: =+VLOOKUP($B43,transacciones!$A$1:$I$39,4,FALSE()) -> Producción de mercado | E43: =+VLOOKUP($B43,transacciones!$A$1:$I$39,4,FALSE()) -> Producción de mercado | F43: =+VLOOKUP(B43,transacciones!$A$2:$I$39,5,FALSE()) -> 1 | G43: =+VLOOKUP(B43,transacciones!$A$2:$I$39,6,FALSE()) -> P1 | H43: =+VLOOKUP(B43,transacciones!$A$1:$I$39,7,FALSE()) -> Producción | I43: 36.1 M | J43: Construcción de edificios | K43: F | L43: =+VLOOKUP(K43,'Correl CIIU'!$A$1:$F$26,2,FALSE()) -> Construcción | M43: =+VLOOKUP(K43,'Correl CIIU'!$A$1:$F$26,3,FALSE()) -> Construcción | N43: =+VLOOKUP(K43,'Correl CIIU'!$A$1:$F$26,4,FALSE()) -> Construction | O43: 3 | P43: =+VLOOKUP(O43,bio!$A$2:$B$4,2,FALSE()) -> No bioeconomía
A44: PANoc043 | B44: P11 | C44: =+VLOOKUP(B44,transacciones!$A$1:$I$39,2,FALSE()) -> ATC01 | D44: =+VLOOKUP($B44,transacciones!$A$1:$I$39,4,FALSE()) -> Producción de mercado | E44: =+VLOOKUP($B44,transacciones!$A$1:$I$39,4,FALSE()) -> Producción de mercado | F44: =+VLOOKUP(B44,transacciones!$A$2:$I$39,5,FALSE()) -> 1 | G44: =+VLOOKUP(B44,transacciones!$A$2:$I$39,6,FALSE()) -> P1 | H44: =+VLOOKUP(B44,transacciones!$A$1:$I$39,7,FALSE()) -> Producción | I44: 37.1 | J44: Comercio al por mayor y menor en zona franca | K44: G | L44: =+VLOOKUP(K44,'Correl CIIU'!$A$1:$F$26,2,FALSE()) -> Comercio al por mayor y al por menor; reparación de vehículos automotores y motocicletas | M44: =+VLOOKUP(K44,'Correl CIIU'!$A$1:$F$26,3,FALSE()) -> Comercio | N44: =+VLOOKUP(K44,'Correl CIIU'!$A$1:$F$26,4,FALSE()) -> Wholesale and retail trade; repair of motor vehicles and motorcycles | O44: 3 | P44: =+VLOOKUP(O44,bio!$A$2:$B$4,2,FALSE()) -> No bioeconomía
A45: PANoc044 | B45: P11 | C45: =+VLOOKUP(B45,transacciones!$A$1:$I$39,2,FALSE()) -> ATC01 | D45: =+VLOOKUP($B45,transacciones!$A$1:$I$39,4,FALSE()) -> Producción de mercado | E45: =+VLOOKUP($B45,transacciones!$A$1:$I$39,4,FALSE()) -> Producción de mercado | F45: =+VLOOKUP(B45,transacciones!$A$2:$I$39,5,FALSE()) -> 1 | G45: =+VLOOKUP(B45,transacciones!$A$2:$I$39,6,FALSE()) -> P1 | H45: =+VLOOKUP(B45,transacciones!$A$1:$I$39,7,FALSE()) -> Producción | I45: 38.1 | J45: Comercio al por mayor, en comisión y de vehículos automotores | K45: G | L45: =+VLOOKUP(K45,'Correl CIIU'!$A$1:$F$26,2,FALSE()) -> Comercio al por mayor y al por menor; reparación de vehículos automotores y motocicletas | M45: =+VLOOKUP(K45,'Correl CIIU'!$A$1:$F$26,3,FALSE()) -> Comercio | N45: =+VLOOKUP(K45,'Correl CIIU'!$A$1:$F$26,4,FALSE()) -> Wholesale and retail trade; repair of motor vehicles and motorcycles | O45: 3 | P45: =+VLOOKUP(O45,bio!$A$2:$B$4,2,FALSE()) -> No bioeconomía
A46: PANoc045 | B46: P11 | C46: =+VLOOKUP(B46,transacciones!$A$1:$I$39,2,FALSE()) -> ATC01 | D46: =+VLOOKUP($B46,transacciones!$A$1:$I$39,4,FALSE()) -> Producción de mercado | E46: =+VLOOKUP($B46,transacciones!$A$1:$I$39,4,FALSE()) -> Producción de mercado | F46: =+VLOOKUP(B46,transacciones!$A$2:$I$39,5,FALSE()) -> 1 | G46: =+VLOOKUP(B46,transacciones!$A$2:$I$39,6,FALSE()) -> P1 | H46: =+VLOOKUP(B46,transacciones!$A$1:$I$39,7,FALSE()) -> Producción | I46: 38.2 | J46: Comercio al por menor | K46: G | L46: =+VLOOKUP(K46,'Correl CIIU'!$A$1:$F$26,2,FALSE()) -> Comercio al por mayor y al por menor; reparación de vehículos automotores y motocicletas | M46: =+VLOOKUP(K46,'Correl CIIU'!$A$1:$F$26,3,FALSE()) -> Comercio | N46: =+VLOOKUP(K46,'Correl CIIU'!$A$1:$F$26,4,FALSE()) -> Wholesale and retail trade; repair of motor vehicles and motorcycles | O46: 3 | P46: =+VLOOKUP(O46,bio!$A$2:$B$4,2,FALSE()) -> No bioeconomía
A47: PANoc046 | B47: P11 | C47: =+VLOOKUP(B47,transacciones!$A$1:$I$39,2,FALSE()) -> ATC01 | D47: =+VLOOKUP($B47,transacciones!$A$1:$I$39,4,FALSE()) -> Producción de mercado | E47: =+VLOOKUP($B47,transacciones!$A$1:$I$39,4,FALSE()) -> Producción de mercado | F47: =+VLOOKUP(B47,transacciones!$A$2:$I$39,5,FALSE()) -> 1 | G47: =+VLOOKUP(B47,transacciones!$A$2:$I$39,6,FALSE()) -> P1 | H47: =+VLOOKUP(B47,transacciones!$A$1:$I$39,7,FALSE()) -> Producción | I47: 38.3 | J47: Mantenimiento y reparación de vehículos automotores y bicicletas | K47: H | L47: =+VLOOKUP(K47,'Correl CIIU'!$A$1:$F$26,2,FALSE()) -> Transporte y almacenamiento | M47: =+VLOOKUP(K47,'Correl CIIU'!$A$1:$F$26,3,FALSE()) -> Transporte y almacenamiento | N47: =+VLOOKUP(K47,'Correl CIIU'!$A$1:$F$26,4,FALSE()) -> Transportation and storage | O47: 3 | P47: =+VLOOKUP(O47,bio!$A$2:$B$4,2,FALSE()) -> No bioeconomía
A48: PANoc047 | B48: P11 | C48: =+VLOOKUP(B48,transacciones!$A$1:$I$39,2,FALSE()) -> ATC01 | D48: =+VLOOKUP($B48,transacciones!$A$1:$I$39,4,FALSE()) -> Producción de mercado | E48: =+VLOOKUP($B48,transacciones!$A$1:$I$39,4,FALSE()) -> Producción de mercado | F48: =+VLOOKUP(B48,transacciones!$A$2:$I$39,5,FALSE()) -> 1 | G48: =+VLOOKUP(B48,transacciones!$A$2:$I$39,6,FALSE()) -> P1 | H48: =+VLOOKUP(B48,transacciones!$A$1:$I$39,7,FALSE()) -> Producción | I48: 39.1 | J48: Transporte por vía terrestre; transporte por tuberías | K48: H | L48: =+VLOOKUP(K48,'Correl CIIU'!$A$1:$F$26,2,FALSE()) -> Transporte y almacenamiento | M48: =+VLOOKUP(K48,'Correl CIIU'!$A$1:$F$26,3,FALSE()) -> Transporte y almacenamiento | N48: =+VLOOKUP(K48,'Correl CIIU'!$A$1:$F$26,4,FALSE()) -> Transportation and storage | O48: 3 | P48: =+VLOOKUP(O48,bio!$A$2:$B$4,2,FALSE()) -> No bioeconomía
A49: PANoc048 | B49: P11 | C49: =+VLOOKUP(B49,transacciones!$A$1:$I$39,2,FALSE()) -> ATC01 | D49: =+VLOOKUP($B49,transacciones!$A$1:$I$39,4,FALSE()) -> Producción de mercado | E49: =+VLOOKUP($B49,transacciones!$A$1:$I$39,4,FALSE()) -> Producción de mercado | F49: =+VLOOKUP(B49,transacciones!$A$2:$I$39,5,FALSE()) -> 1 | G49: =+VLOOKUP(B49,transacciones!$A$2:$I$39,6,FALSE()) -> P1 | H49: =+VLOOKUP(B49,transacciones!$A$1:$I$39,7,FALSE()) -> Producción | I49: 39.2 | J49: Transporte por vía acuática | K49: H | L49: =+VLOOKUP(K49,'Correl CIIU'!$A$1:$F$26,2,FALSE()) -> Transporte y almacenamiento | M49: =+VLOOKUP(K49,'Correl CIIU'!$A$1:$F$26,3,FALSE()) -> Transporte y almacenamiento | N49: =+VLOOKUP(K49,'Correl CIIU'!$A$1:$F$26,4,FALSE()) -> Transportation and storage | O49: 3 | P49: =+VLOOKUP(O49,bio!$A$2:$B$4,2,FALSE()) -> No bioeconomía
A50: PANoc049 | B50: P11 | C50: =+VLOOKUP(B50,transacciones!$A$1:$I$39,2,FALSE()) -> ATC01 | D50: =+VLOOKUP($B50,transacciones!$A$1:$I$39,4,FALSE()) -> Producción de mercado | E50: =+VLOOKUP($B50,transacciones!$A$1:$I$39,4,FALSE()) -> Producción de mercado | F50: =+VLOOKUP(B50,transacciones!$A$2:$I$39,5,FALSE()) -> 1 | G50: =+VLOOKUP(B50,transacciones!$A$2:$I$39,6,FALSE()) -> P1 | H50: =+VLOOKUP(B50,transacciones!$A$1:$I$39,7,FALSE()) -> Producción | I50: 39.3 | J50: Transporte por vía aérea | K50: H | L50: =+VLOOKUP(K50,'Correl CIIU'!$A$1:$F$26,2,FALSE()) -> Transporte y almacenamiento | M50: =+VLOOKUP(K50,'Correl CIIU'!$A$1:$F$26,3,FALSE()) -> Transporte y almacenamiento | N50: =+VLOOKUP(K50,'Correl CIIU'!$A$1:$F$26,4,FALSE()) -> Transportation and storage | O50: 3 | P50: =+VLOOKUP(O50,bio!$A$2:$B$4,2,FALSE()) -> No bioeconomía
A51: PANoc050 | B51: P11 | C51: =+VLOOKUP(B51,transacciones!$A$1:$I$39,2,FALSE()) -> ATC01 | D51: =+VLOOKUP(B51,transacciones!$A$1:$I$39,3,FALSE()) -> Producción / Consumo intermedio | E51: =+VLOOKUP($B51,transacciones!$A$1:$I$39,4,FALSE()) -> Producción de mercado | F51: =+VLOOKUP(B51,transacciones!$A$2:$I$39,5,FALSE()) -> 1 | G51: =+VLOOKUP(B51,transacciones!$A$2:$I$39,6,FALSE()) -> P1 | H51: =+VLOOKUP(B51,transacciones!$A$1:$I$39,7,FALSE()) -> Producción | I51: 39.4 | J51: Servicio de almacenamiento y depósito | K51: H | L51: =+VLOOKUP(K51,'Correl CIIU'!$A$1:$F$26,2,FALSE()) -> Transporte y almacenamiento | M51: =+VLOOKUP(K51,'Correl CIIU'!$A$1:$F$26,3,FALSE()) -> Transporte y almacenamiento | N51: =+VLOOKUP(K51,'Correl CIIU'!$A$1:$F$26,4,FALSE()) -> Transportation and storage | O51: 3 | P51: =+VLOOKUP(O51,bio!$A$2:$B$4,2,FALSE()) -> No bioeconomía
A52: PANoc051 | B52: P11 | C52: =+VLOOKUP(B52,transacciones!$A$1:$I$39,2,FALSE()) -> ATC01 | D52: =+VLOOKUP(B52,transacciones!$A$1:$I$39,3,FALSE()) -> Producción / Consumo intermedio | E52: =+VLOOKUP($B52,transacciones!$A$1:$I$39,4,FALSE()) -> Producción de mercado | F52: =+VLOOKUP(B52,transacciones!$A$2:$I$39,5,FALSE()) -> 1 | G52: =+VLOOKUP(B52,transacciones!$A$2:$I$39,6,FALSE()) -> P1 | H52: =+VLOOKUP(B52,transacciones!$A$1:$I$39,7,FALSE()) -> Producción | I52: 39.5 | J52: Actividades de servicio vinculadas al transporte por vía acuática: Autoridad del Canal de Panamá (ACP) | K52: H | L52: =+VLOOKUP(K52,'Correl CIIU'!$A$1:$F$26,2,FALSE()) -> Transporte y almacenamiento | M52: =+VLOOKUP(K52,'Correl CIIU'!$A$1:$F$26,3,FALSE()) -> Transporte y almacenamiento | N52: =+VLOOKUP(K52,'Correl CIIU'!$A$1:$F$26,4,FALSE()) -> Transportation and storage | O52: 3 | P52: =+VLOOKUP(O52,bio!$A$2:$B$4,2,FALSE()) -> No bioeconomía
A53: PANoc052 | B53: P11 | C53: =+VLOOKUP(B53,transacciones!$A$1:$I$39,2,FALSE()) -> ATC01 | D53: =+VLOOKUP(B53,transacciones!$A$1:$I$39,3,FALSE()) -> Producción / Consumo intermedio | E53: =+VLOOKUP($B53,transacciones!$A$1:$I$39,4,FALSE()) -> Producción de mercado | F53: =+VLOOKUP(B53,transacciones!$A$2:$I$39,5,FALSE()) -> 1 | G53: =+VLOOKUP(B53,transacciones!$A$2:$I$39,6,FALSE()) -> P1 | H53: =+VLOOKUP(B53,transacciones!$A$1:$I$39,7,FALSE()) -> Producción | I53: 39.6 | J53: Otras actividades de servicio vinculado al transporte por vía acuática | K53: H | L53: =+VLOOKUP(K53,'Correl CIIU'!$A$1:$F$26,2,FALSE()) -> Transporte y almacenamiento | M53: =+VLOOKUP(K53,'Correl CIIU'!$A$1:$F$26,3,FALSE()) -> Transporte y almacenamiento | N53: =+VLOOKUP(K53,'Correl CIIU'!$A$1:$F$26,4,FALSE()) -> Transportation and storage | O53: 3 | P53: =+VLOOKUP(O53,bio!$A$2:$B$4,2,FALSE()) -> No bioeconomía
A54: PANoc053 | B54: P11 | C54: =+VLOOKUP(B54,transacciones!$A$1:$I$39,2,FALSE()) -> ATC01 | D54: =+VLOOKUP($B54,transacciones!$A$1:$I$39,4,FALSE()) -> Producción de mercado | E54: =+VLOOKUP($B54,transacciones!$A$1:$I$39,4,FALSE()) -> Producción de mercado | F54: =+VLOOKUP(B54,transacciones!$A$2:$I$39,5,FALSE()) -> 1 | G54: =+VLOOKUP(B54,transacciones!$A$2:$I$39,6,FALSE()) -> P1 | H54: =+VLOOKUP(B54,transacciones!$A$1:$I$39,7,FALSE()) -> Producción | I54: 39.7 | J54: Actividades de servicio vinculado al transporte por vía aérea: aeropuertos | K54: H | L54: =+VLOOKUP(K54,'Correl CIIU'!$A$1:$F$26,2,FALSE()) -> Transporte y almacenamiento | M54: =+VLOOKUP(K54,'Correl CIIU'!$A$1:$F$26,3,FALSE()) -> Transporte y almacenamiento | N54: =+VLOOKUP(K54,'Correl CIIU'!$A$1:$F$26,4,FALSE()) -> Transportation and storage | O54: 3 | P54: =+VLOOKUP(O54,bio!$A$2:$B$4,2,FALSE()) -> No bioeconomía
A55: PANoc054 | B55: P11 | C55: =+VLOOKUP(B55,transacciones!$A$1:$I$39,2,FALSE()) -> ATC01 | D55: =+VLOOKUP($B55,transacciones!$A$1:$I$39,4,FALSE()) -> Producción de mercado | E55: =+VLOOKUP($B55,transacciones!$A$1:$I$39,4,FALSE()) -> Producción de mercado | F55: =+VLOOKUP(B55,transacciones!$A$2:$I$39,5,FALSE()) -> 1 | G55: =+VLOOKUP(B55,transacciones!$A$2:$I$39,6,FALSE()) -> P1 | H55: =+VLOOKUP(B55,transacciones!$A$1:$I$39,7,FALSE()) -> Producción | I55: 39.8 | J55: Otros actividades de apoyo al transporte | K55: H | L55: =+VLOOKUP(K55,'Correl CIIU'!$A$1:$F$26,2,FALSE()) -> Transporte y almacenamiento | M55: =+VLOOKUP(K55,'Correl CIIU'!$A$1:$F$26,3,FALSE()) -> Transporte y almacenamiento | N55: =+VLOOKUP(K55,'Correl CIIU'!$A$1:$F$26,4,FALSE()) -> Transportation and storage | O55: 3 | P55: =+VLOOKUP(O55,bio!$A$2:$B$4,2,FALSE()) -> No bioeconomía
A56: PANoc055 | B56: P11 | C56: =+VLOOKUP(B56,transacciones!$A$1:$I$39,2,FALSE()) -> ATC01 | D56: =+VLOOKUP($B56,transacciones!$A$1:$I$39,4,FALSE()) -> Producción de mercado | E56: =+VLOOKUP($B56,transacciones!$A$1:$I$39,4,FALSE()) -> Producción de mercado | F56: =+VLOOKUP(B56,transacciones!$A$2:$I$39,5,FALSE()) -> 1 | G56: =+VLOOKUP(B56,transacciones!$A$2:$I$39,6,FALSE()) -> P1 | H56: =+VLOOKUP(B56,transacciones!$A$1:$I$39,7,FALSE()) -> Producción | I56: 39.9 | J56: Actividades postales y de mensajería | K56: J | L56: Información y comunicaciones | M56: Información y comunicaciones | N56: Information and communication | O56: 3 | P56: =+VLOOKUP(O56,bio!$A$2:$B$4,2,FALSE()) -> No bioeconomía
A57: PANoc056 | B57: P11 | C57: =+VLOOKUP(B57,transacciones!$A$1:$I$39,2,FALSE()) -> ATC01 | D57: =+VLOOKUP($B57,transacciones!$A$1:$I$39,4,FALSE()) -> Producción de mercado | E57: =+VLOOKUP($B57,transacciones!$A$1:$I$39,4,FALSE()) -> Producción de mercado | F57: =+VLOOKUP(B57,transacciones!$A$2:$I$39,5,FALSE()) -> 1 | G57: =+VLOOKUP(B57,transacciones!$A$2:$I$39,6,FALSE()) -> P1 | H57: =+VLOOKUP(B57,transacciones!$A$1:$I$39,7,FALSE()) -> Producción | I57: 40.1 | J57: Actividades de alojamientos | K57: I | L57: =+VLOOKUP(K57,'Correl CIIU'!$A$1:$F$26,2,FALSE()) -> Actividades de alojamiento y de servicio de comidas | M57: =+VLOOKUP(K57,'Correl CIIU'!$A$1:$F$26,3,FALSE()) -> Alojamiento y alimentación | N57: =+VLOOKUP(K57,'Correl CIIU'!$A$1:$F$26,4,FALSE()) -> Accommodation and food service activities | O57: 3 | P57: =+VLOOKUP(O57,bio!$A$2:$B$4,2,FALSE()) -> No bioeconomía
A58: PANoc057 | B58: P11 | C58: =+VLOOKUP(B58,transacciones!$A$1:$I$39,2,FALSE()) -> ATC01 | D58: =+VLOOKUP($B58,transacciones!$A$1:$I$39,4,FALSE()) -> Producción de mercado | E58: =+VLOOKUP($B58,transacciones!$A$1:$I$39,4,FALSE()) -> Producción de mercado | F58: =+VLOOKUP(B58,transacciones!$A$2:$I$39,5,FALSE()) -> 1 | G58: =+VLOOKUP(B58,transacciones!$A$2:$I$39,6,FALSE()) -> P1 | H58: =+VLOOKUP(B58,transacciones!$A$1:$I$39,7,FALSE()) -> Producción | I58: 40.2 | J58: Actividades de servicios de comidas y bebidas | K58: I | L58: =+VLOOKUP(K58,'Correl CIIU'!$A$1:$F$26,2,FALSE()) -> Actividades de alojamiento y de servicio de comidas | M58: =+VLOOKUP(K58,'Correl CIIU'!$A$1:$F$26,3,FALSE()) -> Alojamiento y alimentación | N58: =+VLOOKUP(K58,'Correl CIIU'!$A$1:$F$26,4,FALSE()) -> Accommodation and food service activities | O58: 2 | P58: =+VLOOKUP(O58,bio!$A$2:$B$4,2,FALSE()) -> Bioeconomía extendida
A59: PANoc058 | B59: P11 | C59: =+VLOOKUP(B59,transacciones!$A$1:$I$39,2,FALSE()) -> ATC01 | D59: =+VLOOKUP($B59,transacciones!$A$1:$I$39,4,FALSE()) -> Producción de mercado | E59: =+VLOOKUP($B59,transacciones!$A$1:$I$39,4,FALSE()) -> Producción de mercado | F59: =+VLOOKUP(B59,transacciones!$A$2:$I$39,5,FALSE()) -> 1 | G59: =+VLOOKUP(B59,transacciones!$A$2:$I$39,6,FALSE()) -> P1 | H59: =+VLOOKUP(B59,transacciones!$A$1:$I$39,7,FALSE()) -> Producción | I59: 41.1 M | J59: Actividades de información y comunicación excluída telecomunicaciones | K59: J | L59: Información y comunicaciones | M59: Información y comunicaciones | N59: Information and communication | O59: 3 | P59: =+VLOOKUP(O59,bio!$A$2:$B$4,2,FALSE()) -> No bioeconomía
A60: PANoc059 | B60: P11 | C60: =+VLOOKUP(B60,transacciones!$A$1:$I$39,2,FALSE()) -> ATC01 | D60: =+VLOOKUP($B60,transacciones!$A$1:$I$39,4,FALSE()) -> Producción de mercado | E60: =+VLOOKUP($B60,transacciones!$A$1:$I$39,4,FALSE()) -> Producción de mercado | F60: =+VLOOKUP(B60,transacciones!$A$2:$I$39,5,FALSE()) -> 1 | G60: =+VLOOKUP(B60,transacciones!$A$2:$I$39,6,FALSE()) -> P1 | H60: =+VLOOKUP(B60,transacciones!$A$1:$I$39,7,FALSE()) -> Producción | I60: 41.2 | J60: Telecomunicaciones | K60: J | L60: =+VLOOKUP(K60,'Correl CIIU'!$A$1:$F$26,2,FALSE()) -> Información y comunicaciones | M60: =+VLOOKUP(K60,'Correl CIIU'!$A$1:$F$26,3,FALSE()) -> Información y comunicaciones | N60: =+VLOOKUP(K60,'Correl CIIU'!$A$1:$F$26,4,FALSE()) -> Information and communication | O60: 3 | P60: =+VLOOKUP(O60,bio!$A$2:$B$4,2,FALSE()) -> No bioeconomía
A61: PANoc060 | B61: P11 | C61: =+VLOOKUP(B61,transacciones!$A$1:$I$39,2,FALSE()) -> ATC01 | D61: =+VLOOKUP($B61,transacciones!$A$1:$I$39,4,FALSE()) -> Producción de mercado | E61: =+VLOOKUP($B61,transacciones!$A$1:$I$39,4,FALSE()) -> Producción de mercado | F61: =+VLOOKUP(B61,transacciones!$A$2:$I$39,5,FALSE()) -> 1 | G61: =+VLOOKUP(B61,transacciones!$A$2:$I$39,6,FALSE()) -> P1 | H61: =+VLOOKUP(B61,transacciones!$A$1:$I$39,7,FALSE()) -> Producción | I61: 42.1 | J61: Actividades de servicios financieros, excepto seguros y fondos de pensiones | K61: K | L61: =+VLOOKUP(K61,'Correl CIIU'!$A$1:$F$26,2,FALSE()) -> Actividades financieras y de seguros | M61: =+VLOOKUP(K61,'Correl CIIU'!$A$1:$F$26,3,FALSE()) -> Finanzas y seguros | N61: =+VLOOKUP(K61,'Correl CIIU'!$A$1:$F$26,4,FALSE()) -> Financial and insurance activities | O61: 3 | P61: =+VLOOKUP(O61,bio!$A$2:$B$4,2,FALSE()) -> No bioeconomía
A62: PANoc061 | B62: P11 | C62: =+VLOOKUP(B62,transacciones!$A$1:$I$39,2,FALSE()) -> ATC01 | D62: =+VLOOKUP(B62,transacciones!$A$1:$I$39,3,FALSE()) -> Producción / Consumo intermedio | E62: =+VLOOKUP($B62,transacciones!$A$1:$I$39,4,FALSE()) -> Producción de mercado | F62: =+VLOOKUP(B62,transacciones!$A$2:$I$39,5,FALSE()) -> 1 | G62: =+VLOOKUP(B62,transacciones!$A$2:$I$39,6,FALSE()) -> P1 | H62: =+VLOOKUP(B62,transacciones!$A$1:$I$39,7,FALSE()) -> Producción | I62: 42.2 | J62: Actividades de seguros, reaseguros y fondos de pensiones, excepto los planes de seguridad social de afiliación obligatoria | K62: K | L62: =+VLOOKUP(K62,'Correl CIIU'!$A$1:$F$26,2,FALSE()) -> Actividades financieras y de seguros | M62: =+VLOOKUP(K62,'Correl CIIU'!$A$1:$F$26,3,FALSE()) -> Finanzas y seguros | N62: =+VLOOKUP(K62,'Correl CIIU'!$A$1:$F$26,4,FALSE()) -> Financial and insurance activities | O62: 3 | P62: =+VLOOKUP(O62,bio!$A$2:$B$4,2,FALSE()) -> No bioeconomía
A63: PANoc062 | B63: P11 | C63: =+VLOOKUP(B63,transacciones!$A$1:$I$39,2,FALSE()) -> ATC01 | D63: =+VLOOKUP(B63,transacciones!$A$1:$I$39,3,FALSE()) -> Producción / Consumo intermedio | E63: =+VLOOKUP($B63,transacciones!$A$1:$I$39,4,FALSE()) -> Producción de mercado | F63: =+VLOOKUP(B63,transacciones!$A$2:$I$39,5,FALSE()) -> 1 | G63: =+VLOOKUP(B63,transacciones!$A$2:$I$39,6,FALSE()) -> P1 | H63: =+VLOOKUP(B63,transacciones!$A$1:$I$39,7,FALSE()) -> Producción | I63: 42.3 | J63: Actividades auxiliares de las actividades de servicios financieros | K63: K | L63: =+VLOOKUP(K63,'Correl CIIU'!$A$1:$F$26,2,FALSE()) -> Actividades financieras y de seguros | M63: =+VLOOKUP(K63,'Correl CIIU'!$A$1:$F$26,3,FALSE()) -> Finanzas y seguros | N63: =+VLOOKUP(K63,'Correl CIIU'!$A$1:$F$26,4,FALSE()) -> Financial and insurance activities | O63: 3 | P63: =+VLOOKUP(O63,bio!$A$2:$B$4,2,FALSE()) -> No bioeconomía
A64: PANoc063 | B64: P11 | C64: =+VLOOKUP(B64,transacciones!$A$1:$I$39,2,FALSE()) -> ATC01 | D64: =+VLOOKUP(B64,transacciones!$A$1:$I$39,3,FALSE()) -> Producción / Consumo intermedio | E64: =+VLOOKUP($B64,transacciones!$A$1:$I$39,4,FALSE()) -> Producción de mercado | F64: =+VLOOKUP(B64,transacciones!$A$2:$I$39,5,FALSE()) -> 1 | G64: =+VLOOKUP(B64,transacciones!$A$2:$I$39,6,FALSE()) -> P1 | H64: =+VLOOKUP(B64,transacciones!$A$1:$I$39,7,FALSE()) -> Producción | I64: 43.1 M | J64: Alquiler de viviendas | K64: L | L64: =+VLOOKUP(K64,'Correl CIIU'!$A$1:$F$26,2,FALSE()) -> Actividades inmobiliarias | M64: =+VLOOKUP(K64,'Correl CIIU'!$A$1:$F$26,3,FALSE()) -> Inmobiliarios | N64: =+VLOOKUP(K64,'Correl CIIU'!$A$1:$F$26,4,FALSE()) -> Real estate activities | O64: 3 | P64: =+VLOOKUP(O64,bio!$A$2:$B$4,2,FALSE()) -> No bioeconomía
A65: PANoc064 | B65: P11 | C65: =+VLOOKUP(B65,transacciones!$A$1:$I$39,2,FALSE()) -> ATC01 | D65: =+VLOOKUP(B65,transacciones!$A$1:$I$39,3,FALSE()) -> Producción / Consumo intermedio | E65: =+VLOOKUP($B65,transacciones!$A$1:$I$39,4,FALSE()) -> Producción de mercado | F65: =+VLOOKUP(B65,transacciones!$A$2:$I$39,5,FALSE()) -> 1 | G65: =+VLOOKUP(B65,transacciones!$A$2:$I$39,6,FALSE()) -> P1 | H65: =+VLOOKUP(B65,transacciones!$A$1:$I$39,7,FALSE()) -> Producción | I65: 43.2 | J65: Alquileres no residenciales y otras actividades inmobiliarias | K65: L | L65: =+VLOOKUP(K65,'Correl CIIU'!$A$1:$F$26,2,FALSE()) -> Actividades inmobiliarias | M65: =+VLOOKUP(K65,'Correl CIIU'!$A$1:$F$26,3,FALSE()) -> Inmobiliarios | N65: =+VLOOKUP(K65,'Correl CIIU'!$A$1:$F$26,4,FALSE()) -> Real estate activities | O65: 3 | P65: =+VLOOKUP(O65,bio!$A$2:$B$4,2,FALSE()) -> No bioeconomía
A66: PANoc065 | B66: P11 | C66: =+VLOOKUP(B66,transacciones!$A$1:$I$39,2,FALSE()) -> ATC01 | D66: =+VLOOKUP($B66,transacciones!$A$1:$I$39,4,FALSE()) -> Producción de mercado | E66: =+VLOOKUP($B66,transacciones!$A$1:$I$39,4,FALSE()) -> Producción de mercado | F66: =+VLOOKUP(B66,transacciones!$A$2:$I$39,5,FALSE()) -> 1 | G66: =+VLOOKUP(B66,transacciones!$A$2:$I$39,6,FALSE()) -> P1 | H66: =+VLOOKUP(B66,transacciones!$A$1:$I$39,7,FALSE()) -> Producción | I66: 44.1 | J66: Actividades jurídicas y de contabilidad | K66: M | L66: =+VLOOKUP(K66,'Correl CIIU'!$A$1:$F$26,2,FALSE()) -> Actividades profesionales, científicas y técnicas | M66: =+VLOOKUP(K66,'Correl CIIU'!$A$1:$F$26,3,FALSE()) -> Servicios profesionales | N66: =+VLOOKUP(K66,'Correl CIIU'!$A$1:$F$26,4,FALSE()) -> Professional, scientific and technical activities | O66: 3 | P66: =+VLOOKUP(O66,bio!$A$2:$B$4,2,FALSE()) -> No bioeconomía
A67: PANoc066 | B67: P11 | C67: =+VLOOKUP(B67,transacciones!$A$1:$I$39,2,FALSE()) -> ATC01 | D67: =+VLOOKUP($B67,transacciones!$A$1:$I$39,4,FALSE()) -> Producción de mercado | E67: =+VLOOKUP($B67,transacciones!$A$1:$I$39,4,FALSE()) -> Producción de mercado | F67: =+VLOOKUP(B67,transacciones!$A$2:$I$39,5,FALSE()) -> 1 | G67: =+VLOOKUP(B67,transacciones!$A$2:$I$39,6,FALSE()) -> P1 | H67: =+VLOOKUP(B67,transacciones!$A$1:$I$39,7,FALSE()) -> Producción | I67: 44.2 | J67: Actividades de arquitectura e ingeniería, ensayos y análisis técnicos | K67: M | L67: =+VLOOKUP(K67,'Correl CIIU'!$A$1:$F$26,2,FALSE()) -> Actividades profesionales, científicas y técnicas | M67: =+VLOOKUP(K67,'Correl CIIU'!$A$1:$F$26,3,FALSE()) -> Servicios profesionales | N67: =+VLOOKUP(K67,'Correl CIIU'!$A$1:$F$26,4,FALSE()) -> Professional, scientific and technical activities | O67: 3 | P67: =+VLOOKUP(O67,bio!$A$2:$B$4,2,FALSE()) -> No bioeconomía
A68: PANoc067 | B68: P11 | C68: =+VLOOKUP(B68,transacciones!$A$1:$I$39,2,FALSE()) -> ATC01 | D68: =+VLOOKUP($B68,transacciones!$A$1:$I$39,4,FALSE()) -> Producción de mercado | E68: =+VLOOKUP($B68,transacciones!$A$1:$I$39,4,FALSE()) -> Producción de mercado | F68: =+VLOOKUP(B68,transacciones!$A$2:$I$39,5,FALSE()) -> 1 | G68: =+VLOOKUP(B68,transacciones!$A$2:$I$39,6,FALSE()) -> P1 | H68: =+VLOOKUP(B68,transacciones!$A$1:$I$39,7,FALSE()) -> Producción | I68: 44.3 M | J68: Investigación científicas y desarrollo | K68: M | L68: =+VLOOKUP(K68,'Correl CIIU'!$A$1:$F$26,2,FALSE()) -> Actividades profesionales, científicas y técnicas | M68: =+VLOOKUP(K68,'Correl CIIU'!$A$1:$F$26,3,FALSE()) -> Servicios profesionales | N68: =+VLOOKUP(K68,'Correl CIIU'!$A$1:$F$26,4,FALSE()) -> Professional, scientific and technical activities | O68: 2 | P68: =+VLOOKUP(O68,bio!$A$2:$B$4,2,FALSE()) -> Bioeconomía extendida
A69: PANoc068 | B69: P11 | C69: =+VLOOKUP(B69,transacciones!$A$1:$I$39,2,FALSE()) -> ATC01 | D69: =+VLOOKUP($B69,transacciones!$A$1:$I$39,4,FALSE()) -> Producción de mercado | E69: =+VLOOKUP($B69,transacciones!$A$1:$I$39,4,FALSE()) -> Producción de mercado | F69: =+VLOOKUP(B69,transacciones!$A$2:$I$39,5,FALSE()) -> 1 | G69: =+VLOOKUP(B69,transacciones!$A$2:$I$39,6,FALSE()) -> P1 | H69: =+VLOOKUP(B69,transacciones!$A$1:$I$39,7,FALSE()) -> Producción | I69: 44.4 | J69: Publicidad y estudios de mercados | K69: N | L69: =+VLOOKUP(K69,'Correl CIIU'!$A$1:$F$26,2,FALSE()) -> Actividades de servicios administrativos y de apoyo | M69: =+VLOOKUP(K69,'Correl CIIU'!$A$1:$F$26,3,FALSE()) -> Servicios administrativos | N69: =+VLOOKUP(K69,'Correl CIIU'!$A$1:$F$26,4,FALSE()) -> Administrative and support service activities | O69: 3 | P69: =+VLOOKUP(O69,bio!$A$2:$B$4,2,FALSE()) -> No bioeconomía
A70: PANoc069 | B70: P11 | C70: =+VLOOKUP(B70,transacciones!$A$1:$I$39,2,FALSE()) -> ATC01 | D70: =+VLOOKUP($B70,transacciones!$A$1:$I$39,4,FALSE()) -> Producción de mercado | E70: =+VLOOKUP($B70,transacciones!$A$1:$I$39,4,FALSE()) -> Producción de mercado | F70: =+VLOOKUP(B70,transacciones!$A$2:$I$39,5,FALSE()) -> 1 | G70: =+VLOOKUP(B70,transacciones!$A$2:$I$39,6,FALSE()) -> P1 | H70: =+VLOOKUP(B70,transacciones!$A$1:$I$39,7,FALSE()) -> Producción | I70: 44.5 | J70: Otras actividades profesionales, científicas y técnicas | K70: M | L70: =+VLOOKUP(K70,'Correl CIIU'!$A$1:$F$26,2,FALSE()) -> Actividades profesionales, científicas y técnicas | M70: =+VLOOKUP(K70,'Correl CIIU'!$A$1:$F$26,3,FALSE()) -> Servicios profesionales | N70: =+VLOOKUP(K70,'Correl CIIU'!$A$1:$F$26,4,FALSE()) -> Professional, scientific and technical activities | O70: 2 | P70: =+VLOOKUP(O70,bio!$A$2:$B$4,2,FALSE()) -> Bioeconomía extendida
A71: PANoc070 | B71: P11 | C71: =+VLOOKUP(B71,transacciones!$A$1:$I$39,2,FALSE()) -> ATC01 | D71: =+VLOOKUP($B71,transacciones!$A$1:$I$39,4,FALSE()) -> Producción de mercado | E71: =+VLOOKUP($B71,transacciones!$A$1:$I$39,4,FALSE()) -> Producción de mercado | F71: =+VLOOKUP(B71,transacciones!$A$2:$I$39,5,FALSE()) -> 1 | G71: =+VLOOKUP(B71,transacciones!$A$2:$I$39,6,FALSE()) -> P1 | H71: =+VLOOKUP(B71,transacciones!$A$1:$I$39,7,FALSE()) -> Producción | I71: 44.6 M | J71: Actividades de servicio administrativo y de apoyo | K71: M | L71: =+VLOOKUP(K71,'Correl CIIU'!$A$1:$F$26,2,FALSE()) -> Actividades profesionales, científicas y técnicas | M71: =+VLOOKUP(K71,'Correl CIIU'!$A$1:$F$26,3,FALSE()) -> Servicios profesionales | N71: =+VLOOKUP(K71,'Correl CIIU'!$A$1:$F$26,4,FALSE()) -> Professional, scientific and technical activities | O71: 3 | P71: =+VLOOKUP(O71,bio!$A$2:$B$4,2,FALSE()) -> No bioeconomía
A72: PANoc071 | B72: P11 | C72: =+VLOOKUP(B72,transacciones!$A$1:$I$39,2,FALSE()) -> ATC01 | D72: =+VLOOKUP($B72,transacciones!$A$1:$I$39,4,FALSE()) -> Producción de mercado | E72: =+VLOOKUP($B72,transacciones!$A$1:$I$39,4,FALSE()) -> Producción de mercado | F72: =+VLOOKUP(B72,transacciones!$A$2:$I$39,5,FALSE()) -> 1 | G72: =+VLOOKUP(B72,transacciones!$A$2:$I$39,6,FALSE()) -> P1 | H72: =+VLOOKUP(B72,transacciones!$A$1:$I$39,7,FALSE()) -> Producción | I72: 45.1 M | J72: Enseñanza | K72: P | L72: =+VLOOKUP(K72,'Correl CIIU'!$A$1:$F$26,2,FALSE()) -> Enseñanza | M72: =+VLOOKUP(K72,'Correl CIIU'!$A$1:$F$26,3,FALSE()) -> Enseñanza | N72: =+VLOOKUP(K72,'Correl CIIU'!$A$1:$F$26,4,FALSE()) -> Education | O72: 3 | P72: =+VLOOKUP(O72,bio!$A$2:$B$4,2,FALSE()) -> No bioeconomía
A73: PANoc072 | B73: P11 | C73: =+VLOOKUP(B73,transacciones!$A$1:$I$39,2,FALSE()) -> ATC01 | D73: =+VLOOKUP($B73,transacciones!$A$1:$I$39,4,FALSE()) -> Producción de mercado | E73: =+VLOOKUP($B73,transacciones!$A$1:$I$39,4,FALSE()) -> Producción de mercado | F73: =+VLOOKUP(B73,transacciones!$A$2:$I$39,5,FALSE()) -> 1 | G73: =+VLOOKUP(B73,transacciones!$A$2:$I$39,6,FALSE()) -> P1 | H73: =+VLOOKUP(B73,transacciones!$A$1:$I$39,7,FALSE()) -> Producción | I73: 46.1 M | J73: Actividades de atención de la salud humana y de asistencia social | K73: Q | L73: =+VLOOKUP(K73,'Correl CIIU'!$A$1:$F$26,2,FALSE()) -> Actividades de atención de la salud humana y de asistencia social | M73: =+VLOOKUP(K73,'Correl CIIU'!$A$1:$F$26,3,FALSE()) -> Salud | N73: =+VLOOKUP(K73,'Correl CIIU'!$A$1:$F$26,4,FALSE()) -> Human health and social work activities | O73: 3 | P73: =+VLOOKUP(O73,bio!$A$2:$B$4,2,FALSE()) -> No bioeconomía
A74: PANoc073 | B74: P11 | C74: =+VLOOKUP(B74,transacciones!$A$1:$I$39,2,FALSE()) -> ATC01 | D74: =+VLOOKUP($B74,transacciones!$A$1:$I$39,4,FALSE()) -> Producción de mercado | E74: =+VLOOKUP($B74,transacciones!$A$1:$I$39,4,FALSE()) -> Producción de mercado | F74: =+VLOOKUP(B74,transacciones!$A$2:$I$39,5,FALSE()) -> 1 | G74: =+VLOOKUP(B74,transacciones!$A$2:$I$39,6,FALSE()) -> P1 | H74: =+VLOOKUP(B74,transacciones!$A$1:$I$39,7,FALSE()) -> Producción | I74: 47.1 M | J74: Actividades artísticas, de entretenimiento y recreativas | K74: S | L74: =+VLOOKUP(K74,'Correl CIIU'!$A$1:$F$26,2,FALSE()) -> Otras actividades de servicios | M74: =+VLOOKUP(K74,'Correl CIIU'!$A$1:$F$26,3,FALSE()) -> Otros servicios | N74: =+VLOOKUP(K74,'Correl CIIU'!$A$1:$F$26,4,FALSE()) -> Other service activities | O74: 3 | P74: =+VLOOKUP(O74,bio!$A$2:$B$4,2,FALSE()) -> No bioeconomía
A75: PANoc074 | B75: P11 | C75: =+VLOOKUP(B75,transacciones!$A$1:$I$39,2,FALSE()) -> ATC01 | D75: =+VLOOKUP(B75,transacciones!$A$1:$I$39,3,FALSE()) -> Producción / Consumo intermedio | E75: =+VLOOKUP($B75,transacciones!$A$1:$I$39,4,FALSE()) -> Producción de mercado | F75: =+VLOOKUP(B75,transacciones!$A$2:$I$39,5,FALSE()) -> 1 | G75: =+VLOOKUP(B75,transacciones!$A$2:$I$39,6,FALSE()) -> P1 | H75: =+VLOOKUP(B75,transacciones!$A$1:$I$39,7,FALSE()) -> Producción | I75: 48.1 M | J75: Otras actividades de servicio | K75: S | L75: =+VLOOKUP(K75,'Correl CIIU'!$A$1:$F$26,2,FALSE()) -> Otras actividades de servicios | M75: =+VLOOKUP(K75,'Correl CIIU'!$A$1:$F$26,3,FALSE()) -> Otros servicios | N75: =+VLOOKUP(K75,'Correl CIIU'!$A$1:$F$26,4,FALSE()) -> Other service activities | O75: 3 | P75: =+VLOOKUP(O75,bio!$A$2:$B$4,2,FALSE()) -> No bioeconomía
A76: PANoc075 | J76: P.11 SUBTOTAL PRODUCCION DE MERCADO
A77: PANoc076 | B77: P12 | C77: =+VLOOKUP(B77,transacciones!$A$1:$I$39,2,FALSE()) -> ATC01 | D77: =+VLOOKUP(B77,transacciones!$A$1:$I$39,3,FALSE()) -> Producción / Consumo intermedio | E77: =+VLOOKUP($B77,transacciones!$A$1:$I$39,4,FALSE()) -> Producción para uso final propio | F77: =+VLOOKUP(B77,transacciones!$A$2:$I$39,5,FALSE()) -> 1 | G77: =+VLOOKUP(B77,transacciones!$A$2:$I$39,6,FALSE()) -> P1 | H77: =+VLOOKUP(B77,transacciones!$A$1:$I$39,7,FALSE()) -> Producción | I77: 36.1 UFP | J77: Construcción de edificios | K77: F | L77: Construcción | M77: Construcción | N77: Construction | O77: 3 | P77: No bioeconomía
A78: PANoc077 | B78: P12 | C78: =+VLOOKUP(B78,transacciones!$A$1:$I$39,2,FALSE()) -> ATC01 | D78: =+VLOOKUP(B78,transacciones!$A$1:$I$39,3,FALSE()) -> Producción / Consumo intermedio | E78: =+VLOOKUP($B78,transacciones!$A$1:$I$39,4,FALSE()) -> Producción para uso final propio | F78: =+VLOOKUP(B78,transacciones!$A$2:$I$39,5,FALSE()) -> 1 | G78: =+VLOOKUP(B78,transacciones!$A$2:$I$39,6,FALSE()) -> P1 | H78: =+VLOOKUP(B78,transacciones!$A$1:$I$39,7,FALSE()) -> Producción | I78: 43.1 UFP | J78: Alquiler de viviendas | K78: L | L78: Actividades inmobiliarias | M78: Inmobiliarios | N78: Real estate activities | O78: 3 | P78: No bioeconomía
A79: PANoc078 | B79: P12 | C79: =+VLOOKUP(B79,transacciones!$A$1:$I$39,2,FALSE()) -> ATC01 | D79: =+VLOOKUP(B79,transacciones!$A$1:$I$39,3,FALSE()) -> Producción / Consumo intermedio | E79: =+VLOOKUP($B79,transacciones!$A$1:$I$39,4,FALSE()) -> Producción para uso final propio | F79: =+VLOOKUP(B79,transacciones!$A$2:$I$39,5,FALSE()) -> 1 | G79: =+VLOOKUP(B79,transacciones!$A$2:$I$39,6,FALSE()) -> P1 | H79: =+VLOOKUP(B79,transacciones!$A$1:$I$39,7,FALSE()) -> Producción | I79: 49.1 | J79: Actividades de los hogares como empleadores de personal doméstico | K79: T | L79: Actividades de los hogares como empleadores; actividades no diferenciadas de los hogares como productores de bienes y servicios para uso propio | M79: Hogares como empleadores | N79: Activities of households as employers; undifferentiated goods- and services-producing activities of households for own use | O79: 3 | P79: No bioeconomía
A80: PANoc079 | J80: P.12 SUBTOTAL PRODUCCION PARA USO FINAL PROPIO
A81: PANoc080 | B81: P13 | C81: ATC01 | D81: Otra producción no de mercado | E81: Otra producción no de mercado | F81: 1 | G81: P1 | H81: Producción | I81: 35.2 NM | J81: Recogida, tratamiento y eliminación de desechos, recuperación de materiales y actividades de descontaminación y otros servicios de eliminación de desechos | K81: E | L81: =+VLOOKUP(K81,'Correl CIIU'!$A$1:$F$26,2,FALSE()) -> Suministro de agua; evacuación de aguas residuales, gestión de desechos y descontaminación | M81: =+VLOOKUP(K81,'Correl CIIU'!$A$1:$F$26,3,FALSE()) -> Suministro de agua | N81: =+VLOOKUP(K81,'Correl CIIU'!$A$1:$F$26,4,FALSE()) -> Water supply; sewerage, waste management and remediation activities | O81: 2 | P81: =+VLOOKUP(O81,bio!$A$2:$B$4,2,FALSE()) -> Bioeconomía extendida
A82: PANoc081 | B82: P13 | C82: ATC01 | D82: Otra producción no de mercado | E82: Otra producción no de mercado | F82: 1 | G82: P1 | H82: Producción | I82: 41.1 NM | J82: Actividades de información y comunicación excluída telecomunicaciones | K82: J | L82: Información y comunicaciones | M82: Información y comunicaciones | N82: Information and communication | O82: 3 | P82: No bioeconomía
A83: PANoc082 | B83: P13 | C83: ATC01 | D83: Otra producción no de mercado | E83: Otra producción no de mercado | F83: 1 | G83: P1 | H83: Producción | I83: 44.3 NM | J83: Investigación científicas y desarrollo | K83: M | L83: =+VLOOKUP(K83,'Correl CIIU'!$A$1:$F$26,2,FALSE()) -> Actividades profesionales, científicas y técnicas | M83: =+VLOOKUP(K83,'Correl CIIU'!$A$1:$F$26,3,FALSE()) -> Servicios profesionales | N83: =+VLOOKUP(K83,'Correl CIIU'!$A$1:$F$26,4,FALSE()) -> Professional, scientific and technical activities | O83: 2 | P83: =+VLOOKUP(O83,bio!$A$2:$B$4,2,FALSE()) -> Bioeconomía extendida
A84: PANoc083 | B84: P13 | C84: ATC01 | D84: Otra producción no de mercado | E84: Otra producción no de mercado | F84: 1 | G84: P1 | H84: Producción | I84: 50.1 | J84: Administración pública y defensa; exceptos planes de seguridad social de afiliación obligatoria | K84: O | L84: =+VLOOKUP(K84,'Correl CIIU'!$A$1:$F$26,2,FALSE()) -> Administración pública y defensa; planes de seguridad social de afiliación obligatoria | M84: =+VLOOKUP(K84,'Correl CIIU'!$A$1:$F$26,3,FALSE()) -> Administración pública | N84: =+VLOOKUP(K84,'Correl CIIU'!$A$1:$F$26,4,FALSE()) -> Public administration and defence; compulsory social security | O84: 3 | P84: =+VLOOKUP(O84,bio!$A$2:$B$4,2,FALSE()) -> No bioeconomía
A85: PANoc084 | B85: P13 | C85: ATC01 | D85: Otra producción no de mercado | E85: Otra producción no de mercado | F85: 1 | G85: P1 | H85: Producción | I85: 50.2 | J85: Prestación de servicios a la comunidad en general | K85: R | L85: =+VLOOKUP(K85,'Correl CIIU'!$A$1:$F$26,2,FALSE()) -> Actividades artísticas, de entretenimiento y recreativas | M85: =+VLOOKUP(K85,'Correl CIIU'!$A$1:$F$26,3,FALSE()) -> Recreación | N85: =+VLOOKUP(K85,'Correl CIIU'!$A$1:$F$26,4,FALSE()) -> Arts, entertainment and recreation | O85: 3 | P85: =+VLOOKUP(O85,bio!$A$2:$B$4,2,FALSE()) -> No bioeconomía
A86: PANoc085 | B86: P13 | C86: ATC01 | D86: Otra producción no de mercado | E86: Otra producción no de mercado | F86: 1 | G86: P1 | H86: Producción | I86: 50.3 | J86: Actividades de planes de seguridad social de afiliación obligatoria | K86: O | L86: =+VLOOKUP(K86,'Correl CIIU'!$A$1:$F$26,2,FALSE()) -> Administración pública y defensa; planes de seguridad social de afiliación obligatoria | M86: =+VLOOKUP(K86,'Correl CIIU'!$A$1:$F$26,3,FALSE()) -> Administración pública | N86: =+VLOOKUP(K86,'Correl CIIU'!$A$1:$F$26,4,FALSE()) -> Public administration and defence; compulsory social security | O86: 3 | P86: =+VLOOKUP(O86,bio!$A$2:$B$4,2,FALSE()) -> No bioeconomía
A87: PANoc086 | B87: P13 | C87: ATC01 | D87: Otra producción no de mercado | E87: Otra producción no de mercado | F87: 1 | G87: P1 | H87: Producción | I87: 45.1 NM | J87: Enseñanza | K87: P | L87: =+VLOOKUP(K87,'Correl CIIU'!$A$1:$F$26,2,FALSE()) -> Enseñanza | M87: =+VLOOKUP(K87,'Correl CIIU'!$A$1:$F$26,3,FALSE()) -> Enseñanza | N87: =+VLOOKUP(K87,'Correl CIIU'!$A$1:$F$26,4,FALSE()) -> Education | O87: 3 | P87: =+VLOOKUP(O87,bio!$A$2:$B$4,2,FALSE()) -> No bioeconomía
A88: PANoc087 | B88: P13 | C88: ATC01 | D88: Otra producción no de mercado | E88: Otra producción no de mercado | F88: 1 | G88: P1 | H88: Producción | I88: 46.1 NM | J88: Actividades de atención de la salud humana y de asistencia social | K88: Q | L88: =+VLOOKUP(K88,'Correl CIIU'!$A$1:$F$26,2,FALSE()) -> Actividades de atención de la salud humana y de asistencia social | M88: =+VLOOKUP(K88,'Correl CIIU'!$A$1:$F$26,3,FALSE()) -> Salud | N88: =+VLOOKUP(K88,'Correl CIIU'!$A$1:$F$26,4,FALSE()) -> Human health and social work activities | O88: 3 | P88: =+VLOOKUP(O88,bio!$A$2:$B$4,2,FALSE()) -> No bioeconomía
A89: PANoc088 | B89: P13 | C89: ATC01 | D89: Otra producción no de mercado | E89: Otra producción no de mercado | F89: 1 | G89: P1 | H89: Producción | I89: 47.1 NM | J89: Actividades artísticas, de entretenimiento y recreativas | K89: S | L89: =+VLOOKUP(K89,'Correl CIIU'!$A$1:$F$26,2,FALSE()) -> Otras actividades de servicios | M89: =+VLOOKUP(K89,'Correl CIIU'!$A$1:$F$26,3,FALSE()) -> Otros servicios | N89: =+VLOOKUP(K89,'Correl CIIU'!$A$1:$F$26,4,FALSE()) -> Other service activities | O89: 3 | P89: =+VLOOKUP(O89,bio!$A$2:$B$4,2,FALSE()) -> No bioeconomía
A90: PANoc089 | B90: P13 | C90: ATC01 | D90: Otra producción no de mercado | E90: Otra producción no de mercado | F90: 1 | G90: P1 | H90: Producción | I90: 48.1 NM | J90: Otras actividades de servicio | K90: S | L90: =+VLOOKUP(K90,'Correl CIIU'!$A$1:$F$26,2,FALSE()) -> Otras actividades de servicios | M90: =+VLOOKUP(K90,'Correl CIIU'!$A$1:$F$26,3,FALSE()) -> Otros servicios | N90: =+VLOOKUP(K90,'Correl CIIU'!$A$1:$F$26,4,FALSE()) -> Other service activities | O90: 3 | P90: =+VLOOKUP(O90,bio!$A$2:$B$4,2,FALSE()) -> No bioeconomía
A91: PANoc090 | J91: P.13 SUBTOTAL OTRA PRODUCCION NO DE MERCADO | K91: - | L91: - | M91: - | N91: - | O91: - | P91: -
A92: PANoc091 | J92: P.1 TOTAL PRODUCCION (precios básicos)
A93: PANoc092 | B93: P71 | C93: =+VLOOKUP(B93,transacciones!$A$1:$I$39,2,FALSE()) -> ATC02 | D93: =+VLOOKUP($B93,transacciones!$A$1:$I$39,4,FALSE()) -> Importaciones de bienes | E93: =+VLOOKUP($B93,transacciones!$A$1:$I$39,4,FALSE()) -> Importaciones de bienes | F93: =+VLOOKUP(B93,transacciones!$A$2:$I$39,5,FALSE()) -> 7 | G93: =+VLOOKUP(B93,transacciones!$A$2:$I$39,6,FALSE()) -> P7 | H93: =+VLOOKUP(B93,transacciones!$A$1:$I$39,7,FALSE()) -> Importaciones de bienes y servicios | I93: IMPORTACIÓN | J93: P.71 BIENES | K93: - | L93: - | M93: - | N93: - | O93: - | P93: -
A94: PANoc093 | B94: P72 | C94: =+VLOOKUP(B94,transacciones!$A$1:$I$39,2,FALSE()) -> ATC02 | D94: =+VLOOKUP($B94,transacciones!$A$1:$I$39,4,FALSE()) -> Importaciones de servicios | E94: =+VLOOKUP($B94,transacciones!$A$1:$I$39,4,FALSE()) -> Importaciones de servicios | F94: =+VLOOKUP(B94,transacciones!$A$2:$I$39,5,FALSE()) -> 7 | G94: =+VLOOKUP(B94,transacciones!$A$2:$I$39,6,FALSE()) -> P7 | H94: =+VLOOKUP(B94,transacciones!$A$1:$I$39,7,FALSE()) -> Importaciones de bienes y servicios | I94: IMPORTACIÓN | J94: P.72 SERVICIOS | K94: - | L94: - | M94: - | N94: - | O94: - | P94: -
A95: PANoc094 | J95: P.7 TOTAL | K95: - | L95: - | M95: - | N95: - | O95: - | P95: -
A96: PANoc095 | B96: CIF | C96: =+VLOOKUP(B96,transacciones!$A$1:$I$39,2,FALSE()) -> ATC03 | D96: =+VLOOKUP($B96,transacciones!$A$1:$I$39,4,FALSE()) -> Ajuste CIF/FOB sobre importaciones | E96: =+VLOOKUP($B96,transacciones!$A$1:$I$39,4,FALSE()) -> Ajuste CIF/FOB sobre importaciones | F96: =+VLOOKUP(B96,transacciones!$A$2:$I$39,5,FALSE()) -> 8 | G96: =+VLOOKUP(B96,transacciones!$A$2:$I$39,6,FALSE()) -> CIF | H96: =+VLOOKUP(B96,transacciones!$A$1:$I$39,7,FALSE()) -> Ajuste CIF/FOB sobre importaciones | I96: AJUSTE CIF/FOB SOBRE IMPORTACIONES | J96: AJUSTE CIF/FOB SOBRE IMPORTACIONES | K96: - | L96: - | M96: - | N96: - | O96: - | P96: -
A97: PANoc096 | J97: TOTAL OFERTA (a precios básicos) | K97: - | L97: - | M97: - | N97: - | O97: - | P97: -
A98: PANoc097 | B98: D211 | C98: =+VLOOKUP(B98,transacciones!$A$1:$I$39,2,FALSE()) -> ATC04 | D98: =+VLOOKUP($B98,transacciones!$A$1:$I$39,4,FALSE()) -> Impuestos tipo valor agregado (IVA) | E98: =+VLOOKUP($B98,transacciones!$A$1:$I$39,4,FALSE()) -> Impuestos tipo valor agregado (IVA) | F98: =+VLOOKUP(B98,transacciones!$A$2:$I$39,5,FALSE()) -> 9 | G98: =+VLOOKUP(B98,transacciones!$A$2:$I$39,6,FALSE()) -> D2 | H98: =+VLOOKUP(B98,transacciones!$A$1:$I$39,7,FALSE()) -> Impuestos sobre la producción y las importaciones | I98: D.211 IMPUESTOS TIPO IVA | J98: D.211 IMPUESTOS TIPO VALOR AGREGADO (IVA) | K98: - | L98: - | M98: - | N98: - | O98: - | P98: -
A99: PANoc098 | B99: D212 | C99: =+VLOOKUP(B99,transacciones!$A$1:$I$39,2,FALSE()) -> ATC04 | D99: =+VLOOKUP($B99,transacciones!$A$1:$I$39,4,FALSE()) -> Impuestos y derechos sobre las importaciones excepto IVA | E99: =+VLOOKUP($B99,transacciones!$A$1:$I$39,4,FALSE()) -> Impuestos y derechos sobre las importaciones excepto IVA | F99: =+VLOOKUP(B99,transacciones!$A$2:$I$39,5,FALSE()) -> 9 | G99: =+VLOOKUP(B99,transacciones!$A$2:$I$39,6,FALSE()) -> D2 | H99: =+VLOOKUP(B99,transacciones!$A$1:$I$39,7,FALSE()) -> Impuestos sobre la producción y las importaciones | I99: D.212 | J99: D.212 IMPUESTOS Y DERECHOS SOBRE IMPORTACIÓN | K99: - | L99: - | M99: - | N99: - | O99: - | P99: -
A100: PANoc099 | B100: D213 | C100: =+VLOOKUP(B100,transacciones!$A$1:$I$39,2,FALSE()) -> ATC04 | D100: =+VLOOKUP($B100,transacciones!$A$1:$I$39,4,FALSE()) -> Impuestos sobre las exportaciones | E100: =+VLOOKUP($B100,transacciones!$A$1:$I$39,4,FALSE()) -> Impuestos sobre las exportaciones | F100: =+VLOOKUP(B100,transacciones!$A$2:$I$39,5,FALSE()) -> 9 | G100: =+VLOOKUP(B100,transacciones!$A$2:$I$39,6,FALSE()) -> D2 | H100: =+VLOOKUP(B100,transacciones!$A$1:$I$39,7,FALSE()) -> Impuestos sobre la producción y las importaciones | I100: D.213 | J100: D.213 IMPUESTOS SOBRE LA EXPORTACIÓN | K100: - | L100: - | M100: - | N100: - | O100: - | P100: -
...

Sheet Correl CIIU
A1: CIIU Secciones | B1: CIIU Secciones descripción | C1: CIIU Corto | D1: CIIU English
A2: A | B2: Agricultura, ganadería, silvicultura y pesca | C2: Agricultura | D2: Agriculture, forestry and fishing
A3: B | B3: Explotación de minas y canteras | C3: Minería | D3: Mining and quarrying
A4: C | B4: Industrias manufactureras | C4: Manufacturas | D4: Manufacturing
A5: C | B5: Industrias manufactureras | C5: Manufacturas | D5: Manufacturing
A6: C | B6: Industrias manufactureras | C6: Manufacturas | D6: Manufacturing
A7: D | B7: Suministro de electricidad, gas, vapor y aire acondicionado | C7: Servicios básicos | D7: Electricity, gas, steam and air conditioning supply
A8: E | B8: Suministro de agua; evacuación de aguas residuales, gestión de desechos y descontaminación | C8: Suministro de agua | D8: Water supply; sewerage, waste management and remediation activities
A9: F | B9: Construcción | C9: Construcción | D9: Construction
A10: G | B10: Comercio al por mayor y al por menor; reparación de vehículos automotores y motocicletas | C10: Comercio | D10: Wholesale and retail trade; repair of motor vehicles and motorcycles
A11: H | B11: Transporte y almacenamiento | C11: Transporte y almacenamiento | D11: Transportation and storage
A12: J | B12: Información y comunicaciones | C12: Información y comunicaciones | D12: Information and communication
... A26: - | B26: - | C26: - | D26: -

Sheet at_columnas
A1: Código Transacciones | B1: Área transaccional columnas No. | C1: Área transaccional | D1: Transacciones | E1: Correlativo Transacciones Agregadas | F1: Código Transacciones Agregadas | G1: Transacciones Agregadas | H1: corr_ntg2 | I1: id_area_columnas
A2: P10 | B2: ATC01 | C2: Producción / Consumo intermedio | D2: Producción | E2: 1 | F2: P1 | G2: Producción | H2: 1 | I2: 0
A3: P11 | B3: ATC01 | C3: Producción / Consumo intermedio | D3: Producción de mercado | E3: 1 | F3: P1 | G3: Producción | H3: 2 | I3: 1
A4: P12 | B4: ATC01 | C4: Producción / Consumo intermedio | D4: Producción para uso final propio | E4: 1 | F4: P1 | G4: Producción | H4: 3 | I4: 2
A5: P13 | B5: ATC01 | C5: Producción / Consumo intermedio | D5: Otra producción no de mercado | E5: 1 | F5: P1 | G5: Producción | H5: 4 | I5: 3
A6: P20 | B6: ATC01 | C6: Producción / Consumo intermedio | D6: Consumo | E6: 2 | F6: P2 | G6: Consumo intermedio | H6: 5 | I6: 0
A7: P21 | B7: ATC01 | C7: Producción / Consumo intermedio | D7: Consumo intermedio de mercado | E7: 2 | F7: P2 | G7: Consumo intermedio | H7: 6 | I7: 1
A8: P22 | B8: ATC01 | C8: Producción / Consumo intermedio | D8: Consumo intermedio para uso final propio | E8: 2 | F8: P2 | G8: Consumo intermedio | H8: 7 | I8: 2
A9: P23 | B9: ATC01 | C9: Producción / Consumo intermedio | D9: Consumo intermedio no de mercado | E9: 2 | F9: P2 | G9: Consumo intermedio | H9: 8 | I9: 3
A10: Pa31 | B10: ATC06 | C10: Gasto de consumo final | D10: Gasto de consumo final de los hogares | E10: 3 | F10: P3 | G10: Gasto de consumo final | H10: 9 | I10: 9
A11: Pb30 | B11: ATC06 | C11: Consumo final | D11: Gasto de consumo ISFLH | E11: 3 | F11: P3 | G11: Gasto de consumo final | H11: 10 | I11: 9
A12: Pb31 | B12: ATC06 | C12: Consumo final | D12: Gasto de consumo individual ISFLSH | E12: 3 | F12: P3 | G12: Gasto de consumo final | H12: 11 | I12: 9
A13: Pb32 | B13: ATC06 | C13: Consumo final | D13: Gasto de consumo colectivo ISFLSH | E13: 3 | F13: P3 | G13: Gasto de consumo final | H13: 12 | I13: 9
A14: Pc30 | B14: ATC06 | C14: Consumo final | D14: Gasto de consumo de gobierno | E14: 3 | F14: P3 | G14: Gasto de consumo final
A15: Pc31 | B15: ATC06 | C15: Consumo final | D15: Gasto de consumo individual de gobierno | E15: 3 | F15: P3 | G15: Gasto de consumo final | H15: 13 | I15: 9
A16: Pc32 | B16: ATC06 | C16: Consumo final | D16: Gasto de consumo colectivo de gobierno | E16: 3 | F16: P3 | G16: Gasto de consumo final | H16: 14 | I16: 9
A17: P41 | B17: ATC06 | C17: Consumo final | D17: Consumo individual efectivo | E17: 4 | F17: P4 | G17: Consumo final efectivo | H17: 15 | I17: 9
A18: P42 | B18: ATC06 | C18: Consumo final | D18: Consumo colectivo efectivo | E18: 4 | F18: P4 | G18: Consumo final efectivo | H18: 16 | I18: 9
A19: P51b | B19: ATC07 | C19: Consumo final | D19: Formación bruta de capital fijo | E19: 5 | F19: P5 | G19: Formación de capital | H19: 17 | I19: 10
A20: P51c | B20: ATC07 | C20: Consumo final | D20: Consumo de capital fijo | E20: 5 | F20: P5 | G20: Formación de capital | H20: 18 | I20: 10
A21: P52 | B21: ATC07 | C21: Consumo final | D21: Variación de existencias | E21: 5 | F21: P5 | G21: Formación de capital | H21: 19 | I21: 10
A22: P53 | B22: ATC07 | C22: Consumo final | D22: Adquisiciones menos disposiciones de objetos valiosos | E22: 5 | F22: P5 | G22: Formación de capital | H22: 20 | I22: 10
A23: P60 | B23: ATC02 | C23: Exportaciones / Importaciones | D23: Exportaciones de bienes y servicios | E23: 6 | F23: P6 | G23: Exportaciones de bienes y servicios | H23: 21 | I23: 4
A24: P61 | B24: ATC02 | C24: Exportaciones / Importaciones | D24: Exportaciones de bienes | E24: 6 | F24: P6 | G24: Exportaciones de bienes y servicios | H24: 22 | I24: 4
A25: P62 | B25: ATC02 | C25: Exportaciones / Importaciones | D25: Exportaciones de servicios | E25: 6 | F25: P6 | G25: Exportaciones de bienes y servicios | H25: 23 | I25: 4
A26: P70 | B26: ATC02 | C26: Exportaciones / Importaciones | D26: Importaciones de bienes y servicios | E26: 7 | F26: P7 | G26: Importaciones de bienes y servicios | H26: 24
A27: P71 | B27: ATC02 | C27: Exportaciones / Importaciones | D27: Importaciones de bienes | E27: 7 | F27: P7 | G27: Importaciones de bienes y servicios | H27: 25 | I27: 4
A28: P72 | B28: ATC02 | C28: Exportaciones / Importaciones | D28: Importaciones de servicios | E28: 7 | F28: P7 | G28: Importaciones de bienes y servicios | H28: 26 | I28: 4
A29: CIF | B29: ATC03 | C29: Ajuste CIF/FOB | D29: Ajuste CIF/FOB sobre importaciones | E29: 8 | F29: CIF | G29: Ajuste CIF/FOB sobre importaciones | H29: 27 | I29: 5
A30: D211 | B30: ATC04 | C30: Impuestos menos subvenciones sobre los productos | D30: Impuestos tipo valor agregado (IVA) | E30: 9 | F30: D2 | G30: Impuestos sobre la producción y las importaciones | H30: 28 | I30: 6
A31: D212 | B31: ATC04 | C31: Impuestos menos subvenciones sobre los productos | D31: Impuestos y derechos sobre las importaciones excepto IVA | E31: 9 | F31: D2 | G31: Impuestos sobre la producción y las importaciones | H31: 29 | I31: 6
A32: D213 | B32: ATC04 | C32: Impuestos menos subvenciones sobre los productos | D32: Impuestos sobre las exportaciones | E32: 9 | F32: D2 | G32: Impuestos sobre la producción y las importaciones | H32: 30 | I32: 6
A33: D214 | B33: ATC04 | C33: Impuestos menos subvenciones sobre los productos | D33: Impuestos sobre los productos, excepto IVA e impuestos sobre las importaciones | E33: 9 | F33: D2 | G33: Impuestos sobre la producción y las importaciones | H33: 31 | I33: 6
A34: D291 | B34: ATC04 | C34: Impuestos menos subvenciones sobre los productos | D34: Otros impuestos sobre la producción | E34: 10 | F34: D29 | G34: Otros impuestos sobre la producción | H34: 32 | I34: 6
A35: D31 | B35: ATC04 | C35: Impuestos menos subvenciones sobre los productos | D35: Subvenciones a los productos | E35: 11 | F35: D3 | G35: Subvenciones | H35: 33 | I35: 7
A36: D39 | B36: ATCO4 | C36: Impuestos menos subvenciones sobre los productos | D36: Otras subvenciones a la producción | E36: 11 | F36: D3 | G36: Subvenciones | H36: 34 | I36: 7
A37: M11 | B37: ATC05 | C37: Márgenes de distribución | D37: Márgenes de comercio | E37: 12 | F37: M1 | G37: Márgenes de distribución | H37: 35 | I37: 8
A38: M12 | B38: ATC05 | C38: Márgenes de distribución | D38: Márgenes de transporte | E38: 12 | F38: M1 | G38: Márgenes de distribución | H38: 36 | I38: 8
A39: M13 | B39: ATC05 | C39: Márgenes de distribución | D39: Márgenes de distribución de electricidad | E39: 12 | F39: M1 | G39: Márgenes de distribución | H39: 37 | I39: 8

Sheet transacciones
A1: Código Transacciones | B1: Área transaccional columnas No. | C1: Área transaccional | D1: Transacciones | E1: Correlativo Transacciones Agregadas | F1: Código Transacciones Agregadas | G1: Transacciones Agregadas | H1: corr_ntg2 | I1: id_area_columnas
A2: P10 | B2: ATC01 | C2: Producción / Consumo intermedio | D2: Producción | E2: 1 | F2: P1 | G2: Producción | H2: 1 | I2: 0
A3: P11 | B3: ATC01 | C3: Producción / Consumo intermedio | D3: Producción de mercado | E3: 1 | F3: P1 | G3: Producción | H3: 2 | I3: 1
A4: P12 | B4: ATC01 | C4: Producción / Consumo intermedio | D4: Producción para uso final propio | E4: 1 | F4: P1 | G4: Producción | H4: 3 | I4: 2
A5: P13 | B5: ATC01 | C5: Producción / Consumo intermedio | D5: Otra producción no de mercado | E5: 1 | F5: P1 | G5: Producción | H5: 4 | I5: 3
A6: P20 | B6: ATC01 | C6: Producción / Consumo intermedio | D6: Consumo | E6: 2 | F6: P2 | G6: Consumo intermedio | H6: 5 | I6: 0
A7: P21 | B7: ATC01 | C7: Producción / Consumo intermedio | D7: Consumo intermedio de mercado | E7: 2 | F7: P2 | G7: Consumo intermedio | H7: 6 | I7: 1
A8: P22 | B8: ATC01 | C8: Producción / Consumo intermedio | D8: Consumo intermedio para uso final propio | E8: 2 | F8: P2 | G8: Consumo intermedio | H8: 7 | I8: 2
A9: P23 | B9: ATC01 | C9: Producción / Consumo intermedio | D9: Consumo intermedio no de mercado | E9: 2 | F9: P2 | G9: Consumo intermedio | H9: 8 | I9: 3
A10: Pa31 | B10: ATC06 | C10: Gasto de consumo final | D10: Gasto de consumo final de los hogares | E10: 3 | F10: P3 | G10: Gasto de consumo final | H10: 9 | I10: 9
A11: Pb30 | B11: ATC06 | C11: Consumo final | D11: Gasto de consumo ISFLH | E11: 3 | F11: P3 | G11: Gasto de consumo final | H11: 10 | I11: 9
A12: Pb31 | B12: ATC06 | C12: Consumo final | D12: Gasto de consumo individual ISFLSH | E12: 3 | F12: P3 | G12: Gasto de consumo final | H12: 11 | I12: 9
A13: Pb32 | B13: ATC06 | C13: Consumo final | D13: Gasto de consumo colectivo ISFLSH | E13: 3 | F13: P3 | G13: Gasto de consumo final | H13: 12 | I13: 9
A14: Pc30 | B14: ATC06 | C14: Consumo final | D14: Gasto de consumo de gobierno | E14: 3 | F14: P3 | G14: Gasto de consumo final
A15: Pc31 | B15: ATC06 | C15: Consumo final | D15: Gasto de consumo individual de gobierno | E15: 3 | F15: P3 | G15: Gasto de consumo final | H15: 13 | I15: 9
A16: Pc32 | B16: ATC06 | C16: Consumo final | D16: Gasto de consumo colectivo de gobierno | E16: 3 | F16: P3 | G16: Gasto de consumo final | H16: 14 | I16: 9
A17: P41 | B17: ATC06 | C17: Consumo final | D17: Consumo individual efectivo | E17: 4 | F17: P4 | G17: Consumo final efectivo | H17: 15 | I17: 9
A18: P42 | B18: ATC06 | C18: Consumo final | D18: Consumo colectivo efectivo | E18: 4 | F18: P4 | G18: Consumo final efectivo | H18: 16 | I18: 9
A19: P51b | B19: ATC07 | C19: Consumo final | D19: Formación bruta de capital fijo | E19: 5 | F19: P5 | G19: Formación de capital | H19: 17 | I19: 10
A20: P51c | B20: ATC07 | C20: Consumo final | D20: Consumo de capital fijo | E20: 5 | F20: P5 | G20: Formación de capital | H20: 18 | I20: 10
A21: P52 | B21: ATC07 | C21: Consumo final | D21: Variación de existencias | E21: 5 | F21: P5 | G21: Formación de capital | H21: 19 | I21: 10
A22: P53 | B22: ATC07 | C22: Consumo final | D22: Adquisiciones menos disposiciones de objetos valiosos | E22: 5 | F22: P5 | G22: Formación de capital | H22: 20 | I22: 10
A23: P60 | B23: ATC02 | C23: Exportaciones / Importaciones | D23: Exportaciones de bienes y servicios | E23: 6 | F23: P6 | G23: Exportaciones de bienes y servicios | H23: 21 | I23: 4
A24: P61 | B24: ATC02 | C24: Exportaciones / Importaciones | D24: Exportaciones de bienes | E24: 6 | F24: P6 | G24: Exportaciones de bienes y servicios | H24: 22 | I24: 4
A25: P62 | B25: ATC02 | C25: Exportaciones / Importaciones | D25: Exportaciones de servicios | E25: 6 | F25: P6 | G25: Exportaciones de bienes y servicios | H25: 23 | I25: 4
A26: P70 | B26: ATC02 | C26: Exportaciones / Importaciones | D26: Importaciones de bienes y servicios | E26: 7 | F26: P7 | G26: Importaciones de bienes y servicios | H26: 24
A27: P71 | B27: ATC02 | C27: Exportaciones / Importaciones | D27: Importaciones de bienes | E27: 7 | F27: P7 | G27: Importaciones de bienes y servicios | H27: 25 | I27: 4
A28: P72 | B28: ATC02 | C28: Exportaciones / Importaciones | D28: Importaciones de servicios | E28: 7 | F28: P7 | G28: Importaciones de bienes y servicios | H28: 26 | I28: 4
A29: CIF | B29: ATC03 | C29: Ajuste CIF/FOB | D29: Ajuste CIF/FOB sobre importaciones | E29: 8 | F29: CIF | G29: Ajuste CIF/FOB sobre importaciones | H29: 27 | I29: 5
A30: D211 | B30: ATC04 | C30: Impuestos menos subvenciones sobre los productos | D30: Impuestos tipo valor agregado (IVA) | E30: 9 | F30: D2 | G30: Impuestos sobre la producción y las importaciones | H30: 28 | I30: 6
A31: D212 | B31: ATC04 | C31: Impuestos menos subvenciones sobre los productos | D31: Impuestos y derechos sobre las importaciones excepto IVA | E31: 9 | F31: D2 | G31: Impuestos sobre la producción y las importaciones | H31: 29 | I31: 6
A32: D213 | B32: ATC04 | C32: Impuestos menos subvenciones sobre los productos | D32: Impuestos sobre las exportaciones | E32: 9 | F32: D2 | G32: Impuestos sobre la producción y las importaciones | H32: 30 | I32: 6
A33: D214 | B33: ATC04 | C33: Impuestos menos subvenciones sobre los productos | D33: Impuestos sobre los productos, excepto IVA e impuestos sobre las importaciones | E33: 9 | F33: D2 | G33: Impuestos sobre la producción y las importaciones | H33: 31 | I33: 6
A34: D291 | B34: ATC04 | C34: Impuestos menos subvenciones sobre los productos | D34: Otros impuestos sobre la producción | E34: 10 | F34: D29 | G34: Otros impuestos sobre la producción | H34: 32 | I34: 6
A35: D31 | B35: ATC04 | C35: Impuestos menos subvenciones sobre los productos | D35: Subvenciones a los productos | E35: 11 | F35: D3 | G35: Subvenciones | H35: 33 | I35: 7
A36: D39 | B36: ATCO4 | C36: Impuestos menos subvenciones sobre los productos | D36: Otras subvenciones a la producción | E36: 11 | F36: D3 | G36: Subvenciones | H36: 34 | I36: 7
A37: M11 | B37: ATC05 | C37: Márgenes de distribución | D37: Márgenes de comercio | E37: 12 | F37: M1 | G37: Márgenes de distribución | H37: 35 | I37: 8
A38: M12 | B38: ATC05 | C38: Márgenes de distribución | D38: Márgenes de transporte | E38: 12 | F38: M1 | G38: Márgenes de distribución | H38: 36 | I38: 8
A39: M13 | B39: ATC05 | C39: Márgenes de distribución | D39: Márgenes de distribución de electricidad | E39: 12 | F39: M1 | G39: Márgenes de distribución | H39: 37 | I39: 8

Sheet AT_FILAS
A1: Áreas Transaccionales Filas No. | B1: Áreas Transaccionales Filas Descripción | C1: Codigo Transacción Filas
A2: ATF01 | B2: Producción | C2: 1
A3: ATF02 | B3: Consumo intermedio | C3: 2
A4: ATF03 | B4: Ajuste CIF/FOB | C4: 3
A5: ATF04 | B5: Compras directas en el exterior por residentes | C5: 4
A6: ATF05 | B6: Compras directas en el territorio nacional por no residentes | C6: 5
A7: ATF06 | B7: Valor Agregado | C7: 6
A8: ATF07 | B8: Puestos de trabajo | C8: 7

Sheet filas
A1: Filas | B1: Áreas Transaccionales Filas No. | C1: Áreas Transaccionales Filas Descripción | D1: Codigo Transacción Filas | E1: Código Nomenclatura Local de Productos | F1: Nomenclatura Local de Productos | G1: Clasificación Productos | H1: Cod_Bioec Productos | I1: Tipo de bioeconomía Productos | J1: Sectores produuctos | K1: Cód_Div_CPC_3 | L1: División CPC_3 | M1: Cód_Div_CPC_2 | N1: División CPC_2 | O1: Cod. Elem. Def. Bioeconomía | P1: Tipo de elemento | Q1: Código CPC | R1: Elemento CPC | S1: Código Bioeconomía | T1: Clasificación Bioeconomí
A2: PANof001 | B2: ATF01 | C2: =VLOOKUP(B2, AT_FILAS!$A$2:$C$8,2,FALSE()) -> Producción | D2: =VLOOKUP(B2, AT_FILAS!$A$2:$C$8,3,FALSE()) -> 1 | E2: 0101 | F2: TRIGO | G2: Productos agricolas_Cereales | H2: 1 | I2: Bioeconomía de productos básicos | J2: Productos agropecuarios | K2: 1 | L2: =VLOOKUP(K2,clasif_filas!$A$2:$J$39,2,FALSE()) -> Productos de la agricultura, la horticultura y la jardinería comercial | M2: =VLOOKUP(K2,clasif_filas!$A$2:$J$39,3,FALSE()) -> 1 | N2: =VLOOKUP(K2,clasif_filas!$A$2:$J$39,4,FALSE()) -> Productos de la agricultura, la horticultura y la jardinería comercial | O2: =VLOOKUP(K2,clasif_filas!$A$2:$J$39,5,FALSE()) -> 1 | P2: =VLOOKUP(K2,clasif_filas!$A$2:$J$39,6,FALSE()) -> Biomasa que se cultiva para producir alimentos, forrajes, fibras y energía | Q2: =VLOOKUP(K2,clasif_filas!$A$2:$J$39,7,FALSE()) -> 0 | R2: =VLOOKUP(K2,clasif_filas!$A$2:$J$39,8,FALSE()) -> Productos de la agricultura, la silvicultura yla pesca | S2: =VLOOKUP(K2,clasif_filas!$A$2:$J$39,9,FALSE()) -> 1 | T2: =VLOOKUP(K2,clasif_filas!$A$2:$J$39,10,FALSE()) -> Bioeconomía
A3: PANof002 | B3: ATF01 | C3: =VLOOKUP(B3, AT_FILAS!$A$2:$C$8,2,FALSE()) -> Producción | D3: =VLOOKUP(B3, AT_FILAS!$A$2:$C$8,3,FALSE()) -> 1 | E3: 0102 | F3: OTROS CEREALES (EXCL. MAÍZ Y ARROZ) | G3: Productos agricolas_Cereales | H3: 1 | I3: Bioeconomía de productos básicos | J3: Productos agropecuarios | K3: 1 | L3: =VLOOKUP(K3,clasif_filas!$A$2:$J$39,2,FALSE()) -> Productos de la agricultura, la horticultura y la jardinería comercial | M3: =VLOOKUP(K3,clasif_filas!$A$2:$J$39,3,FALSE()) -> 1 | N3: =VLOOKUP(K3,clasif_filas!$A$2:$J$39,4,FALSE()) -> Productos de la agricultura, la horticultura y la jardinería comercial | O3: =VLOOKUP(K3,clasif_filas!$A$2:$J$39,5,FALSE()) -> 1 | P3: =VLOOKUP(K3,clasif_filas!$A$2:$J$39,6,FALSE()) -> Biomasa que se cultiva para producir alimentos, forrajes, fibras y energía | Q3: =VLOOKUP(K3,clasif_filas!$A$2:$J$39,7,FALSE()) -> 0 | R3: =VLOOKUP(K3,clasif_filas!$A$2:$J$39,8,FALSE()) -> Productos de la agricultura, la silvicultura yla pesca | S3: =VLOOKUP(K3,clasif_filas!$A$2:$J$39,9,FALSE()) -> 1 | T3: =VLOOKUP(K3,clasif_filas!$A$2:$J$39,10,FALSE()) -> Bioeconomía
A4: PANof003 | B4: ATF01 | C4: =VLOOKUP(B4, AT_FILAS!$A$2:$C$8,2,FALSE()) -> Producción | D4: =VLOOKUP(B4, AT_FILAS!$A$2:$C$8,3,FALSE()) -> 1 | E4: 0103 | F4: LEGUMBRES | G4: Productos agropecuarios_Vegetales | H4: 1 | I4: Bioeconomía de productos básicos | J4: Productos agropecuarios | K4: 1 | L4: =VLOOKUP(K4,clasif_filas!$A$2:$J$39,2,FALSE()) -> Productos de la agricultura, la horticultura y la jardinería comercial | M4: =VLOOKUP(K4,clasif_filas!$A$2:$J$39,3,FALSE()) -> 1 | N4: =VLOOKUP(K4,clasif_filas!$A$2:$J$39,4,FALSE()) -> Productos de la agricultura, la horticultura y la jardinería comercial | O4: =VLOOKUP(K4,clasif_filas!$A$2:$J$39,5,FALSE()) -> 1 | P4: =VLOOKUP(K4,clasif_filas!$A$2:$J$39,6,FALSE()) -> Biomasa que se cultiva para producir alimentos, forrajes, fibras y energía | Q4: =VLOOKUP(K4,clasif_filas!$A$2:$J$39,7,FALSE()) -> 0 | R4: =VLOOKUP(K4,clasif_filas!$A$2:$J$39,8,FALSE()) -> Productos de la agricultura, la silvicultura yla pesca | S4: =VLOOKUP(K4,clasif_filas!$A$2:$J$39,9,FALSE()) -> 1 | T4: =VLOOKUP(K4,clasif_filas!$A$2:$J$39,10,FALSE()) -> Bioeconomía
A5: PANof004 | B5: ATF01 | C5: =VLOOKUP(B5, AT_FILAS!$A$2:$C$8,2,FALSE()) -> Producción | D5: =VLOOKUP(B5, AT_FILAS!$A$2:$C$8,3,FALSE()) -> 1 | E5: 0104 | F5: SEMILLAS OLEAGINOSAS | G5: Productos agricolas_Oleaginosas | H5: 1 | I5: Bioeconomía de productos básicos | J5: Productos agropecuarios | K5: 1 | L5: =VLOOKUP(K5,clasif_filas!$A$2:$J$39,2,FALSE()) -> Productos de la agricultura, la horticultura y la jardinería comercial | M5: =VLOOKUP(K5,clasif_filas!$A$2:$J$39,3,FALSE()) -> 1 | N5: =VLOOKUP(K5,clasif_filas!$A$2:$J$39,4,FALSE()) -> Productos de la agricultura, la horticultura y la jardinería comercial | O5: =VLOOKUP(K5,clasif_filas!$A$2:$J$39,5,FALSE()) -> 1 | P5: =VLOOKUP(K5,clasif_filas!$A$2:$J$39,6,FALSE()) -> Biomasa que se cultiva para producir alimentos, forrajes, fibras y energía | Q5: =VLOOKUP(K5,clasif_filas!$A$2:$J$39,7,FALSE()) -> 0 | R5: =VLOOKUP(K5,clasif_filas!$A$2:$J$39,8,FALSE()) -> Productos de la agricultura, la silvicultura yla pesca | S5: =VLOOKUP(K5,clasif_filas!$A$2:$J$39,9,FALSE()) -> 1 | T5: =VLOOKUP(K5,clasif_filas!$A$2:$J$39,10,FALSE()) -> Bioeconomía
A6: PANof005 | B6: ATF01 | C6: =VLOOKUP(B6, AT_FILAS!$A$2:$C$8,2,FALSE()) -> Producción | D6: =VLOOKUP(B6, AT_FILAS!$A$2:$C$8,3,FALSE()) -> 1 | E6: 0201 | F6: MAÍZ | G6: Productos agricolas_Cereales | H6: 1 | I6: Bioeconomía de productos básicos | J6: Productos agropecuarios | K6: 1 | L6: =VLOOKUP(K6,clasif_filas!$A$2:$J$39,2,FALSE()) -> Productos de la agricultura, la horticultura y la jardinería comercial | M6: =VLOOKUP(K6,clasif_filas!$A$2:$J$39,3,FALSE()) -> 1 | N6: =VLOOKUP(K6,clasif_filas!$A$2:$J$39,4,FALSE()) -> Productos de la agricultura, la horticultura y la jardinería comercial | O6: =VLOOKUP(K6,clasif_filas!$A$2:$J$39,5,FALSE()) -> 1 | P6: =VLOOKUP(K6,clasif_filas!$A$2:$J$39,6,FALSE()) -> Biomasa que se cultiva para producir alimentos, forrajes, fibras y energía | Q6: =VLOOKUP(K6,clasif_filas!$A$2:$J$39,7,FALSE()) -> 0 | R6: =VLOOKUP(K6,clasif_filas!$A$2:$J$39,8,FALSE()) -> Productos de la agricultura, la silvicultura yla pesca | S6: =VLOOKUP(K6,clasif_filas!$A$2:$J$39,9,FALSE()) -> 1 | T6: =VLOOKUP(K6,clasif_filas!$A$2:$J$39,10,FALSE()) -> Bioeconomía
A7: PANof006 | B7: ATF01 | C7: =VLOOKUP(B7, AT_FILAS!$A$2:$C$8,2,FALSE()) -> Producción | D7: =VLOOKUP(B7, AT_FILAS!$A$2:$C$8,3,FALSE()) -> 1 | E7: 0301 | F7: ARROZ | G7: Productos agricolas_Cereales | H7: 1 | I7: Bioeconomía de productos básicos | J7: Productos agropecuarios | K7: 1 | L7: =VLOOKUP(K7,clasif_filas!$A$2:$J$39,2,FALSE()) -> Productos de la agricultura, la horticultura y la jardinería comercial | M7: =VLOOKUP(K7,clasif_filas!$A$2:$J$39,3,FALSE()) -> 1 | N7: =VLOOKUP(K7,clasif_filas!$A$2:$J$39,4,FALSE()) -> Productos de la agricultura, la horticultura y la jardinería comercial | O7: =VLOOKUP(K7,clasif_filas!$A$2:$J$39,5,FALSE()) -> 1 | P7: =VLOOKUP(K7,clasif_filas!$A$2:$J$39,6,FALSE()) -> Biomasa que se cultiva para producir alimentos, forrajes, fibras y energía | Q7: =VLOOKUP(K7,clasif_filas!$A$2:$J$39,7,FALSE()) -> 0 | R7: =VLOOKUP(K7,clasif_filas!$A$2:$J$39,8,FALSE()) -> Productos de la agricultura, la silvicultura yla pesca | S7: =VLOOKUP(K7,clasif_filas!$A$2:$J$39,9,FALSE()) -> 1 | T7: =VLOOKUP(K7,clasif_filas!$A$2:$J$39,10,FALSE()) -> Bioeconomía
A8: PANof007 | B8: ATF01 | C8: =VLOOKUP(B8, AT_FILAS!$A$2:$C$8,2,FALSE()) -> Producción | D8: =VLOOKUP(B8, AT_FILAS!$A$2:$C$8,3,FALSE()) -> 1 | E8: 0401 | F8: HORTALIZAS DE HOJA O DE TALLO | G8: Productos agropecuarios_Vegetales | H8: 1 | I8: Bioeconomía de productos básicos | J8: Productos agropecuarios | K8: 1 | L8: =VLOOKUP(K8,clasif_filas!$A$2:$J$39,2,FALSE()) -> Productos de la agricultura, la horticultura y la jardinería comercial | M8: =VLOOKUP(K8,clasif_filas!$A$2:$J$39,3,FALSE()) -> 1 | N8: =VLOOKUP(K8,clasif_filas!$A$2:$J$39,4,FALSE()) -> Productos de la agricultura, la horticultura y la jardinería comercial | O8: =VLOOKUP(K8,clasif_filas!$A$2:$J$39,5,FALSE()) -> 1 | P8: =VLOOKUP(K8,clasif_filas!$A$2:$J$39,6,FALSE()) -> Biomasa que se cultiva para producir alimentos, forrajes, fibras y energía | Q8: =VLOOKUP(K8,clasif_filas!$A$2:$J$39,7,FALSE()) -> 0 | R8: =VLOOKUP(K8,clasif_filas!$A$2:$J$39,8,FALSE()) -> Productos de la agricultura, la silvicultura yla pesca | S8: =VLOOKUP(K8,clasif_filas!$A$2:$J$39,9,FALSE()) -> 1 | T8: =VLOOKUP(K8,clasif_filas!$A$2:$J$39,10,FALSE()) -> Bioeconomía
A9: PANof008 | B9: ATF01 | C9: =VLOOKUP(B9, AT_FILAS!$A$2:$C$8,2,FALSE()) -> Producción | D9: =VLOOKUP(B9, AT_FILAS!$A$2:$C$8,3,FALSE()) -> 1 | E9: 0402 | F9: SANDÍAS | G9: Productos agricolas_Frutas | H9: 1 | I9: Bioeconomía de productos básicos | J9: Productos agropecuarios | K9: 1 | L9: =VLOOKUP(K9,clasif_filas!$A$2:$J$39,2,FALSE()) -> Productos de la agricultura, la horticultura y la jardinería comercial | M9: =VLOOKUP(K9,clasif_filas!$A$2:$J$39,3,FALSE()) -> 1 | N9: =VLOOKUP(K9,clasif_filas!$A$2:$J$39,4,FALSE()) -> Productos de la agricultura, la horticultura y la jardinería comercial | O9: =VLOOKUP(K9,clasif_filas!$A$2:$J$39,5,FALSE()) -> 1 | P9: =VLOOKUP(K9,clasif_filas!$A$2:$J$39,6,FALSE()) -> Biomasa que se cultiva para producir alimentos, forrajes, fibras y energía | Q9: =VLOOKUP(K9,clasif_filas!$A$2:$J$39,7,FALSE()) -> 0 | R9: =VLOOKUP(K9,clasif_filas!$A$2:$J$39,8,FALSE()) -> Productos de la agricultura, la silvicultura yla pesca | S9: =VLOOKUP(K9,clasif_filas!$A$2:$J$39,9,FALSE()) -> 1 | T9: =VLOOKUP(K9,clasif_filas!$A$2:$J$39,10,FALSE()) -> Bioeconomía
A10: PANof009 | B10: ATF01 | C10: =VLOOKUP(B10, AT_FILAS!$A$2:$C$8,2,FALSE()) -> Producción | D10: =VLOOKUP(B10, AT_FILAS!$A$2:$C$8,3,FALSE()) -> 1 | E10: 0403 | F10: MELONES | G10: Productos agricolas_Frutas | H10: 1 | I10: Bioeconomía de productos básicos | J10: Productos agropecuarios | K10: 1 | L10: =VLOOKUP(K10,clasif_filas!$A$2:$J$39,2,FALSE()) -> Productos de la agricultura, la horticultura y la jardinería comercial | M10: =VLOOKUP(K10,clasif_filas!$A$2:$J$39,3,FALSE()) -> 1 | N10: =VLOOKUP(K10,clasif_filas!$A$2:$J$39,4,FALSE()) -> Productos de la agricultura, la horticultura y la jardinería comercial | O10: =VLOOKUP(K10,clasif_filas!$A$2:$J$39,5,FALSE()) -> 1 | P10: =VLOOKUP(K10,clasif_filas!$A$2:$J$39,6,FALSE()) -> Biomasa que se cultiva para producir alimentos, forrajes, fibras y energía | Q10: =VLOOKUP(K10,clasif_filas!$A$2:$J$39,7,FALSE()) -> 0 | R10: =VLOOKUP(K10,clasif_filas!$A$2:$J$39,8,FALSE()) -> Productos de la agricultura, la silvicultura yla pesca | S10: =VLOOKUP(K10,clasif_filas!$A$2:$J$39,9,FALSE()) -> 1 | T10: =VLOOKUP(K10,clasif_filas!$A$2:$J$39,10,FALSE()) -> Bioeconomía
A11: PANof010 | B11: ATF01 | C11: =VLOOKUP(B11, AT_FILAS!$A$2:$C$8,2,FALSE()) -> Producción | D11: =VLOOKUP(B11, AT_FILAS!$A$2:$C$8,3,FALSE()) -> 1 | E11: 0404 | F11: TOMATES | G11: Productos agricolas_Frutas | H11: 1 | I11: Bioeconomía de productos básicos | J11: Productos agropecuarios | K11: 1 | L11: =VLOOKUP(K11,clasif_filas!$A$2:$J$39,2,FALSE()) -> Productos de la agricultura, la horticultura y la jardinería comercial | M11: =VLOOKUP(K11,clasif_filas!$A$2:$J$39,3,FALSE()) -> 1 | N11: =VLOOKUP(K11,clasif_filas!$A$2:$J$39,4,FALSE()) -> Productos de la agricultura, la horticultura y la jardinería comercial | O11: =VLOOKUP(K11,clasif_filas!$A$2:$J$39,5,FALSE()) -> 1 | P11: =VLOOKUP(K11,clasif_filas!$A$2:$J$39,6,FALSE()) -> Biomasa que se cultiva para producir alimentos, forrajes, fibras y energía | Q11: =VLOOKUP(K11,clasif_filas!$A$2:$J$39,7,FALSE()) -> 0 | R11: =VLOOKUP(K11,clasif_filas!$A$2:$J$39,8,FALSE()) -> Productos de la agricultura, la silvicultura yla pesca | S11: =VLOOKUP(K11,clasif_filas!$A$2:$J$39,9,FALSE()) -> 1 | T11: =VLOOKUP(K11,clasif_filas!$A$2:$J$39,10,FALSE()) -> Bioeconomía
A12: PANof011 | B12: ATF01 | C12: =VLOOKUP(B12, AT_FILAS!$A$2:$C$8,2,FALSE()) -> Producción | D12: =VLOOKUP(B12, AT_FILAS!$A$2:$C$8,3,FALSE()) -> 1 | E12: 0405 | F12: OTRAS HORTALIZAS | G12: Productos agropecuarios_Vegetales | H12: 1 | I12: Bioeconomía de productos básicos | J12: Productos agropecuarios | K12: 1 | L12: =VLOOKUP(K12,clasif_filas!$A$2:$J$39,2,FALSE()) -> Productos de la agricultura, la horticultura y la jardinería comercial | M12: =VLOOKUP(K12,clasif_filas!$A$2:$J$39,3,FALSE()) -> 1 | N12: =VLOOKUP(K12,clasif_filas!$A$2:$J$39,4,FALSE()) -> Productos de la agricultura, la horticultura y la jardinería comercial | O12: =VLOOKUP(K12,clasif_filas!$A$2:$J$39,5,FALSE()) -> 1 | P12: =VLOOKUP(K12,clasif_filas!$A$2:$J$39,6,FALSE()) -> Biomasa que se cultiva para producir alimentos, forrajes, fibras y energía | Q12: =VLOOKUP(K12,clasif_filas!$A$2:$J$39,7,FALSE()) -> 0 | R12: =VLOOKUP(K12,clasif_filas!$A$2:$J$39,8,FALSE()) -> Productos de la agricultura, la silvicultura yla pesca | S12: =VLOOKUP(K12,clasif_filas!$A$2:$J$39,9,FALSE()) -> 1 | T12: =VLOOKUP(K12,clasif_filas!$A$2:$J$39,10,FALSE()) -> Bioeconomía
A13: PANof012 | B13: ATF01 | C13: =VLOOKUP(B13, AT_FILAS!$A$2:$C$8,2,FALSE()) -> Producción | D13: =VLOOKUP(B13, AT_FILAS!$A$2:$C$8,3,FALSE()) -> 1 | E13: 0406 | F13: CEBOLLAS | G13: Productos agropecuarios_Vegetales | H13: 1 | I13: Bioeconomía de productos básicos | J13: Productos agropecuarios | K13: 1 | L13: =VLOOKUP(K13,clasif_filas!$A$2:$J$39,2,FALSE()) -> Productos de la agricultura, la horticultura y la jardinería comercial | M13: =VLOOKUP(K13,clasif_filas!$A$2:$J$39,3,FALSE()) -> 1 | N13: =VLOOKUP(K13,clasif_filas!$A$2:$J$39,4,FALSE()) -> Productos de la agricultura, la horticultura y la jardinería comercial | O13: =VLOOKUP(K13,clasif_filas!$A$2:$J$39,5,FALSE()) -> 1 | P13: =VLOOKUP(K13,clasif_filas!$A$2:$J$39,6,FALSE()) -> Biomasa que se cultiva para producir alimentos, forrajes, fibras y energía | Q13: =VLOOKUP(K13,clasif_filas!$A$2:$J$39,7,FALSE()) -> 0 | R13: =VLOOKUP(K13,clasif_filas!$A$2:$J$39,8,FALSE()) -> Productos de la agricultura, la silvicultura yla pesca | S13: =VLOOKUP(K13,clasif_filas!$A$2:$J$39,9,FALSE()) -> 1 | T13: =VLOOKUP(K13,clasif_filas!$A$2:$J$39,10,FALSE()) -> Bioeconomía
... A33: PANof032 | B33: ATF01 | C33: =VLOOKUP(B33, AT_FILAS!$A$2:$C$8,2,FALSE()) -> Producción | D33: =VLOOKUP(B33, AT_FILAS!$A$2:$C$8,3,FALSE()) -> 1 | E33: 1303 | F33: OTROS ANIMALES Y OTROS PRODUCTOS ANIMALES | G33: Animales y plantas | H33: 1 | I33: Bioeconomía de productos básicos | J33: Productos agropecuarios | K33: 1 | L33: =VLOOKUP(K33,clasif_filas!$A$2:$J$39,2,FALSE()) -> Productos de la agricultura, la horticultura y la jardinería comercial | M33: =VLOOKUP(K33,clasif_filas!$A$2:$J$39,3,FALSE()) -> 1 | N33: =VLOOKUP(K33,clasif_filas!$A$2:$J$39,4,FALSE()) -> Productos de la agricultura, la horticultura y la jardinería comercial | O33: =VLOOKUP(K33,clasif_filas!$A$2:$J$39,5,FALSE()) -> 1 | P33: =VLOOKUP(K33,clasif_filas!$A$2:$J$39,6,FALSE()) -> Biomasa que se cultiva para producir alimentos, forrajes, fibras y energía | Q33: =VLOOKUP(K33,clasif_filas!$A$2:$J$39,7,FALSE()) -> 0 | R33: =VLOOKUP(K33,clasif_filas!$A$2:$J$39,8,FALSE()) -> Productos de la agricultura, la silvicultura yla pesca | S33: =VLOOKUP(K33,clasif_filas!$A$2:$J$39,9,FALSE()) -> 1 | T33: =VLOOKUP(K33,clasif_filas!$A$2:$J$39,10,FALSE()) -> Bioeconomía
A34: PANof033 | B34: ATF01 | C34: =VLOOKUP(B34, AT_FILAS!$A$2:$C$8,2,FALSE()) -> Producción | D34: =VLOOKUP(B34, AT_FILAS!$A$2:$C$8,3,FALSE()) -> 1 | E34: 1401 | F34: SERVICIOS DE APOYO A LA AGRICULTURA, LA GANADERÍA Y ACTIVIDADES POSTCOSECHA | G34: Servicios | H34: 3 | I34: Bioeconomía avanzada | J34: Servicios | K34: 86 | L34: =VLOOKUP(K34,clasif_filas!$A$2:$J$39,2,FALSE()) -> Servicios de apoyo a la agricultura,la caza, la silvicutura, la pesca, la minería y los servicios públicos | M34: =VLOOKUP(K34,clasif_filas!$A$2:$J$39,3,FALSE()) -> 86 | N34: =VLOOKUP(K34,clasif_filas!$A$2:$J$39,4,FALSE()) -> Servicios de apoyo a la agricultura,la caza, la silvicutura, la pesca, la minería y los servicios públicos | O34: =VLOOKUP(K34,clasif_filas!$A$2:$J$39,5,FALSE()) -> 6 | P34: =VLOOKUP(K34,clasif_filas!$A$2:$J$39,6,FALSE()) -> Conocimiento, procesos y servicios relacionados | Q34: =VLOOKUP(K34,clasif_filas!$A$2:$J$39,7,FALSE()) -> 8 | R34: =VLOOKUP(K34,clasif_filas!$A$2:$J$39,8,FALSE()) -> Servicios prestados a las empresas y servicios de producción | S34: =VLOOKUP(K34,clasif_filas!$A$2:$J$39,9,FALSE()) -> 1 | T34: Bioeconomía
A35: PANof034 | B35: ATF01 | C35: =VLOOKUP(B35, AT_FILAS!$A$2:$C$8,2,FALSE()) -> Producción | D35: =VLOOKUP(B35, AT_FILAS!$A$2:$C$8,3,FALSE()) -> 1 | E35: 1501 | F35: MADERA EN BRUTO | G35: Materias primas | H35: 1 | I35: Bioeconomía de productos básicos | J35: Materias primas | K35: 3 | L35: =VLOOKUP(K35,clasif_filas!$A$2:$J$39,2,FALSE()) -> Productos forestales y de la tala | M35: =VLOOKUP(K35,clasif_filas!$A$2:$J$39,3,FALSE()) -> 3 | N35: =VLOOKUP(K35,clasif_filas!$A$2:$J$39,4,FALSE()) -> Productos forestales y de la tala | O35: =VLOOKUP(K35,clasif_filas!$A$2:$J$39,5,FALSE()) -> 3 | P35: =VLOOKUP(K35,clasif_filas!$A$2:$J$39,6,FALSE()) -> Biomasa forestal, sobre todo la que se cultiva para su aprovechamiento en las industrias forestal y del papel, y aquella extraída legalmente de ecosistemas naturales | Q35: =VLOOKUP(K35,clasif_filas!$A$2:$J$39,7,FALSE()) -> 0 | R35: =VLOOKUP(K35,clasif_filas!$A$2:$J$39,8,FALSE()) -> Productos de la agricultura, la silvicultura yla pesca | S35: =VLOOKUP(K35,clasif_filas!$A$2:$J$39,9,FALSE()) -> 1 | T35: =VLOOKUP(K35,clasif_filas!$A$2:$J$39,10,FALSE()) -> Bioeconomía
A36: PANof035 | B36: ATF01 | C36: =VLOOKUP(B36, AT_FILAS!$A$2:$C$8,2,FALSE()) -> Producción | D36: =VLOOKUP(B36, AT_FILAS!$A$2:$C$8,3,FALSE()) -> 1 | E36: 1502 | F36: OTROS PRODUCTOS SILVÍCOLAS | G36: Materias primas | H36: 1 | I36: Bioeconomía de productos básicos | J36: Materias primas | K36: 3 | L36: =VLOOKUP(K36,clasif_filas!$A$2:$J$39,2,FALSE()) -> Productos forestales y de la tala | M36: =VLOOKUP(K36,clasif_filas!$A$2:$J$39,3,FALSE()) -> 3 | N36: =VLOOKUP(K36,clasif_filas!$A$2:$J$39,4,FALSE()) -> Productos forestales y de la tala | O36: =VLOOKUP(K36,clasif_filas!$A$2:$J$39,5,FALSE()) -> 3 | P36: =VLOOKUP(K36,clasif_filas!$A$2:$J$39,6,FALSE()) -> Biomasa forestal, sobre todo la que se cultiva para su aprovechamiento en las industrias forestal y del papel, y aquella extraída legalmente de ecosistemas naturales | Q36: =VLOOKUP(K36,clasif_filas!$A$2:$J$39,7,FALSE()) -> 0 | R36: =VLOOKUP(K36,clasif_filas!$A$2:$J$39,8,FALSE()) -> Productos de la agricultura, la silvicultura yla pesca | S36: =VLOOKUP(K36,clasif_filas!$A$2:$J$39,9,FALSE()) -> 1 | T36: =VLOOKUP(K36,clasif_filas!$A$2:$J$39,10,FALSE()) -> Bioeconomía
A37: PANof036 | B37: ATF01 | C37: =VLOOKUP(B37, AT_FILAS!$A$2:$C$8,2,FALSE()) -> Producción | D37: =VLOOKUP(B37, AT_FILAS!$A$2:$C$8,3,FALSE()) -> 1 | E37: 1601 | F37: PESCADOS VIVOS, FRESCOS O REFRIGERADOS | G37: Animales y plantas | H37: 1 | I37: Bioeconomía de productos básicos | J37: Productos agropecuarios | K37: 4 | L37: =VLOOKUP(K37,clasif_filas!$A$2:$J$39,2,FALSE()) -> Pescado y otros productos de la pesca | M37: =VLOOKUP(K37,clasif_filas!$A$2:$J$39,3,FALSE()) -> 4 | N37: =VLOOKUP(K37,clasif_filas!$A$2:$J$39,4,FALSE()) -> Pescado y otros productos de la pesca | O37: =VLOOKUP(K37,clasif_filas!$A$2:$J$39,5,FALSE()) -> 2 | P37: =VLOOKUP(K37,clasif_filas!$A$2:$J$39,6,FALSE()) -> Biomasa de los recursos marinos y la producida mediante la acuicultura | Q37: =VLOOKUP(K37,clasif_filas!$A$2:$J$39,7,FALSE()) -> 0 | R37: =VLOOKUP(K37,clasif_filas!$A$2:$J$39,8,FALSE()) -> Productos de la agricultura, la silvicultura yla pesca | S37: =VLOOKUP(K37,clasif_filas!$A$2:$J$39,9,FALSE()) -> 1 | T37: =VLOOKUP(K37,clasif_filas!$A$2:$J$39,10,FALSE()) -> Bioeconomía
A38: PANof037 | B38: ATF01 | C38: =VLOOKUP(B38, AT_FILAS!$A$2:$C$8,2,FALSE()) -> Producción | D38: =VLOOKUP(B38, AT_FILAS!$A$2:$C$8,3,FALSE()) -> 1 | E38: 1602 | F38: CAMARÓN Y OTROS CRUSTÁCEOS VIVOS, FRESCOS O REFRIGERADOS | G38: Animales y plantas | H38: 1 | I38: Bioeconomía de productos básicos | J38: Productos agropecuarios | K38: 4 | L38: =VLOOKUP(K38,clasif_filas!$A$2:$J$39,2,FALSE()) -> Pescado y otros productos de la pesca | M38: =VLOOKUP(K38,clasif_filas!$A$2:$J$39,3,FALSE()) -> 4 | N38: =VLOOKUP(K38,clasif_filas!$A$2:$J$39,4,FALSE()) -> Pescado y otros productos de la pesca | O38: =VLOOKUP(K38,clasif_filas!$A$2:$J$39,5,FALSE()) -> 2 | P38: =VLOOKUP(K38,clasif_filas!$A$2:$J$39,6,FALSE()) -> Biomasa de los recursos marinos y la producida mediante la acuicultura | Q38: =VLOOKUP(K38,clasif_filas!$A$2:$J$39,7,FALSE()) -> 0 | R38: =VLOOKUP(K38,clasif_filas!$A$2:$J$39,8,FALSE()) -> Productos de la agricultura, la silvicultura yla pesca | S38: =VLOOKUP(K38,clasif_filas!$A$2:$J$39,9,FALSE()) -> 1 | T38: =VLOOKUP(K38,clasif_filas!$A$2:$J$39,10,FALSE()) -> Bioeconomía
A39: PANof038 | B39: ATF01 | C39: =VLOOKUP(B39, AT_FILAS!$A$2:$C$8,2,FALSE()) -> Producción | D39: =VLOOKUP(B39, AT_FILAS!$A$2:$C$8,3,FALSE()) -> 1 | E39: 1603 | F39: OTROS PRODUCTOS DE LA PESCA | G39: Animales y plantas | H39: 1 | I39: Bioeconomía de productos básicos | J39: Productos agropecuarios | K39: 4 | L39: =VLOOKUP(K39,clasif_filas!$A$2:$J$39,2,FALSE()) -> Pescado y otros productos de la pesca | M39: =VLOOKUP(K39,clasif_filas!$A$2:$J$39,3,FALSE()) -> 4 | N39: =VLOOKUP(K39,clasif_filas!$A$2:$J$39,4,FALSE()) -> Pescado y otros productos de la pesca | O39: =VLOOKUP(K39,clasif_filas!$A$2:$J$39,5,FALSE()) -> 2 | P39: =VLOOKUP(K39,clasif_filas!$A$2:$J$39,6,FALSE()) -> Biomasa de los recursos marinos y la producida mediante la acuicultura | Q39: =VLOOKUP(K39,clasif_filas!$A$2:$J$39,7,FALSE()) -> 0 | R39: =VLOOKUP(K39,clasif_filas!$A$2:$J$39,8,FALSE()) -> Productos de la agricultura, la silvicultura yla pesca | S39: =VLOOKUP(K39,clasif_filas!$A$2:$J$39,9,FALSE()) -> 1 | T39: =VLOOKUP(K39,clasif_filas!$A$2:$J$39,10,FALSE()) -> Bioeconomía
A40: PANof039 | B40: ATF01 | C40: =VLOOKUP(B40, AT_FILAS!$A$2:$C$8,2,FALSE()) -> Producción | D40: =VLOOKUP(B40, AT_FILAS!$A$2:$C$8,3,FALSE()) -> 1 | E40: 1701 | F40: MINERALES DE COBRE Y SUS CONCENTRADOS | G40: No bioeconomía | H40: 4 | I40: No bioeconomía | J40: No bioeconomía | K40: 11 | L40: =VLOOKUP(K40,clasif_filas!$A$2:$J$39,2,FALSE()) -> Minerales, combustibles y derivados | M40: =VLOOKUP(K40,clasif_filas!$A$2:$J$39,3,FALSE()) -> 11 | N40: =VLOOKUP(K40,clasif_filas!$A$2:$J$39,4,FALSE()) -> Minerales, combustibles y derivados | O40: =VLOOKUP(K40,clasif_filas!$A$2:$J$39,5,FALSE()) -> 99 | P40: =VLOOKUP(K40,clasif_filas!$A$2:$J$39,6,FALSE()) -> No Bioeconomía | Q40: =VLOOKUP(K40,clasif_filas!$A$2:$J$39,7,FALSE()) -> 1 | R40: =VLOOKUP(K40,clasif_filas!$A$2:$J$39,8,FALSE()) -> Minerales; electricidad, gas y agua | S40: =VLOOKUP(K40,clasif_filas!$A$2:$J$39,9,FALSE()) -> 3 | T40: =VLOOKUP(K40,clasif_filas!$A$2:$J$39,10,FALSE()) -> No bioeconomía
A41: PANof040 | B41: ATF01 | C41: =VLOOKUP(B41, AT_FILAS!$A$2:$C$8,2,FALSE()) -> Producción | D41: =VLOOKUP(B41, AT_FILAS!$A$2:$C$8,3,FALSE()) -> 1 | E41: 1702 | F41: OTROS MINERALES METÁLICOS | G41: No bioeconomía | H41: 4 | I41: No bioeconomía | J41: No bioeconomía | K41: 11 | L41: =VLOOKUP(K41,clasif_filas!$A$2:$J$39,2,FALSE()) -> Minerales, combustibles y derivados | M41: =VLOOKUP(K41,clasif_filas!$A$2:$J$39,3,FALSE()) -> 11 | N41: =VLOOKUP(K41,clasif_filas!$A$2:$J$39,4,FALSE()) -> Minerales, combustibles y derivados | O41: =VLOOKUP(K41,clasif_filas!$A$2:$J$39,5,FALSE()) -> 99 | P41: =VLOOKUP(K41,clasif_filas!$A$2:$J$39,6,FALSE()) -> No Bioeconomía | Q41: =VLOOKUP(K41,clasif_filas!$A$2:$J$39,7,FALSE()) -> 1 | R41: =VLOOKUP(K41,clasif_filas!$A$2:$J$39,8,FALSE()) -> Minerales; electricidad, gas y agua | S41: =VLOOKUP(K41,clasif_filas!$A$2:$J$39,9,FALSE()) -> 3 | T41: =VLOOKUP(K41,clasif_filas!$A$2:$J$39,10,FALSE()) -> No bioeconomía
A42: PANof041 | B42: ATF01 | C42: =VLOOKUP(B42, AT_FILAS!$A$2:$C$8,2,FALSE()) -> Producción | D42: =VLOOKUP(B42, AT_FILAS!$A$2:$C$8,3,FALSE()) -> 1 | E42: 1801 | F42: MINERALES NO METÁLICOS | G42: No bioeconomía | H42: 4 | I42: No bioeconomía | J42: No bioeconomía | K42: 11 | L42: =VLOOKUP(K42,clasif_filas!$A$2:$J$39,2,FALSE()) -> Minerales, combustibles y derivados | M42: =VLOOKUP(K42,clasif_filas!$A$2:$J$39,3,FALSE()) -> 11 | N42: =VLOOKUP(K42,clasif_filas!$A$2:$J$39,4,FALSE()) -> Minerales, combustibles y derivados | O42: =VLOOKUP(K42,clasif_filas!$A$2:$J$39,5,FALSE()) -> 99 | P42: =VLOOKUP(K42,clasif_filas!$A$2:$J$39,6,FALSE()) -> No Bioeconomía | Q42: =VLOOKUP(K42,clasif_filas!$A$2:$J$39,7,FALSE()) -> 1 | R42: =VLOOKUP(K42,clasif_filas!$A$2:$J$39,8,FALSE()) -> Minerales; electricidad, gas y agua | S42: =VLOOKUP(K42,clasif_filas!$A$2:$J$39,9,FALSE()) -> 3 | T42: =VLOOKUP(K42,clasif_filas!$A$2:$J$39,10,FALSE()) -> No bioeconomía
A43: PANof042 | B43: ATF01 | C43: =VLOOKUP(B43, AT_FILAS!$A$2:$C$8,2,FALSE()) -> Producción | D43: =VLOOKUP(B43, AT_FILAS!$A$2:$C$8,3,FALSE()) -> 1 | E43: 1901 | F43: SAL | G43: No bioeconomía | H43: 4 | I43: No bioeconomía | J43: No bioeconomía | K43: 37 | L43: =VLOOKUP(K43,clasif_filas!$A$2:$J$39,2,FALSE()) -> Vidrios y productos de vidrio y otros productos no metálicos n.c.p. | M43: =VLOOKUP(K43,clasif_filas!$A$2:$J$39,3,FALSE()) -> 37 | N43: =VLOOKUP(K43,clasif_filas!$A$2:$J$39,4,FALSE()) -> Vidrios y productos de vidrio y otros productos no metálicos n.c.p. | O43: =VLOOKUP(K43,clasif_filas!$A$2:$J$39,5,FALSE()) -> 99 | P43: =VLOOKUP(K43,clasif_filas!$A$2:$J$39,6,FALSE()) -> No Bioeconomía | Q43: =VLOOKUP(K43,clasif_filas!$A$2:$J$39,7,FALSE()) -> 3 | R43: =VLOOKUP(K43,clasif_filas!$A$2:$J$39,8,FALSE()) -> Otros bienes transportables, excepto productos metálicos, maquinaria y equipo | S43: =VLOOKUP(K43,clasif_filas!$A$2:$J$39,9,FALSE()) -> 3 | T43: =VLOOKUP(K43,clasif_filas!$A$2:$J$39,10,FALSE()) -> No bioeconomía
A44: PANof043 | B44: ATF01 | C44: =VLOOKUP(B44, AT_FILAS!$A$2:$C$8,2,FALSE()) -> Producción | D44: =VLOOKUP(B44, AT_FILAS!$A$2:$C$8,3,FALSE()) -> 1 | E44: 2001 | F44: OTROS MINERALES Y SERVICIOS DE APOYO PARA LA EXPLOTACIÓN DE MINAS Y CANTERAS | G44: No bioeconomía | H44: 4 | I44: No bioeconomía | J44: No bioeconomía | K44: 37 | L44: =VLOOKUP(K44,clasif_filas!$A$2:$J$39,2,FALSE()) -> Vidrios y productos de vidrio y otros productos no metálicos n.c.p. | M44: =VLOOKUP(K44,clasif_filas!$A$2:$J$39,3,FALSE()) -> 37 | N44: =VLOOKUP(K44,clasif_filas!$A$2:$J$39,4,FALSE()) -> Vidrios y productos de vidrio y otros productos no metálicos n.c.p. | O44: =VLOOKUP(K44,clasif_filas!$A$2:$J$39,5,FALSE()) -> 99 | P44: =VLOOKUP(K44,clasif_filas!$A$2:$J$39,6,FALSE()) -> No Bioeconomía | Q44: =VLOOKUP(K44,clasif_filas!$A$2:$J$39,7,FALSE()) -> 3 | R44: =VLOOKUP(K44,clasif_filas!$A$2:$J$39,8,FALSE()) -> Otros bienes transportables, excepto productos metálicos, maquinaria y equipo | S44: =VLOOKUP(K44,clasif_filas!$A$2:$J$39,9,FALSE()) -> 3 | T44: =VLOOKUP(K44,clasif_filas!$A$2:$J$39,10,FALSE()) -> No bioeconomía
A45: PANof044 | B45: ATF01 | C45: =VLOOKUP(B45, AT_FILAS!$A$2:$C$8,2,FALSE()) -> Producción | D45: =VLOOKUP(B45, AT_FILAS!$A$2:$C$8,3,FALSE()) -> 1 | E45: 2101 | F45: CARNE Y DESPOJOS COMESTIBLES DE GANADO BOVINO | G45: Productos alimentarios_Carne | H45: 2 | I45: Bioeconomía de transformación de productos básicos | J45: Industria alimentaria | K45: 21 | L45: =VLOOKUP(K45,clasif_filas!$A$2:$J$39,2,FALSE()) -> Carne, pescado, frutas, vegetales, aceites y grasas | M45: =VLOOKUP(K45,clasif_filas!$A$2:$J$39,3,FALSE()) -> 21 | N45: =VLOOKUP(K45,clasif_filas!$A$2:$J$39,4,FALSE()) -> Carne, pescado, frutas, vegetales, aceites y grasas | O45: =VLOOKUP(K45,clasif_filas!$A$2:$J$39,5,FALSE()) -> 6 | P45: =VLOOKUP(K45,clasif_filas!$A$2:$J$39,6,FALSE()) -> Conocimiento, procesos y servicios relacionados | Q45: =VLOOKUP(K45,clasif_filas!$A$2:$J$39,7,FALSE()) -> 2 | R45: =VLOOKUP(K45,clasif_filas!$A$2:$J$39,8,FALSE()) -> Productos alimenticios, bebidas y tabaco; textiles, prendas de vestir y productos de cuero | S45: =VLOOKUP(K45,clasif_filas!$A$2:$J$39,9,FALSE()) -> 1 | T45: =VLOOKUP(K45,clasif_filas!$A$2:$J$39,10,FALSE()) -> Bioeconomía
A46: PANof045 | B46: ATF01 | C46: =VLOOKUP(B46, AT_FILAS!$A$2:$C$8,2,FALSE()) -> Producción | D46: =VLOOKUP(B46, AT_FILAS!$A$2:$C$8,3,FALSE()) -> 1 | E46: 2102 | F46: CARNE Y DESPOJOS COMESTIBLES DE GANADO PORCINO | G46: Productos alimentarios_Carne | H46: 2 | I46: Bioeconomía de transformación de productos básicos | J46: Industria alimentaria | K46: 21 | L46: =VLOOKUP(K46,clasif_filas!$A$2:$J$39,2,FALSE()) -> Carne, pescado, frutas, vegetales, aceites y grasas | M46: =VLOOKUP(K46,clasif_filas!$A$2:$J$39,3,FALSE()) -> 21 | N46: =VLOOKUP(K46,clasif_filas!$A$2:$J$39,4,FALSE()) -> Carne, pescado, frutas, vegetales, aceites y grasas | O46: =VLOOKUP(K46,clasif_filas!$A$2:$J$39,5,FALSE()) -> 6 | P46: =VLOOKUP(K46,clasif_filas!$A$2:$J$39,6,FALSE()) -> Conocimiento, procesos y servicios relacionados | Q46: =VLOOKUP(K46,clasif_filas!$A$2:$J$39,7,FALSE()) -> 2 | R46: =VLOOKUP(K46,clasif_filas!$A$2:$J$39,8,FALSE()) -> Productos alimenticios, bebidas y tabaco; textiles, prendas de vestir y productos de cuero | S46: =VLOOKUP(K46,clasif_filas!$A$2:$J$39,9,FALSE()) -> 1 | T46: =VLOOKUP(K46,clasif_filas!$A$2:$J$39,10,FALSE()) -> Bioeconomía
... A52: PANof051 | B52: ATF01 | C52: =VLOOKUP(B52, AT_FILAS!$A$2:$C$8,2,FALSE()) -> Producción | D52: =VLOOKUP(B52, AT_FILAS!$A$2:$C$8,3,FALSE()) -> 1 | E52: 2203 | F52: ACEITES Y GRASAS DE ORIGEN VEGETAL Y ANIMAL | G52: Productos alimentarios_Oleaginosas | H52: 2 | I52: Bioeconomía de transformación de productos básicos | J52: Industria alimentaria | K52: 21 | L52: =VLOOKUP(K52,clasif_filas!$A$2:$J$39,2,FALSE()) -> Carne, pescado, frutas, vegetales, aceites y grasas | M52: =VLOOKUP(K52,clasif_filas!$A$2:$J$39,3,FALSE()) -> 21 | N52: =VLOOKUP(K52,clasif_filas!$A$2:$J$39,4,FALSE()) -> Carne, pescado, frutas, vegetales, aceites y grasas | O52: =VLOOKUP(K52,clasif_filas!$A$2:$J$39,5,FALSE()) -> 6 | P52: =VLOOKUP(K52,clasif_filas!$A$2:$J$39,6,FALSE()) -> Conocimiento, procesos y servicios relacionados | Q52: =VLOOKUP(K52,clasif_filas!$A$2:$J$39,7,FALSE()) -> 2 | R52: =VLOOKUP(K52,clasif_filas!$A$2:$J$39,8,FALSE()) -> Productos alimenticios, bebidas y tabaco; textiles, prendas de vestir y productos de cuero | S52: =VLOOKUP(K52,clasif_filas!$A$2:$J$39,9,FALSE()) -> 1 | T52: =VLOOKUP(K52,clasif_filas!$A$2:$J$39,10,FALSE()) -> Bioeconomía
A53: PANof052 | B53: ATF01 | C53: Producción | D53: =VLOOKUP(B53, AT_FILAS!$A$2:$C$8,3,FALSE()) -> 1 | E53: 2301 | F53: LECHE LÍQUIDA PROCESADA | G53: Productos alimentarios_Lácteos | H53: 2 | I53: Bioeconomía de transformación de productos básicos | J53: Industria alimentaria | K53: 22 | L53: =VLOOKUP(K53,clasif_filas!$A$2:$J$39,2,FALSE()) -> Productos lácteos y productos de huevo | M53: =VLOOKUP(K53,clasif_filas!$A$2:$J$39,3,FALSE()) -> 22 | N53: =VLOOKUP(K53,clasif_filas!$A$2:$J$39,4,FALSE()) -> Productos lácteos y productos de huevo | O53: =VLOOKUP(K53,clasif_filas!$A$2:$J$39,5,FALSE()) -> 6 | P53: =VLOOKUP(K53,clasif_filas!$A$2:$J$39,6,FALSE()) -> Conocimiento, procesos y servicios relacionados | Q53: =VLOOKUP(K53,clasif_filas!$A$2:$J$39,7,FALSE()) -> 2 | R53: =VLOOKUP(K53,clasif_filas!$A$2:$J$39,8,FALSE()) -> Productos alimenticios, bebidas y tabaco; textiles, prendas de vestir y productos de cuero | S53: =VLOOKUP(K53,clasif_filas!$A$2:$J$39,9,FALSE()) -> 1 | T53: =VLOOKUP(K53,clasif_filas!$A$2:$J$39,10,FALSE()) -> Bioeconomía
A54: PANof053 | B54: ATF01 | C54: Producción | D54: =VLOOKUP(B54, AT_FILAS!$A$2:$C$8,3,FALSE()) -> 1 | E54: 2302 | F54: LECHE ENTERA EN POLVO | G54: Productos alimentarios_Lácteos | H54: 2 | I54: Bioeconomía de transformación de productos básicos | J54: Industria alimentaria | K54: 22 | L54: =VLOOKUP(K54,clasif_filas!$A$2:$J$39,2,FALSE()) -> Productos lácteos y productos de huevo | M54: =VLOOKUP(K54,clasif_filas!$A$2:$J$39,3,FALSE()) -> 22 | N54: =VLOOKUP(K54,clasif_filas!$A$2:$J$39,4,FALSE()) -> Productos lácteos y productos de huevo | O54: =VLOOKUP(K54,clasif_filas!$A$2:$J$39,5,FALSE()) -> 6 | P54: =VLOOKUP(K54,clasif_filas!$A$2:$J$39,6,FALSE()) -> Conocimiento, procesos y servicios relacionados | Q54: =VLOOKUP(K54,clasif_filas!$A$2:$J$39,7,FALSE()) -> 2 | R54: =VLOOKUP(K54,clasif_filas!$A$2:$J$39,8,FALSE()) -> Productos alimenticios, bebidas y tabaco; textiles, prendas de vestir y productos de cuero | S54: =VLOOKUP(K54,clasif_filas!$A$2:$J$39,9,FALSE()) -> 1 | T54: =VLOOKUP(K54,clasif_filas!$A$2:$J$39,10,FALSE()) -> Bioeconomía
A55: PANof054 | B55: ATF01 | C55: Producción | D55: =VLOOKUP(B55, AT_FILAS!$A$2:$C$8,3,FALSE()) -> 1 | E55: 2303 | F55: OTROS PRODUCTOS LÁCTEOS N.C.P. | G55: Productos alimentarios_Lácteos | H55: 2 | I55: Bioeconomía de transformación de productos básicos | J55: Industria alimentaria | K55: 22 | L55: =VLOOKUP(K55,clasif_filas!$A$2:$J$39,2,FALSE()) -> Productos lácteos y productos de huevo | M55: =VLOOKUP(K55,clasif_filas!$A$2:$J$39,3,FALSE()) -> 22 | N55: =VLOOKUP(K55,clasif_filas!$A$2:$J$39,4,FALSE()) -> Productos lácteos y productos de huevo | O55: =VLOOKUP(K55,clasif_filas!$A$2:$J$39,5,FALSE()) -> 6 | P55: =VLOOKUP(K55,clasif_filas!$A$2:$J$39,6,FALSE()) -> Conocimiento, procesos y servicios relacionados | Q55: =VLOOKUP(K55,clasif_filas!$A$2:$J$39,7,FALSE()) -> 2 | R55: =VLOOKUP(K55,clasif_filas!$A$2:$J$39,8,FALSE()) -> Productos alimenticios, bebidas y tabaco; textiles, prendas de vestir y productos de cuero | S55: =VLOOKUP(K55,clasif_filas!$A$2:$J$39,9,FALSE()) -> 1 | T55: =VLOOKUP(K55,clasif_filas!$A$2:$J$39,10,FALSE()) -> Bioeconomía
A56: PANof055 | B56: ATF01 | C56: Producción | D56: 1 | E56: 2401 | F56: HARINA DE TRIGO | G56: Productos alimentarios_Cereales | H56: 2 | I56: Bioeconomía de transformación de productos básicos | J56: Industria alimentaria | K56: 23 | L56: =VLOOKUP(K56,clasif_filas!$A$2:$J$39,2,FALSE()) -> Productos de molienda, productos con almidón o maicena; otros productos de alimenticios | M56: =VLOOKUP(K56,clasif_filas!$A$2:$J$39,3,FALSE()) -> 23 | N56: =VLOOKUP(K56,clasif_filas!$A$2:$J$39,4,FALSE()) -> Productos de molienda, productos con almidón o maicena; otros productos de alimenticios | O56: =VLOOKUP(K56,clasif_filas!$A$2:$J$39,5,FALSE()) -> 6 | P56: =VLOOKUP(K56,clasif_filas!$A$2:$J$39,6,FALSE()) -> Conocimiento, procesos y servicios relacionados | Q56: =VLOOKUP(K56,clasif_filas!$A$2:$J$39,7,FALSE()) -> 2 | R56: =VLOOKUP(K56,clasif_filas!$A$2:$J$39,8,FALSE()) -> Productos alimenticios, bebidas y tabaco; textiles, prendas de vestir y productos de cuero | S56: =VLOOKUP(K56,clasif_filas!$A$2:$J$39,9,FALSE()) -> 1 | T56: =VLOOKUP(K56,clasif_filas!$A$2:$J$39,10,FALSE()) -> Bioeconomía
A57: PANof056 | B57: ATF01 | C57: Producción | D57: 1 | E57: 2402 | F57: ARROZ SIN CÁSCARA | G57: Productos alimentarios_Cereales | H57: 2 | I57: Bioeconomía de transformación de productos básicos | J57: Industria alimentaria | K57: 23 | L57: =VLOOKUP(K57,clasif_filas!$A$2:$J$39,2,FALSE()) -> Productos de molienda, productos con almidón o maicena; otros productos de alimenticios | M57: =VLOOKUP(K57,clasif_filas!$A$2:$J$39,3,FALSE()) -> 23 | N57: =VLOOKUP(K57,clasif_filas!$A$2:$J$39,4,FALSE()) -> Productos de molienda, productos con almidón o maicena; otros productos de alimenticios | O57: =VLOOKUP(K57,clasif_filas!$A$2:$J$39,5,FALSE()) -> 6 | P57: =VLOOKUP(K57,clasif_filas!$A$2:$J$39,6,FALSE()) -> Conocimiento, procesos y servicios relacionados | Q57: =VLOOKUP(K57,clasif_filas!$A$2:$J$39,7,FALSE()) -> 2 | R57: =VLOOKUP(K57,clasif_filas!$A$2:$J$39,8,FALSE()) -> Productos alimenticios, bebidas y tabaco; textiles, prendas de vestir y productos de cuero | S57: =VLOOKUP(K57,clasif_filas!$A$2:$J$39,9,FALSE()) -> 1 | T57: =VLOOKUP(K57,clasif_filas!$A$2:$J$39,10,FALSE()) -> Bioeconomía
A58: PANof057 | B58: ATF01 | C58: Producción | D58: 1 | E58: 2403 | F58: OTROS PRODUCTOS DE MOLINERÍA N.C.P. Y ALMIDONES Y SUS PRODUCTOS, AZUCARES Y JARABES DE AZÚCAR N.C.P. | G58: Productos alimentarios_Cereales | H58: 2 | I58: Bioeconomía de transformación de productos básicos | J58: Industria alimentaria | K58: 23 | L58: =VLOOKUP(K58,clasif_filas!$A$2:$J$39,2,FALSE()) -> Productos de molienda, productos con almidón o maicena; otros productos de alimenticios | M58: =VLOOKUP(K58,clasif_filas!$A$2:$J$39,3,FALSE()) -> 23 | N58: =VLOOKUP(K58,clasif_filas!$A$2:$J$39,4,FALSE()) -> Productos de molienda, productos con almidón o maicena; otros productos de alimenticios | O58: =VLOOKUP(K58,clasif_filas!$A$2:$J$39,5,FALSE()) -> 6 | P58: =VLOOKUP(K58,clasif_filas!$A$2:$J$39,6,FALSE()) -> Conocimiento, procesos y servicios relacionados | Q58: =VLOOKUP(K58,clasif_filas!$A$2:$J$39,7,FALSE()) -> 2 | R58: =VLOOKUP(K58,clasif_filas!$A$2:$J$39,8,FALSE()) -> Productos alimenticios, bebidas y tabaco; textiles, prendas de vestir y productos de cuero | S58: =VLOOKUP(K58,clasif_filas!$A$2:$J$39,9,FALSE()) -> 1 | T58: =VLOOKUP(K58,clasif_filas!$A$2:$J$39,10,FALSE()) -> Bioeconomía
A59: PANof058 | B59: ATF01 | C59: Producción | D59: 1 | E59: 2404 | F59: PRODUCTOS DE PANADERÍA | G59: Productos alimentarios_Cereales | H59: 2 | I59: Bioeconomía de transformación de productos básicos | J59: Industria alimentaria | K59: 23 | L59: =VLOOKUP(K59,clasif_filas!$A$2:$J$39,2,FALSE()) -> Productos de molienda, productos con almidón o maicena; otros productos de alimenticios | M59: =VLOOKUP(K59,clasif_filas!$A$2:$J$39,3,FALSE()) -> 23 | N59: =VLOOKUP(K59,clasif_filas!$A$2:$J$39,4,FALSE()) -> Productos de molienda, productos con almidón o maicena; otros productos de alimenticios | O59: =VLOOKUP(K59,clasif_filas!$A$2:$J$39,5,FALSE()) -> 6 | P59: =VLOOKUP(K59,clasif_filas!$A$2:$J$39,6,FALSE()) -> Conocimiento, procesos y servicios relacionados | Q59: =VLOOKUP(K59,clasif_filas!$A$2:$J$39,7,FALSE()) -> 2 | R59: =VLOOKUP(K59,clasif_filas!$A$2:$J$39,8,FALSE()) -> Productos alimenticios, bebidas y tabaco; textiles, prendas de vestir y productos de cuero | S59: =VLOOKUP(K59,clasif_filas!$A$2:$J$39,9,FALSE()) -> 1 | T59: =VLOOKUP(K59,clasif_filas!$A$2:$J$39,10,FALSE()) -> Bioeconomía
A60: PANof059 | B60: ATF01 | C60: Producción | D60: 1 | E60: 2405 | F60: AZÚCAR | G60: Productos alimentarios_Azúcar | H60: 2 | I60: Bioeconomía de transformación de productos básicos | J60: Industria alimentaria | K60: 23 | L60: =VLOOKUP(K60,clasif_filas!$A$2:$J$39,2,FALSE()) -> Productos de molienda, productos con almidón o maicena; otros productos de alimenticios | M60: =VLOOKUP(K60,clasif_filas!$A$2:$J$39,3,FALSE()) -> 23 | N60: =VLOOKUP(K60,clasif_filas!$A$2:$J$39,4,FALSE()) -> Productos de molienda, productos con almidón o maicena; otros productos de alimenticios | O60: =VLOOKUP(K60,clasif_filas!$A$2:$J$39,5,FALSE()) -> 6 | P60: =VLOOKUP(K60,clasif_filas!$A$2:$J$39,6,FALSE()) -> Conocimiento, procesos y servicios relacionados | Q60: =VLOOKUP(K60,clasif_filas!$A$2:$J$39,7,FALSE()) -> 2 | R60: =VLOOKUP(K60,clasif_filas!$A$2:$J$39,8,FALSE()) -> Productos alimenticios, bebidas y tabaco; textiles, prendas de vestir y productos de cuero | S60: =VLOOKUP(K60,clasif_filas!$A$2:$J$39,9,FALSE()) -> 1 | T60: =VLOOKUP(K60,clasif_filas!$A$2:$J$39,10,FALSE()) -> Bioeconomía
A61: PANof060 | B61: ATF01 | C61: Producción | D61: 1 | E61: 2406 | F61: CACAO, CHOCOLATE Y ARTÍCULOS DE CONFITERÍA PREPARADOS CON AZÚCAR | G61: Productos alimentarios_Otros | H61: 2 | I61: Bioeconomía de transformación de productos básicos | J61: Industria alimentaria | K61: 23 | L61: =VLOOKUP(K61,clasif_filas!$A$2:$J$39,2,FALSE()) -> Productos de molienda, productos con almidón o maicena; otros productos de alimenticios | M61: =VLOOKUP(K61,clasif_filas!$A$2:$J$39,3,FALSE()) -> 23 | N61: =VLOOKUP(K61,clasif_filas!$A$2:$J$39,4,FALSE()) -> Productos de molienda, productos con almidón o maicena; otros productos de alimenticios | O61: =VLOOKUP(K61,clasif_filas!$A$2:$J$39,5,FALSE()) -> 6 | P61: =VLOOKUP(K61,clasif_filas!$A$2:$J$39,6,FALSE()) -> Conocimiento, procesos y servicios relacionados | Q61: =VLOOKUP(K61,clasif_filas!$A$2:$J$39,7,FALSE()) -> 2 | R61: =VLOOKUP(K61,clasif_filas!$A$2:$J$39,8,FALSE()) -> Productos alimenticios, bebidas y tabaco; textiles, prendas de vestir y productos de cuero | S61: =VLOOKUP(K61,clasif_filas!$A$2:$J$39,9,FALSE()) -> 1 | T61: =VLOOKUP(K61,clasif_filas!$A$2:$J$39,10,FALSE()) -> Bioeconomía
A62: PANof061 | B62: ATF01 | C62: Producción | D62: 1 | E62: 2407 | F62: MACARRONES, FIDEOS Y PRODUCTOS FARINÁCEOS ANÁLOGOS | G62: Productos alimentarios_Cereales | H62: 2 | I62: Bioeconomía de transformación de productos básicos | J62: Industria alimentaria | K62: 23 | L62: =VLOOKUP(K62,clasif_filas!$A$2:$J$39,2,FALSE()) -> Productos de molienda, productos con almidón o maicena; otros productos de alimenticios | M62: =VLOOKUP(K62,clasif_filas!$A$2:$J$39,3,FALSE()) -> 23 | N62: =VLOOKUP(K62,clasif_filas!$A$2:$J$39,4,FALSE()) -> Productos de molienda, productos con almidón o maicena; otros productos de alimenticios | O62: =VLOOKUP(K62,clasif_filas!$A$2:$J$39,5,FALSE()) -> 6 | P62: =VLOOKUP(K62,clasif_filas!$A$2:$J$39,6,FALSE()) -> Conocimiento, procesos y servicios relacionados | Q62: =VLOOKUP(K62,clasif_filas!$A$2:$J$39,7,FALSE()) -> 2 | R62: =VLOOKUP(K62,clasif_filas!$A$2:$J$39,8,FALSE()) -> Productos alimenticios, bebidas y tabaco; textiles, prendas de vestir y productos de cuero | S62: =VLOOKUP(K62,clasif_filas!$A$2:$J$39,9,FALSE()) -> 1 | T62: =VLOOKUP(K62,clasif_filas!$A$2:$J$39,10,FALSE()) -> Bioeconomía
A63: PANof062 | B63: ATF01 | C63: Producción | D63: 1 | E63: 2408 | F63: PRODUCTOS ALIMENTICIOS N.C.P | G63: Productos alimentarios_Otros | H63: 2 | I63: Bioeconomía de transformación de productos básicos | J63: Industria alimentaria | K63: 23 | L63: =VLOOKUP(K63,clasif_filas!$A$2:$J$39,2,FALSE()) -> Productos de molienda, productos con almidón o maicena; otros productos de alimenticios | M63: =VLOOKUP(K63,clasif_filas!$A$2:$J$39,3,FALSE()) -> 23 | N63: =VLOOKUP(K63,clasif_filas!$A$2:$J$39,4,FALSE()) -> Productos de molienda, productos con almidón o maicena; otros productos de alimenticios | O63: =VLOOKUP(K63,clasif_filas!$A$2:$J$39,5,FALSE()) -> 6 | P63: =VLOOKUP(K63,clasif_filas!$A$2:$J$39,6,FALSE()) -> Conocimiento, procesos y servicios relacionados | Q63: =VLOOKUP(K63,clasif_filas!$A$2:$J$39,7,FALSE()) -> 2 | R63: =VLOOKUP(K63,clasif_filas!$A$2:$J$39,8,FALSE()) -> Productos alimenticios, bebidas y tabaco; textiles, prendas de vestir y productos de cuero | S63: =VLOOKUP(K63,clasif_filas!$A$2:$J$39,9,FALSE()) -> 1 | T63: =VLOOKUP(K63,clasif_filas!$A$2:$J$39,10,FALSE()) -> Bioeconomía
A64: PANof063 | B64: ATF01 | C64: Producción | D64: 1 | E64: 2409 | F64: PREPARADOS DEL TIPO UTILIZADOS PARA LA ALIMENTACIÓN DE ANIMALES | G64: Piensos | H64: 2 | I64: Bioeconomía de transformación de productos básicos | J64: Piensos | K64: 21 | L64: =VLOOKUP(K64,clasif_filas!$A$2:$J$39,2,FALSE()) -> Carne, pescado, frutas, vegetales, aceites y grasas | M64: =VLOOKUP(K64,clasif_filas!$A$2:$J$39,3,FALSE()) -> 21 | N64: =VLOOKUP(K64,clasif_filas!$A$2:$J$39,4,FALSE()) -> Carne, pescado, frutas, vegetales, aceites y grasas | O64: =VLOOKUP(K64,clasif_filas!$A$2:$J$39,5,FALSE()) -> 6 | P64: =VLOOKUP(K64,clasif_filas!$A$2:$J$39,6,FALSE()) -> Conocimiento, procesos y servicios relacionados | Q64: =VLOOKUP(K64,clasif_filas!$A$2:$J$39,7,FALSE()) -> 2 | R64: =VLOOKUP(K64,clasif_filas!$A$2:$J$39,8,FALSE()) -> Productos alimenticios, bebidas y tabaco; textiles, prendas de vestir y productos de cuero | S64: =VLOOKUP(K64,clasif_filas!$A$2:$J$39,9,FALSE()) -> 1 | T64: =VLOOKUP(K64,clasif_filas!$A$2:$J$39,10,FALSE()) -> Bioeconomía
A65: PANof064 | B65: ATF01 | C65: Producción | D65: 1 | E65: 2501 | F65: ALCOHOL ETÍLICO, BEBIDAS ALCOHÓLICAS, LICORES Y OTRAS BEBIDAS ALCOHÓLICAS | G65: Productos alimentarios_Bebidas | H65: 2 | I65: Bioeconomía de transformación de productos básicos | J65: Industria alimentaria | K65: 24 | L65: =VLOOKUP(K65,clasif_filas!$A$2:$J$39,2,FALSE()) -> Bebidas | M65: =VLOOKUP(K65,clasif_filas!$A$2:$J$39,3,FALSE()) -> 24 | N65: =VLOOKUP(K65,clasif_filas!$A$2:$J$39,4,FALSE()) -> Bebidas | O65: =VLOOKUP(K65,clasif_filas!$A$2:$J$39,5,FALSE()) -> 6 | P65: =VLOOKUP(K65,clasif_filas!$A$2:$J$39,6,FALSE()) -> Conocimiento, procesos y servicios relacionados | Q65: =VLOOKUP(K65,clasif_filas!$A$2:$J$39,7,FALSE()) -> 2 | R65: =VLOOKUP(K65,clasif_filas!$A$2:$J$39,8,FALSE()) -> Productos alimenticios, bebidas y tabaco; textiles, prendas de vestir y productos de cuero | S65: =VLOOKUP(K65,clasif_filas!$A$2:$J$39,9,FALSE()) -> 1 | T65: =VLOOKUP(K65,clasif_filas!$A$2:$J$39,10,FALSE()) -> Bioeconomía
A66: PANof065 | B66: ATF01 | C66: Producción | D66: 1 | E66: 2502 | F66: VINOS | G66: Productos alimentarios_Bebidas | H66: 2 | I66: Bioeconomía de transformación de productos básicos | J66: Industria alimentaria | K66: 24 | L66: =VLOOKUP(K66,clasif_filas!$A$2:$J$39,2,FALSE()) -> Bebidas | M66: =VLOOKUP(K66,clasif_filas!$A$2:$J$39,3,FALSE()) -> 24 | N66: =VLOOKUP(K66,clasif_filas!$A$2:$J$39,4,FALSE()) -> Bebidas | O66: =VLOOKUP(K66,clasif_filas!$A$2:$J$39,5,FALSE()) -> 6 | P66: =VLOOKUP(K66,clasif_filas!$A$2:$J$39,6,FALSE()) -> Conocimiento, procesos y servicios relacionados | Q66: =VLOOKUP(K66,clasif_filas!$A$2:$J$39,7,FALSE()) -> 2 | R66: =VLOOKUP(K66,clasif_filas!$A$2:$J$39,8,FALSE()) -> Productos alimenticios, bebidas y tabaco; textiles, prendas de vestir y productos de cuero | S66: =VLOOKUP(K66,clasif_filas!$A$2:$J$39,9,FALSE()) -> 1 | T66: =VLOOKUP(K66,clasif_filas!$A$2:$J$39,10,FALSE()) -> Bioeconomía
A67: PANof066 | B67: ATF01 | C67: Producción | D67: 1 | E67: 2503 | F67: LICORES DE MALTA Y MALTA | G67: Productos alimentarios_Bebidas | H67: 2 | I67: Bioeconomía de transformación de productos básicos | J67: Industria alimentaria | K67: 24 | L67: =VLOOKUP(K67,clasif_filas!$A$2:$J$39,2,FALSE()) -> Bebidas | M67: =VLOOKUP(K67,clasif_filas!$A$2:$J$39,3,FALSE()) -> 24 | N67: =VLOOKUP(K67,clasif_filas!$A$2:$J$39,4,FALSE()) -> Bebidas | O67: =VLOOKUP(K67,clasif_filas!$A$2:$J$39,5,FALSE()) -> 6 | P67: =VLOOKUP(K67,clasif_filas!$A$2:$J$39,6,FALSE()) -> Conocimiento, procesos y servicios relacionados | Q67: =VLOOKUP(K67,clasif_filas!$A$2:$J$39,7,FALSE()) -> 2 | R67: =VLOOKUP(K67,clasif_filas!$A$2:$J$39,8,FALSE()) -> Productos alimenticios, bebidas y tabaco; textiles, prendas de vestir y productos de cuero | S67: =VLOOKUP(K67,clasif_filas!$A$2:$J$39,9,FALSE()) -> 1 | T67: =VLOOKUP(K67,clasif_filas!$A$2:$J$39,10,FALSE()) -> Bioeconomía
... A104: PANof103 | B104: ATF01 | C104: Producción | D104: 1 | E104: 3706 | F104: OTROS MINERALES NO METÁLICOS | G104: No bioeconomía | H104: 4 | I104: No bioeconomía | J104: No bioeconomía | K104: 11 | L104: =VLOOKUP(K104,clasif_filas!$A$2:$J$39,2,FALSE()) -> Minerales, combustibles y derivados | M104: =VLOOKUP(K104,clasif_filas!$A$2:$J$39,3,FALSE()) -> 11 | N104: =VLOOKUP(K104,clasif_filas!$A$2:$J$39,4,FALSE()) -> Minerales, combustibles y derivados | O104: =VLOOKUP(K104,clasif_filas!$A$2:$J$39,5,FALSE()) -> 99 | P104: =VLOOKUP(K104,clasif_filas!$A$2:$J$39,6,FALSE()) -> No Bioeconomía | Q104: =VLOOKUP(K104,clasif_filas!$A$2:$J$39,7,FALSE()) -> 1 | R104: =VLOOKUP(K104,clasif_filas!$A$2:$J$39,8,FALSE()) -> Minerales; electricidad, gas y agua | S104: =VLOOKUP(K104,clasif_filas!$A$2:$J$39,9,FALSE()) -> 3 | T104: =VLOOKUP(K104,clasif_filas!$A$2:$J$39,10,FALSE()) -> No bioeconomía
A105: PANof104 | B105: ATF01 | C105: Producción | D105: 1 | E105: 3801 | F105: PRODUCTOS BÁSICOS DE HIERRO Y ACERO | G105: No bioeconomía | H105: 4 | I105: No bioeconomía | J105: No bioeconomía | K105: 41-49 | L105: =VLOOKUP(K105,clasif_filas!$A$2:$J$39,2,FALSE()) -> Metales, Maquianria, equipos y transporte | M105: =VLOOKUP(K105,clasif_filas!$A$2:$J$39,3,FALSE()) -> 41-49 | N105: =VLOOKUP(K105,clasif_filas!$A$2:$J$39,4,FALSE()) -> Metales, Maquianria, equipos y transporte | O105: =VLOOKUP(K105,clasif_filas!$A$2:$J$39,5,FALSE()) -> 99 | P105: =VLOOKUP(K105,clasif_filas!$A$2:$J$39,6,FALSE()) -> No Bioeconomía | Q105: =VLOOKUP(K105,clasif_filas!$A$2:$J$39,7,FALSE()) -> 4 | R105: =VLOOKUP(K105,clasif_filas!$A$2:$J$39,8,FALSE()) -> Productos metálicos, maquinaria y equipo | S105: =VLOOKUP(K105,clasif_filas!$A$2:$J$39,9,FALSE()) -> 3 | T105: =VLOOKUP(K105,clasif_filas!$A$2:$J$39,10,FALSE()) -> No bioeconomía
A106: PANof105 | B106: ATF01 | C106: Producción | D106: 1 | E106: 3802 | F106: PRODUCTOS PRIMARIOS DE METALES PRECIOSOS Y METALES NO FERROSOS | G106: No bioeconomía | H106: 4 | I106: No bioeconomía | J106: No bioeconomía | K106: 41-49 | L106: =VLOOKUP(K106,clasif_filas!$A$2:$J$39,2,FALSE()) -> Metales, Maquianria, equipos y transporte | M106: =VLOOKUP(K106,clasif_filas!$A$2:$J$39,3,FALSE()) -> 41-49 | N106: =VLOOKUP(K106,clasif_filas!$A$2:$J$39,4,FALSE()) -> Metales, Maquianria, equipos y transporte | O106: =VLOOKUP(K106,clasif_filas!$A$2:$J$39,5,FALSE()) -> 99 | P106: =VLOOKUP(K106,clasif_filas!$A$2:$J$39,6,FALSE()) -> No Bioeconomía | Q106: =VLOOKUP(K106,clasif_filas!$A$2:$J$39,7,FALSE()) -> 4 | R106: =VLOOKUP(K106,clasif_filas!$A$2:$J$39,8,FALSE()) -> Productos metálicos, maquinaria y equipo | S106: =VLOOKUP(K106,clasif_filas!$A$2:$J$39,9,FALSE()) -> 3 | T106: =VLOOKUP(K106,clasif_filas!$A$2:$J$39,10,FALSE()) -> No bioeconomía
A107: PANof106 | B107: ATF01 | C107: Producción | D107: 1 | E107: 3901 | F107: PRODUCTOS METÁLICOS ESTRUCTURALES Y SUS PARTES | G107: No bioeconomía | H107: 4 | I107: No bioeconomía | J107: No bioeconomía | K107: 41-49 | L107: =VLOOKUP(K107,clasif_filas!$A$2:$J$39,2,FALSE()) -> Metales, Maquianria, equipos y transporte | M107: =VLOOKUP(K107,clasif_filas!$A$2:$J$39,3,FALSE()) -> 41-49 | N107: =VLOOKUP(K107,clasif_filas!$A$2:$J$39,4,FALSE()) -> Metales, Maquianria, equipos y transporte | O107: =VLOOKUP(K107,clasif_filas!$A$2:$J$39,5,FALSE()) -> 99 | P107: =VLOOKUP(K107,clasif_filas!$A$2:$J$39,6,FALSE()) -> No Bioeconomía | Q107: =VLOOKUP(K107,clasif_filas!$A$2:$J$39,7,FALSE()) -> 4 | R107: =VLOOKUP(K107,clasif_filas!$A$2:$J$39,8,FALSE()) -> Productos metálicos, maquinaria y equipo | S107: =VLOOKUP(K107,clasif_filas!$A$2:$J$39,9,FALSE()) -> 3 | T107: =VLOOKUP(K107,clasif_filas!$A$2:$J$39,10,FALSE()) -> No bioeconomía
A108: PANof107 | B108: ATF01 | C108: Producción | D108: 1 | E108: 3902 | F108: OTROS PRODUCTOS METÁLICOS ELABORADOS | G108: No bioeconomía | H108: 4 | I108: No bioeconomía | J108: No bioeconomía | K108: 41-49 | L108: =VLOOKUP(K108,clasif_filas!$A$2:$J$39,2,FALSE()) -> Metales, Maquianria, equipos y transporte | M108: =VLOOKUP(K108,clasif_filas!$A$2:$J$39,3,FALSE()) -> 41-49 | N108: =VLOOKUP(K108,clasif_filas!$A$2:$J$39,4,FALSE()) -> Metales, Maquianria, equipos y transporte | O108: =VLOOKUP(K108,clasif_filas!$A$2:$J$39,5,FALSE()) -> 99 | P108: =VLOOKUP(K108,clasif_filas!$A$2:$J$39,6,FALSE()) -> No Bioeconomía | Q108: =VLOOKUP(K108,clasif_filas!$A$2:$J$39,7,FALSE()) -> 4 | R108: =VLOOKUP(K108,clasif_filas!$A$2:$J$39,8,FALSE()) -> Productos metálicos, maquinaria y equipo | S108: =VLOOKUP(K108,clasif_filas!$A$2:$J$39,9,FALSE()) -> 3 | T108: =VLOOKUP(K108,clasif_filas!$A$2:$J$39,10,FALSE()) -> No bioeconomía
A109: PANof108 | B109: ATF01 | C109: Producción | D109: 1 | E109: 4001 | F109: MAQUINARIA PARA USOS GENERALES, SUS PARTES Y PIEZAS | G109: No bioeconomía | H109: 4 | I109: No bioeconomía | J109: No bioeconomía | K109: 41-49 | L109: =VLOOKUP(K109,clasif_filas!$A$2:$J$39,2,FALSE()) -> Metales, Maquianria, equipos y transporte | M109: =VLOOKUP(K109,clasif_filas!$A$2:$J$39,3,FALSE()) -> 41-49 | N109: =VLOOKUP(K109,clasif_filas!$A$2:$J$39,4,FALSE()) -> Metales, Maquianria, equipos y transporte | O109: =VLOOKUP(K109,clasif_filas!$A$2:$J$39,5,FALSE()) -> 99 | P109: =VLOOKUP(K109,clasif_filas!$A$2:$J$39,6,FALSE()) -> No Bioeconomía | Q109: =VLOOKUP(K109,clasif_filas!$A$2:$J$39,7,FALSE()) -> 4 | R109: =VLOOKUP(K109,clasif_filas!$A$2:$J$39,8,FALSE()) -> Productos metálicos, maquinaria y equipo | S109: =VLOOKUP(K109,clasif_filas!$A$2:$J$39,9,FALSE()) -> 3 | T109: =VLOOKUP(K109,clasif_filas!$A$2:$J$39,10,FALSE()) -> No bioeconomía
A110: PANof109 | B110: ATF01 | C110: Producción | D110: 1 | E110: 4002 | F110: MAQUINARIA PARA USOS ESPECIALES, SUS PARTES Y PIEZAS; EXC. APARATOS DE USO DOMÉSTICO | G110: No bioeconomía | H110: 4 | I110: No bioeconomía | J110: No bioeconomía | K110: 41-49 | L110: =VLOOKUP(K110,clasif_filas!$A$2:$J$39,2,FALSE()) -> Metales, Maquianria, equipos y transporte | M110: =VLOOKUP(K110,clasif_filas!$A$2:$J$39,3,FALSE()) -> 41-49 | N110: =VLOOKUP(K110,clasif_filas!$A$2:$J$39,4,FALSE()) -> Metales, Maquianria, equipos y transporte | O110: =VLOOKUP(K110,clasif_filas!$A$2:$J$39,5,FALSE()) -> 99 | P110: =VLOOKUP(K110,clasif_filas!$A$2:$J$39,6,FALSE()) -> No Bioeconomía | Q110: =VLOOKUP(K110,clasif_filas!$A$2:$J$39,7,FALSE()) -> 4 | R110: =VLOOKUP(K110,clasif_filas!$A$2:$J$39,8,FALSE()) -> Productos metálicos, maquinaria y equipo | S110: =VLOOKUP(K110,clasif_filas!$A$2:$J$39,9,FALSE()) -> 3 | T110: =VLOOKUP(K110,clasif_filas!$A$2:$J$39,10,FALSE()) -> No bioeconomía
A111: PANof110 | B111: ATF01 | C111: Producción | D111: 1 | E111: 4003 | F111: APARATOS DE USO DOMÉSTICO, SUS PARTES Y PIEZAS | G111: No bioeconomía | H111: 4 | I111: No bioeconomía | J111: No bioeconomía | K111: 41-49 | L111: =VLOOKUP(K111,clasif_filas!$A$2:$J$39,2,FALSE()) -> Metales, Maquianria, equipos y transporte | M111: =VLOOKUP(K111,clasif_filas!$A$2:$J$39,3,FALSE()) -> 41-49 | N111: =VLOOKUP(K111,clasif_filas!$A$2:$J$39,4,FALSE()) -> Metales, Maquianria, equipos y transporte | O111: =VLOOKUP(K111,clasif_filas!$A$2:$J$39,5,FALSE()) -> 99 | P111: =VLOOKUP(K111,clasif_filas!$A$2:$J$39,6,FALSE()) -> No Bioeconomía | Q111: =VLOOKUP(K111,clasif_filas!$A$2:$J$39,7,FALSE()) -> 4 | R111: =VLOOKUP(K111,clasif_filas!$A$2:$J$39,8,FALSE()) -> Productos metálicos, maquinaria y equipo | S111: =VLOOKUP(K111,clasif_filas!$A$2:$J$39,9,FALSE()) -> 3 | T111: =VLOOKUP(K111,clasif_filas!$A$2:$J$39,10,FALSE()) -> No bioeconomía
A112: PANof111 | B112: ATF01 | C112: Producción | D112: 1 | E112: 4004 | F112: MAQUINARIA DE OFICINA Y DE CONTABILIDAD; SUS PARTES Y PIEZAS | G112: No bioeconomía | H112: 4 | I112: No bioeconomía | J112: No bioeconomía | K112: 41-49 | L112: =VLOOKUP(K112,clasif_filas!$A$2:$J$39,2,FALSE()) -> Metales, Maquianria, equipos y transporte | M112: =VLOOKUP(K112,clasif_filas!$A$2:$J$39,3,FALSE()) -> 41-49 | N112: =VLOOKUP(K112,clasif_filas!$A$2:$J$39,4,FALSE()) -> Metales, Maquianria, equipos y transporte | O112: =VLOOKUP(K112,clasif_filas!$A$2:$J$39,5,FALSE()) -> 99 | P112: =VLOOKUP(K112,clasif_filas!$A$2:$J$39,6,FALSE()) -> No Bioeconomía | Q112: =VLOOKUP(K112,clasif_filas!$A$2:$J$39,7,FALSE()) -> 4 | R112: =VLOOKUP(K112,clasif_filas!$A$2:$J$39,8,FALSE()) -> Productos metálicos, maquinaria y equipo | S112: =VLOOKUP(K112,clasif_filas!$A$2:$J$39,9,FALSE()) -> 3 | T112: =VLOOKUP(K112,clasif_filas!$A$2:$J$39,10,FALSE()) -> No bioeconomía
A113: PANof112 | B113: ATF01 | C113: Producción | D113: 1 | E113: 4005 | F113: MAQUINARIA Y APARATOS ELÉCTRICOS, Y SUS PARTES Y PIEZAS | G113: No bioeconomía | H113: 4 | I113: No bioeconomía | J113: No bioeconomía | K113: 41-49 | L113: =VLOOKUP(K113,clasif_filas!$A$2:$J$39,2,FALSE()) -> Metales, Maquianria, equipos y transporte | M113: =VLOOKUP(K113,clasif_filas!$A$2:$J$39,3,FALSE()) -> 41-49 | N113: =VLOOKUP(K113,clasif_filas!$A$2:$J$39,4,FALSE()) -> Metales, Maquianria, equipos y transporte | O113: =VLOOKUP(K113,clasif_filas!$A$2:$J$39,5,FALSE()) -> 99 | P113: =VLOOKUP(K113,clasif_filas!$A$2:$J$39,6,FALSE()) -> No Bioeconomía | Q113: =VLOOKUP(K113,clasif_filas!$A$2:$J$39,7,FALSE()) -> 4 | R113: =VLOOKUP(K113,clasif_filas!$A$2:$J$39,8,FALSE()) -> Productos metálicos, maquinaria y equipo | S113: =VLOOKUP(K113,clasif_filas!$A$2:$J$39,9,FALSE()) -> 3 | T113: =VLOOKUP(K113,clasif_filas!$A$2:$J$39,10,FALSE()) -> No bioeconomía
A114: PANof113 | B114: ATF01 | C114: Producción | D114: 1 | E114: 4006 | F114: EQUIPOS Y APARATOS PARA RADIO, TELEVISIÓN Y COMUNICACIONES | G114: No bioeconomía | H114: 4 | I114: No bioeconomía | J114: No bioeconomía | K114: 41-49 | L114: =VLOOKUP(K114,clasif_filas!$A$2:$J$39,2,FALSE()) -> Metales, Maquianria, equipos y transporte | M114: =VLOOKUP(K114,clasif_filas!$A$2:$J$39,3,FALSE()) -> 41-49 | N114: =VLOOKUP(K114,clasif_filas!$A$2:$J$39,4,FALSE()) -> Metales, Maquianria, equipos y transporte | O114: =VLOOKUP(K114,clasif_filas!$A$2:$J$39,5,FALSE()) -> 99 | P114: =VLOOKUP(K114,clasif_filas!$A$2:$J$39,6,FALSE()) -> No Bioeconomía | Q114: =VLOOKUP(K114,clasif_filas!$A$2:$J$39,7,FALSE()) -> 4 | R114: =VLOOKUP(K114,clasif_filas!$A$2:$J$39,8,FALSE()) -> Productos metálicos, maquinaria y equipo | S114: =VLOOKUP(K114,clasif_filas!$A$2:$J$39,9,FALSE()) -> 3 | T114: =VLOOKUP(K114,clasif_filas!$A$2:$J$39,10,FALSE()) -> No bioeconomía
A115: PANof114 | B115: ATF01 | C115: Producción | D115: 1 | E115: 4007 | F115: APARATOS MÉDICOS, INSTRUMENTOS ÓPTICOS Y DE PRECISIÓN, RELOJES; SUS PARTES Y PIEZAS | G115: No bioeconomía | H115: 4 | I115: No bioeconomía | J115: No bioeconomía | K115: 41-49 | L115: =VLOOKUP(K115,clasif_filas!$A$2:$J$39,2,FALSE()) -> Metales, Maquianria, equipos y transporte | M115: =VLOOKUP(K115,clasif_filas!$A$2:$J$39,3,FALSE()) -> 41-49 | N115: =VLOOKUP(K115,clasif_filas!$A$2:$J$39,4,FALSE()) -> Metales, Maquianria, equipos y transporte | O115: =VLOOKUP(K115,clasif_filas!$A$2:$J$39,5,FALSE()) -> 99 | P115: =VLOOKUP(K115,clasif_filas!$A$2:$J$39,6,FALSE()) -> No Bioeconomía | Q115: =VLOOKUP(K115,clasif_filas!$A$2:$J$39,7,FALSE()) -> 4 | R115: =VLOOKUP(K115,clasif_filas!$A$2:$J$39,8,FALSE()) -> Productos metálicos, maquinaria y equipo | S115: =VLOOKUP(K115,clasif_filas!$A$2:$J$39,9,FALSE()) -> 3 | T115: =VLOOKUP(K115,clasif_filas!$A$2:$J$39,10,FALSE()) -> No bioeconomía
A116: PANof115 | B116: ATF01 | C116: Producción | D116: 1 | E116: 4008 | F116: EQUIPOS DE TRANSPORTES, SUS PARTES Y PIEZAS | G116: No bioeconomía | H116: 4 | I116: No bioeconomía | J116: No bioeconomía | K116: 41-49 | L116: =VLOOKUP(K116,clasif_filas!$A$2:$J$39,2,FALSE()) -> Metales, Maquianria, equipos y transporte | M116: =VLOOKUP(K116,clasif_filas!$A$2:$J$39,3,FALSE()) -> 41-49 | N116: =VLOOKUP(K116,clasif_filas!$A$2:$J$39,4,FALSE()) -> Metales, Maquianria, equipos y transporte | O116: =VLOOKUP(K116,clasif_filas!$A$2:$J$39,5,FALSE()) -> 99 | P116: =VLOOKUP(K116,clasif_filas!$A$2:$J$39,6,FALSE()) -> No Bioeconomía | Q116: =VLOOKUP(K116,clasif_filas!$A$2:$J$39,7,FALSE()) -> 4 | R116: =VLOOKUP(K116,clasif_filas!$A$2:$J$39,8,FALSE()) -> Productos metálicos, maquinaria y equipo | S116: =VLOOKUP(K116,clasif_filas!$A$2:$J$39,9,FALSE()) -> 3 | T116: =VLOOKUP(K116,clasif_filas!$A$2:$J$39,10,FALSE()) -> No bioeconomía
A117: PANof116 | B117: ATF01 | C117: Producción | D117: 1 | E117: 4101 | F117: MUEBLES | G117: No bioeconomía | H117: 4 | I117: No bioeconomía | J117: No bioeconomía | K117: 38 | L117: =VLOOKUP(K117,clasif_filas!$A$2:$J$39,2,FALSE()) -> Muebles; otros bienes transportables n.c.p. | M117: =VLOOKUP(K117,clasif_filas!$A$2:$J$39,3,FALSE()) -> 38 | N117: =VLOOKUP(K117,clasif_filas!$A$2:$J$39,4,FALSE()) -> Muebles; otros bienes transportables n.c.p. | O117: =VLOOKUP(K117,clasif_filas!$A$2:$J$39,5,FALSE()) -> 99 | P117: =VLOOKUP(K117,clasif_filas!$A$2:$J$39,6,FALSE()) -> No Bioeconomía | Q117: =VLOOKUP(K117,clasif_filas!$A$2:$J$39,7,FALSE()) -> 3 | R117: =VLOOKUP(K117,clasif_filas!$A$2:$J$39,8,FALSE()) -> Otros bienes transportables, excepto productos metálicos, maquinaria y equipo | S117: =VLOOKUP(K117,clasif_filas!$A$2:$J$39,9,FALSE()) -> 3 | T117: =VLOOKUP(K117,clasif_filas!$A$2:$J$39,10,FALSE()) -> No bioeconomía
A118: PANof117 | B118: ATF01 | C118: Producción | D118: 1 | E118: 4201 | F118: JOYAS Y ARTÍCULOS CONEXOS | G118: No bioeconomía | H118: 4 | I118: No bioeconomía | J118: No bioeconomía | K118: 38 | L118: =VLOOKUP(K118,clasif_filas!$A$2:$J$39,2,FALSE()) -> Muebles; otros bienes transportables n.c.p. | M118: =VLOOKUP(K118,clasif_filas!$A$2:$J$39,3,FALSE()) -> 38 | N118: =VLOOKUP(K118,clasif_filas!$A$2:$J$39,4,FALSE()) -> Muebles; otros bienes transportables n.c.p. | O118: =VLOOKUP(K118,clasif_filas!$A$2:$J$39,5,FALSE()) -> 99 | P118: =VLOOKUP(K118,clasif_filas!$A$2:$J$39,6,FALSE()) -> No Bioeconomía | Q118: =VLOOKUP(K118,clasif_filas!$A$2:$J$39,7,FALSE()) -> 3 | R118: =VLOOKUP(K118,clasif_filas!$A$2:$J$39,8,FALSE()) -> Otros bienes transportables, excepto productos metálicos, maquinaria y equipo | S118: =VLOOKUP(K118,clasif_filas!$A$2:$J$39,9,FALSE()) -> 3 | T118: =VLOOKUP(K118,clasif_filas!$A$2:$J$39,10,FALSE()) -> No bioeconomía
A119: PANof118 | B119: ATF01 | C119: Producción | D119: 1 | E119: 4202 | F119: INSTRUMENTOS MUSICALES | G119: No bioeconomía | H119: 4 | I119: No bioeconomía | J119: No bioeconomía | K119: 38 | L119: =VLOOKUP(K119,clasif_filas!$A$2:$J$39,2,FALSE()) -> Muebles; otros bienes transportables n.c.p. | M119: =VLOOKUP(K119,clasif_filas!$A$2:$J$39,3,FALSE()) -> 38 | N119: =VLOOKUP(K119,clasif_filas!$A$2:$J$39,4,FALSE()) -> Muebles; otros bienes transportables n.c.p. | O119: =VLOOKUP(K119,clasif_filas!$A$2:$J$39,5,FALSE()) -> 99 | P119: =VLOOKUP(K119,clasif_filas!$A$2:$J$39,6,FALSE()) -> No Bioeconomía | Q119: =VLOOKUP(K119,clasif_filas!$A$2:$J$39,7,FALSE()) -> 3 | R119: =VLOOKUP(K119,clasif_filas!$A$2:$J$39,8,FALSE()) -> Otros bienes transportables, excepto productos metálicos, maquinaria y equipo | S119: =VLOOKUP(K119,clasif_filas!$A$2:$J$39,9,FALSE()) -> 3 | T119: =VLOOKUP(K119,clasif_filas!$A$2:$J$39,10,FALSE()) -> No bioeconomía
A120: PANof119 | B120: ATF01 | C120: Producción | D120: 1 | E120: 4203 | F120: ARTÍCULOS DE DEPORTE | G120: No bioeconomía | H120: 4 | I120: No bioeconomía | J120: No bioeconomía | K120: 38 | L120: =VLOOKUP(K120,clasif_filas!$A$2:$J$39,2,FALSE()) -> Muebles; otros bienes transportables n.c.p. | M120: =VLOOKUP(K120,clasif_filas!$A$2:$J$39,3,FALSE()) -> 38 | N120: =VLOOKUP(K120,clasif_filas!$A$2:$J$39,4,FALSE()) -> Muebles; otros bienes transportables n.c.p. | O120: =VLOOKUP(K120,clasif_filas!$A$2:$J$39,5,FALSE()) -> 99 | P120: =VLOOKUP(K120,clasif_filas!$A$2:$J$39,6,FALSE()) -> No Bioeconomía | Q120: =VLOOKUP(K120,clasif_filas!$A$2:$J$39,7,FALSE()) -> 3 | R120: =VLOOKUP(K120,clasif_filas!$A$2:$J$39,8,FALSE()) -> Otros bienes transportables, excepto productos metálicos, maquinaria y equipo | S120: =VLOOKUP(K120,clasif_filas!$A$2:$J$39,9,FALSE()) -> 3 | T120: =VLOOKUP(K120,clasif_filas!$A$2:$J$39,10,FALSE()) -> No bioeconomía
A121: PANof120 | B121: ATF01 | C121: Producción | D121: 1 | E121: 4204 | F121: JUEGOS Y JUGUETES | G121: No bioeconomía | H121: 4 | I121: No bioeconomía | J121: No bioeconomía | K121: 38 | L121: =VLOOKUP(K121,clasif_filas!$A$2:$J$39,2,FALSE()) -> Muebles; otros bienes transportables n.c.p. | M121: =VLOOKUP(K121,clasif_filas!$A$2:$J$39,3,FALSE()) -> 38 | N121: =VLOOKUP(K121,clasif_filas!$A$2:$J$39,4,FALSE()) -> Muebles; otros bienes transportables n.c.p. | O121: =VLOOKUP(K121,clasif_filas!$A$2:$J$39,5,FALSE()) -> 99 | P121: =VLOOKUP(K121,clasif_filas!$A$2:$J$39,6,FALSE()) -> No Bioeconomía | Q121: =VLOOKUP(K121,clasif_filas!$A$2:$J$39,7,FALSE()) -> 3 | R121: =VLOOKUP(K121,clasif_filas!$A$2:$J$39,8,FALSE()) -> Otros bienes transportables, excepto productos metálicos, maquinaria y equipo | S121: =VLOOKUP(K121,clasif_filas!$A$2:$J$39,9,FALSE()) -> 3 | T121: =VLOOKUP(K121,clasif_filas!$A$2:$J$39,10,FALSE()) -> No bioeconomía
A122: PANof121 | B122: ATF01 | C122: Producción | D122: 1 | E122: 4205 | F122: OTROS ARTÍCULOS MANUFACTURADOS N.C.P. | G122: No bioeconomía | H122: 4 | I122: No bioeconomía | J122: No bioeconomía | K122: 38 | L122: =VLOOKUP(K122,clasif_filas!$A$2:$J$39,2,FALSE()) -> Muebles; otros bienes transportables n.c.p. | M122: =VLOOKUP(K122,clasif_filas!$A$2:$J$39,3,FALSE()) -> 38 | N122: =VLOOKUP(K122,clasif_filas!$A$2:$J$39,4,FALSE()) -> Muebles; otros bienes transportables n.c.p. | O122: =VLOOKUP(K122,clasif_filas!$A$2:$J$39,5,FALSE()) -> 99 | P122: =VLOOKUP(K122,clasif_filas!$A$2:$J$39,6,FALSE()) -> No Bioeconomía | Q122: =VLOOKUP(K122,clasif_filas!$A$2:$J$39,7,FALSE()) -> 3 | R122: =VLOOKUP(K122,clasif_filas!$A$2:$J$39,8,FALSE()) -> Otros bienes transportables, excepto productos metálicos, maquinaria y equipo | S122: =VLOOKUP(K122,clasif_filas!$A$2:$J$39,9,FALSE()) -> 3 | T122: =VLOOKUP(K122,clasif_filas!$A$2:$J$39,10,FALSE()) -> No bioeconomía
A123: PANof122 | B123: ATF01 | C123: Producción | D123: 1 | E123: 4301 | F123: DESPERDICIOS Y DESECHOS | G123: Productos agricolas_Residuos | H123: 1 | I123: Bioeconomía de productos básicos | J123: Productos agropecuarios | K123: 39 | L123: =VLOOKUP(K123,clasif_filas!$A$2:$J$39,2,FALSE()) -> Desperdicios o desechos | M123: =VLOOKUP(K123,clasif_filas!$A$2:$J$39,3,FALSE()) -> 39 | N123: =VLOOKUP(K123,clasif_filas!$A$2:$J$39,4,FALSE()) -> Desperdicios o desechos | O123: =VLOOKUP(K123,clasif_filas!$A$2:$J$39,5,FALSE()) -> 4 | P123: =VLOOKUP(K123,clasif_filas!$A$2:$J$39,6,FALSE()) -> Biomasa residual en los sectores agropecuario, pesca y acuacultura, forestal y agroindustrial | Q123: =VLOOKUP(K123,clasif_filas!$A$2:$J$39,7,FALSE()) -> 3 | R123: =VLOOKUP(K123,clasif_filas!$A$2:$J$39,8,FALSE()) -> Otros bienes transportables, excepto productos metálicos, maquinaria y equipo | S123: =VLOOKUP(K123,clasif_filas!$A$2:$J$39,9,FALSE()) -> 2 | T123: =VLOOKUP(K123,clasif_filas!$A$2:$J$39,10,FALSE()) -> Bioeconomía extendida
A124: PANof123 | B124: ATF01 | C124: Producción | D124: 1 | E124: 4401 | F124: SERVICIOS DE MANTENIMIENTO, REPARACIÓN E INSTALACIÓN DE MAQUINARIA Y EQUIPOS COMERCIAL E INDUSTRIAL | G124: No bioeconomía | H124: 4 | I124: No bioeconomía | J124: No bioeconomía | K124: 6 | L124: =VLOOKUP(K124,clasif_filas!$A$2:$J$39,2,FALSE()) -> Otros servicios | M124: =VLOOKUP(K124,clasif_filas!$A$2:$J$39,3,FALSE()) -> 6 | N124: =VLOOKUP(K124,clasif_filas!$A$2:$J$39,4,FALSE()) -> Otros servicios | O124: =VLOOKUP(K124,clasif_filas!$A$2:$J$39,5,FALSE()) -> 99 | P124: =VLOOKUP(K124,clasif_filas!$A$2:$J$39,6,FALSE()) -> No Bioeconomía | Q124: =VLOOKUP(K124,clasif_filas!$A$2:$J$39,7,FALSE()) -> 6 | R124: =VLOOKUP(K124,clasif_filas!$A$2:$J$39,8,FALSE()) -> Servicios comerciales de distribución; alojamiento, servicios de suministro de comidas y bebidas; servicios de transporte; y servicios de distribución de electricidad, gas y agua | S124: =VLOOKUP(K124,clasif_filas!$A$2:$J$39,9,FALSE()) -> 3 | T124: =VLOOKUP(K124,clasif_filas!$A$2:$J$39,10,FALSE()) -> No bioeconomía
A125: PANof124 | B125: ATF01 | C125: Producción | D125: 1 | E125: 4402 | F125: SERVICIOS DE MANUFACTURA | G125: No bioeconomía | H125: 4 | I125: No bioeconomía | J125: No bioeconomía | K125: 6 | L125: =VLOOKUP(K125,clasif_filas!$A$2:$J$39,2,FALSE()) -> Otros servicios | M125: =VLOOKUP(K125,clasif_filas!$A$2:$J$39,3,FALSE()) -> 6 | N125: =VLOOKUP(K125,clasif_filas!$A$2:$J$39,4,FALSE()) -> Otros servicios | O125: =VLOOKUP(K125,clasif_filas!$A$2:$J$39,5,FALSE()) -> 99 | P125: =VLOOKUP(K125,clasif_filas!$A$2:$J$39,6,FALSE()) -> No Bioeconomía | Q125: =VLOOKUP(K125,clasif_filas!$A$2:$J$39,7,FALSE()) -> 6 | R125: =VLOOKUP(K125,clasif_filas!$A$2:$J$39,8,FALSE()) -> Servicios comerciales de distribución; alojamiento, servicios de suministro de comidas y bebidas; servicios de transporte; y servicios de distribución de electricidad, gas y agua | S125: =VLOOKUP(K125,clasif_filas!$A$2:$J$39,9,FALSE()) -> 3 | T125: =VLOOKUP(K125,clasif_filas!$A$2:$J$39,10,FALSE()) -> No bioeconomía
A126: PANof125 | B126: ATF01 | C126: Producción | D126: 1 | E126: 4501 | F126: ENERGÍA ELÉCTRICA, GAS, VAPOR Y AIRE ACONDICIONADO | G126: Materias primas | H126: 1 | I126: Bioeconomía de productos básicos | J126: Materias primas | K126: 69 | L126: =VLOOKUP(K126,clasif_filas!$A$2:$J$39,2,FALSE()) -> Distribución de electricidad, gas y agua (por cuenta propia) | M126: =VLOOKUP(K126,clasif_filas!$A$2:$J$39,3,FALSE()) -> 69 | N126: =VLOOKUP(K126,clasif_filas!$A$2:$J$39,4,FALSE()) -> Distribución de electricidad, gas y agua (por cuenta propia) | O126: =VLOOKUP(K126,clasif_filas!$A$2:$J$39,5,FALSE()) -> 6 | P126: =VLOOKUP(K126,clasif_filas!$A$2:$J$39,6,FALSE()) -> Conocimiento, procesos y servicios relacionados | Q126: =VLOOKUP(K126,clasif_filas!$A$2:$J$39,7,FALSE()) -> 6 | R126: =VLOOKUP(K126,clasif_filas!$A$2:$J$39,8,FALSE()) -> Servicios comerciales de distribución; alojamiento, servicios de suministro de comidas y bebidas; servicios de transporte; y servicios de distribución de electricidad, gas y agua | S126: =VLOOKUP(K126,clasif_filas!$A$2:$J$39,9,FALSE()) -> 2 | T126: =VLOOKUP(K126,clasif_filas!$A$2:$J$39,10,FALSE()) -> Bioeconomía extendida
A127: PANof126 | B127: ATF01 | C127: Producción | D127: 1 | E127: 4502 | F127: DISTRIBUCIÓN DE ENERGÍA ELÉCTRICA, GAS, VAPOR Y AIRE ACONDICIONADO | G127: Servicios | H127: 3 | I127: Bioeconomía avanzada | J127: Servicios | K127: 69 | L127: =VLOOKUP(K127,clasif_filas!$A$2:$J$39,2,FALSE()) -> Distribución de electricidad, gas y agua (por cuenta propia) | M127: =VLOOKUP(K127,clasif_filas!$A$2:$J$39,3,FALSE()) -> 69 | N127: =VLOOKUP(K127,clasif_filas!$A$2:$J$39,4,FALSE()) -> Distribución de electricidad, gas y agua (por cuenta propia) | O127: =VLOOKUP(K127,clasif_filas!$A$2:$J$39,5,FALSE()) -> 6 | P127: =VLOOKUP(K127,clasif_filas!$A$2:$J$39,6,FALSE()) -> Conocimiento, procesos y servicios relacionados | Q127: =VLOOKUP(K127,clasif_filas!$A$2:$J$39,7,FALSE()) -> 6 | R127: =VLOOKUP(K127,clasif_filas!$A$2:$J$39,8,FALSE()) -> Servicios comerciales de distribución; alojamiento, servicios de suministro de comidas y bebidas; servicios de transporte; y servicios de distribución de electricidad, gas y agua | S127: =VLOOKUP(K127,clasif_filas!$A$2:$J$39,9,FALSE()) -> 2 | T127: =VLOOKUP(K127,clasif_filas!$A$2:$J$39,10,FALSE()) -> Bioeconomía extendida
A128: PANof127 | B128: ATF01 | C128: Producción | D128: 1 | E128: 4503 | F128: TRANSMISIÓN DE ENERGÍA ELÉCTRICA | G128: Servicios | H128: 3 | I128: Bioeconomía avanzada | J128: Servicios | K128: 69 | L128: =VLOOKUP(K128,clasif_filas!$A$2:$J$39,2,FALSE()) -> Distribución de electricidad, gas y agua (por cuenta propia) | M128: =VLOOKUP(K128,clasif_filas!$A$2:$J$39,3,FALSE()) -> 69 | N128: =VLOOKUP(K128,clasif_filas!$A$2:$J$39,4,FALSE()) -> Distribución de electricidad, gas y agua (por cuenta propia) | O128: =VLOOKUP(K128,clasif_filas!$A$2:$J$39,5,FALSE()) -> 6 | P128: =VLOOKUP(K128,clasif_filas!$A$2:$J$39,6,FALSE()) -> Conocimiento, procesos y servicios relacionados | Q128: =VLOOKUP(K128,clasif_filas!$A$2:$J$39,7,FALSE()) -> 6 | R128: =VLOOKUP(K128,clasif_filas!$A$2:$J$39,8,FALSE()) -> Servicios comerciales de distribución; alojamiento, servicios de suministro de comidas y bebidas; servicios de transporte; y servicios de distribución de electricidad, gas y agua | S128: =VLOOKUP(K128,clasif_filas!$A$2:$J$39,9,FALSE()) -> 2 | T128: =VLOOKUP(K128,clasif_filas!$A$2:$J$39,10,FALSE()) -> Bioeconomía extendida
... A166: PANof165 | B166: ATF01 | C166: Producción | D166: 1 | E166: 5801 | F166: SERVICIOS DE PUBLICIDAD Y ESTUDIOS DE MERCADO | G166: No bioeconomía | H166: 4 | I166: No bioeconomía | J166: No bioeconomía | K166: 6 | L166: =VLOOKUP(K166,clasif_filas!$A$2:$J$39,2,FALSE()) -> Otros servicios | M166: =VLOOKUP(K166,clasif_filas!$A$2:$J$39,3,FALSE()) -> 6 | N166: =VLOOKUP(K166,clasif_filas!$A$2:$J$39,4,FALSE()) -> Otros servicios | O166: =VLOOKUP(K166,clasif_filas!$A$2:$J$39,5,FALSE()) -> 99 | P166: =VLOOKUP(K166,clasif_filas!$A$2:$J$39,6,FALSE()) -> No Bioeconomía | Q166: =VLOOKUP(K166,clasif_filas!$A$2:$J$39,7,FALSE()) -> 6 | R166: =VLOOKUP(K166,clasif_filas!$A$2:$J$39,8,FALSE()) -> Servicios comerciales de distribución; alojamiento, servicios de suministro de comidas y bebidas; servicios de transporte; y servicios de distribución de electricidad, gas y agua | S166: =VLOOKUP(K166,clasif_filas!$A$2:$J$39,9,FALSE()) -> 3 | T166: =VLOOKUP(K166,clasif_filas!$A$2:$J$39,10,FALSE()) -> No bioeconomía
A167: PANof166 | B167: ATF01 | C167: Producción | D167: 1 | E167: 5901 | F167: SERVICIOS VETERINARIOS | G167: Servicios | H167: 3 | I167: Bioeconomía avanzada | J167: Servicios | K167: 86 | L167: =VLOOKUP(K167,clasif_filas!$A$2:$J$39,2,FALSE()) -> Servicios de apoyo a la agricultura,la caza, la silvicutura, la pesca, la minería y los servicios públicos | M167: =VLOOKUP(K167,clasif_filas!$A$2:$J$39,3,FALSE()) -> 86 | N167: =VLOOKUP(K167,clasif_filas!$A$2:$J$39,4,FALSE()) -> Servicios de apoyo a la agricultura,la caza, la silvicutura, la pesca, la minería y los servicios públicos | O167: =VLOOKUP(K167,clasif_filas!$A$2:$J$39,5,FALSE()) -> 6 | P167: =VLOOKUP(K167,clasif_filas!$A$2:$J$39,6,FALSE()) -> Conocimiento, procesos y servicios relacionados | Q167: =VLOOKUP(K167,clasif_filas!$A$2:$J$39,7,FALSE()) -> 8 | R167: =VLOOKUP(K167,clasif_filas!$A$2:$J$39,8,FALSE()) -> Servicios prestados a las empresas y servicios de producción | S167: =VLOOKUP(K167,clasif_filas!$A$2:$J$39,9,FALSE()) -> 1 | T167: Bioeconomía
A168: PANof167 | B168: ATF01 | C168: Producción | D168: 1 | E168: 5902 | F168: OTROS SERVICIOS PROFESIONALES, TÉCNICOS Y DE NEGOCIOS | G168: No bioeconomía | H168: 4 | I168: No bioeconomía | J168: No bioeconomía | K168: 6 | L168: =VLOOKUP(K168,clasif_filas!$A$2:$J$39,2,FALSE()) -> Otros servicios | M168: =VLOOKUP(K168,clasif_filas!$A$2:$J$39,3,FALSE()) -> 6 | N168: =VLOOKUP(K168,clasif_filas!$A$2:$J$39,4,FALSE()) -> Otros servicios | O168: =VLOOKUP(K168,clasif_filas!$A$2:$J$39,5,FALSE()) -> 99 | P168: =VLOOKUP(K168,clasif_filas!$A$2:$J$39,6,FALSE()) -> No Bioeconomía | Q168: =VLOOKUP(K168,clasif_filas!$A$2:$J$39,7,FALSE()) -> 6 | R168: =VLOOKUP(K168,clasif_filas!$A$2:$J$39,8,FALSE()) -> Servicios comerciales de distribución; alojamiento, servicios de suministro de comidas y bebidas; servicios de transporte; y servicios de distribución de electricidad, gas y agua | S168: =VLOOKUP(K168,clasif_filas!$A$2:$J$39,9,FALSE()) -> 3 | T168: =VLOOKUP(K168,clasif_filas!$A$2:$J$39,10,FALSE()) -> No bioeconomía
A169: PANof168 | B169: ATF01 | C169: Producción | D169: 1 | E169: 6001 | F169: SERVICIOS DE ALQUILER O ARRENDAMIENTO DE VEHÍCULOS, MAQUINARIAS Y EQUIPO SIN OPERARIOS | G169: No bioeconomía | H169: 4 | I169: No bioeconomía | J169: No bioeconomía | K169: 6 | L169: =VLOOKUP(K169,clasif_filas!$A$2:$J$39,2,FALSE()) -> Otros servicios | M169: =VLOOKUP(K169,clasif_filas!$A$2:$J$39,3,FALSE()) -> 6 | N169: =VLOOKUP(K169,clasif_filas!$A$2:$J$39,4,FALSE()) -> Otros servicios | O169: =VLOOKUP(K169,clasif_filas!$A$2:$J$39,5,FALSE()) -> 99 | P169: =VLOOKUP(K169,clasif_filas!$A$2:$J$39,6,FALSE()) -> No Bioeconomía | Q169: =VLOOKUP(K169,clasif_filas!$A$2:$J$39,7,FALSE()) -> 6 | R169: =VLOOKUP(K169,clasif_filas!$A$2:$J$39,8,FALSE()) -> Servicios comerciales de distribución; alojamiento, servicios de suministro de comidas y bebidas; servicios de transporte; y servicios de distribución de electricidad, gas y agua | S169: =VLOOKUP(K169,clasif_filas!$A$2:$J$39,9,FALSE()) -> 3 | T169: =VLOOKUP(K169,clasif_filas!$A$2:$J$39,10,FALSE()) -> No bioeconomía
A170: PANof169 | B170: ATF01 | C170: Producción | D170: 1 | E170: 6002 | F170: SERVICIOS DE ALQUILER O ARRENDAMIENTOS DE OTROS BIENES | G170: No bioeconomía | H170: 4 | I170: No bioeconomía | J170: No bioeconomía | K170: 6 | L170: =VLOOKUP(K170,clasif_filas!$A$2:$J$39,2,FALSE()) -> Otros servicios | M170: =VLOOKUP(K170,clasif_filas!$A$2:$J$39,3,FALSE()) -> 6 | N170: =VLOOKUP(K170,clasif_filas!$A$2:$J$39,4,FALSE()) -> Otros servicios | O170: =VLOOKUP(K170,clasif_filas!$A$2:$J$39,5,FALSE()) -> 99 | P170: =VLOOKUP(K170,clasif_filas!$A$2:$J$39,6,FALSE()) -> No Bioeconomía | Q170: =VLOOKUP(K170,clasif_filas!$A$2:$J$39,7,FALSE()) -> 6 | R170: =VLOOKUP(K170,clasif_filas!$A$2:$J$39,8,FALSE()) -> Servicios comerciales de distribución; alojamiento, servicios de suministro de comidas y bebidas; servicios de transporte; y servicios de distribución de electricidad, gas y agua | S170: =VLOOKUP(K170,clasif_filas!$A$2:$J$39,9,FALSE()) -> 3 | T170: =VLOOKUP(K170,clasif_filas!$A$2:$J$39,10,FALSE()) -> No bioeconomía
A171: PANof170 | B171: ATF01 | C171: Producción | D171: 1 | E171: 6003 | F171: SERVICIOS DE AUTORIZACIÓN PARA EL DERECHO DE USO DE LA PROPIEDAD INTELECTUAL Y PRODUCTOS SIMILARES | G171: No bioeconomía | H171: 4 | I171: No bioeconomía | J171: No bioeconomía | K171: 6 | L171: =VLOOKUP(K171,clasif_filas!$A$2:$J$39,2,FALSE()) -> Otros servicios | M171: =VLOOKUP(K171,clasif_filas!$A$2:$J$39,3,FALSE()) -> 6 | N171: =VLOOKUP(K171,clasif_filas!$A$2:$J$39,4,FALSE()) -> Otros servicios | O171: =VLOOKUP(K171,clasif_filas!$A$2:$J$39,5,FALSE()) -> 99 | P171: =VLOOKUP(K171,clasif_filas!$A$2:$J$39,6,FALSE()) -> No Bioeconomía | Q171: =VLOOKUP(K171,clasif_filas!$A$2:$J$39,7,FALSE()) -> 6 | R171: =VLOOKUP(K171,clasif_filas!$A$2:$J$39,8,FALSE()) -> Servicios comerciales de distribución; alojamiento, servicios de suministro de comidas y bebidas; servicios de transporte; y servicios de distribución de electricidad, gas y agua | S171: =VLOOKUP(K171,clasif_filas!$A$2:$J$39,9,FALSE()) -> 3 | T171: =VLOOKUP(K171,clasif_filas!$A$2:$J$39,10,FALSE()) -> No bioeconomía
A172: PANof171 | B172: ATF01 | C172: Producción | D172: 1 | E172: 6004 | F172: SERVICIOS DE AGENCIAS DE EMPLEO Y DE DOTACIÓN DE RECURSOS HUMANOS | G172: No bioeconomía | H172: 4 | I172: No bioeconomía | J172: No bioeconomía | K172: 6 | L172: =VLOOKUP(K172,clasif_filas!$A$2:$J$39,2,FALSE()) -> Otros servicios | M172: =VLOOKUP(K172,clasif_filas!$A$2:$J$39,3,FALSE()) -> 6 | N172: =VLOOKUP(K172,clasif_filas!$A$2:$J$39,4,FALSE()) -> Otros servicios | O172: =VLOOKUP(K172,clasif_filas!$A$2:$J$39,5,FALSE()) -> 99 | P172: =VLOOKUP(K172,clasif_filas!$A$2:$J$39,6,FALSE()) -> No Bioeconomía | Q172: =VLOOKUP(K172,clasif_filas!$A$2:$J$39,7,FALSE()) -> 6 | R172: =VLOOKUP(K172,clasif_filas!$A$2:$J$39,8,FALSE()) -> Servicios comerciales de distribución; alojamiento, servicios de suministro de comidas y bebidas; servicios de transporte; y servicios de distribución de electricidad, gas y agua | S172: =VLOOKUP(K172,clasif_filas!$A$2:$J$39,9,FALSE()) -> 3 | T172: =VLOOKUP(K172,clasif_filas!$A$2:$J$39,10,FALSE()) -> No bioeconomía
A173: PANof172 | B173: ATF01 | C173: Producción | D173: 1 | E173: 6005 | F173: SERVICIOS AGENCIAS DE VIAJES, OPERADORES TURÍSTICOS Y ACTIVIDADES CONEXAS | G173: No bioeconomía | H173: 4 | I173: No bioeconomía | J173: No bioeconomía | K173: 6 | L173: =VLOOKUP(K173,clasif_filas!$A$2:$J$39,2,FALSE()) -> Otros servicios | M173: =VLOOKUP(K173,clasif_filas!$A$2:$J$39,3,FALSE()) -> 6 | N173: =VLOOKUP(K173,clasif_filas!$A$2:$J$39,4,FALSE()) -> Otros servicios | O173: =VLOOKUP(K173,clasif_filas!$A$2:$J$39,5,FALSE()) -> 99 | P173: =VLOOKUP(K173,clasif_filas!$A$2:$J$39,6,FALSE()) -> No Bioeconomía | Q173: =VLOOKUP(K173,clasif_filas!$A$2:$J$39,7,FALSE()) -> 6 | R173: =VLOOKUP(K173,clasif_filas!$A$2:$J$39,8,FALSE()) -> Servicios comerciales de distribución; alojamiento, servicios de suministro de comidas y bebidas; servicios de transporte; y servicios de distribución de electricidad, gas y agua | S173: =VLOOKUP(K173,clasif_filas!$A$2:$J$39,9,FALSE()) -> 3 | T173: =VLOOKUP(K173,clasif_filas!$A$2:$J$39,10,FALSE()) -> No bioeconomía
A174: PANof173 | B174: ATF01 | C174: Producción | D174: 1 | E174: 6006 | F174: SERVICIOS DE SEGURIDAD, SISTEMA DE SEGURIDAD E INVESTIGACIÓN PRIVADA | G174: No bioeconomía | H174: 4 | I174: No bioeconomía | J174: No bioeconomía | K174: 6 | L174: =VLOOKUP(K174,clasif_filas!$A$2:$J$39,2,FALSE()) -> Otros servicios | M174: =VLOOKUP(K174,clasif_filas!$A$2:$J$39,3,FALSE()) -> 6 | N174: =VLOOKUP(K174,clasif_filas!$A$2:$J$39,4,FALSE()) -> Otros servicios | O174: =VLOOKUP(K174,clasif_filas!$A$2:$J$39,5,FALSE()) -> 99 | P174: =VLOOKUP(K174,clasif_filas!$A$2:$J$39,6,FALSE()) -> No Bioeconomía | Q174: =VLOOKUP(K174,clasif_filas!$A$2:$J$39,7,FALSE()) -> 6 | R174: =VLOOKUP(K174,clasif_filas!$A$2:$J$39,8,FALSE()) -> Servicios comerciales de distribución; alojamiento, servicios de suministro de comidas y bebidas; servicios de transporte; y servicios de distribución de electricidad, gas y agua | S174: =VLOOKUP(K174,clasif_filas!$A$2:$J$39,9,FALSE()) -> 3 | T174: =VLOOKUP(K174,clasif_filas!$A$2:$J$39,10,FALSE()) -> No bioeconomía
A175: PANof174 | B175: ATF01 | C175: Producción | D175: 1 | E175: 6007 | F175: SERVICIOS DE LIMPIEZA | G175: No bioeconomía | H175: 4 | I175: No bioeconomía | J175: No bioeconomía | K175: 6 | L175: =VLOOKUP(K175,clasif_filas!$A$2:$J$39,2,FALSE()) -> Otros servicios | M175: =VLOOKUP(K175,clasif_filas!$A$2:$J$39,3,FALSE()) -> 6 | N175: =VLOOKUP(K175,clasif_filas!$A$2:$J$39,4,FALSE()) -> Otros servicios | O175: =VLOOKUP(K175,clasif_filas!$A$2:$J$39,5,FALSE()) -> 99 | P175: =VLOOKUP(K175,clasif_filas!$A$2:$J$39,6,FALSE()) -> No Bioeconomía | Q175: =VLOOKUP(K175,clasif_filas!$A$2:$J$39,7,FALSE()) -> 6 | R175: =VLOOKUP(K175,clasif_filas!$A$2:$J$39,8,FALSE()) -> Servicios comerciales de distribución; alojamiento, servicios de suministro de comidas y bebidas; servicios de transporte; y servicios de distribución de electricidad, gas y agua | S175: =VLOOKUP(K175,clasif_filas!$A$2:$J$39,9,FALSE()) -> 3 | T175: =VLOOKUP(K175,clasif_filas!$A$2:$J$39,10,FALSE()) -> No bioeconomía
A176: PANof175 | B176: ATF01 | C176: Producción | D176: 1 | E176: 6008 | F176: SERVICIOS TELEFÓNICOS DE CENTROS DE LLAMADAS | G176: No bioeconomía | H176: 4 | I176: No bioeconomía | J176: No bioeconomía | K176: 6 | L176: =VLOOKUP(K176,clasif_filas!$A$2:$J$39,2,FALSE()) -> Otros servicios | M176: =VLOOKUP(K176,clasif_filas!$A$2:$J$39,3,FALSE()) -> 6 | N176: =VLOOKUP(K176,clasif_filas!$A$2:$J$39,4,FALSE()) -> Otros servicios | O176: =VLOOKUP(K176,clasif_filas!$A$2:$J$39,5,FALSE()) -> 99 | P176: =VLOOKUP(K176,clasif_filas!$A$2:$J$39,6,FALSE()) -> No Bioeconomía | Q176: =VLOOKUP(K176,clasif_filas!$A$2:$J$39,7,FALSE()) -> 6 | R176: =VLOOKUP(K176,clasif_filas!$A$2:$J$39,8,FALSE()) -> Servicios comerciales de distribución; alojamiento, servicios de suministro de comidas y bebidas; servicios de transporte; y servicios de distribución de electricidad, gas y agua | S176: =VLOOKUP(K176,clasif_filas!$A$2:$J$39,9,FALSE()) -> 3 | T176: =VLOOKUP(K176,clasif_filas!$A$2:$J$39,10,FALSE()) -> No bioeconomía
A177: PANof176 | B177: ATF01 | C177: Producción | D177: 1 | E177: 6009 | F177: SERVICIOS ADMINISTRATIVO Y DE APOYO DE OFICINA Y OTROS SERVICIOS DE APOYO A LAS EMPRESAS | G177: No bioeconomía | H177: 4 | I177: No bioeconomía | J177: No bioeconomía | K177: 6 | L177: =VLOOKUP(K177,clasif_filas!$A$2:$J$39,2,FALSE()) -> Otros servicios | M177: =VLOOKUP(K177,clasif_filas!$A$2:$J$39,3,FALSE()) -> 6 | N177: =VLOOKUP(K177,clasif_filas!$A$2:$J$39,4,FALSE()) -> Otros servicios | O177: =VLOOKUP(K177,clasif_filas!$A$2:$J$39,5,FALSE()) -> 99 | P177: =VLOOKUP(K177,clasif_filas!$A$2:$J$39,6,FALSE()) -> No Bioeconomía | Q177: =VLOOKUP(K177,clasif_filas!$A$2:$J$39,7,FALSE()) -> 6 | R177: =VLOOKUP(K177,clasif_filas!$A$2:$J$39,8,FALSE()) -> Servicios comerciales de distribución; alojamiento, servicios de suministro de comidas y bebidas; servicios de transporte; y servicios de distribución de electricidad, gas y agua | S177: =VLOOKUP(K177,clasif_filas!$A$2:$J$39,9,FALSE()) -> 3 | T177: =VLOOKUP(K177,clasif_filas!$A$2:$J$39,10,FALSE()) -> No bioeconomía
A178: PANof177 | B178: ATF01 | C178: Producción | D178: 1 | E178: 6101 | F178: SERVICIOS ADMINISTRATIVOS DEL GOBIERNO | G178: No bioeconomía | H178: 4 | I178: No bioeconomía | J178: No bioeconomía | K178: 6 | L178: =VLOOKUP(K178,clasif_filas!$A$2:$J$39,2,FALSE()) -> Otros servicios | M178: =VLOOKUP(K178,clasif_filas!$A$2:$J$39,3,FALSE()) -> 6 | N178: =VLOOKUP(K178,clasif_filas!$A$2:$J$39,4,FALSE()) -> Otros servicios | O178: =VLOOKUP(K178,clasif_filas!$A$2:$J$39,5,FALSE()) -> 99 | P178: =VLOOKUP(K178,clasif_filas!$A$2:$J$39,6,FALSE()) -> No Bioeconomía | Q178: =VLOOKUP(K178,clasif_filas!$A$2:$J$39,7,FALSE()) -> 6 | R178: =VLOOKUP(K178,clasif_filas!$A$2:$J$39,8,FALSE()) -> Servicios comerciales de distribución; alojamiento, servicios de suministro de comidas y bebidas; servicios de transporte; y servicios de distribución de electricidad, gas y agua | S178: =VLOOKUP(K178,clasif_filas!$A$2:$J$39,9,FALSE()) -> 3 | T178: =VLOOKUP(K178,clasif_filas!$A$2:$J$39,10,FALSE()) -> No bioeconomía
A179: PANof178 | B179: ATF01 | C179: Producción | D179: 1 | E179: 6102 | F179: SERVICIOS PARA LA COMUNIDAD EN GENERAL | G179: No bioeconomía | H179: 4 | I179: No bioeconomía | J179: No bioeconomía | K179: 6 | L179: =VLOOKUP(K179,clasif_filas!$A$2:$J$39,2,FALSE()) -> Otros servicios | M179: =VLOOKUP(K179,clasif_filas!$A$2:$J$39,3,FALSE()) -> 6 | N179: =VLOOKUP(K179,clasif_filas!$A$2:$J$39,4,FALSE()) -> Otros servicios | O179: =VLOOKUP(K179,clasif_filas!$A$2:$J$39,5,FALSE()) -> 99 | P179: =VLOOKUP(K179,clasif_filas!$A$2:$J$39,6,FALSE()) -> No Bioeconomía | Q179: =VLOOKUP(K179,clasif_filas!$A$2:$J$39,7,FALSE()) -> 6 | R179: =VLOOKUP(K179,clasif_filas!$A$2:$J$39,8,FALSE()) -> Servicios comerciales de distribución; alojamiento, servicios de suministro de comidas y bebidas; servicios de transporte; y servicios de distribución de electricidad, gas y agua | S179: =VLOOKUP(K179,clasif_filas!$A$2:$J$39,9,FALSE()) -> 3 | T179: =VLOOKUP(K179,clasif_filas!$A$2:$J$39,10,FALSE()) -> No bioeconomía
... A189: PANof188 | B189: ATF01 | C189: Producción | D189: 1 | E189: 6601 | F189: SERVICIOS DOMÉSTICOS | G189: No bioeconomía | H189: 4 | I189: No bioeconomía | J189: No bioeconomía | K189: 6 | L189: =VLOOKUP(K189,clasif_filas!$A$2:$J$39,2,FALSE()) -> Otros servicios | M189: =VLOOKUP(K189,clasif_filas!$A$2:$J$39,3,FALSE()) -> 6 | N189: =VLOOKUP(K189,clasif_filas!$A$2:$J$39,4,FALSE()) -> Otros servicios | O189: =VLOOKUP(K189,clasif_filas!$A$2:$J$39,5,FALSE()) -> 99 | P189: =VLOOKUP(K189,clasif_filas!$A$2:$J$39,6,FALSE()) -> No Bioeconomía | Q189: =VLOOKUP(K189,clasif_filas!$A$2:$J$39,7,FALSE()) -> 6 | R189: =VLOOKUP(K189,clasif_filas!$A$2:$J$39,8,FALSE()) -> Servicios comerciales de distribución; alojamiento, servicios de suministro de comidas y bebidas; servicios de transporte; y servicios de distribución de electricidad, gas y agua | S189: =VLOOKUP(K189,clasif_filas!$A$2:$J$39,9,FALSE()) -> 3 | T189: =VLOOKUP(K189,clasif_filas!$A$2:$J$39,10,FALSE()) -> No bioeconomía
A190: PANof189 | B190: ATF03 | C190: =VLOOKUP(B190, AT_FILAS!$A$2:$C$8,2,FALSE()) -> Ajuste CIF/FOB | D190: =VLOOKUP(B190, AT_FILAS!$A$2:$C$8,3,FALSE()) -> 3 | E190: Ajustes: | F190: CIF/FOB SOBRE IMPORTACIONES | G190: No bioeconomía | H190: 4 | I190: No bioeconomía | J190: No bioeconomía | K190: - | L190: - | M190: - | N190: - | O190: - | P190: - | Q190: - | R190: - | S190: - | T190: -
A191: PANof190 | B191: ATF04 | C191: =VLOOKUP(B191, AT_FILAS!$A$2:$C$8,2,FALSE()) -> Compras directas en el exterior por residentes | D191: =VLOOKUP(B191, AT_FILAS!$A$2:$C$8,3,FALSE()) -> 4 | E191: 6701 | F191: COMPRAS DIRECTAS EN EL EXTERIOR POR RESIDENTES (EMBAJADAS) | G191: No bioeconomía | H191: 4 | I191: No bioeconomía | J191: No bioeconomía | K191: - | L191: - | M191: - | N191: - | O191: - | P191: - | Q191: - | R191: - | S191: - | T191: -
A192: PANof191 | B192: ATF04 | C192: =VLOOKUP(B192, AT_FILAS!$A$2:$C$8,2,FALSE()) -> Compras directas en el exterior por residentes | D192: =VLOOKUP(B192, AT_FILAS!$A$2:$C$8,3,FALSE()) -> 4 | E192: 6702 | F192: COMPRAS DIRECTAS EN EL EXTERIOR POR RESIDENTES (VIAJES) | G192: No bioeconomía | H192: 4 | I192: No bioeconomía | J192: No bioeconomía | K192: - | L192: - | M192: - | N192: - | O192: - | P192: - | Q192: - | R192: - | S192: - | T192: -
A193: PANof192 | B193: ATF04 | C193: =VLOOKUP(B193, AT_FILAS!$A$2:$C$8,2,FALSE()) -> Compras directas en el exterior por residentes | D193: =VLOOKUP(B193, AT_FILAS!$A$2:$C$8,3,FALSE()) -> 4 | E193: 6703 | F193: COMPRAS DIRECTAS EN EL TERRITORIO NACIONAL POR NO RESIDENTES (EMBAJADAS) | G193: No bioeconomía | H193: 4 | I193: No bioeconomía | J193: No bioeconomía | K193: - | L193: - | M193: - | N193: - | O193: - | P193: - | Q193: - | R193: - | S193: - | T193: -
A194: PANof193 | B194: ATF04 | C194: =VLOOKUP(B194, AT_FILAS!$A$2:$C$8,2,FALSE()) -> Compras directas en el exterior por residentes | D194: =VLOOKUP(B194, AT_FILAS!$A$2:$C$8,3,FALSE()) -> 4 | E194: 6704 | F194: COMPRAS DIRECTAS EN EL TERRITORIO NACIONAL POR NO RESIDENTES (VIAJES) | G194: No bioeconomía | H194: 4 | I194: No bioeconomía | J194: No bioeconomía | K194: - | L194: - | M194: - | N194: - | O194: - | P194: - | Q194: - | R194: - | S194: - | T194: -
A195: PANuf001 | B195: ATF02 | C195: =VLOOKUP(B195, AT_FILAS!$A$2:$C$8,2,FALSE()) -> Consumo intermedio | D195: =VLOOKUP(B195, AT_FILAS!$A$2:$C$8,3,FALSE()) -> 2 | E195: 0101 | F195: TRIGO | G195: Productos agricolas_Cereales | H195: 1 | I195: Bioeconomía de productos básicos | J195: Productos agropecuarios | K195: 1 | L195: =VLOOKUP(K195,clasif_filas!$A$2:$J$39,2,FALSE()) -> Productos de la agricultura, la horticultura y la jardinería comercial | M195: =VLOOKUP(K195,clasif_filas!$A$2:$J$39,3,FALSE()) -> 1 | N195: =VLOOKUP(K195,clasif_filas!$A$2:$J$39,4,FALSE()) -> Productos de la agricultura, la horticultura y la jardinería comercial | O195: =VLOOKUP(K195,clasif_filas!$A$2:$J$39,5,FALSE()) -> 1 | P195: =VLOOKUP(K195,clasif_filas!$A$2:$J$39,6,FALSE()) -> Biomasa que se cultiva para producir alimentos, forrajes, fibras y energía | Q195: =VLOOKUP(K195,clasif_filas!$A$2:$J$39,7,FALSE()) -> 0 | R195: =VLOOKUP(K195,clasif_filas!$A$2:$J$39,8,FALSE()) -> Productos de la agricultura, la silvicultura yla pesca | S195: =VLOOKUP(K195,clasif_filas!$A$2:$J$39,9,FALSE()) -> 1 | T195: =VLOOKUP(K195,clasif_filas!$A$2:$J$39,10,FALSE()) -> Bioeconomía
A196: PANuf002 | B196: ATF02 | C196: =VLOOKUP(B196, AT_FILAS!$A$2:$C$8,2,FALSE()) -> Consumo intermedio | D196: =VLOOKUP(B196, AT_FILAS!$A$2:$C$8,3,FALSE()) -> 2 | E196: 0102 | F196: OTROS CEREALES (EXCL. MAÍZ Y ARROZ) | G196: Productos agricolas_Cereales | H196: 1 | I196: Bioeconomía de productos básicos | J196: Productos agropecuarios | K196: 1 | L196: =VLOOKUP(K196,clasif_filas!$A$2:$J$39,2,FALSE()) -> Productos de la agricultura, la horticultura y la jardinería comercial | M196: =VLOOKUP(K196,clasif_filas!$A$2:$J$39,3,FALSE()) -> 1 | N196: =VLOOKUP(K196,clasif_filas!$A$2:$J$39,4,FALSE()) -> Productos de la agricultura, la horticultura y la jardinería comercial | O196: =VLOOKUP(K196,clasif_filas!$A$2:$J$39,5,FALSE()) -> 1 | P196: =VLOOKUP(K196,clasif_filas!$A$2:$J$39,6,FALSE()) -> Biomasa que se cultiva para producir alimentos, forrajes, fibras y energía | Q196: =VLOOKUP(K196,clasif_filas!$A$2:$J$39,7,FALSE()) -> 0 | R196: =VLOOKUP(K196,clasif_filas!$A$2:$J$39,8,FALSE()) -> Productos de la agricultura, la silvicultura yla pesca | S196: =VLOOKUP(K196,clasif_filas!$A$2:$J$39,9,FALSE()) -> 1 | T196: =VLOOKUP(K196,clasif_filas!$A$2:$J$39,10,FALSE()) -> Bioeconomía
A197: PANuf003 | B197: ATF02 | C197: =VLOOKUP(B197, AT_FILAS!$A$2:$C$8,2,FALSE()) -> Consumo intermedio | D197: =VLOOKUP(B197, AT_FILAS!$A$2:$C$8,3,FALSE()) -> 2 | E197: 0103 | F197: LEGUMBRES | G197: Productos agropecuarios_Vegetales | H197: 1 | I197: Bioeconomía de productos básicos | J197: Productos agropecuarios | K197: 1 | L197: =VLOOKUP(K197,clasif_filas!$A$2:$J$39,2,FALSE()) -> Productos de la agricultura, la horticultura y la jardinería comercial | M197: =VLOOKUP(K197,clasif_filas!$A$2:$J$39,3,FALSE()) -> 1 | N197: =VLOOKUP(K197,clasif_filas!$A$2:$J$39,4,FALSE()) -> Productos de la agricultura, la horticultura y la jardinería comercial | O197: =VLOOKUP(K197,clasif_filas!$A$2:$J$39,5,FALSE()) -> 1 | P197: =VLOOKUP(K197,clasif_filas!$A$2:$J$39,6,FALSE()) -> Biomasa que se cultiva para producir alimentos, forrajes, fibras y energía | Q197: =VLOOKUP(K197,clasif_filas!$A$2:$J$39,7,FALSE()) -> 0 | R197: =VLOOKUP(K197,clasif_filas!$A$2:$J$39,8,FALSE()) -> Productos de la agricultura, la silvicultura yla pesca | S197: =VLOOKUP(K197,clasif_filas!$A$2:$J$39,9,FALSE()) -> 1 | T197: =VLOOKUP(K197,clasif_filas!$A$2:$J$39,10,FALSE()) -> Bioeconomía
A198: PANuf004 | B198: ATF02 | C198: =VLOOKUP(B198, AT_FILAS!$A$2:$C$8,2,FALSE()) -> Consumo intermedio | D198: =VLOOKUP(B198, AT_FILAS!$A$2:$C$8,3,FALSE()) -> 2 | E198: 0104 | F198: SEMILLAS OLEAGINOSAS | G198: Productos agricolas_Oleaginosas | H198: 1 | I198: Bioeconomía de productos básicos | J198: Productos agropecuarios | K198: 1 | L198: =VLOOKUP(K198,clasif_filas!$A$2:$J$39,2,FALSE()) -> Productos de la agricultura, la horticultura y la jardinería comercial | M198: =VLOOKUP(K198,clasif_filas!$A$2:$J$39,3,FALSE()) -> 1 | N198: =VLOOKUP(K198,clasif_filas!$A$2:$J$39,4,FALSE()) -> Productos de la agricultura, la horticultura y la jardinería comercial | O198: =VLOOKUP(K198,clasif_filas!$A$2:$J$39,5,FALSE()) -> 1 | P198: =VLOOKUP(K198,clasif_filas!$A$2:$J$39,6,FALSE()) -> Biomasa que se cultiva para producir alimentos, forrajes, fibras y energía | Q198: =VLOOKUP(K198,clasif_filas!$A$2:$J$39,7,FALSE()) -> 0 | R198: =VLOOKUP(K198,clasif_filas!$A$2:$J$39,8,FALSE()) -> Productos de la agricultura, la silvicultura yla pesca | S198: =VLOOKUP(K198,clasif_filas!$A$2:$J$39,9,FALSE()) -> 1 | T198: =VLOOKUP(K198,clasif_filas!$A$2:$J$39,10,FALSE()) -> Bioeconomía
A199: PANuf005 | B199: ATF02 | C199: =VLOOKUP(B199, AT_FILAS!$A$2:$C$8,2,FALSE()) -> Consumo intermedio | D199: =VLOOKUP(B199, AT_FILAS!$A$2:$C$8,3,FALSE()) -> 2 | E199: 0201 | F199: MAÍZ | G199: Productos agricolas_Cereales | H199: 1 | I199: Bioeconomía de productos básicos | J199: Productos agropecuarios | K199: 1 | L199: =VLOOKUP(K199,clasif_filas!$A$2:$J$39,2,FALSE()) -> Productos de la agricultura, la horticultura y la jardinería comercial | M199: =VLOOKUP(K199,clasif_filas!$A$2:$J$39,3,FALSE()) -> 1 | N199: =VLOOKUP(K199,clasif_filas!$A$2:$J$39,4,FALSE()) -> Productos de la agricultura, la horticultura y la jardinería comercial | O199: =VLOOKUP(K199,clasif_filas!$A$2:$J$39,5,FALSE()) -> 1 | P199: =VLOOKUP(K199,clasif_filas!$A$2:$J$39,6,FALSE()) -> Biomasa que se cultiva para producir alimentos, forrajes, fibras y energía | Q199: =VLOOKUP(K199,clasif_filas!$A$2:$J$39,7,FALSE()) -> 0 | R199: =VLOOKUP(K199,clasif_filas!$A$2:$J$39,8,FALSE()) -> Productos de la agricultura, la silvicultura yla pesca | S199: =VLOOKUP(K199,clasif_filas!$A$2:$J$39,9,FALSE()) -> 1 | T199: =VLOOKUP(K199,clasif_filas!$A$2:$J$39,10,FALSE()) -> Bioeconomía
A200: PANuf006 | B200: ATF02 | C200: =VLOOKUP(B200, AT_FILAS!$A$2:$C$8,2,FALSE()) -> Consumo intermedio | D200: =VLOOKUP(B200, AT_FILAS!$A$2:$C$8,3,FALSE()) -> 2 | E200: 0301 | F200: ARROZ | G200: Productos agricolas_Cereales | H200: 1 | I200: Bioeconomía de productos básicos | J200: Productos agropecuarios | K200: 1 | L200: =VLOOKUP(K200,clasif_filas!$A$2:$J$39,2,FALSE()) -> Productos de la agricultura, la horticultura y la jardinería comercial | M200: =VLOOKUP(K200,clasif_filas!$A$2:$J$39,3,FALSE()) -> 1 | N200: =VLOOKUP(K200,clasif_filas!$A$2:$J$39,4,FALSE()) -> Productos de la agricultura, la horticultura y la jardinería comercial | O200: =VLOOKUP(K200,clasif_filas!$A$2:$J$39,5,FALSE()) -> 1 | P200: =VLOOKUP(K200,clasif_filas!$A$2:$J$39,6,FALSE()) -> Biomasa que se cultiva para producir alimentos, forrajes, fibras y energía | Q200: =VLOOKUP(K200,clasif_filas!$A$2:$J$39,7,FALSE()) -> 0 | R200: =VLOOKUP(K200,clasif_filas!$A$2:$J$39,8,FALSE()) -> Productos de la agricultura, la silvicultura yla pesca | S200: =VLOOKUP(K200,clasif_filas!$A$2:$J$39,9,FALSE()) -> 1 | T200: =VLOOKUP(K200,clasif_filas!$A$2:$J$39,10,FALSE()) -> Bioeconomía
A201: PANuf007 | B201: ATF02 | C201: =VLOOKUP(B201, AT_FILAS!$A$2:$C$8,2,FALSE()) -> Consumo intermedio | D201: =VLOOKUP(B201, AT_FILAS!$A$2:$C$8,3,FALSE()) -> 2 | E201: 0401 | F201: HORTALIZAS DE HOJA O DE TALLO | G201: Productos agropecuarios_Vegetales | H201: 1 | I201: Bioeconomía de productos básicos | J201: Productos agropecuarios | K201: 1 | L201: =VLOOKUP(K201,clasif_filas!$A$2:$J$39,2,FALSE()) -> Productos de la agricultura, la horticultura y la jardinería comercial | M201: =VLOOKUP(K201,clasif_filas!$A$2:$J$39,3,FALSE()) -> 1 | N201: =VLOOKUP(K201,clasif_filas!$A$2:$J$39,4,FALSE()) -> Productos de la agricultura, la horticultura y la jardinería comercial | O201: =VLOOKUP(K201,clasif_filas!$A$2:$J$39,5,FALSE()) -> 1 | P201: =VLOOKUP(K201,clasif_filas!$A$2:$J$39,6,FALSE()) -> Biomasa que se cultiva para producir alimentos, forrajes, fibras y energía | Q201: =VLOOKUP(K201,clasif_filas!$A$2:$J$39,7,FALSE()) -> 0 | R201: =VLOOKUP(K201,clasif_filas!$A$2:$J$39,8,FALSE()) -> Productos de la agricultura, la silvicultura yla pesca | S201: =VLOOKUP(K201,clasif_filas!$A$2:$J$39,9,FALSE()) -> 1 | T201: =VLOOKUP(K201,clasif_filas!$A$2:$J$39,10,FALSE()) -> Bioeconomía
A202: PANuf008 | B202: ATF02 | C202: =VLOOKUP(B202, AT_FILAS!$A$2:$C$8,2,FALSE()) -> Consumo intermedio | D202: =VLOOKUP(B202, AT_FILAS!$A$2:$C$8,3,FALSE()) -> 2 | E202: 0402 | F202: SANDÍAS | G202: Productos agricolas_Frutas | H202: 1 | I202: Bioeconomía de productos básicos | J202: Productos agropecuarios | K202: 1 | L202: =VLOOKUP(K202,clasif_filas!$A$2:$J$39,2,FALSE()) -> Productos de la agricultura, la horticultura y la jardinería comercial | M202: =VLOOKUP(K202,clasif_filas!$A$2:$J$39,3,FALSE()) -> 1 | N202: =VLOOKUP(K202,clasif_filas!$A$2:$J$39,4,FALSE()) -> Productos de la agricultura, la horticultura y la jardinería comercial | O202: =VLOOKUP(K202,clasif_filas!$A$2:$J$39,5,FALSE()) -> 1 | P202: =VLOOKUP(K202,clasif_filas!$A$2:$J$39,6,FALSE()) -> Biomasa que se cultiva para producir alimentos, forrajes, fibras y energía | Q202: =VLOOKUP(K202,clasif_filas!$A$2:$J$39,7,FALSE()) -> 0 | R202: =VLOOKUP(K202,clasif_filas!$A$2:$J$39,8,FALSE()) -> Productos de la agricultura, la silvicultura yla pesca | S202: =VLOOKUP(K202,clasif_filas!$A$2:$J$39,9,FALSE()) -> 1 | T202: =VLOOKUP(K202,clasif_filas!$A$2:$J$39,10,FALSE()) -> Bioeconomía
A203: PANuf009 | B203: ATF02 | C203: =VLOOKUP(B203, AT_FILAS!$A$2:$C$8,2,FALSE()) -> Consumo intermedio | D203: =VLOOKUP(B203, AT_FILAS!$A$2:$C$8,3,FALSE()) -> 2 | E203: 0403 | F203: MELONES | G203: Productos agricolas_Frutas | H203: 1 | I203: Bioeconomía de productos básicos | J203: Productos agropecuarios | K203: 1 | L203: =VLOOKUP(K203,clasif_filas!$A$2:$J$39,2,FALSE()) -> Productos de la agricultura, la horticultura y la jardinería comercial | M203: =VLOOKUP(K203,clasif_filas!$A$2:$J$39,3,FALSE()) -> 1 | N203: =VLOOKUP(K203,clasif_filas!$A$2:$J$39,4,FALSE()) -> Productos de la agricultura, la horticultura y la jardinería comercial | O203: =VLOOKUP(K203,clasif_filas!$A$2:$J$39,5,FALSE()) -> 1 | P203: =VLOOKUP(K203,clasif_filas!$A$2:$J$39,6,FALSE()) -> Biomasa que se cultiva para producir alimentos, forrajes, fibras y energía | Q203: =VLOOKUP(K203,clasif_filas!$A$2:$J$39,7,FALSE()) -> 0 | R203: =VLOOKUP(K203,clasif_filas!$A$2:$J$39,8,FALSE()) -> Productos de la agricultura, la silvicultura yla pesca | S203: =VLOOKUP(K203,clasif_filas!$A$2:$J$39,9,FALSE()) -> 1 | T203: =VLOOKUP(K203,clasif_filas!$A$2:$J$39,10,FALSE()) -> Bioeconomía
A204: PANuf010 | B204: ATF02 | C204: =VLOOKUP(B204, AT_FILAS!$A$2:$C$8,2,FALSE()) -> Consumo intermedio | D204: =VLOOKUP(B204, AT_FILAS!$A$2:$C$8,3,FALSE()) -> 2 | E204: 0404 | F204: TOMATES | G204: Productos agricolas_Frutas | H204: 1 | I204: Bioeconomía de productos básicos | J204: Productos agropecuarios | K204: 1 | L204: =VLOOKUP(K204,clasif_filas!$A$2:$J$39,2,FALSE()) -> Productos de la agricultura, la horticultura y la jardinería comercial | M204: =VLOOKUP(K204,clasif_filas!$A$2:$J$39,3,FALSE()) -> 1 | N204: =VLOOKUP(K204,clasif_filas!$A$2:$J$39,4,FALSE()) -> Productos de la agricultura, la horticultura y la jardinería comercial | O204: =VLOOKUP(K204,clasif_filas!$A$2:$J$39,5,FALSE()) -> 1 | P204: =VLOOKUP(K204,clasif_filas!$A$2:$J$39,6,FALSE()) -> Biomasa que se cultiva para producir alimentos, forrajes, fibras y energía | Q204: =VLOOKUP(K204,clasif_filas!$A$2:$J$39,7,FALSE()) -> 0 | R204: =VLOOKUP(K204,clasif_filas!$A$2:$J$39,8,FALSE()) -> Productos de la agricultura, la silvicultura yla pesca | S204: =VLOOKUP(K204,clasif_filas!$A$2:$J$39,9,FALSE()) -> 1 | T204: =VLOOKUP(K204,clasif_filas!$A$2:$J$39,10,FALSE()) -> Bioeconomía
A205: PANuf011 | B205: ATF02 | C205: =VLOOKUP(B205, AT_FILAS!$A$2:$C$8,2,FALSE()) -> Consumo intermedio | D205: =VLOOKUP(B205, AT_FILAS!$A$2:$C$8,3,FALSE()) -> 2 | E205: 0405 | F205: OTRAS HORTALIZAS | G205: Productos agropecuarios_Vegetales | H205: 1 | I205: Bioeconomía de productos básicos | J205: Productos agropecuarios | K205: 1 | L205: =VLOOKUP(K205,clasif_filas!$A$2:$J$39,2,FALSE()) -> Productos de la agricultura, la horticultura y la jardinería comercial | M205: =VLOOKUP(K205,clasif_filas!$A$2:$J$39,3,FALSE()) -> 1 | N205: =VLOOKUP(K205,clasif_filas!$A$2:$J$39,4,FALSE()) -> Productos de la agricultura, la horticultura y la jardinería comercial | O205: =VLOOKUP(K205,clasif_filas!$A$2:$J$39,5,FALSE()) -> 1 | P205: =VLOOKUP(K205,clasif_filas!$A$2:$J$39,6,FALSE()) -> Biomasa que se cultiva para producir alimentos, forrajes, fibras y energía | Q205: =VLOOKUP(K205,clasif_filas!$A$2:$J$39,7,FALSE()) -> 0 | R205: =VLOOKUP(K205,clasif_filas!$A$2:$J$39,8,FALSE()) -> Productos de la agricultura, la silvicultura yla pesca | S205: =VLOOKUP(K205,clasif_filas!$A$2:$J$39,9,FALSE()) -> 1 | T205: =VLOOKUP(K205,clasif_filas!$A$2:$J$39,10,FALSE()) -> Bioeconomía
A206: PANuf012 | B206: ATF02 | C206: =VLOOKUP(B206, AT_FILAS!$A$2:$C$8,2,FALSE()) -> Consumo intermedio | D206: =VLOOKUP(B206, AT_FILAS!$A$2:$C$8,3,FALSE()) -> 2 | E206: 0406 | F206: CEBOLLAS | G206: Productos agropecuarios_Vegetales | H206: 1 | I206: Bioeconomía de productos básicos | J206: Productos agropecuarios | K206: 1 | L206: =VLOOKUP(K206,clasif_filas!$A$2:$J$39,2,FALSE()) -> Productos de la agricultura, la horticultura y la jardinería comercial | M206: =VLOOKUP(K206,clasif_filas!$A$2:$J$39,3,FALSE()) -> 1 | N206: =VLOOKUP(K206,clasif_filas!$A$2:$J$39,4,FALSE()) -> Productos de la agricultura, la horticultura y la jardinería comercial | O206: =VLOOKUP(K206,clasif_filas!$A$2:$J$39,5,FALSE()) -> 1 | P206: =VLOOKUP(K206,clasif_filas!$A$2:$J$39,6,FALSE()) -> Biomasa que se cultiva para producir alimentos, forrajes, fibras y energía | Q206: =VLOOKUP(K206,clasif_filas!$A$2:$J$39,7,FALSE()) -> 0 | R206: =VLOOKUP(K206,clasif_filas!$A$2:$J$39,8,FALSE()) -> Productos de la agricultura, la silvicultura yla pesca | S206: =VLOOKUP(K206,clasif_filas!$A$2:$J$39,9,FALSE()) -> 1 | T206: =VLOOKUP(K206,clasif_filas!$A$2:$J$39,10,FALSE()) -> Bioeconomía
...

Sheet clasif_filas
A1: Cód_Div_CPC_3 | B1: División CPC_3 | C1: Cód_Div_CPC_2 | D1: División CPC_2 | E1: Cod. Elem. Def. Bioeconomía | F1: Tipo de elemento | G1: Código CPC | H1: Elemento CPC | I1: Código Bioeconomía | J1: Clasificación Bioeconomí
A2: 1 | B2: Productos de la agricultura, la horticultura y la jardinería comercial | C2: 1 | D2: Productos de la agricultura, la horticultura y la jardinería comercial | E2: 1 | F2: Biomasa que se cultiva para producir alimentos, forrajes, fibras y energía | G2: 0 | H2: Productos de la agricultura, la silvicultura yla pesca | I2: 1 | J2: Bioeconomía
A3: 2 | B3: Animales vivos y productos animales (excepto la carne) | C3: 2 | D3: Animales vivos y productos animales (excepto la carne) | E3: 1 | F3: Biomasa que se cultiva para producir alimentos, forrajes, fibras y energía | G3: 0 | H3: Productos de la agricultura, la silvicultura yla pesca | I3: 1 | J3: Bioeconomía
A4: 3 | B4: Productos forestales y de la tala | C4: 3 | D4: Productos forestales y de la tala | E4: 3 | F4: Biomasa forestal, sobre todo la que se cultiva para su aprovechamiento en las industrias forestal y del papel, y aquella extraída legalmente de ecosistemas naturales | G4: 0 | H4: Productos de la agricultura, la silvicultura yla pesca | I4: 1 | J4: Bioeconomía
