Workbook

Sheet rows
A1: row_id | B1: Filas
A2: bra_v01_q01_r0001 | B2: BRAof001
A3: bra_v01_q01_r0002 | B3: BRAof002
A4: bra_v01_q01_r0003 | B4: BRAof003
A5: bra_v01_q01_r0004 | B5: BRAof004
A6: bra_v01_q01_r0005 | B6: BRAof005
A7: bra_v01_q01_r0006 | B7: BRAof006
A8: bra_v01_q01_r0007 | B8: BRAof007
A9: bra_v01_q01_r0008 | B9: BRAof008
A10: bra_v01_q01_r0009 | B10: BRAof009
A11: bra_v01_q01_r0010 | B11: BRAof010
A12: bra_v01_q01_r0011 | B12: BRAof011
... A129: bra_v01_q01_r0128 | B129: BRAof128
A130: bra_v01_q01_r0129
A131: bra_v01_q01_r0130
A132: bra_v01_q02_r0001 | B132: BRAof001
A133: bra_v01_q02_r0002 | B133: BRAof002
A134: bra_v01_q02_r0003 | B134: BRAof003
A135: bra_v01_q02_r0004 | B135: BRAof004
A136: bra_v01_q02_r0005 | B136: BRAof005
A137: bra_v01_q02_r0006 | B137: BRAof006
A138: bra_v01_q02_r0007 | B138: BRAof007
A139: bra_v01_q02_r0008 | B139: BRAof008
A140: bra_v01_q02_r0009 | B140: BRAof009
A141: bra_v01_q02_r0010 | B141: BRAof010
A142: bra_v01_q02_r0011 | B142: BRAof011
A143: bra_v01_q02_r0012 | B143: BRAof012
... A259: bra_v01_q02_r0128 | B259: BRAof128
A260: bra_v01_q02_r0129
A261: bra_v01_q02_r0130
A262: bra_v01_q03_r0001 | B262: BRAof001
A263: bra_v01_q03_r0002 | B263: BRAof002
A264: bra_v01_q03_r0003 | B264: BRAof003
A265: bra_v01_q03_r0004 | B265: BRAof004
A266: bra_v01_q03_r0005 | B266: BRAof005
A267: bra_v01_q03_r0006 | B267: BRAof006
A268: bra_v01_q03_r0007 | B268: BRAof007
A269: bra_v01_q03_r0008 | B269: BRAof008
A270: bra_v01_q03_r0009 | B270: BRAof009
A271: bra_v01_q03_r0010 | B271: BRAof010
A272: bra_v01_q03_r0011 | B272: BRAof011
A273: bra_v01_q03_r0012 | B273: BRAof012
... A389: bra_v01_q03_r0128 | B389: BRAof128
A390: bra_v01_q03_r0129
A391: bra_v01_q03_r0130
A392: bra_v01_q04_r0001 | B392: BRAuf001
A393: bra_v01_q04_r0002 | B393: BRAuf002
A394: bra_v01_q04_r0003 | B394: BRAuf003
A395: bra_v01_q04_r0004 | B395: BRAuf004
A396: bra_v01_q04_r0005 | B396: BRAuf005
A397: bra_v01_q04_r0006 | B397: BRAuf006
A398: bra_v01_q04_r0007 | B398: BRAuf007
A399: bra_v01_q04_r0008 | B399: BRAuf008
A400: bra_v01_q04_r0009 | B400: BRAuf009
A401: bra_v01_q04_r0010 | B401: BRAuf010
A402: bra_v01_q04_r0011 | B402: BRAuf011
A403: bra_v01_q04_r0012 | B403: BRAuf012
... A519: bra_v01_q04_r0128 | B519: BRAuf128
A520: bra_v01_q04_r0129
A521: bra_v01_q04_r0130
A522: bra_v01_q05_r0001 | B522: BRAuf001
A523: bra_v01_q05_r0002 | B523: BRAuf002
A524: bra_v01_q05_r0003 | B524: BRAuf003
A525: bra_v01_q05_r0004 | B525: BRAuf004
A526: bra_v01_q05_r0005 | B526: BRAuf005
A527: bra_v01_q05_r0006 | B527: BRAuf006
A528: bra_v01_q05_r0007 | B528: BRAuf007
A529: bra_v01_q05_r0008 | B529: BRAuf008
A530: bra_v01_q05_r0009 | B530: BRAuf009
A531: bra_v01_q05_r0010 | B531: BRAuf010
A532: bra_v01_q05_r0011 | B532: BRAuf011
A533: bra_v01_q05_r0012 | B533: BRAuf012
... A649: bra_v01_q05_r0128 | B649: BRAuf128
A650: bra_v01_q05_r0129
A651: bra_v01_q05_r0130
A652: bra_v01_q06_r0001 | B652: BRAvf001

Sheet columns
A1: col_id | B1: Columnas
A2: bra_v01_q01_c0001 | B2: BRAoc001
A3: bra_v01_q01_c0002 | B3: BRAoc002
A4: bra_v01_q01_c0003 | B4: BRAoc003
A5: bra_v01_q01_c0004 | B5: BRAoc004
A6: bra_v01_q01_c0005 | B6: BRAoc005
A7: bra_v01_q01_c0006 | B7: BRAoc006
A8: bra_v01_q01_c0007 | B8: BRAoc007
A9: bra_v01_q01_c0008 | B9: BRAoc008
A10: bra_v01_q01_c0009 | B10: BRAoc009
A11: bra_v01_q01_c0010 | B11: BRAoc010
A12: bra_v01_q01_c0011 | B12: BRAoc011
... A71: bra_v01_q02_c0001 | B71: BRAoc070
A72: bra_v01_q03_c0001
A73: bra_v01_q03_c0002 | B73: BRAoc071
A74: bra_v01_q03_c0003 | B74: BRAoc072
A75: bra_v01_q03_c0004 | B75: BRAoc073
A76: bra_v01_q03_c0005 | B76: BRAoc074
A77: bra_v01_q03_c0006 | B77: BRAoc075
A78: bra_v01_q03_c0007 | B78: BRAoc076
A79: bra_v01_q03_c0008 | B79: BRAoc077
A80: bra_v01_q03_c0009
A81: bra_v01_q04_c0001 | B81: BRAuc001
A82: bra_v01_q04_c0002 | B82: BRAuc002
A83: bra_v01_q04_c0003 | B83: BRAuc003
A84: bra_v01_q04_c0004 | B84: BRAuc004
A85: bra_v01_q04_c0005 | B85: BRAuc005
A86: bra_v01_q04_c0006 | B86: BRAuc006
A87: bra_v01_q04_c0007 | B87: BRAuc007
A88: bra_v01_q04_c0008 | B88: BRAuc008
A89: bra_v01_q04_c0009 | B89: BRAuc009
A90: bra_v01_q04_c0010 | B90: BRAuc010
A91: bra_v01_q04_c0011 | B91: BRAuc011
A92: bra_v01_q04_c0012 | B92: BRAuc012
... A226: bra_v01_q06_c0069 | B226: BRAvc069

Sheet quadrants
A1: quadrant_code | B1: quadrant | C1: target_table | D1: cell_range | E1: excl_rows | F1: excl_cols
A2: q01 | B2: producao | C2: Supply | D2: C6:BS135 | E2: 129,130 | F2: 69
A3: q02 | B3: importacao | C3: Supply | D3: C6:C135 | E3: 129,130
A4: q03 | B4: oferta | C4: Supply | D4: C6:K135 | E4: 129,130 | F4: 1,8,9
A5: q04 | B5: CI | C5: Use | D5: C6:BS135 | E5: 129,130 | F5: 69
A6: q05 | B6: demanda | C6: Use | D6: C6:J135 | E6: 129,130 | F6: 7,8
A7: q06 | B7: VA | C7: Value Added | D7: B6:BR6 | F7: 69

Sheet columnas
A1: Columnas | B1: Código Transacciones | C1: Área transaccional columnas No. | D1: Área transaccional | E1: Transacciones | F1: Correlativo Transacciones Agregadas | G1: Código Transacciones Agregadas | H1: Transacciones Agregadas | I1: Código Clasificación Actividades | J1: Descripción Actividades | K1: CIIU Secciones | L1: CIIU Secciones descripción | M1: CIIU Corto | N1: CIIU English | O1: Correlativo Bioeconomía Actividades | P1: Bioeconomía Actividades
A2: BRAoc001 | B2: P10 | C2: =+VLOOKUP(B2,'transacciones '!$A$2:$I$39,2,FALSE()) -> ATC01 | D2: =+VLOOKUP(B2,'transacciones '!$A$2:$I$39,3,FALSE()) -> Producción / Consumo intermedio | E2: =+VLOOKUP(B2,'transacciones '!$A$2:$I$39,4,FALSE()) -> Producción | F2: =+VLOOKUP(B2,'transacciones '!$A$2:$I$39,5,FALSE()) -> 1 | G2: =+VLOOKUP(B2,'transacciones '!$A$2:$I$39,6,FALSE()) -> P1 | H2: =+VLOOKUP(B2,'transacciones '!$A$2:$I$39,7,FALSE()) -> Producción | I2: 0191 | J2: 0191 Agricultura, inclusive o apoio à agricultura e a pós-colheita | K2: A | L2: =+VLOOKUP(K2,'Correl CIIU'!$A$1:$F$26,2,FALSE()) -> Agricultura, ganadería, silvicultura y pesca | M2: =+VLOOKUP(K2,'Correl CIIU'!$A$1:$F$26,3,FALSE()) -> Agricultura | N2: =+VLOOKUP(K2,'Correl CIIU'!$A$1:$F$26,4,FALSE()) -> Agriculture, forestry and fishing | O2: 1 | P2: =+VLOOKUP(O2,bio!$A$2:$B$4,2,FALSE()) -> Bioeconomía
A3: BRAoc002 | B3: P10 | C3: =+VLOOKUP(B3,'transacciones '!$A$2:$I$39,2,FALSE()) -> ATC01 | D3: =+VLOOKUP(B3,'transacciones '!$A$2:$I$39,3,FALSE()) -> Producción / Consumo intermedio | E3: =+VLOOKUP(B3,'transacciones '!$A$2:$I$39,4,FALSE()) -> Producción | F3: =+VLOOKUP(B3,'transacciones '!$A$2:$I$39,5,FALSE()) -> 1 | G3: =+VLOOKUP(B3,'transacciones '!$A$2:$I$39,6,FALSE()) -> P1 | H3: =+VLOOKUP(B3,'transacciones '!$A$2:$I$39,7,FALSE()) -> Producción | I3: 0192 | J3: 0192 Pecuária, inclusive o apoio à pecuária | K3: A | L3: =+VLOOKUP(K3,'Correl CIIU'!$A$1:$F$26,2,FALSE()) -> Agricultura, ganadería, silvicultura y pesca | M3: =+VLOOKUP(K3,'Correl CIIU'!$A$1:$F$26,3,FALSE()) -> Agricultura | N3: =+VLOOKUP(K3,'Correl CIIU'!$A$1:$F$26,4,FALSE()) -> Agriculture, forestry and fishing | O3: 1 | P3: =+VLOOKUP(O3,bio!$A$2:$B$4,2,FALSE()) -> Bioeconomía
A4: BRAoc003 | B4: P10 | C4: =+VLOOKUP(B4,'transacciones '!$A$2:$I$39,2,FALSE()) -> ATC01 | D4: =+VLOOKUP(B4,'transacciones '!$A$2:$I$39,3,FALSE()) -> Producción / Consumo intermedio | E4: =+VLOOKUP(B4,'transacciones '!$A$2:$I$39,4,FALSE()) -> Producción | F4: =+VLOOKUP(B4,'transacciones '!$A$2:$I$39,5,FALSE()) -> 1 | G4: =+VLOOKUP(B4,'transacciones '!$A$2:$I$39,6,FALSE()) -> P1 | H4: =+VLOOKUP(B4,'transacciones '!$A$2:$I$39,7,FALSE()) -> Producción | I4: 0280 | J4: 0280 Produção florestal; pesca e aquicultura | K4: A | L4: =+VLOOKUP(K4,'Correl CIIU'!$A$1:$F$26,2,FALSE()) -> Agricultura, ganadería, silvicultura y pesca | M4: =+VLOOKUP(K4,'Correl CIIU'!$A$1:$F$26,3,FALSE()) -> Agricultura | N4: =+VLOOKUP(K4,'Correl CIIU'!$A$1:$F$26,4,FALSE()) -> Agriculture, forestry and fishing | O4: 1 | P4: =+VLOOKUP(O4,bio!$A$2:$B$4,2,FALSE()) -> Bioeconomía
A5: BRAoc004 | B5: P10 | C5: =+VLOOKUP(B5,'transacciones '!$A$2:$I$39,2,FALSE()) -> ATC01 | D5: =+VLOOKUP(B5,'transacciones '!$A$2:$I$39,3,FALSE()) -> Producción / Consumo intermedio | E5: =+VLOOKUP(B5,'transacciones '!$A$2:$I$39,4,FALSE()) -> Producción | F5: =+VLOOKUP(B5,'transacciones '!$A$2:$I$39,5,FALSE()) -> 1 | G5: =+VLOOKUP(B5,'transacciones '!$A$2:$I$39,6,FALSE()) -> P1 | H5: =+VLOOKUP(B5,'transacciones '!$A$2:$I$39,7,FALSE()) -> Producción | I5: 0580 | J5: 0580 Extração de carvão mineral e de minerais não-metálicos | K5: B | L5: =+VLOOKUP(K5,'Correl CIIU'!$A$1:$F$26,2,FALSE()) -> Explotación de minas y canteras | M5: =+VLOOKUP(K5,'Correl CIIU'!$A$1:$F$26,3,FALSE()) -> Minería | N5: =+VLOOKUP(K5,'Correl CIIU'!$A$1:$F$26,4,FALSE()) -> Mining and quarrying | O5: 3 | P5: =+VLOOKUP(O5,bio!$A$2:$B$4,2,FALSE()) -> No bioeconomía
A6: BRAoc005 | B6: P10 | C6: =+VLOOKUP(B6,'transacciones '!$A$2:$I$39,2,FALSE()) -> ATC01 | D6: =+VLOOKUP(B6,'transacciones '!$A$2:$I$39,3,FALSE()) -> Producción / Consumo intermedio | E6: =+VLOOKUP(B6,'transacciones '!$A$2:$I$39,4,FALSE()) -> Producción | F6: =+VLOOKUP(B6,'transacciones '!$A$2:$I$39,5,FALSE()) -> 1 | G6: =+VLOOKUP(B6,'transacciones '!$A$2:$I$39,6,FALSE()) -> P1 | H6: =+VLOOKUP(B6,'transacciones '!$A$2:$I$39,7,FALSE()) -> Producción | I6: 0680 | J6: 0680 Extração de petróleo e gás, inclusive as atividades de apoio | K6: B | L6: =+VLOOKUP(K6,'Correl CIIU'!$A$1:$F$26,2,FALSE()) -> Explotación de minas y canteras | M6: =+VLOOKUP(K6,'Correl CIIU'!$A$1:$F$26,3,FALSE()) -> Minería | N6: =+VLOOKUP(K6,'Correl CIIU'!$A$1:$F$26,4,FALSE()) -> Mining and quarrying | O6: 3 | P6: =+VLOOKUP(O6,bio!$A$2:$B$4,2,FALSE()) -> No bioeconomía
A7: BRAoc006 | B7: P10 | C7: =+VLOOKUP(B7,'transacciones '!$A$2:$I$39,2,FALSE()) -> ATC01 | D7: =+VLOOKUP(B7,'transacciones '!$A$2:$I$39,3,FALSE()) -> Producción / Consumo intermedio | E7: =+VLOOKUP(B7,'transacciones '!$A$2:$I$39,4,FALSE()) -> Producción | F7: =+VLOOKUP(B7,'transacciones '!$A$2:$I$39,5,FALSE()) -> 1 | G7: =+VLOOKUP(B7,'transacciones '!$A$2:$I$39,6,FALSE()) -> P1 | H7: =+VLOOKUP(B7,'transacciones '!$A$2:$I$39,7,FALSE()) -> Producción | I7: 0791 | J7: 0791 Extração de minério de ferro, inclusive beneficiamentos e a aglomeração | K7: B | L7: =+VLOOKUP(K7,'Correl CIIU'!$A$1:$F$26,2,FALSE()) -> Explotación de minas y canteras | M7: =+VLOOKUP(K7,'Correl CIIU'!$A$1:$F$26,3,FALSE()) -> Minería | N7: =+VLOOKUP(K7,'Correl CIIU'!$A$1:$F$26,4,FALSE()) -> Mining and quarrying | O7: 3 | P7: =+VLOOKUP(O7,bio!$A$2:$B$4,2,FALSE()) -> No bioeconomía
A8: BRAoc007 | B8: P10 | C8: =+VLOOKUP(B8,'transacciones '!$A$2:$I$39,2,FALSE()) -> ATC01 | D8: =+VLOOKUP(B8,'transacciones '!$A$2:$I$39,3,FALSE()) -> Producción / Consumo intermedio | E8: =+VLOOKUP(B8,'transacciones '!$A$2:$I$39,4,FALSE()) -> Producción | F8: =+VLOOKUP(B8,'transacciones '!$A$2:$I$39,5,FALSE()) -> 1 | G8: =+VLOOKUP(B8,'transacciones '!$A$2:$I$39,6,FALSE()) -> P1 | H8: =+VLOOKUP(B8,'transacciones '!$A$2:$I$39,7,FALSE()) -> Producción | I8: 0792 | J8: 0792 Extração de minerais metálicos não-ferrosos, inclusive beneficiamentos | K8: B | L8: =+VLOOKUP(K8,'Correl CIIU'!$A$1:$F$26,2,FALSE()) -> Explotación de minas y canteras | M8: =+VLOOKUP(K8,'Correl CIIU'!$A$1:$F$26,3,FALSE()) -> Minería | N8: =+VLOOKUP(K8,'Correl CIIU'!$A$1:$F$26,4,FALSE()) -> Mining and quarrying | O8: 3 | P8: =+VLOOKUP(O8,bio!$A$2:$B$4,2,FALSE()) -> No bioeconomía
A9: BRAoc008 | B9: P10 | C9: =+VLOOKUP(B9,'transacciones '!$A$2:$I$39,2,FALSE()) -> ATC01 | D9: =+VLOOKUP(B9,'transacciones '!$A$2:$I$39,3,FALSE()) -> Producción / Consumo intermedio | E9: =+VLOOKUP(B9,'transacciones '!$A$2:$I$39,4,FALSE()) -> Producción | F9: =+VLOOKUP(B9,'transacciones '!$A$2:$I$39,5,FALSE()) -> 1 | G9: =+VLOOKUP(B9,'transacciones '!$A$2:$I$39,6,FALSE()) -> P1 | H9: =+VLOOKUP(B9,'transacciones '!$A$2:$I$39,7,FALSE()) -> Producción | I9: 1091 | J9: 1091 Abate e produtos de carne, inclusive os produtos do laticínio e da pesca | K9: C | L9: =+VLOOKUP(K9,'Correl CIIU'!$A$1:$F$26,2,FALSE()) -> Industrias manufactureras | M9: =+VLOOKUP(K9,'Correl CIIU'!$A$1:$F$26,3,FALSE()) -> Manufacturas | N9: =+VLOOKUP(K9,'Correl CIIU'!$A$1:$F$26,4,FALSE()) -> Manufacturing | O9: 1 | P9: =+VLOOKUP(O9,bio!$A$2:$B$4,2,FALSE()) -> Bioeconomía
A10: BRAoc009 | B10: P10 | C10: =+VLOOKUP(B10,'transacciones '!$A$2:$I$39,2,FALSE()) -> ATC01 | D10: =+VLOOKUP(B10,'transacciones '!$A$2:$I$39,3,FALSE()) -> Producción / Consumo intermedio | E10: =+VLOOKUP(B10,'transacciones '!$A$2:$I$39,4,FALSE()) -> Producción | F10: =+VLOOKUP(B10,'transacciones '!$A$2:$I$39,5,FALSE()) -> 1 | G10: =+VLOOKUP(B10,'transacciones '!$A$2:$I$39,6,FALSE()) -> P1 | H10: =+VLOOKUP(B10,'transacciones '!$A$2:$I$39,7,FALSE()) -> Producción | I10: 1092 | J10: 1092 Fabricação e refino de açúcar | K10: C | L10: =+VLOOKUP(K10,'Correl CIIU'!$A$1:$F$26,2,FALSE()) -> Industrias manufactureras | M10: =+VLOOKUP(K10,'Correl CIIU'!$A$1:$F$26,3,FALSE()) -> Manufacturas | N10: =+VLOOKUP(K10,'Correl CIIU'!$A$1:$F$26,4,FALSE()) -> Manufacturing | O10: 1 | P10: =+VLOOKUP(O10,bio!$A$2:$B$4,2,FALSE()) -> Bioeconomía
A11: BRAoc010 | B11: P10 | C11: =+VLOOKUP(B11,'transacciones '!$A$2:$I$39,2,FALSE()) -> ATC01 | D11: =+VLOOKUP(B11,'transacciones '!$A$2:$I$39,3,FALSE()) -> Producción / Consumo intermedio | E11: =+VLOOKUP(B11,'transacciones '!$A$2:$I$39,4,FALSE()) -> Producción | F11: =+VLOOKUP(B11,'transacciones '!$A$2:$I$39,5,FALSE()) -> 1 | G11: =+VLOOKUP(B11,'transacciones '!$A$2:$I$39,6,FALSE()) -> P1 | H11: =+VLOOKUP(B11,'transacciones '!$A$2:$I$39,7,FALSE()) -> Producción | I11: 1093 | J11: 1093 Outros produtos alimentares | K11: C | L11: =+VLOOKUP(K11,'Correl CIIU'!$A$1:$F$26,2,FALSE()) -> Industrias manufactureras | M11: =+VLOOKUP(K11,'Correl CIIU'!$A$1:$F$26,3,FALSE()) -> Manufacturas | N11: =+VLOOKUP(K11,'Correl CIIU'!$A$1:$F$26,4,FALSE()) -> Manufacturing | O11: 1 | P11: =+VLOOKUP(O11,bio!$A$2:$B$4,2,FALSE()) -> Bioeconomía
A12: BRAoc011 | B12: P10 | C12: =+VLOOKUP(B12,'transacciones '!$A$2:$I$39,2,FALSE()) -> ATC01 | D12: =+VLOOKUP(B12,'transacciones '!$A$2:$I$39,3,FALSE()) -> Producción / Consumo intermedio | E12: =+VLOOKUP(B12,'transacciones '!$A$2:$I$39,4,FALSE()) -> Producción | F12: =+VLOOKUP(B12,'transacciones '!$A$2:$I$39,5,FALSE()) -> 1 | G12: =+VLOOKUP(B12,'transacciones '!$A$2:$I$39,6,FALSE()) -> P1 | H12: =+VLOOKUP(B12,'transacciones '!$A$2:$I$39,7,FALSE()) -> Producción | I12: 1100 | J12: 1100 Fabricação de bebidas | K12: C | L12: =+VLOOKUP(K12,'Correl CIIU'!$A$1:$F$26,2,FALSE()) -> Industrias manufactureras | M12: =+VLOOKUP(K12,'Correl CIIU'!$A$1:$F$26,3,FALSE()) -> Manufacturas | N12: =+VLOOKUP(K12,'Correl CIIU'!$A$1:$F$26,4,FALSE()) -> Manufacturing | O12: 1 | P12: =+VLOOKUP(O12,bio!$A$2:$B$4,2,FALSE()) -> Bioeconomía
A13: BRAoc012 | B13: P10 | C13: =+VLOOKUP(B13,'transacciones '!$A$2:$I$39,2,FALSE()) -> ATC01 | D13: =+VLOOKUP(B13,'transacciones '!$A$2:$I$39,3,FALSE()) -> Producción / Consumo intermedio | E13: =+VLOOKUP(B13,'transacciones '!$A$2:$I$39,4,FALSE()) -> Producción | F13: =+VLOOKUP(B13,'transacciones '!$A$2:$I$39,5,FALSE()) -> 1 | G13: =+VLOOKUP(B13,'transacciones '!$A$2:$I$39,6,FALSE()) -> P1 | H13: =+VLOOKUP(B13,'transacciones '!$A$2:$I$39,7,FALSE()) -> Producción | I13: 1200 | J13: 1200 Fabricação de produtos do fumo | K13: C | L13: =+VLOOKUP(K13,'Correl CIIU'!$A$1:$F$26,2,FALSE()) -> Industrias manufactureras | M13: =+VLOOKUP(K13,'Correl CIIU'!$A$1:$F$26,3,FALSE()) -> Manufacturas | N13: =+VLOOKUP(K13,'Correl CIIU'!$A$1:$F$26,4,FALSE()) -> Manufacturing | O13: 1 | P13: =+VLOOKUP(O13,bio!$A$2:$B$4,2,FALSE()) -> Bioeconomía
... A66: BRAoc065 | B66: P10 | C66: =+VLOOKUP(B66,'transacciones '!$A$2:$I$39,2,FALSE()) -> ATC01 | D66: =+VLOOKUP(B66,'transacciones '!$A$2:$I$39,3,FALSE()) -> Producción / Consumo intermedio | E66: =+VLOOKUP(B66,'transacciones '!$A$2:$I$39,4,FALSE()) -> Producción | F66: =+VLOOKUP(B66,'transacciones '!$A$2:$I$39,5,FALSE()) -> 1 | G66: =+VLOOKUP(B66,'transacciones '!$A$2:$I$39,6,FALSE()) -> P1 | H66: =+VLOOKUP(B66,'transacciones '!$A$2:$I$39,7,FALSE()) -> Producción | I66: 8692 | J66: 8692 Saúde privada | K66: Q | L66: =+VLOOKUP(K66,'Correl CIIU'!$A$1:$F$26,2,FALSE()) -> Actividades de atención de la salud humana y de asistencia social | M66: =+VLOOKUP(K66,'Correl CIIU'!$A$1:$F$26,3,FALSE()) -> Salud | N66: =+VLOOKUP(K66,'Correl CIIU'!$A$1:$F$26,4,FALSE()) -> Human health and social work activities | O66: 3 | P66: =+VLOOKUP(O66,bio!$A$2:$B$4,2,FALSE()) -> No bioeconomía
A67: BRAoc066 | B67: P10 | C67: =+VLOOKUP(B67,'transacciones '!$A$2:$I$39,2,FALSE()) -> ATC01 | D67: =+VLOOKUP(B67,'transacciones '!$A$2:$I$39,3,FALSE()) -> Producción / Consumo intermedio | E67: =+VLOOKUP(B67,'transacciones '!$A$2:$I$39,4,FALSE()) -> Producción | F67: =+VLOOKUP(B67,'transacciones '!$A$2:$I$39,5,FALSE()) -> 1 | G67: =+VLOOKUP(B67,'transacciones '!$A$2:$I$39,6,FALSE()) -> P1 | H67: =+VLOOKUP(B67,'transacciones '!$A$2:$I$39,7,FALSE()) -> Producción | I67: 9080 | J67: 9080 Atividades artísticas, criativas e de espetáculos | K67: R | L67: =+VLOOKUP(K67,'Correl CIIU'!$A$1:$F$26,2,FALSE()) -> Actividades artísticas, de entretenimiento y recreativas | M67: =+VLOOKUP(K67,'Correl CIIU'!$A$1:$F$26,3,FALSE()) -> Recreación | N67: =+VLOOKUP(K67,'Correl CIIU'!$A$1:$F$26,4,FALSE()) -> Arts, entertainment and recreation | O67: 3 | P67: =+VLOOKUP(O68,bio!$A$2:$B$4,2,FALSE()) -> No bioeconomía
A68: BRAoc067 | B68: P10 | C68: =+VLOOKUP(B68,'transacciones '!$A$2:$I$39,2,FALSE()) -> ATC01 | D68: =+VLOOKUP(B68,'transacciones '!$A$2:$I$39,3,FALSE()) -> Producción / Consumo intermedio | E68: =+VLOOKUP(B68,'transacciones '!$A$2:$I$39,4,FALSE()) -> Producción | F68: =+VLOOKUP(B68,'transacciones '!$A$2:$I$39,5,FALSE()) -> 1 | G68: =+VLOOKUP(B68,'transacciones '!$A$2:$I$39,6,FALSE()) -> P1 | H68: =+VLOOKUP(B68,'transacciones '!$A$2:$I$39,7,FALSE()) -> Producción | I68: 9480 | J68: 9480 Organizações associativas e outros serviços pessoais | K68: R | L68: =+VLOOKUP(K68,'Correl CIIU'!$A$1:$F$26,2,FALSE()) -> Actividades artísticas, de entretenimiento y recreativas | M68: =+VLOOKUP(K68,'Correl CIIU'!$A$1:$F$26,3,FALSE()) -> Recreación | N68: =+VLOOKUP(K68,'Correl CIIU'!$A$1:$F$26,4,FALSE()) -> Arts, entertainment and recreation | O68: 3 | P68: =+VLOOKUP(O69,bio!$A$2:$B$4,2,FALSE()) -> No bioeconomía
A69: BRAoc068 | B69: P10 | C69: =+VLOOKUP(B69,'transacciones '!$A$2:$I$39,2,FALSE()) -> ATC01 | D69: =+VLOOKUP(B69,'transacciones '!$A$2:$I$39,3,FALSE()) -> Producción / Consumo intermedio | E69: =+VLOOKUP(B69,'transacciones '!$A$2:$I$39,4,FALSE()) -> Producción | F69: =+VLOOKUP(B69,'transacciones '!$A$2:$I$39,5,FALSE()) -> 1 | G69: =+VLOOKUP(B69,'transacciones '!$A$2:$I$39,6,FALSE()) -> P1 | H69: =+VLOOKUP(B69,'transacciones '!$A$2:$I$39,7,FALSE()) -> Producción | I69: 9700 | J69: 9700 Serviços domésticos | K69: T | L69: =+VLOOKUP(K69,'Correl CIIU'!$A$1:$F$26,2,FALSE()) -> Actividades de los hogares como empleadores; actividades no diferenciadas de los hogares como productores de bienes y servicios para uso propio | M69: =+VLOOKUP(K69,'Correl CIIU'!$A$1:$F$26,3,FALSE()) -> Hogares como empleadores | N69: =+VLOOKUP(K69,'Correl CIIU'!$A$1:$F$26,4,FALSE()) -> Activities of households as employers; undifferentiated goods- and services-producing activities of households for own use | O69: 3 | P69: =+VLOOKUP(O69,bio!$A$2:$B$4,2,FALSE()) -> No bioeconomía
A70: BRAoc069 | I70: =LEFT(J70,4) -> Tota | J70: Total do produto
A71: BRAoc070 | B71: P70 | C71: =+VLOOKUP(B71,'transacciones '!$A$2:$I$39,2,FALSE()) -> ATC02 | D71: =+VLOOKUP(B71,'transacciones '!$A$2:$I$39,3,FALSE()) -> Exportaciones / Importaciones | E71: =+VLOOKUP(B71,'transacciones '!$A$2:$I$39,4,FALSE()) -> Importaciones de bienes Y SERVICIOS | F71: =+VLOOKUP(B71,'transacciones '!$A$2:$I$39,5,FALSE()) -> 0 | G71: =+VLOOKUP(B71,'transacciones '!$A$2:$I$39,6,FALSE()) -> P7 | H71: =+VLOOKUP(B71,'transacciones '!$A$2:$I$39,7,FALSE()) -> Importaciones de bienes y servicios | I71: =LEFT(J71,4) -> Impo | J71: Importação de bens e serviços (1) | K71: - | L71: - | M71: - | N71: - | O71: - | P71: -
A72: BRAoc071 | B72: M11 | C72: =+VLOOKUP(B72,'transacciones '!$A$2:$I$39,2,FALSE()) -> ATC05 | D72: =+VLOOKUP(B72,'transacciones '!$A$2:$I$39,3,FALSE()) -> Márgenes de distribución | E72: =+VLOOKUP(B72,'transacciones '!$A$2:$I$39,4,FALSE()) -> Márgenes de comercio | F72: =+VLOOKUP(B72,'transacciones '!$A$2:$I$39,5,FALSE()) -> 12 | G72: =+VLOOKUP(B72,'transacciones '!$A$2:$I$39,6,FALSE()) -> M1 | H72: =+VLOOKUP(B72,'transacciones '!$A$2:$I$39,7,FALSE()) -> Márgenes de distribución | I72: =LEFT(J72,4) -> Marg | J72: Margem de comércio | K72: - | L72: - | M72: - | N72: - | O72: - | P72: -
A73: BRAoc072 | B73: M12 | C73: =+VLOOKUP(B73,'transacciones '!$A$2:$I$39,2,FALSE()) -> ATC05 | D73: =+VLOOKUP(B73,'transacciones '!$A$2:$I$39,3,FALSE()) -> Márgenes de distribución | E73: =+VLOOKUP(B73,'transacciones '!$A$2:$I$39,4,FALSE()) -> Márgenes de transporte | F73: =+VLOOKUP(B73,'transacciones '!$A$2:$I$39,5,FALSE()) -> 12 | G73: =+VLOOKUP(B73,'transacciones '!$A$2:$I$39,6,FALSE()) -> M1 | H73: =+VLOOKUP(B73,'transacciones '!$A$2:$I$39,7,FALSE()) -> Márgenes de distribución | I73: =LEFT(J73,4) -> Marg | J73: Margem de transporte | K73: - | L73: - | M73: - | N73: - | O73: - | P73: -
A74: BRAoc073 | B74: D212 | C74: =+VLOOKUP(B74,'transacciones '!$A$2:$I$39,2,FALSE()) -> ATC04 | D74: =+VLOOKUP(B74,'transacciones '!$A$2:$I$39,3,FALSE()) -> Impuestos menos subvenciones sobre los productos | E74: =+VLOOKUP(B74,'transacciones '!$A$2:$I$39,4,FALSE()) -> Impuestos y derechos sobre las importaciones excepto IVA | F74: =+VLOOKUP(B74,'transacciones '!$A$2:$I$39,5,FALSE()) -> 9 | G74: =+VLOOKUP(B74,'transacciones '!$A$2:$I$39,6,FALSE()) -> D2 | H74: =+VLOOKUP(B74,'transacciones '!$A$2:$I$39,7,FALSE()) -> Impuestos sobre la producción y las importaciones | I74: =LEFT(J74,4) -> Impo | J74: Imposto de importação | K74: - | L74: - | M74: - | N74: - | O74: - | P74: -
A75: BRAoc074 | B75: D211 | C75: =+VLOOKUP(B75,'transacciones '!$A$2:$I$39,2,FALSE()) -> ATC04 | D75: =+VLOOKUP(B75,'transacciones '!$A$2:$I$39,3,FALSE()) -> Impuestos menos subvenciones sobre los productos | E75: =+VLOOKUP(B75,'transacciones '!$A$2:$I$39,4,FALSE()) -> Impuestos tipo valor agregado (IVA) | F75: =+VLOOKUP(B75,'transacciones '!$A$2:$I$39,5,FALSE()) -> 9 | G75: =+VLOOKUP(B75,'transacciones '!$A$2:$I$39,6,FALSE()) -> D2 | H75: =+VLOOKUP(B75,'transacciones '!$A$2:$I$39,7,FALSE()) -> Impuestos sobre la producción y las importaciones | I75: =LEFT(J75,4) -> IPI | J75: IPI | K75: - | L75: - | M75: - | N75: - | O75: - | P75: -
A76: BRAoc075 | B76: D214 | C76: =+VLOOKUP(B76,'transacciones '!$A$2:$I$39,2,FALSE()) -> ATC04 | D76: =+VLOOKUP(B76,'transacciones '!$A$2:$I$39,3,FALSE()) -> Impuestos menos subvenciones sobre los productos | E76: =+VLOOKUP(B76,'transacciones '!$A$2:$I$39,4,FALSE()) -> Impuestos sobre los productos, excepto IVA e impuestos sobre las importaciones | F76: =+VLOOKUP(B76,'transacciones '!$A$2:$I$39,5,FALSE()) -> 9 | G76: =+VLOOKUP(B76,'transacciones '!$A$2:$I$39,6,FALSE()) -> D2 | H76: =+VLOOKUP(B76,'transacciones '!$A$2:$I$39,7,FALSE()) -> Impuestos sobre la producción y las importaciones | I76: =LEFT(J76,4) -> ICMS | J76: ICMS | K76: - | L76: - | M76: - | N76: - | O76: - | P76: -
A77: BRAoc076 | B77: D214 | C77: =+VLOOKUP(B77,'transacciones '!$A$2:$I$39,2,FALSE()) -> ATC04 | D77: =+VLOOKUP(B77,'transacciones '!$A$2:$I$39,3,FALSE()) -> Impuestos menos subvenciones sobre los productos | E77: =+VLOOKUP(B77,'transacciones '!$A$2:$I$39,4,FALSE()) -> Impuestos sobre los productos, excepto IVA e impuestos sobre las importaciones | F77: =+VLOOKUP(B77,'transacciones '!$A$2:$I$39,5,FALSE()) -> 9 | G77: =+VLOOKUP(B77,'transacciones '!$A$2:$I$39,6,FALSE()) -> D2 | H77: =+VLOOKUP(B77,'transacciones '!$A$2:$I$39,7,FALSE()) -> Impuestos sobre la producción y las importaciones | I77: =LEFT(J77,4) -> Outr | J77: Outros impostos menos subsídios | K77: - | L77: - | M77: - | N77: - | O77: - | P77: -
A78: BRAoc077 | J78: Total de impostos líquidos de subsídios
A79: BRAuc001 | B79: P20 | C79: =+VLOOKUP(B79,'transacciones '!$A$2:$I$39,2,FALSE()) -> ATC01 | D79: =+VLOOKUP(B79,'transacciones '!$A$2:$I$39,3,FALSE()) -> Producción / Consumo intermedio | E79: =+VLOOKUP(B79,'transacciones '!$A$2:$I$39,4,FALSE()) -> Consumo | F79: =+VLOOKUP(B79,'transacciones '!$A$2:$I$39,5,FALSE()) -> 2 | G79: =+VLOOKUP(B79,'transacciones '!$A$2:$I$39,6,FALSE()) -> P2 | H79: =+VLOOKUP(B79,'transacciones '!$A$2:$I$39,7,FALSE()) -> Consumo intermedio | I79: 0191 | J79: 0191 Agricultura, inclusive o apoio à agricultura e a pós-colheita | K79: C | L79: =+VLOOKUP(K79,'Correl CIIU'!$A$1:$F$26,2,FALSE()) -> Industrias manufactureras | M79: =+VLOOKUP(K79,'Correl CIIU'!$A$1:$F$26,3,FALSE()) -> Manufacturas | N79: =+VLOOKUP(K79,'Correl CIIU'!$A$1:$F$26,4,FALSE()) -> Manufacturing | O79: 1 | P79: =+VLOOKUP(O79,bio!$A$2:$B$4,2,FALSE()) -> Bioeconomía
A80: BRAuc002 | B80: P20 | C80: =+VLOOKUP(B80,'transacciones '!$A$2:$I$39,2,FALSE()) -> ATC01 | D80: =+VLOOKUP(B80,'transacciones '!$A$2:$I$39,3,FALSE()) -> Producción / Consumo intermedio | E80: =+VLOOKUP(B80,'transacciones '!$A$2:$I$39,4,FALSE()) -> Consumo | F80: =+VLOOKUP(B80,'transacciones '!$A$2:$I$39,5,FALSE()) -> 2 | G80: =+VLOOKUP(B80,'transacciones '!$A$2:$I$39,6,FALSE()) -> P2 | H80: =+VLOOKUP(B80,'transacciones '!$A$2:$I$39,7,FALSE()) -> Consumo intermedio | I80: 0192 | J80: 0192 Pecuária, inclusive o apoio à pecuária | K80: A | L80: =+VLOOKUP(K80,'Correl CIIU'!$A$1:$F$26,2,FALSE()) -> Agricultura, ganadería, silvicultura y pesca | M80: =+VLOOKUP(K80,'Correl CIIU'!$A$1:$F$26,3,FALSE()) -> Agricultura | N80: =+VLOOKUP(K80,'Correl CIIU'!$A$1:$F$26,4,FALSE()) -> Agriculture, forestry and fishing | O80: 1 | P80: =+VLOOKUP(O80,bio!$A$2:$B$4,2,FALSE()) -> Bioeconomía
A81: BRAuc003 | B81: P20 | C81: =+VLOOKUP(B81,'transacciones '!$A$2:$I$39,2,FALSE()) -> ATC01 | D81: =+VLOOKUP(B81,'transacciones '!$A$2:$I$39,3,FALSE()) -> Producción / Consumo intermedio | E81: =+VLOOKUP(B81,'transacciones '!$A$2:$I$39,4,FALSE()) -> Consumo | F81: =+VLOOKUP(B81,'transacciones '!$A$2:$I$39,5,FALSE()) -> 2 | G81: =+VLOOKUP(B81,'transacciones '!$A$2:$I$39,6,FALSE()) -> P2 | H81: =+VLOOKUP(B81,'transacciones '!$A$2:$I$39,7,FALSE()) -> Consumo intermedio | I81: 0280 | J81: 0280 Produção florestal; pesca e aquicultura | K81: A | L81: =+VLOOKUP(K81,'Correl CIIU'!$A$1:$F$26,2,FALSE()) -> Agricultura, ganadería, silvicultura y pesca | M81: =+VLOOKUP(K81,'Correl CIIU'!$A$1:$F$26,3,FALSE()) -> Agricultura | N81: =+VLOOKUP(K81,'Correl CIIU'!$A$1:$F$26,4,FALSE()) -> Agriculture, forestry and fishing | O81: 1 | P81: =+VLOOKUP(O81,bio!$A$2:$B$4,2,FALSE()) -> Bioeconomía
A82: BRAuc004 | B82: P20 | C82: =+VLOOKUP(B82,'transacciones '!$A$2:$I$39,2,FALSE()) -> ATC01 | D82: =+VLOOKUP(B82,'transacciones '!$A$2:$I$39,3,FALSE()) -> Producción / Consumo intermedio | E82: =+VLOOKUP(B82,'transacciones '!$A$2:$I$39,4,FALSE()) -> Consumo | F82: =+VLOOKUP(B82,'transacciones '!$A$2:$I$39,5,FALSE()) -> 2 | G82: =+VLOOKUP(B82,'transacciones '!$A$2:$I$39,6,FALSE()) -> P2 | H82: =+VLOOKUP(B82,'transacciones '!$A$2:$I$39,7,FALSE()) -> Consumo intermedio | I82: 0580 | J82: 0580 Extração de carvão mineral e de minerais não-metálicos | K82: B | L82: =+VLOOKUP(K82,'Correl CIIU'!$A$1:$F$26,2,FALSE()) -> Explotación de minas y canteras | M82: =+VLOOKUP(K82,'Correl CIIU'!$A$1:$F$26,3,FALSE()) -> Minería | N82: =+VLOOKUP(K82,'Correl CIIU'!$A$1:$F$26,4,FALSE()) -> Mining and quarrying | O82: 3 | P82: =+VLOOKUP(O82,bio!$A$2:$B$4,2,FALSE()) -> No bioeconomía
A83: BRAuc005 | B83: P20 | C83: =+VLOOKUP(B83,'transacciones '!$A$2:$I$39,2,FALSE()) -> ATC01 | D83: =+VLOOKUP(B83,'transacciones '!$A$2:$I$39,3,FALSE()) -> Producción / Consumo intermedio | E83: =+VLOOKUP(B83,'transacciones '!$A$2:$I$39,4,FALSE()) -> Consumo | F83: =+VLOOKUP(B83,'transacciones '!$A$2:$I$39,5,FALSE()) -> 2 | G83: =+VLOOKUP(B83,'transacciones '!$A$2:$I$39,6,FALSE()) -> P2 | H83: =+VLOOKUP(B83,'transacciones '!$A$2:$I$39,7,FALSE()) -> Consumo intermedio | I83: 0680 | J83: 0680 Extração de petróleo e gás, inclusive as atividades de apoio | K83: B | L83: =+VLOOKUP(K83,'Correl CIIU'!$A$1:$F$26,2,FALSE()) -> Explotación de minas y canteras | M83: =+VLOOKUP(K83,'Correl CIIU'!$A$1:$F$26,3,FALSE()) -> Minería | N83: =+VLOOKUP(K83,'Correl CIIU'!$A$1:$F$26,4,FALSE()) -> Mining and quarrying | O83: 3 | P83: =+VLOOKUP(O83,bio!$A$2:$B$4,2,FALSE()) -> No bioeconomía
A84: BRAuc006 | B84: P20 | C84: =+VLOOKUP(B84,'transacciones '!$A$2:$I$39,2,FALSE()) -> ATC01 | D84: =+VLOOKUP(B84,'transacciones '!$A$2:$I$39,3,FALSE()) -> Producción / Consumo intermedio | E84: =+VLOOKUP(B84,'transacciones '!$A$2:$I$39,4,FALSE()) -> Consumo | F84: =+VLOOKUP(B84,'transacciones '!$A$2:$I$39,5,FALSE()) -> 2 | G84: =+VLOOKUP(B84,'transacciones '!$A$2:$I$39,6,FALSE()) -> P2 | H84: =+VLOOKUP(B84,'transacciones '!$A$2:$I$39,7,FALSE()) -> Consumo intermedio | I84: 0791 | J84: 0791 Extração de minério de ferro, inclusive beneficiamentos e a aglomeração | K84: B | L84: =+VLOOKUP(K84,'Correl CIIU'!$A$1:$F$26,2,FALSE()) -> Explotación de minas y canteras | M84: =+VLOOKUP(K84,'Correl CIIU'!$A$1:$F$26,3,FALSE()) -> Minería | N84: =+VLOOKUP(K84,'Correl CIIU'!$A$1:$F$26,4,FALSE()) -> Mining and quarrying | O84: 3 | P84: =+VLOOKUP(O84,bio!$A$2:$B$4,2,FALSE()) -> No bioeconomía
A85: BRAuc007 | B85: P20 | C85: =+VLOOKUP(B85,'transacciones '!$A$2:$I$39,2,FALSE()) -> ATC01 | D85: =+VLOOKUP(B85,'transacciones '!$A$2:$I$39,3,FALSE()) -> Producción / Consumo intermedio | E85: =+VLOOKUP(B85,'transacciones '!$A$2:$I$39,4,FALSE()) -> Consumo | F85: =+VLOOKUP(B85,'transacciones '!$A$2:$I$39,5,FALSE()) -> 2 | G85: =+VLOOKUP(B85,'transacciones '!$A$2:$I$39,6,FALSE()) -> P2 | H85: =+VLOOKUP(B85,'transacciones '!$A$2:$I$39,7,FALSE()) -> Consumo intermedio | I85: 0792 | J85: 0792 Extração de minerais metálicos não-ferrosos, inclusive beneficiamentos | K85: B | L85: =+VLOOKUP(K85,'Correl CIIU'!$A$1:$F$26,2,FALSE()) -> Explotación de minas y canteras | M85: =+VLOOKUP(K85,'Correl CIIU'!$A$1:$F$26,3,FALSE()) -> Minería | N85: =+VLOOKUP(K85,'Correl CIIU'!$A$1:$F$26,4,FALSE()) -> Mining and quarrying | O85: 3 | P85: =+VLOOKUP(O85,bio!$A$2:$B$4,2,FALSE()) -> No bioeconomía
A86: BRAuc008 | B86: P20 | C86: =+VLOOKUP(B86,'transacciones '!$A$2:$I$39,2,FALSE()) -> ATC01 | D86: =+VLOOKUP(B86,'transacciones '!$A$2:$I$39,3,FALSE()) -> Producción / Consumo intermedio | E86: =+VLOOKUP(B86,'transacciones '!$A$2:$I$39,4,FALSE()) -> Consumo | F86: =+VLOOKUP(B86,'transacciones '!$A$2:$I$39,5,FALSE()) -> 2 | G86: =+VLOOKUP(B86,'transacciones '!$A$2:$I$39,6,FALSE()) -> P2 | H86: =+VLOOKUP(B86,'transacciones '!$A$2:$I$39,7,FALSE()) -> Consumo intermedio | I86: 1091 | J86: 1091 Abate e produtos de carne, inclusive os produtos do laticínio e da pesca | K86: C | L86: =+VLOOKUP(K86,'Correl CIIU'!$A$1:$F$26,2,FALSE()) -> Industrias manufactureras | M86: =+VLOOKUP(K86,'Correl CIIU'!$A$1:$F$26,3,FALSE()) -> Manufacturas | N86: =+VLOOKUP(K86,'Correl CIIU'!$A$1:$F$26,4,FALSE()) -> Manufacturing | O86: 1 | P86: =+VLOOKUP(O86,bio!$A$2:$B$4,2,FALSE()) -> Bioeconomía
A87: BRAuc009 | B87: P20 | C87: =+VLOOKUP(B87,'transacciones '!$A$2:$I$39,2,FALSE()) -> ATC01 | D87: =+VLOOKUP(B87,'transacciones '!$A$2:$I$39,3,FALSE()) -> Producción / Consumo intermedio | E87: =+VLOOKUP(B87,'transacciones '!$A$2:$I$39,4,FALSE()) -> Consumo | F87: =+VLOOKUP(B87,'transacciones '!$A$2:$I$39,5,FALSE()) -> 2 | G87: =+VLOOKUP(B87,'transacciones '!$A$2:$I$39,6,FALSE()) -> P2 | H87: =+VLOOKUP(B87,'transacciones '!$A$2:$I$39,7,FALSE()) -> Consumo intermedio | I87: 1092 | J87: 1092 Fabricação e refino de açúcar | K87: C | L87: =+VLOOKUP(K87,'Correl CIIU'!$A$1:$F$26,2,FALSE()) -> Industrias manufactureras | M87: =+VLOOKUP(K87,'Correl CIIU'!$A$1:$F$26,3,FALSE()) -> Manufacturas | N87: =+VLOOKUP(K87,'Correl CIIU'!$A$1:$F$26,4,FALSE()) -> Manufacturing | O87: 1 | P87: =+VLOOKUP(O87,bio!$A$2:$B$4,2,FALSE()) -> Bioeconomía
A88: BRAuc010 | B88: P20 | C88: =+VLOOKUP(B88,'transacciones '!$A$2:$I$39,2,FALSE()) -> ATC01 | D88: =+VLOOKUP(B88,'transacciones '!$A$2:$I$39,3,FALSE()) -> Producción / Consumo intermedio | E88: =+VLOOKUP(B88,'transacciones '!$A$2:$I$39,4,FALSE()) -> Consumo | F88: =+VLOOKUP(B88,'transacciones '!$A$2:$I$39,5,FALSE()) -> 2 | G88: =+VLOOKUP(B88,'transacciones '!$A$2:$I$39,6,FALSE()) -> P2 | H88: =+VLOOKUP(B88,'transacciones '!$A$2:$I$39,7,FALSE()) -> Consumo intermedio | I88: 1093 | J88: 1093 Outros produtos alimentares | K88: C | L88: =+VLOOKUP(K88,'Correl CIIU'!$A$1:$F$26,2,FALSE()) -> Industrias manufactureras | M88: =+VLOOKUP(K88,'Correl CIIU'!$A$1:$F$26,3,FALSE()) -> Manufacturas | N88: =+VLOOKUP(K88,'Correl CIIU'!$A$1:$F$26,4,FALSE()) -> Manufacturing | O88: 1 | P88: =+VLOOKUP(O88,bio!$A$2:$B$4,2,FALSE()) -> Bioeconomía
A89: BRAuc011 | B89: P20 | C89: =+VLOOKUP(B89,'transacciones '!$A$2:$I$39,2,FALSE()) -> ATC01 | D89: =+VLOOKUP(B89,'transacciones '!$A$2:$I$39,3,FALSE()) -> Producción / Consumo intermedio | E89: =+VLOOKUP(B89,'transacciones '!$A$2:$I$39,4,FALSE()) -> Consumo | F89: =+VLOOKUP(B89,'transacciones '!$A$2:$I$39,5,FALSE()) -> 2 | G89: =+VLOOKUP(B89,'transacciones '!$A$2:$I$39,6,FALSE()) -> P2 | H89: =+VLOOKUP(B89,'transacciones '!$A$2:$I$39,7,FALSE()) -> Consumo intermedio | I89: 1100 | J89: 1100 Fabricação de bebidas | K89: C | L89: =+VLOOKUP(K89,'Correl CIIU'!$A$1:$F$26,2,FALSE()) -> Industrias manufactureras | M89: =+VLOOKUP(K89,'Correl CIIU'!$A$1:$F$26,3,FALSE()) -> Manufacturas | N89: =+VLOOKUP(K89,'Correl CIIU'!$A$1:$F$26,4,FALSE()) -> Manufacturing | O89: 1 | P89: =+VLOOKUP(O89,bio!$A$2:$B$4,2,FALSE()) -> Bioeconomía
A90: BRAuc012 | B90: P20 | C90: =+VLOOKUP(B90,'transacciones '!$A$2:$I$39,2,FALSE()) -> ATC01 | D90: =+VLOOKUP(B90,'transacciones '!$A$2:$I$39,3,FALSE()) -> Producción / Consumo intermedio | E90: =+VLOOKUP(B90,'transacciones '!$A$2:$I$39,4,FALSE()) -> Consumo | F90: =+VLOOKUP(B90,'transacciones '!$A$2:$I$39,5,FALSE()) -> 2 | G90: =+VLOOKUP(B90,'transacciones '!$A$2:$I$39,6,FALSE()) -> P2 | H90: =+VLOOKUP(B90,'transacciones '!$A$2:$I$39,7,FALSE()) -> Consumo intermedio | I90: 1200 | J90: 1200 Fabricação de produtos do fumo | K90: C | L90: =+VLOOKUP(K90,'Correl CIIU'!$A$1:$F$26,2,FALSE()) -> Industrias manufactureras | M90: =+VLOOKUP(K90,'Correl CIIU'!$A$1:$F$26,3,FALSE()) -> Manufacturas | N90: =+VLOOKUP(K90,'Correl CIIU'!$A$1:$F$26,4,FALSE()) -> Manufacturing | O90: 1 | P90: =+VLOOKUP(O90,bio!$A$2:$B$4,2,FALSE()) -> Bioeconomía
... A143: BRAuc065 | B143: P20 | C143: =+VLOOKUP(B143,'transacciones '!$A$2:$I$39,2,FALSE()) -> ATC01 | D143: =+VLOOKUP(B143,'transacciones '!$A$2:$I$39,3,FALSE()) -> Producción / Consumo intermedio | E143: =+VLOOKUP(B143,'transacciones '!$A$2:$I$39,4,FALSE()) -> Consumo | F143: =+VLOOKUP(B143,'transacciones '!$A$2:$I$39,5,FALSE()) -> 2 | G143: =+VLOOKUP(B143,'transacciones '!$A$2:$I$39,6,FALSE()) -> P2 | H143: =+VLOOKUP(B143,'transacciones '!$A$2:$I$39,7,FALSE()) -> Consumo intermedio | I143: 8692 | J143: 8692 Saúde privada | K143: Q | L143: =+VLOOKUP(K143,'Correl CIIU'!$A$1:$F$26,2,FALSE()) -> Actividades de atención de la salud humana y de asistencia social | M143: =+VLOOKUP(K143,'Correl CIIU'!$A$1:$F$26,3,FALSE()) -> Salud | N143: =+VLOOKUP(K143,'Correl CIIU'!$A$1:$F$26,4,FALSE()) -> Human health and social work activities | O143: 3 | P143: =+VLOOKUP(O143,bio!$A$2:$B$4,2,FALSE()) -> No bioeconomía
A144: BRAuc066 | B144: P20 | C144: =+VLOOKUP(B144,'transacciones '!$A$2:$I$39,2,FALSE()) -> ATC01 | D144: =+VLOOKUP(B144,'transacciones '!$A$2:$I$39,3,FALSE()) -> Producción / Consumo intermedio | E144: =+VLOOKUP(B144,'transacciones '!$A$2:$I$39,4,FALSE()) -> Consumo | F144: =+VLOOKUP(B144,'transacciones '!$A$2:$I$39,5,FALSE()) -> 2 | G144: =+VLOOKUP(B144,'transacciones '!$A$2:$I$39,6,FALSE()) -> P2 | H144: =+VLOOKUP(B144,'transacciones '!$A$2:$I$39,7,FALSE()) -> Consumo intermedio | I144: 9080 | J144: 9080 Atividades artísticas, criativas e de espetáculos | K144: R | L144: =+VLOOKUP(K144,'Correl CIIU'!$A$1:$F$26,2,FALSE()) -> Actividades artísticas, de entretenimiento y recreativas | M144: =+VLOOKUP(K144,'Correl CIIU'!$A$1:$F$26,3,FALSE()) -> Recreación | N144: =+VLOOKUP(K144,'Correl CIIU'!$A$1:$F$26,4,FALSE()) -> Arts, entertainment and recreation | O144: 3 | P144: =+VLOOKUP(O145,bio!$A$2:$B$4,2,FALSE()) -> No bioeconomía
A145: BRAuc067 | B145: P20 | C145: =+VLOOKUP(B145,'transacciones '!$A$2:$I$39,2,FALSE()) -> ATC01 | D145: =+VLOOKUP(B145,'transacciones '!$A$2:$I$39,3,FALSE()) -> Producción / Consumo intermedio | E145: =+VLOOKUP(B145,'transacciones '!$A$2:$I$39,4,FALSE()) -> Consumo | F145: =+VLOOKUP(B145,'transacciones '!$A$2:$I$39,5,FALSE()) -> 2 | G145: =+VLOOKUP(B145,'transacciones '!$A$2:$I$39,6,FALSE()) -> P2 | H145: =+VLOOKUP(B145,'transacciones '!$A$2:$I$39,7,FALSE()) -> Consumo intermedio | I145: 9480 | J145: 9480 Organizações associativas e outros serviços pessoais | K145: R | L145: =+VLOOKUP(K145,'Correl CIIU'!$A$1:$F$26,2,FALSE()) -> Actividades artísticas, de entretenimiento y recreativas | M145: =+VLOOKUP(K145,'Correl CIIU'!$A$1:$F$26,3,FALSE()) -> Recreación | N145: =+VLOOKUP(K145,'Correl CIIU'!$A$1:$F$26,4,FALSE()) -> Arts, entertainment and recreation | O145: 3 | P145: =+VLOOKUP(O146,bio!$A$2:$B$4,2,FALSE()) -> No bioeconomía
A146: BRAuc068 | B146: P20 | C146: =+VLOOKUP(B146,'transacciones '!$A$2:$I$39,2,FALSE()) -> ATC01 | D146: =+VLOOKUP(B146,'transacciones '!$A$2:$I$39,3,FALSE()) -> Producción / Consumo intermedio | E146: =+VLOOKUP(B146,'transacciones '!$A$2:$I$39,4,FALSE()) -> Consumo | F146: =+VLOOKUP(B146,'transacciones '!$A$2:$I$39,5,FALSE()) -> 2 | G146: =+VLOOKUP(B146,'transacciones '!$A$2:$I$39,6,FALSE()) -> P2 | H146: =+VLOOKUP(B146,'transacciones '!$A$2:$I$39,7,FALSE()) -> Consumo intermedio | I146: 9700 | J146: 9700 Serviços domésticos | K146: T | L146: =+VLOOKUP(K146,'Correl CIIU'!$A$1:$F$26,2,FALSE()) -> Actividades de los hogares como empleadores; actividades no diferenciadas de los hogares como productores de bienes y servicios para uso propio | M146: =+VLOOKUP(K146,'Correl CIIU'!$A$1:$F$26,3,FALSE()) -> Hogares como empleadores | N146: =+VLOOKUP(K146,'Correl CIIU'!$A$1:$F$26,4,FALSE()) -> Activities of households as employers; undifferentiated goods- and services-producing activities of households for own use | O146: 3 | P146: =+VLOOKUP(O146,bio!$A$2:$B$4,2,FALSE()) -> No bioeconomía
A147: BRAuc069 | I147: - | J147: Total do produto
A148: BRAuc070 | B148: P60 | C148: =+VLOOKUP(B148,'transacciones '!$A$2:$I$39,2,FALSE()) -> ATC02 | D148: =+VLOOKUP(B148,'transacciones '!$A$2:$I$39,3,FALSE()) -> Exportaciones / Importaciones | E148: =+VLOOKUP(B148,'transacciones '!$A$2:$I$39,4,FALSE()) -> Exportaciones de bienes y servicios | F148: =+VLOOKUP(B148,'transacciones '!$A$2:$I$39,5,FALSE()) -> 6 | G148: =+VLOOKUP(B148,'transacciones '!$A$2:$I$39,6,FALSE()) -> P6 | H148: =+VLOOKUP(B148,'transacciones '!$A$2:$I$39,7,FALSE()) -> Exportaciones de bienes y servicios | I148: - | J148: Exportação de bens e serviços (1) | K148: - | L148: - | M148: - | N148: - | O148: - | P148: -
A149: BRAuc071 | B149: Pc30 | C149: =+VLOOKUP(B149,'transacciones '!$A$2:$I$39,2,FALSE()) -> ATC06 | D149: =+VLOOKUP(B149,'transacciones '!$A$2:$I$39,3,FALSE()) -> Consumo final | E149: =+VLOOKUP(B149,'transacciones '!$A$2:$I$39,4,FALSE()) -> Gasto de consumo de gobierno | F149: =+VLOOKUP(B149,'transacciones '!$A$2:$I$39,5,FALSE()) -> 3 | G149: =+VLOOKUP(B149,'transacciones '!$A$2:$I$39,6,FALSE()) -> P3 | H149: =+VLOOKUP(B149,'transacciones '!$A$2:$I$39,7,FALSE()) -> Gasto de consumo final | I149: - | J149: Consumo do governo | K149: - | L149: - | M149: - | N149: - | O149: - | P149: -
A150: BRAuc072 | B150: Pb30 | C150: =+VLOOKUP(B150,'transacciones '!$A$2:$I$39,2,FALSE()) -> ATC06 | D150: =+VLOOKUP(B150,'transacciones '!$A$2:$I$39,3,FALSE()) -> Consumo final | E150: =+VLOOKUP(B150,'transacciones '!$A$2:$I$39,4,FALSE()) -> Gasto de consumo ISFLH | F150: =+VLOOKUP(B150,'transacciones '!$A$2:$I$39,5,FALSE()) -> 3 | G150: =+VLOOKUP(B150,'transacciones '!$A$2:$I$39,6,FALSE()) -> P3 | H150: =+VLOOKUP(B150,'transacciones '!$A$2:$I$39,7,FALSE()) -> Gasto de consumo final | I150: - | J150: Consumo das ISFLSF | K150: - | L150: - | M150: - | N150: - | O150: - | P150: -
A151: BRAuc073 | B151: Pa31 | C151: =+VLOOKUP(B151,'transacciones '!$A$2:$I$39,2,FALSE()) -> ATC06 | D151: =+VLOOKUP(B151,'transacciones '!$A$2:$I$39,3,FALSE()) -> Gasto de consumo final | E151: =+VLOOKUP(B151,'transacciones '!$A$2:$I$39,4,FALSE()) -> Gasto de consumo final de los hogares | F151: =+VLOOKUP(B151,'transacciones '!$A$2:$I$39,5,FALSE()) -> 3 | G151: =+VLOOKUP(B151,'transacciones '!$A$2:$I$39,6,FALSE()) -> P3 | H151: =+VLOOKUP(B151,'transacciones '!$A$2:$I$39,7,FALSE()) -> Gasto de consumo final | I151: - | J151: Consumo das famílias | K151: - | L151: - | M151: - | N151: - | O151: - | P151: -
A152: BRAuc074 | B152: P51b | C152: =+VLOOKUP(B152,'transacciones '!$A$2:$I$39,2,FALSE()) -> ATC07 | D152: =+VLOOKUP(B152,'transacciones '!$A$2:$I$39,3,FALSE()) -> Consumo final | E152: =+VLOOKUP(B152,'transacciones '!$A$2:$I$39,4,FALSE()) -> Formación bruta de capital fijo | F152: =+VLOOKUP(B152,'transacciones '!$A$2:$I$39,5,FALSE()) -> 5 | G152: =+VLOOKUP(B152,'transacciones '!$A$2:$I$39,6,FALSE()) -> P5 | H152: =+VLOOKUP(B152,'transacciones '!$A$2:$I$39,7,FALSE()) -> Formación de capital | I152: - | J152: Formação bruta de capital fixo | K152: - | L152: - | M152: - | N152: - | O152: - | P152: -
A153: BRAuc075 | B153: P52 | C153: =+VLOOKUP(B153,'transacciones '!$A$2:$I$39,2,FALSE()) -> ATC07 | D153: =+VLOOKUP(B153,'transacciones '!$A$2:$I$39,3,FALSE()) -> Consumo final | E153: =+VLOOKUP(B153,'transacciones '!$A$2:$I$39,4,FALSE()) -> Variación de existencias | F153: =+VLOOKUP(B153,'transacciones '!$A$2:$I$39,5,FALSE()) -> 5 | G153: =+VLOOKUP(B153,'transacciones '!$A$2:$I$39,6,FALSE()) -> P5 | H153: =+VLOOKUP(B153,'transacciones '!$A$2:$I$39,7,FALSE()) -> Formación de capital | I153: - | J153: Variação de estoque | K153: - | L153: - | M153: - | N153: - | O153: - | P153: -
A154: BRAuc076 | J154: Demanda final
A155: BRAuc077 | J155: Demanda total
A156: BRAvc001 | B156: P10 | C156: =+VLOOKUP(B156,'transacciones '!$A$2:$I$39,2,FALSE()) -> ATC01 | D156: =+VLOOKUP(B156,'transacciones '!$A$2:$I$39,3,FALSE()) -> Producción / Consumo intermedio | E156: =+VLOOKUP(B156,'transacciones '!$A$2:$I$39,4,FALSE()) -> Producción | F156: =+VLOOKUP(B156,'transacciones '!$A$2:$I$39,5,FALSE()) -> 1 | G156: =+VLOOKUP(B156,'transacciones '!$A$2:$I$39,6,FALSE()) -> P1 | H156: =+VLOOKUP(B156,'transacciones '!$A$2:$I$39,7,FALSE()) -> Producción | I156: - | J156: 0191 Agricultura, inclusive o apoio à agricultura e a pós-colheita | K156: A | L156: =+VLOOKUP(K156,'Correl CIIU'!$A$1:$F$26,2,FALSE()) -> Agricultura, ganadería, silvicultura y pesca | M156: =+VLOOKUP(K156,'Correl CIIU'!$A$1:$F$26,3,FALSE()) -> Agricultura | N156: =+VLOOKUP(K156,'Correl CIIU'!$A$1:$F$26,4,FALSE()) -> Agriculture, forestry and fishing | O156: 1 | P156: =+VLOOKUP(O156,bio!$A$2:$B$4,2,FALSE()) -> Bioeconomía
A157: BRAvc002 | B157: P10 | C157: =+VLOOKUP(B157,'transacciones '!$A$2:$I$39,2,FALSE()) -> ATC01 | D157: =+VLOOKUP(B157,'transacciones '!$A$2:$I$39,3,FALSE()) -> Producción / Consumo intermedio | E157: =+VLOOKUP(B157,'transacciones '!$A$2:$I$39,4,FALSE()) -> Producción | F157: =+VLOOKUP(B157,'transacciones '!$A$2:$I$39,5,FALSE()) -> 1 | G157: =+VLOOKUP(B157,'transacciones '!$A$2:$I$39,6,FALSE()) -> P1 | H157: =+VLOOKUP(B157,'transacciones '!$A$2:$I$39,7,FALSE()) -> Producción | I157: - | J157: 0192 Pecuária, inclusive o apoio à pecuária | K157: A | L157: =+VLOOKUP(K157,'Correl CIIU'!$A$1:$F$26,2,FALSE()) -> Agricultura, ganadería, silvicultura y pesca | M157: =+VLOOKUP(K157,'Correl CIIU'!$A$1:$F$26,3,FALSE()) -> Agricultura | N157: =+VLOOKUP(K157,'Correl CIIU'!$A$1:$F$26,4,FALSE()) -> Agriculture, forestry and fishing | O157: 1 | P157: =+VLOOKUP(O157,bio!$A$2:$B$4,2,FALSE()) -> Bioeconomía
A158: BRAvc003 | B158: P10 | C158: =+VLOOKUP(B158,'transacciones '!$A$2:$I$39,2,FALSE()) -> ATC01 | D158: =+VLOOKUP(B158,'transacciones '!$A$2:$I$39,3,FALSE()) -> Producción / Consumo intermedio | E158: =+VLOOKUP(B158,'transacciones '!$A$2:$I$39,4,FALSE()) -> Producción | F158: =+VLOOKUP(B158,'transacciones '!$A$2:$I$39,5,FALSE()) -> 1 | G158: =+VLOOKUP(B158,'transacciones '!$A$2:$I$39,6,FALSE()) -> P1 | H158: =+VLOOKUP(B158,'transacciones '!$A$2:$I$39,7,FALSE()) -> Producción | I158: - | J158: 0280 Produção florestal; pesca e aquicultura | K158: A | L158: =+VLOOKUP(K158,'Correl CIIU'!$A$1:$F$26,2,FALSE()) -> Agricultura, ganadería, silvicultura y pesca | M158: =+VLOOKUP(K158,'Correl CIIU'!$A$1:$F$26,3,FALSE()) -> Agricultura | N158: =+VLOOKUP(K158,'Correl CIIU'!$A$1:$F$26,4,FALSE()) -> Agriculture, forestry and fishing | O158: 1 | P158: =+VLOOKUP(O158,bio!$A$2:$B$4,2,FALSE()) -> Bioeconomía
A159: BRAvc004 | B159: P10 | C159: =+VLOOKUP(B159,'transacciones '!$A$2:$I$39,2,FALSE()) -> ATC01 | D159: =+VLOOKUP(B159,'transacciones '!$A$2:$I$39,3,FALSE()) -> Producción / Consumo intermedio | E159: =+VLOOKUP(B159,'transacciones '!$A$2:$I$39,4,FALSE()) -> Producción | F159: =+VLOOKUP(B159,'transacciones '!$A$2:$I$39,5,FALSE()) -> 1 | G159: =+VLOOKUP(B159,'transacciones '!$A$2:$I$39,6,FALSE()) -> P1 | H159: =+VLOOKUP(B159,'transacciones '!$A$2:$I$39,7,FALSE()) -> Producción | I159: - | J159: 0580 Extração de carvão mineral e de minerais não-metálicos | K159: B | L159: =+VLOOKUP(K159,'Correl CIIU'!$A$1:$F$26,2,FALSE()) -> Explotación de minas y canteras | M159: =+VLOOKUP(K159,'Correl CIIU'!$A$1:$F$26,3,FALSE()) -> Minería | N159: =+VLOOKUP(K159,'Correl CIIU'!$A$1:$F$26,4,FALSE()) -> Mining and quarrying | O159: 3 | P159: =+VLOOKUP(O159,bio!$A$2:$B$4,2,FALSE()) -> No bioeconomía
A160: BRAvc005 | B160: P10 | C160: =+VLOOKUP(B160,'transacciones '!$A$2:$I$39,2,FALSE()) -> ATC01 | D160: =+VLOOKUP(B160,'transacciones '!$A$2:$I$39,3,FALSE()) -> Producción / Consumo intermedio | E160: =+VLOOKUP(B160,'transacciones '!$A$2:$I$39,4,FALSE()) -> Producción | F160: =+VLOOKUP(B160,'transacciones '!$A$2:$I$39,5,FALSE()) -> 1 | G160: =+VLOOKUP(B160,'transacciones '!$A$2:$I$39,6,FALSE()) -> P1 | H160: =+VLOOKUP(B160,'transacciones '!$A$2:$I$39,7,FALSE()) -> Producción | I160: - | J160: 0680 Extração de petróleo e gás, inclusive as atividades de apoio | K160: B | L160: =+VLOOKUP(K160,'Correl CIIU'!$A$1:$F$26,2,FALSE()) -> Explotación de minas y canteras | M160: =+VLOOKUP(K160,'Correl CIIU'!$A$1:$F$26,3,FALSE()) -> Minería | N160: =+VLOOKUP(K160,'Correl CIIU'!$A$1:$F$26,4,FALSE()) -> Mining and quarrying | O160: 3 | P160: =+VLOOKUP(O160,bio!$A$2:$B$4,2,FALSE()) -> No bioeconomía
A161: BRAvc006 | B161: P10 | C161: =+VLOOKUP(B161,'transacciones '!$A$2:$I$39,2,FALSE()) -> ATC01 | D161: =+VLOOKUP(B161,'transacciones '!$A$2:$I$39,3,FALSE()) -> Producción / Consumo intermedio | E161: =+VLOOKUP(B161,'transacciones '!$A$2:$I$39,4,FALSE()) -> Producción | F161: =+VLOOKUP(B161,'transacciones '!$A$2:$I$39,5,FALSE()) -> 1 | G161: =+VLOOKUP(B161,'transacciones '!$A$2:$I$39,6,FALSE()) -> P1 | H161: =+VLOOKUP(B161,'transacciones '!$A$2:$I$39,7,FALSE()) -> Producción | I161: - | J161: 0791 Extração de minério de ferro, inclusive beneficiamentos e a aglomeração | K161: B | L161: =+VLOOKUP(K161,'Correl CIIU'!$A$1:$F$26,2,FALSE()) -> Explotación de minas y canteras | M161: =+VLOOKUP(K161,'Correl CIIU'!$A$1:$F$26,3,FALSE()) -> Minería | N161: =+VLOOKUP(K161,'Correl CIIU'!$A$1:$F$26,4,FALSE()) -> Mining and quarrying | O161: 3 | P161: =+VLOOKUP(O161,bio!$A$2:$B$4,2,FALSE()) -> No bioeconomía
A162: BRAvc007 | B162: P10 | C162: =+VLOOKUP(B162,'transacciones '!$A$2:$I$39,2,FALSE()) -> ATC01 | D162: =+VLOOKUP(B162,'transacciones '!$A$2:$I$39,3,FALSE()) -> Producción / Consumo intermedio | E162: =+VLOOKUP(B162,'transacciones '!$A$2:$I$39,4,FALSE()) -> Producción | F162: =+VLOOKUP(B162,'transacciones '!$A$2:$I$39,5,FALSE()) -> 1 | G162: =+VLOOKUP(B162,'transacciones '!$A$2:$I$39,6,FALSE()) -> P1 | H162: =+VLOOKUP(B162,'transacciones '!$A$2:$I$39,7,FALSE()) -> Producción | I162: - | J162: 0792 Extração de minerais metálicos não-ferrosos, inclusive beneficiamentos | K162: B | L162: =+VLOOKUP(K162,'Correl CIIU'!$A$1:$F$26,2,FALSE()) -> Explotación de minas y canteras | M162: =+VLOOKUP(K162,'Correl CIIU'!$A$1:$F$26,3,FALSE()) -> Minería | N162: =+VLOOKUP(K162,'Correl CIIU'!$A$1:$F$26,4,FALSE()) -> Mining and quarrying | O162: 3 | P162: =+VLOOKUP(O162,bio!$A$2:$B$4,2,FALSE()) -> No bioeconomía
A163: BRAvc008 | B163: P10 | C163: =+VLOOKUP(B163,'transacciones '!$A$2:$I$39,2,FALSE()) -> ATC01 | D163: =+VLOOKUP(B163,'transacciones '!$A$2:$I$39,3,FALSE()) -> Producción / Consumo intermedio | E163: =+VLOOKUP(B163,'transacciones '!$A$2:$I$39,4,FALSE()) -> Producción | F163: =+VLOOKUP(B163,'transacciones '!$A$2:$I$39,5,FALSE()) -> 1 | G163: =+VLOOKUP(B163,'transacciones '!$A$2:$I$39,6,FALSE()) -> P1 | H163: =+VLOOKUP(B163,'transacciones '!$A$2:$I$39,7,FALSE()) -> Producción | I163: - | J163: 1091 Abate e produtos de carne, inclusive os produtos do laticínio e da pesca | K163: C | L163: =+VLOOKUP(K163,'Correl CIIU'!$A$1:$F$26,2,FALSE()) -> Industrias manufactureras | M163: =+VLOOKUP(K163,'Correl CIIU'!$A$1:$F$26,3,FALSE()) -> Manufacturas | N163: =+VLOOKUP(K163,'Correl CIIU'!$A$1:$F$26,4,FALSE()) -> Manufacturing | O163: 1 | P163: =+VLOOKUP(O163,bio!$A$2:$B$4,2,FALSE()) -> Bioeconomía
A164: BRAvc009 | B164: P10 | C164: =+VLOOKUP(B164,'transacciones '!$A$2:$I$39,2,FALSE()) -> ATC01 | D164: =+VLOOKUP(B164,'transacciones '!$A$2:$I$39,3,FALSE()) -> Producción / Consumo intermedio | E164: =+VLOOKUP(B164,'transacciones '!$A$2:$I$39,4,FALSE()) -> Producción | F164: =+VLOOKUP(B164,'transacciones '!$A$2:$I$39,5,FALSE()) -> 1 | G164: =+VLOOKUP(B164,'transacciones '!$A$2:$I$39,6,FALSE()) -> P1 | H164: =+VLOOKUP(B164,'transacciones '!$A$2:$I$39,7,FALSE()) -> Producción | I164: - | J164: 1092 Fabricação e refino de açúcar | K164: C | L164: =+VLOOKUP(K164,'Correl CIIU'!$A$1:$F$26,2,FALSE()) -> Industrias manufactureras | M164: =+VLOOKUP(K164,'Correl CIIU'!$A$1:$F$26,3,FALSE()) -> Manufacturas | N164: =+VLOOKUP(K164,'Correl CIIU'!$A$1:$F$26,4,FALSE()) -> Manufacturing | O164: 1 | P164: =+VLOOKUP(O164,bio!$A$2:$B$4,2,FALSE()) -> Bioeconomía
A165: BRAvc010 | B165: P10 | C165: =+VLOOKUP(B165,'transacciones '!$A$2:$I$39,2,FALSE()) -> ATC01 | D165: =+VLOOKUP(B165,'transacciones '!$A$2:$I$39,3,FALSE()) -> Producción / Consumo intermedio | E165: =+VLOOKUP(B165,'transacciones '!$A$2:$I$39,4,FALSE()) -> Producción | F165: =+VLOOKUP(B165,'transacciones '!$A$2:$I$39,5,FALSE()) -> 1 | G165: =+VLOOKUP(B165,'transacciones '!$A$2:$I$39,6,FALSE()) -> P1 | H165: =+VLOOKUP(B165,'transacciones '!$A$2:$I$39,7,FALSE()) -> Producción | I165: - | J165: 1093 Outros produtos alimentares | K165: C | L165: =+VLOOKUP(K165,'Correl CIIU'!$A$1:$F$26,2,FALSE()) -> Industrias manufactureras | M165: =+VLOOKUP(K165,'Correl CIIU'!$A$1:$F$26,3,FALSE()) -> Manufacturas | N165: =+VLOOKUP(K165,'Correl CIIU'!$A$1:$F$26,4,FALSE()) -> Manufacturing | O165: 1 | P165: =+VLOOKUP(O165,bio!$A$2:$B$4,2,FALSE()) -> Bioeconomía
A166: BRAvc011 | B166: P10 | C166: =+VLOOKUP(B166,'transacciones '!$A$2:$I$39,2,FALSE()) -> ATC01 | D166: =+VLOOKUP(B166,'transacciones '!$A$2:$I$39,3,FALSE()) -> Producción / Consumo intermedio | E166: =+VLOOKUP(B166,'transacciones '!$A$2:$I$39,4,FALSE()) -> Producción | F166: =+VLOOKUP(B166,'transacciones '!$A$2:$I$39,5,FALSE()) -> 1 | G166: =+VLOOKUP(B166,'transacciones '!$A$2:$I$39,6,FALSE()) -> P1 | H166: =+VLOOKUP(B166,'transacciones '!$A$2:$I$39,7,FALSE()) -> Producción | I166: - | J166: 1100 Fabricação de bebidas | K166: C | L166: =+VLOOKUP(K166,'Correl CIIU'!$A$1:$F$26,2,FALSE()) -> Industrias manufactureras | M166: =+VLOOKUP(K166,'Correl CIIU'!$A$1:$F$26,3,FALSE()) -> Manufacturas | N166: =+VLOOKUP(K166,'Correl CIIU'!$A$1:$F$26,4,FALSE()) -> Manufacturing | O166: 1 | P166: =+VLOOKUP(O166,bio!$A$2:$B$4,2,FALSE()) -> Bioeconomía
A167: BRAvc012 | B167: P10 | C167: =+VLOOKUP(B167,'transacciones '!$A$2:$I$39,2,FALSE()) -> ATC01 | D167: =+VLOOKUP(B167,'transacciones '!$A$2:$I$39,3,FALSE()) -> Producción / Consumo intermedio | E167: =+VLOOKUP(B167,'transacciones '!$A$2:$I$39,4,FALSE()) -> Producción | F167: =+VLOOKUP(B167,'transacciones '!$A$2:$I$39,5,FALSE()) -> 1 | G167: =+VLOOKUP(B167,'transacciones '!$A$2:$I$39,6,FALSE()) -> P1 | H167: =+VLOOKUP(B167,'transacciones '!$A$2:$I$39,7,FALSE()) -> Producción | I167: - | J167: 1200 Fabricação de produtos do fumo | K167: C | L167: =+VLOOKUP(K167,'Correl CIIU'!$A$1:$F$26,2,FALSE()) -> Industrias manufactureras | M167: =+VLOOKUP(K167,'Correl CIIU'!$A$1:$F$26,3,FALSE()) -> Manufacturas | N167: =+VLOOKUP(K167,'Correl CIIU'!$A$1:$F$26,4,FALSE()) -> Manufacturing | O167: 1 | P167: =+VLOOKUP(O167,bio!$A$2:$B$4,2,FALSE()) -> Bioeconomía
... A220: BRAvc065 | B220: P10 | C220: =+VLOOKUP(B220,'transacciones '!$A$2:$I$39,2,FALSE()) -> ATC01 | D220: =+VLOOKUP(B220,'transacciones '!$A$2:$I$39,3,FALSE()) -> Producción / Consumo intermedio | E220: =+VLOOKUP(B220,'transacciones '!$A$2:$I$39,4,FALSE()) -> Producción | F220: =+VLOOKUP(B220,'transacciones '!$A$2:$I$39,5,FALSE()) -> 1 | G220: =+VLOOKUP(B220,'transacciones '!$A$2:$I$39,6,FALSE()) -> P1 | H220: =+VLOOKUP(B220,'transacciones '!$A$2:$I$39,7,FALSE()) -> Producción | I220: - | J220: 8692 Saúde privada | K220: Q | L220: =+VLOOKUP(K220,'Correl CIIU'!$A$1:$F$26,2,FALSE()) -> Actividades de atención de la salud humana y de asistencia social | M220: =+VLOOKUP(K220,'Correl CIIU'!$A$1:$F$26,3,FALSE()) -> Salud | N220: =+VLOOKUP(K220,'Correl CIIU'!$A$1:$F$26,4,FALSE()) -> Human health and social work activities | O220: 3 | P220: =+VLOOKUP(O220,bio!$A$2:$B$4,2,FALSE()) -> No bioeconomía
A221: BRAvc066 | B221: P10 | C221: =+VLOOKUP(B221,'transacciones '!$A$2:$I$39,2,FALSE()) -> ATC01 | D221: =+VLOOKUP(B221,'transacciones '!$A$2:$I$39,3,FALSE()) -> Producción / Consumo intermedio | E221: =+VLOOKUP(B221,'transacciones '!$A$2:$I$39,4,FALSE()) -> Producción | F221: =+VLOOKUP(B221,'transacciones '!$A$2:$I$39,5,FALSE()) -> 1 | G221: =+VLOOKUP(B221,'transacciones '!$A$2:$I$39,6,FALSE()) -> P1 | H221: =+VLOOKUP(B221,'transacciones '!$A$2:$I$39,7,FALSE()) -> Producción | I221: - | J221: 9080 Atividades artísticas, criativas e de espetáculos | K221: R | L221: =+VLOOKUP(K221,'Correl CIIU'!$A$1:$F$26,2,FALSE()) -> Actividades artísticas, de entretenimiento y recreativas | M221: =+VLOOKUP(K221,'Correl CIIU'!$A$1:$F$26,3,FALSE()) -> Recreación | N221: =+VLOOKUP(K221,'Correl CIIU'!$A$1:$F$26,4,FALSE()) -> Arts, entertainment and recreation | O221: 3 | P221: =+VLOOKUP(O222,bio!$A$2:$B$4,2,FALSE()) -> No bioeconomía
A222: BRAvc067 | B222: P10 | C222: =+VLOOKUP(B222,'transacciones '!$A$2:$I$39,2,FALSE()) -> ATC01 | D222: =+VLOOKUP(B222,'transacciones '!$A$2:$I$39,3,FALSE()) -> Producción / Consumo intermedio | E222: =+VLOOKUP(B222,'transacciones '!$A$2:$I$39,4,FALSE()) -> Producción | F222: =+VLOOKUP(B222,'transacciones '!$A$2:$I$39,5,FALSE()) -> 1 | G222: =+VLOOKUP(B222,'transacciones '!$A$2:$I$39,6,FALSE()) -> P1 | H222: =+VLOOKUP(B222,'transacciones '!$A$2:$I$39,7,FALSE()) -> Producción | I222: - | J222: 9480 Organizações associativas e outros serviços pessoais | K222: R | L222: =+VLOOKUP(K222,'Correl CIIU'!$A$1:$F$26,2,FALSE()) -> Actividades artísticas, de entretenimiento y recreativas | M222: =+VLOOKUP(K222,'Correl CIIU'!$A$1:$F$26,3,FALSE()) -> Recreación | N222: =+VLOOKUP(K222,'Correl CIIU'!$A$1:$F$26,4,FALSE()) -> Arts, entertainment and recreation | O222: 3 | P222: =+VLOOKUP(O223,bio!$A$2:$B$4,2,FALSE()) -> No bioeconomía
A223: BRAvc068 | B223: P10 | C223: =+VLOOKUP(B223,'transacciones '!$A$2:$I$39,2,FALSE()) -> ATC01 | D223: =+VLOOKUP(B223,'transacciones '!$A$2:$I$39,3,FALSE()) -> Producción / Consumo intermedio | E223: =+VLOOKUP(B223,'transacciones '!$A$2:$I$39,4,FALSE()) -> Producción | F223: =+VLOOKUP(B223,'transacciones '!$A$2:$I$39,5,FALSE()) -> 1 | G223: =+VLOOKUP(B223,'transacciones '!$A$2:$I$39,6,FALSE()) -> P1 | H223: =+VLOOKUP(B223,'transacciones '!$A$2:$I$39,7,FALSE()) -> Producción | I223: - | J223: 9700 Serviços domésticos | K223: T | L223: =+VLOOKUP(K223,'Correl CIIU'!$A$1:$F$26,2,FALSE()) -> Actividades de los hogares como empleadores; actividades no diferenciadas de los hogares como productores de bienes y servicios para uso propio | M223: =+VLOOKUP(K223,'Correl CIIU'!$A$1:$F$26,3,FALSE()) -> Hogares como empleadores | N223: =+VLOOKUP(K223,'Correl CIIU'!$A$1:$F$26,4,FALSE()) -> Activities of households as employers; undifferentiated goods- and services-producing activities of households for own use | O223: 3 | P223: =+VLOOKUP(O223,bio!$A$2:$B$4,2,FALSE()) -> No bioeconomía
A224: BRAvc069 | B224: P10 | C224: =+VLOOKUP(B224,'transacciones '!$A$2:$I$39,2,FALSE()) -> ATC01 | D224: =+VLOOKUP(B224,'transacciones '!$A$2:$I$39,3,FALSE()) -> Producción / Consumo intermedio | E224: =+VLOOKUP(B224,'transacciones '!$A$2:$I$39,4,FALSE()) -> Producción | F224: =+VLOOKUP(B224,'transacciones '!$A$2:$I$39,5,FALSE()) -> 1 | G224: =+VLOOKUP(B224,'transacciones '!$A$2:$I$39,6,FALSE()) -> P1 | H224: =+VLOOKUP(B224,'transacciones '!$A$2:$I$39,7,FALSE()) -> Producción | I224: - | J224: Total do produto

Sheet Correl CIIU
A1: CIIU Secciones | B1: CIIU Secciones descripción | C1: CIIU Corto | D1: CIIU English
A2: A | B2: Agricultura, ganadería, silvicultura y pesca | C2: Agricultura | D2: Agriculture, forestry and fishing
A3: B | B3: Explotación de minas y canteras | C3: Minería | D3: Mining and quarrying
A4: C | B4: Industrias manufactureras | C4: Manufacturas | D4: Manufacturing
A5: C | B5: Industrias manufactureras | C5: Manufacturas | D5: Manufacturing
A6: C | B6: Industrias manufactureras | C6: Manufacturas | D6: Manufacturing
A7: D | B7: Suministro de electricidad, gas, vapor y aire acondicionado | C7: Servicios básicos | D7: Electricity, gas, steam and air conditioning supply
A8: E | B8: Suministro de agua; evacuación de aguas residuales, gestión de desechos y descontaminación | C8: Suministro de agua | D8: Water supply; sewerage, waste management and remediation activities
A9: F | B9: Construcción | C9: Construcción | D9: Construction
A10: G | B10: Comercio al por mayor y al por menor; reparación de vehículos automotores y motocicletas | C10: Comercio | D10: Wholesale and retail trade; repair of motor vehicles and motorcycles
A11: H | B11: Transporte y almacenamiento | C11: Transporte y almacenamiento | D11: Transportation and storage
A12: J | B12: Información y comunicaciones | C12: Información y comunicaciones | D12: Information and communication
... A26: - | B26: - | C26: - | D26: -

Sheet transacciones 
A1: Código Transacciones | B1: Área transaccional columnas No. | C1: Área transaccional | D1: Transacciones | E1: Correlativo Transacciones Agregadas | F1: Código Transacciones Agregadas | G1: Transacciones Agregadas | H1: corr_ntg2 | I1: id_area_columnas
A2: P10 | B2: ATC01 | C2: Producción / Consumo intermedio | D2: Producción | E2: 1 | F2: P1 | G2: Producción | H2: 1 | I2: 0
A3: P11 | B3: ATC01 | C3: Producción / Consumo intermedio | D3: Producción de mercado | E3: 1 | F3: P1 | G3: Producción | H3: 2 | I3: 1
A4: P12 | B4: ATC01 | C4: Producción / Consumo intermedio | D4: Producción para uso final propio | E4: 1 | F4: P1 | G4: Producción | H4: 3 | I4: 2
A5: P13 | B5: ATC01 | C5: Producción / Consumo intermedio | D5: Otra producción no de mercado | E5: 1 | F5: P1 | G5: Producción | H5: 4 | I5: 3
A6: P20 | B6: ATC01 | C6: Producción / Consumo intermedio | D6: Consumo | E6: 2 | F6: P2 | G6: Consumo intermedio | H6: 5 | I6: 0
A7: P21 | B7: ATC01 | C7: Producción / Consumo intermedio | D7: Consumo intermedio de mercado | E7: 2 | F7: P2 | G7: Consumo intermedio | H7: 6 | I7: 1
A8: P22 | B8: ATC01 | C8: Producción / Consumo intermedio | D8: Consumo intermedio para uso final propio | E8: 2 | F8: P2 | G8: Consumo intermedio | H8: 7 | I8: 2
A9: P23 | B9: ATC01 | C9: Producción / Consumo intermedio | D9: Consumo intermedio no de mercado | E9: 2 | F9: P2 | G9: Consumo intermedio | H9: 8 | I9: 3
A10: Pa31 | B10: ATC06 | C10: Gasto de consumo final | D10: Gasto de consumo final de los hogares | E10: 3 | F10: P3 | G10: Gasto de consumo final | H10: 9 | I10: 9
A11: Pb30 | B11: ATC06 | C11: Consumo final | D11: Gasto de consumo ISFLH | E11: 3 | F11: P3 | G11: Gasto de consumo final | H11: 10 | I11: 9
A12: Pb31 | B12: ATC06 | C12: Consumo final | D12: Gasto de consumo individual ISFLSH | E12: 3 | F12: P3 | G12: Gasto de consumo final | H12: 11 | I12: 9
A13: Pb32 | B13: ATC06 | C13: Consumo final | D13: Gasto de consumo colectivo ISFLSH | E13: 3 | F13: P3 | G13: Gasto de consumo final | H13: 12 | I13: 9
A14: Pc30 | B14: ATC06 | C14: Consumo final | D14: Gasto de consumo de gobierno | E14: 3 | F14: P3 | G14: Gasto de consumo final
A15: Pc31 | B15: ATC06 | C15: Consumo final | D15: Gasto de consumo individual de gobierno | E15: 3 | F15: P3 | G15: Gasto de consumo final | H15: 13 | I15: 9
A16: Pc32 | B16: ATC06 | C16: Consumo final | D16: Gasto de consumo colectivo de gobierno | E16: 3 | F16: P3 | G16: Gasto de consumo final | H16: 14 | I16: 9
A17: P41 | B17: ATC06 | C17: Consumo final | D17: Consumo individual efectivo | E17: 4 | F17: P4 | G17: Consumo final efectivo | H17: 15 | I17: 9
A18: P42 | B18: ATC06 | C18: Consumo final | D18: Consumo colectivo efectivo | E18: 4 | F18: P4 | G18: Consumo final efectivo | H18: 16 | I18: 9
A19: P51b | B19: ATC07 | C19: Consumo final | D19: Formación bruta de capital fijo | E19: 5 | F19: P5 | G19: Formación de capital | H19: 17 | I19: 10
A20: P51c | B20: ATC07 | C20: Consumo final | D20: Consumo de capital fijo | E20: 5 | F20: P5 | G20: Formación de capital | H20: 18 | I20: 10
A21: P52 | B21: ATC07 | C21: Consumo final | D21: Variación de existencias | E21: 5 | F21: P5 | G21: Formación de capital | H21: 19 | I21: 10
A22: P53 | B22: ATC07 | C22: Consumo final | D22: Adquisiciones menos disposiciones de objetos valiosos | E22: 5 | F22: P5 | G22: Formación de capital | H22: 20 | I22: 10
A23: P60 | B23: ATC02 | C23: Exportaciones / Importaciones | D23: Exportaciones de bienes y servicios | E23: 6 | F23: P6 | G23: Exportaciones de bienes y servicios | H23: 21 | I23: 4
A24: P61 | B24: ATC02 | C24: Exportaciones / Importaciones | D24: Exportaciones de bienes | E24: 6 | F24: P6 | G24: Exportaciones de bienes y servicios | H24: 22 | I24: 4
A25: P62 | B25: ATC02 | C25: Exportaciones / Importaciones | D25: Exportaciones de servicios | E25: 6 | F25: P6 | G25: Exportaciones de bienes y servicios | H25: 23 | I25: 4
A26: P70 | B26: ATC02 | C26: Exportaciones / Importaciones | D26: Importaciones de bienes Y SERVICIOS | F26: P7 | G26: Importaciones de bienes y servicios | H26: 24 | I26: 4
A27: P71 | B27: ATC02 | C27: Exportaciones / Importaciones | D27: Importaciones de bienes | E27: 7 | F27: P7 | G27: Importaciones de bienes y servicios | H27: 25 | I27: 4
A28: P72 | B28: ATC02 | C28: Exportaciones / Importaciones | D28: Importaciones de servicios | E28: 7 | F28: P7 | G28: Importaciones de bienes y servicios | H28: 26 | I28: 4
A29: CIF | B29: ATC03 | C29: Ajuste CIF/FOB | D29: Ajuste CIF/FOB sobre importaciones | E29: 8 | F29: CIF | G29: Ajuste CIF/FOB sobre importaciones | H29: 27 | I29: 5
A30: D211 | B30: ATC04 | C30: Impuestos menos subvenciones sobre los productos | D30: Impuestos tipo valor agregado (IVA) | E30: 9 | F30: D2 | G30: Impuestos sobre la producción y las importaciones | H30: 28 | I30: 6
A31: D212 | B31: ATC04 | C31: Impuestos menos subvenciones sobre los productos | D31: Impuestos y derechos sobre las importaciones excepto IVA | E31: 9 | F31: D2 | G31: Impuestos sobre la producción y las importaciones | H31: 29 | I31: 6
A32: D213 | B32: ATC04 | C32: Impuestos menos subvenciones sobre los productos | D32: Impuestos sobre las exportaciones | E32: 9 | F32: D2 | G32: Impuestos sobre la producción y las importaciones | H32: 30 | I32: 6
A33: D214 | B33: ATC04 | C33: Impuestos menos subvenciones sobre los productos | D33: Impuestos sobre los productos, excepto IVA e impuestos sobre las importaciones | E33: 9 | F33: D2 | G33: Impuestos sobre la producción y las importaciones | H33: 31 | I33: 6
A34: D291 | B34: ATC04 | C34: Impuestos menos subvenciones sobre los productos | D34: Otros impuestos sobre la producción | E34: 10 | F34: D29 | G34: Otros impuestos sobre la producción | H34: 32 | I34: 6
A35: D31 | B35: ATC04 | C35: Impuestos menos subvenciones sobre los productos | D35: Subvenciones a los productos | E35: 11 | F35: D3 | G35: Subvenciones | H35: 33 | I35: 7
A36: D39 | B36: ATCO4 | C36: Impuestos menos subvenciones sobre los productos | D36: Otras subvenciones a la producción | E36: 11 | F36: D3 | G36: Subvenciones | H36: 34 | I36: 7
A37: M11 | B37: ATC05 | C37: Márgenes de distribución | D37: Márgenes de comercio | E37: 12 | F37: M1 | G37: Márgenes de distribución | H37: 35 | I37: 8
A38: M12 | B38: ATC05 | C38: Márgenes de distribución | D38: Márgenes de transporte | E38: 12 | F38: M1 | G38: Márgenes de distribución | H38: 36 | I38: 8
A39: M13 | B39: ATC05 | C39: Márgenes de distribución | D39: Márgenes de distribución de electricidad | E39: 12 | F39: M1 | G39: Márgenes de distribución | H39: 37 | I39: 8

Sheet bio
A1: Correlativo Bioeconomía Productos | B1: Bioeconomía Productos | D1: Correlativo Bioeconomía Actividades | E1: Bioeconomía Actividades
A2: 1 | B2: Bioeconomía | D2: 1 | E2: Bioeconomía
A3: 2 | B3: Bioeconomía extendida | D3: 2 | E3: Bioeconomía extendida
A4: 3 | B4: No bioeconomía | D4: 3 | E4: No bioeconomía

Sheet at_columnas
A1: Área transaccional columnas No. | B1: Área transaccional | C1: Código Transacciones | D1: Detalle Transacciones
A2: ATC01 | B2: Producción / Consumo intermedio | C2: P11 | D2: Producción de mercado
A3: ATC01 | B3: Producción / Consumo intermedio | C3: P12 | D3: Producción para uso final propio
A4: ATC01 | B4: Producción / Consumo intermedio | C4: P13 | D4: Producción no de mercado
A5: ATC01 | B5: Producción / Consumo intermedio | C5: P21 | D5: Consumo intermedio de mercado
A6: ATC01 | B6: Producción / Consumo intermedio | C6: P22 | D6: Consumo intermedio para uso final propio
A7: ATC01 | B7: Producción / Consumo intermedio | C7: P23 | D7: Consumo intermedio no de mercado
A8: ATC02 | B8: Exportaciones / Importaciones | C8: P6 | D8: Total Exportaciones
A9: ATC02 | B9: Exportaciones / Importaciones | C9: P61 | D9: Exportación de bienes
A10: ATC02 | B10: Exportaciones / Importaciones | C10: P62 | D10: Exportación de servicios
A11: ATC02 | B11: Exportaciones / Importaciones | C11: P7 | D11: Importación de bienes
A12: ATC02 | B12: Exportaciones / Importaciones | C12: P7 | D12: Importación de servicios
... A23: ATC07 | B23: Formación bruta de capital | C23: P52 | D23: Variación de existencias

Sheet filas
A1: Filas | B1: Áreas Transaccionales Filas No. | C1: Áreas Transaccionales Filas Descripción | D1: Codigo Transacción Filas | E1: Código Nomenclatura Local de Productos | F1: Nomenclatura Local de Productos | G1: Clasificación Productos | H1: Cod_Bioec Productos | I1: Tipo de bioeconomía Productos | J1: Sectores produuctos | K1: Cód_Div_CPC_3 | L1: División CPC_3 | M1: Cód_Div_CPC_2 | N1: División CPC_2 | O1: Cod. Elem. Def. Bioeconomía | P1: Tipo de elemento | Q1: Código CPC | R1: Elemento CPC | S1: Código Bioeconomía | T1: Clasificación Bioeconomí
A2: BRAof001 | B2: ATF01 | C2: =VLOOKUP(B2, AT_FILAS!$A$2:$C$8,2,FALSE()) -> Producción | D2: =VLOOKUP(B2, AT_FILAS!$A$2:$C$8,3,FALSE()) -> P1 | E2: 01911 | F2: Arroz, trigo e outros cereais | G2: Productos agricolas_Cereales | H2: 1 | I2: Bioeconomía de productos básicos | J2: Productos agropecuarios | K2: 1 | L2: =VLOOKUP(K2,clasif_filas!$A$1:$J$39,2,FALSE()) -> Productos de la agricultura, la horticultura y la jardinería comercial | M2: =VLOOKUP(K2,clasif_filas!$A$1:$J$39,3,FALSE()) -> 1 | N2: =VLOOKUP(K2,clasif_filas!$A$1:$J$39,4,FALSE()) -> Productos de la agricultura, la horticultura y la jardinería comercial | O2: =VLOOKUP(K2,clasif_filas!$A$1:$J$39,5,FALSE()) -> 1 | P2: =VLOOKUP(K2,clasif_filas!$A$1:$J$39,6,FALSE()) -> Biomasa que se cultiva para producir alimentos, forrajes, fibras y energía | Q2: =VLOOKUP(K2,clasif_filas!$A$1:$J$39,7,FALSE()) -> 0 | R2: =VLOOKUP(K2,clasif_filas!$A$1:$J$39,8,FALSE()) -> Productos de la agricultura, la silvicultura yla pesca | S2: =VLOOKUP(K2,clasif_filas!$A$1:$J$39,9,FALSE()) -> 1 | T2: =VLOOKUP(K2,clasif_filas!$A$1:$J$39,10,FALSE()) -> Bioeconomía
A3: BRAof002 | B3: ATF01 | C3: =VLOOKUP(B3, AT_FILAS!$A$2:$C$8,2,FALSE()) -> Producción | D3: =VLOOKUP(B3, AT_FILAS!$A$2:$C$8,3,FALSE()) -> P1 | E3: 01912 | F3: Milho em grão | G3: Productos agricolas_Cereales | H3: 1 | I3: Bioeconomía de productos básicos | J3: Productos agropecuarios | K3: 1 | L3: =VLOOKUP(K3,clasif_filas!$A$1:$J$39,2,FALSE()) -> Productos de la agricultura, la horticultura y la jardinería comercial | M3: =VLOOKUP(K3,clasif_filas!$A$1:$J$39,3,FALSE()) -> 1 | N3: =VLOOKUP(K3,clasif_filas!$A$1:$J$39,4,FALSE()) -> Productos de la agricultura, la horticultura y la jardinería comercial | O3: =VLOOKUP(K3,clasif_filas!$A$1:$J$39,5,FALSE()) -> 1 | P3: =VLOOKUP(K3,clasif_filas!$A$1:$J$39,6,FALSE()) -> Biomasa que se cultiva para producir alimentos, forrajes, fibras y energía | Q3: =VLOOKUP(K3,clasif_filas!$A$1:$J$39,7,FALSE()) -> 0 | R3: =VLOOKUP(K3,clasif_filas!$A$1:$J$39,8,FALSE()) -> Productos de la agricultura, la silvicultura yla pesca | S3: =VLOOKUP(K3,clasif_filas!$A$1:$J$39,9,FALSE()) -> 1 | T3: =VLOOKUP(K3,clasif_filas!$A$1:$J$39,10,FALSE()) -> Bioeconomía
A4: BRAof003 | B4: ATF01 | C4: =VLOOKUP(B4, AT_FILAS!$A$2:$C$8,2,FALSE()) -> Producción | D4: =VLOOKUP(B4, AT_FILAS!$A$2:$C$8,3,FALSE()) -> P1 | E4: 01913 | F4: Algodão herbáceo, outras fibras da lav. temporária | G4: Productos agricolas_Oleaginosas | H4: 1 | I4: Bioeconomía de productos básicos | J4: Productos agropecuarios | K4: 1 | L4: =VLOOKUP(K4,clasif_filas!$A$1:$J$39,2,FALSE()) -> Productos de la agricultura, la horticultura y la jardinería comercial | M4: =VLOOKUP(K4,clasif_filas!$A$1:$J$39,3,FALSE()) -> 1 | N4: =VLOOKUP(K4,clasif_filas!$A$1:$J$39,4,FALSE()) -> Productos de la agricultura, la horticultura y la jardinería comercial | O4: =VLOOKUP(K4,clasif_filas!$A$1:$J$39,5,FALSE()) -> 1 | P4: =VLOOKUP(K4,clasif_filas!$A$1:$J$39,6,FALSE()) -> Biomasa que se cultiva para producir alimentos, forrajes, fibras y energía | Q4: =VLOOKUP(K4,clasif_filas!$A$1:$J$39,7,FALSE()) -> 0 | R4: =VLOOKUP(K4,clasif_filas!$A$1:$J$39,8,FALSE()) -> Productos de la agricultura, la silvicultura yla pesca | S4: =VLOOKUP(K4,clasif_filas!$A$1:$J$39,9,FALSE()) -> 1 | T4: =VLOOKUP(K4,clasif_filas!$A$1:$J$39,10,FALSE()) -> Bioeconomía
A5: BRAof004 | B5: ATF01 | C5: =VLOOKUP(B5, AT_FILAS!$A$2:$C$8,2,FALSE()) -> Producción | D5: =VLOOKUP(B5, AT_FILAS!$A$2:$C$8,3,FALSE()) -> P1 | E5: 01914 | F5: Cana-de-açúcar | G5: Productos agricolas_Azúcar | H5: 1 | I5: Bioeconomía de productos básicos | J5: Productos agropecuarios | K5: 1 | L5: =VLOOKUP(K5,clasif_filas!$A$1:$J$39,2,FALSE()) -> Productos de la agricultura, la horticultura y la jardinería comercial | M5: =VLOOKUP(K5,clasif_filas!$A$1:$J$39,3,FALSE()) -> 1 | N5: =VLOOKUP(K5,clasif_filas!$A$1:$J$39,4,FALSE()) -> Productos de la agricultura, la horticultura y la jardinería comercial | O5: =VLOOKUP(K5,clasif_filas!$A$1:$J$39,5,FALSE()) -> 1 | P5: =VLOOKUP(K5,clasif_filas!$A$1:$J$39,6,FALSE()) -> Biomasa que se cultiva para producir alimentos, forrajes, fibras y energía | Q5: =VLOOKUP(K5,clasif_filas!$A$1:$J$39,7,FALSE()) -> 0 | R5: =VLOOKUP(K5,clasif_filas!$A$1:$J$39,8,FALSE()) -> Productos de la agricultura, la silvicultura yla pesca | S5: =VLOOKUP(K5,clasif_filas!$A$1:$J$39,9,FALSE()) -> 1 | T5: =VLOOKUP(K5,clasif_filas!$A$1:$J$39,10,FALSE()) -> Bioeconomía
A6: BRAof005 | B6: ATF01 | C6: =VLOOKUP(B6, AT_FILAS!$A$2:$C$8,2,FALSE()) -> Producción | D6: =VLOOKUP(B6, AT_FILAS!$A$2:$C$8,3,FALSE()) -> P1 | E6: 01915 | F6: Soja em grão | G6: Productos agricolas_Oleaginosas | H6: 1 | I6: Bioeconomía de productos básicos | J6: Productos agropecuarios | K6: 1 | L6: =VLOOKUP(K6,clasif_filas!$A$1:$J$39,2,FALSE()) -> Productos de la agricultura, la horticultura y la jardinería comercial | M6: =VLOOKUP(K6,clasif_filas!$A$1:$J$39,3,FALSE()) -> 1 | N6: =VLOOKUP(K6,clasif_filas!$A$1:$J$39,4,FALSE()) -> Productos de la agricultura, la horticultura y la jardinería comercial | O6: =VLOOKUP(K6,clasif_filas!$A$1:$J$39,5,FALSE()) -> 1 | P6: =VLOOKUP(K6,clasif_filas!$A$1:$J$39,6,FALSE()) -> Biomasa que se cultiva para producir alimentos, forrajes, fibras y energía | Q6: =VLOOKUP(K6,clasif_filas!$A$1:$J$39,7,FALSE()) -> 0 | R6: =VLOOKUP(K6,clasif_filas!$A$1:$J$39,8,FALSE()) -> Productos de la agricultura, la silvicultura yla pesca | S6: =VLOOKUP(K6,clasif_filas!$A$1:$J$39,9,FALSE()) -> 1 | T6: =VLOOKUP(K6,clasif_filas!$A$1:$J$39,10,FALSE()) -> Bioeconomía
A7: BRAof006 | B7: ATF01 | C7: =VLOOKUP(B7, AT_FILAS!$A$2:$C$8,2,FALSE()) -> Producción | D7: =VLOOKUP(B7, AT_FILAS!$A$2:$C$8,3,FALSE()) -> P1 | E7: 01916 | F7: Outros produtos e serviços da lavoura temporária | G7: Productos alimentarios_Otros | H7: 1 | I7: Bioeconomía de productos básicos | J7: Productos agropecuarios | K7: 1 | L7: =VLOOKUP(K7,clasif_filas!$A$1:$J$39,2,FALSE()) -> Productos de la agricultura, la horticultura y la jardinería comercial | M7: =VLOOKUP(K7,clasif_filas!$A$1:$J$39,3,FALSE()) -> 1 | N7: =VLOOKUP(K7,clasif_filas!$A$1:$J$39,4,FALSE()) -> Productos de la agricultura, la horticultura y la jardinería comercial | O7: =VLOOKUP(K7,clasif_filas!$A$1:$J$39,5,FALSE()) -> 1 | P7: =VLOOKUP(K7,clasif_filas!$A$1:$J$39,6,FALSE()) -> Biomasa que se cultiva para producir alimentos, forrajes, fibras y energía | Q7: =VLOOKUP(K7,clasif_filas!$A$1:$J$39,7,FALSE()) -> 0 | R7: =VLOOKUP(K7,clasif_filas!$A$1:$J$39,8,FALSE()) -> Productos de la agricultura, la silvicultura yla pesca | S7: =VLOOKUP(K7,clasif_filas!$A$1:$J$39,9,FALSE()) -> 1 | T7: =VLOOKUP(K7,clasif_filas!$A$1:$J$39,10,FALSE()) -> Bioeconomía
A8: BRAof007 | B8: ATF01 | C8: =VLOOKUP(B8, AT_FILAS!$A$2:$C$8,2,FALSE()) -> Producción | D8: =VLOOKUP(B8, AT_FILAS!$A$2:$C$8,3,FALSE()) -> P1 | E8: 01917 | F8: Laranja | G8: Productos agricolas_Frutas | H8: 1 | I8: Bioeconomía de productos básicos | J8: Productos agropecuarios | K8: 1 | L8: =VLOOKUP(K8,clasif_filas!$A$1:$J$39,2,FALSE()) -> Productos de la agricultura, la horticultura y la jardinería comercial | M8: =VLOOKUP(K8,clasif_filas!$A$1:$J$39,3,FALSE()) -> 1 | N8: =VLOOKUP(K8,clasif_filas!$A$1:$J$39,4,FALSE()) -> Productos de la agricultura, la horticultura y la jardinería comercial | O8: =VLOOKUP(K8,clasif_filas!$A$1:$J$39,5,FALSE()) -> 1 | P8: =VLOOKUP(K8,clasif_filas!$A$1:$J$39,6,FALSE()) -> Biomasa que se cultiva para producir alimentos, forrajes, fibras y energía | Q8: =VLOOKUP(K8,clasif_filas!$A$1:$J$39,7,FALSE()) -> 0 | R8: =VLOOKUP(K8,clasif_filas!$A$1:$J$39,8,FALSE()) -> Productos de la agricultura, la silvicultura yla pesca | S8: =VLOOKUP(K8,clasif_filas!$A$1:$J$39,9,FALSE()) -> 1 | T8: =VLOOKUP(K8,clasif_filas!$A$1:$J$39,10,FALSE()) -> Bioeconomía
A9: BRAof008 | B9: ATF01 | C9: =VLOOKUP(B9, AT_FILAS!$A$2:$C$8,2,FALSE()) -> Producción | D9: =VLOOKUP(B9, AT_FILAS!$A$2:$C$8,3,FALSE()) -> P1 | E9: 01918 | F9: Café em grão | G9: Productos agricolas_Café y te | H9: 1 | I9: Bioeconomía de productos básicos | J9: Productos agropecuarios | K9: 1 | L9: =VLOOKUP(K9,clasif_filas!$A$1:$J$39,2,FALSE()) -> Productos de la agricultura, la horticultura y la jardinería comercial | M9: =VLOOKUP(K9,clasif_filas!$A$1:$J$39,3,FALSE()) -> 1 | N9: =VLOOKUP(K9,clasif_filas!$A$1:$J$39,4,FALSE()) -> Productos de la agricultura, la horticultura y la jardinería comercial | O9: =VLOOKUP(K9,clasif_filas!$A$1:$J$39,5,FALSE()) -> 1 | P9: =VLOOKUP(K9,clasif_filas!$A$1:$J$39,6,FALSE()) -> Biomasa que se cultiva para producir alimentos, forrajes, fibras y energía | Q9: =VLOOKUP(K9,clasif_filas!$A$1:$J$39,7,FALSE()) -> 0 | R9: =VLOOKUP(K9,clasif_filas!$A$1:$J$39,8,FALSE()) -> Productos de la agricultura, la silvicultura yla pesca | S9: =VLOOKUP(K9,clasif_filas!$A$1:$J$39,9,FALSE()) -> 1 | T9: =VLOOKUP(K9,clasif_filas!$A$1:$J$39,10,FALSE()) -> Bioeconomía
A10: BRAof009 | B10: ATF01 | C10: =VLOOKUP(B10, AT_FILAS!$A$2:$C$8,2,FALSE()) -> Producción | D10: =VLOOKUP(B10, AT_FILAS!$A$2:$C$8,3,FALSE()) -> P1 | E10: 01919 | F10: Outros produtos da lavoura permanente | G10: Productos agricolas_Otros | H10: 1 | I10: Bioeconomía de productos básicos | J10: Industria alimentaria | K10: 1 | L10: =VLOOKUP(K10,clasif_filas!$A$1:$J$39,2,FALSE()) -> Productos de la agricultura, la horticultura y la jardinería comercial | M10: =VLOOKUP(K10,clasif_filas!$A$1:$J$39,3,FALSE()) -> 1 | N10: =VLOOKUP(K10,clasif_filas!$A$1:$J$39,4,FALSE()) -> Productos de la agricultura, la horticultura y la jardinería comercial | O10: =VLOOKUP(K10,clasif_filas!$A$1:$J$39,5,FALSE()) -> 1 | P10: =VLOOKUP(K10,clasif_filas!$A$1:$J$39,6,FALSE()) -> Biomasa que se cultiva para producir alimentos, forrajes, fibras y energía | Q10: =VLOOKUP(K10,clasif_filas!$A$1:$J$39,7,FALSE()) -> 0 | R10: =VLOOKUP(K10,clasif_filas!$A$1:$J$39,8,FALSE()) -> Productos de la agricultura, la silvicultura yla pesca | S10: =VLOOKUP(K10,clasif_filas!$A$1:$J$39,9,FALSE()) -> 1 | T10: =VLOOKUP(K10,clasif_filas!$A$1:$J$39,10,FALSE()) -> Bioeconomía
A11: BRAof010 | B11: ATF01 | C11: =VLOOKUP(B11, AT_FILAS!$A$2:$C$8,2,FALSE()) -> Producción | D11: =VLOOKUP(B11, AT_FILAS!$A$2:$C$8,3,FALSE()) -> P1 | E11: 01921 | F11: Bovinos e outros animais vivos, prods. animal, caça e serv. | G11: Animales y plantas | H11: 1 | I11: Bioeconomía de productos básicos | J11: Productos agropecuarios | K11: 2 | L11: =VLOOKUP(K11,clasif_filas!$A$1:$J$39,2,FALSE()) -> Animales vivos y productos animales (excepto la carne) | M11: =VLOOKUP(K11,clasif_filas!$A$1:$J$39,3,FALSE()) -> 2 | N11: =VLOOKUP(K11,clasif_filas!$A$1:$J$39,4,FALSE()) -> Animales vivos y productos animales (excepto la carne) | O11: =VLOOKUP(K11,clasif_filas!$A$1:$J$39,5,FALSE()) -> 1 | P11: =VLOOKUP(K11,clasif_filas!$A$1:$J$39,6,FALSE()) -> Biomasa que se cultiva para producir alimentos, forrajes, fibras y energía | Q11: =VLOOKUP(K11,clasif_filas!$A$1:$J$39,7,FALSE()) -> 0 | R11: =VLOOKUP(K11,clasif_filas!$A$1:$J$39,8,FALSE()) -> Productos de la agricultura, la silvicultura yla pesca | S11: =VLOOKUP(K11,clasif_filas!$A$1:$J$39,9,FALSE()) -> 1 | T11: =VLOOKUP(K11,clasif_filas!$A$1:$J$39,10,FALSE()) -> Bioeconomía
A12: BRAof011 | B12: ATF01 | C12: =VLOOKUP(B12, AT_FILAS!$A$2:$C$8,2,FALSE()) -> Producción | D12: =VLOOKUP(B12, AT_FILAS!$A$2:$C$8,3,FALSE()) -> P1 | E12: 01922 | F12: Leite de vaca e de outros animais | G12: Productos agricolas_Lácteos | H12: 1 | I12: Bioeconomía de productos básicos | J12: Productos agropecuarios | K12: 2 | L12: =VLOOKUP(K12,clasif_filas!$A$1:$J$39,2,FALSE()) -> Animales vivos y productos animales (excepto la carne) | M12: =VLOOKUP(K12,clasif_filas!$A$1:$J$39,3,FALSE()) -> 2 | N12: =VLOOKUP(K12,clasif_filas!$A$1:$J$39,4,FALSE()) -> Animales vivos y productos animales (excepto la carne) | O12: =VLOOKUP(K12,clasif_filas!$A$1:$J$39,5,FALSE()) -> 1 | P12: =VLOOKUP(K12,clasif_filas!$A$1:$J$39,6,FALSE()) -> Biomasa que se cultiva para producir alimentos, forrajes, fibras y energía | Q12: =VLOOKUP(K12,clasif_filas!$A$1:$J$39,7,FALSE()) -> 0 | R12: =VLOOKUP(K12,clasif_filas!$A$1:$J$39,8,FALSE()) -> Productos de la agricultura, la silvicultura yla pesca | S12: =VLOOKUP(K12,clasif_filas!$A$1:$J$39,9,FALSE()) -> 1 | T12: =VLOOKUP(K12,clasif_filas!$A$1:$J$39,10,FALSE()) -> Bioeconomía
A13: BRAof012 | B13: ATF01 | C13: =VLOOKUP(B13, AT_FILAS!$A$2:$C$8,2,FALSE()) -> Producción | D13: =VLOOKUP(B13, AT_FILAS!$A$2:$C$8,3,FALSE()) -> P1 | E13: 01923 | F13: Suínos | G13: Animales y plantas | H13: 1 | I13: Bioeconomía de productos básicos | J13: Productos agropecuarios | K13: 2 | L13: =VLOOKUP(K13,clasif_filas!$A$1:$J$39,2,FALSE()) -> Animales vivos y productos animales (excepto la carne) | M13: =VLOOKUP(K13,clasif_filas!$A$1:$J$39,3,FALSE()) -> 2 | N13: =VLOOKUP(K13,clasif_filas!$A$1:$J$39,4,FALSE()) -> Animales vivos y productos animales (excepto la carne) | O13: =VLOOKUP(K13,clasif_filas!$A$1:$J$39,5,FALSE()) -> 1 | P13: =VLOOKUP(K13,clasif_filas!$A$1:$J$39,6,FALSE()) -> Biomasa que se cultiva para producir alimentos, forrajes, fibras y energía | Q13: =VLOOKUP(K13,clasif_filas!$A$1:$J$39,7,FALSE()) -> 0 | R13: =VLOOKUP(K13,clasif_filas!$A$1:$J$39,8,FALSE()) -> Productos de la agricultura, la silvicultura yla pesca | S13: =VLOOKUP(K13,clasif_filas!$A$1:$J$39,9,FALSE()) -> 1 | T13: =VLOOKUP(K13,clasif_filas!$A$1:$J$39,10,FALSE()) -> Bioeconomía
... A69: BRAof068 | B69: ATF01 | C69: =VLOOKUP(B69, AT_FILAS!$A$2:$C$8,2,FALSE()) -> Producción | D69: =VLOOKUP(B69, AT_FILAS!$A$2:$C$8,3,FALSE()) -> P1 | E69: 24912 | F69: Semi-acabacados, laminados planos, longos e tubos de aço | G69: No bioeconomía | H69: 4 | I69: No bioeconomía | J69: No bioeconomía | K69: 38 | L69: =VLOOKUP(K69,clasif_filas!$A$1:$J$39,2,FALSE()) -> Muebles; otros bienes transportables n.c.p. | M69: =VLOOKUP(K69,clasif_filas!$A$1:$J$39,3,FALSE()) -> 38 | N69: =VLOOKUP(K69,clasif_filas!$A$1:$J$39,4,FALSE()) -> Muebles; otros bienes transportables n.c.p. | O69: =VLOOKUP(K69,clasif_filas!$A$1:$J$39,5,FALSE()) -> 99 | P69: =VLOOKUP(K69,clasif_filas!$A$1:$J$39,6,FALSE()) -> No Bioeconomía | Q69: =VLOOKUP(K69,clasif_filas!$A$1:$J$39,7,FALSE()) -> 3 | R69: =VLOOKUP(K69,clasif_filas!$A$1:$J$39,8,FALSE()) -> Otros bienes transportables, excepto productos metálicos, maquinaria y equipo | S69: =VLOOKUP(K69,clasif_filas!$A$1:$J$39,9,FALSE()) -> 3 | T69: =VLOOKUP(K69,clasif_filas!$A$1:$J$39,10,FALSE()) -> No bioeconomía
A70: BRAof069 | B70: ATF01 | C70: =VLOOKUP(B70, AT_FILAS!$A$2:$C$8,2,FALSE()) -> Producción | D70: =VLOOKUP(B70, AT_FILAS!$A$2:$C$8,3,FALSE()) -> P1 | E70: 24921 | F70: Produtos da metalurgia de metais não-ferrosos | G70: No bioeconomía | H70: 4 | I70: No bioeconomía | J70: No bioeconomía | K70: 41-49 | L70: =VLOOKUP(K70,clasif_filas!$A$1:$J$39,2,FALSE()) -> Metales, Maquianria, equipos y transporte | M70: =VLOOKUP(K70,clasif_filas!$A$1:$J$39,3,FALSE()) -> 41-49 | N70: =VLOOKUP(K70,clasif_filas!$A$1:$J$39,4,FALSE()) -> Metales, Maquianria, equipos y transporte | O70: =VLOOKUP(K70,clasif_filas!$A$1:$J$39,5,FALSE()) -> 99 | P70: =VLOOKUP(K70,clasif_filas!$A$1:$J$39,6,FALSE()) -> No Bioeconomía | Q70: =VLOOKUP(K70,clasif_filas!$A$1:$J$39,7,FALSE()) -> 4 | R70: =VLOOKUP(K70,clasif_filas!$A$1:$J$39,8,FALSE()) -> Productos metálicos, maquinaria y equipo | S70: =VLOOKUP(K70,clasif_filas!$A$1:$J$39,9,FALSE()) -> 3 | T70: =VLOOKUP(K70,clasif_filas!$A$1:$J$39,10,FALSE()) -> No bioeconomía
A71: BRAof070 | B71: ATF01 | C71: =VLOOKUP(B71, AT_FILAS!$A$2:$C$8,2,FALSE()) -> Producción | D71: =VLOOKUP(B71, AT_FILAS!$A$2:$C$8,3,FALSE()) -> P1 | E71: 24922 | F71: Peças fundidas de aço e de metais não ferrosos | G71: No bioeconomía | H71: 4 | I71: No bioeconomía | J71: No bioeconomía | K71: 41-49 | L71: =VLOOKUP(K71,clasif_filas!$A$1:$J$39,2,FALSE()) -> Metales, Maquianria, equipos y transporte | M71: =VLOOKUP(K71,clasif_filas!$A$1:$J$39,3,FALSE()) -> 41-49 | N71: =VLOOKUP(K71,clasif_filas!$A$1:$J$39,4,FALSE()) -> Metales, Maquianria, equipos y transporte | O71: =VLOOKUP(K71,clasif_filas!$A$1:$J$39,5,FALSE()) -> 99 | P71: =VLOOKUP(K71,clasif_filas!$A$1:$J$39,6,FALSE()) -> No Bioeconomía | Q71: =VLOOKUP(K71,clasif_filas!$A$1:$J$39,7,FALSE()) -> 4 | R71: =VLOOKUP(K71,clasif_filas!$A$1:$J$39,8,FALSE()) -> Productos metálicos, maquinaria y equipo | S71: =VLOOKUP(K71,clasif_filas!$A$1:$J$39,9,FALSE()) -> 3 | T71: =VLOOKUP(K71,clasif_filas!$A$1:$J$39,10,FALSE()) -> No bioeconomía
A72: BRAof071 | B72: ATF01 | C72: =VLOOKUP(B72, AT_FILAS!$A$2:$C$8,2,FALSE()) -> Producción | D72: =VLOOKUP(B72, AT_FILAS!$A$2:$C$8,3,FALSE()) -> P1 | E72: 25001 | F72: Produtos de metal, excl. máquinas e equipamentos | G72: No bioeconomía | H72: 4 | I72: No bioeconomía | J72: No bioeconomía | K72: 41-49 | L72: =VLOOKUP(K72,clasif_filas!$A$1:$J$39,2,FALSE()) -> Metales, Maquianria, equipos y transporte | M72: =VLOOKUP(K72,clasif_filas!$A$1:$J$39,3,FALSE()) -> 41-49 | N72: =VLOOKUP(K72,clasif_filas!$A$1:$J$39,4,FALSE()) -> Metales, Maquianria, equipos y transporte | O72: =VLOOKUP(K72,clasif_filas!$A$1:$J$39,5,FALSE()) -> 99 | P72: =VLOOKUP(K72,clasif_filas!$A$1:$J$39,6,FALSE()) -> No Bioeconomía | Q72: =VLOOKUP(K72,clasif_filas!$A$1:$J$39,7,FALSE()) -> 4 | R72: =VLOOKUP(K72,clasif_filas!$A$1:$J$39,8,FALSE()) -> Productos metálicos, maquinaria y equipo | S72: =VLOOKUP(K72,clasif_filas!$A$1:$J$39,9,FALSE()) -> 3 | T72: =VLOOKUP(K72,clasif_filas!$A$1:$J$39,10,FALSE()) -> No bioeconomía
A73: BRAof072 | B73: ATF01 | C73: =VLOOKUP(B73, AT_FILAS!$A$2:$C$8,2,FALSE()) -> Producción | D73: =VLOOKUP(B73, AT_FILAS!$A$2:$C$8,3,FALSE()) -> P1 | E73: 26001 | F73: Componentes eletrônicos | G73: No bioeconomía | H73: 4 | I73: No bioeconomía | J73: No bioeconomía | K73: 41-49 | L73: =VLOOKUP(K73,clasif_filas!$A$1:$J$39,2,FALSE()) -> Metales, Maquianria, equipos y transporte | M73: =VLOOKUP(K73,clasif_filas!$A$1:$J$39,3,FALSE()) -> 41-49 | N73: =VLOOKUP(K73,clasif_filas!$A$1:$J$39,4,FALSE()) -> Metales, Maquianria, equipos y transporte | O73: =VLOOKUP(K73,clasif_filas!$A$1:$J$39,5,FALSE()) -> 99 | P73: =VLOOKUP(K73,clasif_filas!$A$1:$J$39,6,FALSE()) -> No Bioeconomía | Q73: =VLOOKUP(K73,clasif_filas!$A$1:$J$39,7,FALSE()) -> 4 | R73: =VLOOKUP(K73,clasif_filas!$A$1:$J$39,8,FALSE()) -> Productos metálicos, maquinaria y equipo | S73: =VLOOKUP(K73,clasif_filas!$A$1:$J$39,9,FALSE()) -> 3 | T73: =VLOOKUP(K73,clasif_filas!$A$1:$J$39,10,FALSE()) -> No bioeconomía
A74: BRAof073 | B74: ATF01 | C74: =VLOOKUP(B74, AT_FILAS!$A$2:$C$8,2,FALSE()) -> Producción | D74: =VLOOKUP(B74, AT_FILAS!$A$2:$C$8,3,FALSE()) -> P1 | E74: 26002 | F74: Máquinas para escritório e equip. de informática | G74: No bioeconomía | H74: 4 | I74: No bioeconomía | J74: No bioeconomía | K74: 41-49 | L74: =VLOOKUP(K74,clasif_filas!$A$1:$J$39,2,FALSE()) -> Metales, Maquianria, equipos y transporte | M74: =VLOOKUP(K74,clasif_filas!$A$1:$J$39,3,FALSE()) -> 41-49 | N74: =VLOOKUP(K74,clasif_filas!$A$1:$J$39,4,FALSE()) -> Metales, Maquianria, equipos y transporte | O74: =VLOOKUP(K74,clasif_filas!$A$1:$J$39,5,FALSE()) -> 99 | P74: =VLOOKUP(K74,clasif_filas!$A$1:$J$39,6,FALSE()) -> No Bioeconomía | Q74: =VLOOKUP(K74,clasif_filas!$A$1:$J$39,7,FALSE()) -> 4 | R74: =VLOOKUP(K74,clasif_filas!$A$1:$J$39,8,FALSE()) -> Productos metálicos, maquinaria y equipo | S74: =VLOOKUP(K74,clasif_filas!$A$1:$J$39,9,FALSE()) -> 3 | T74: =VLOOKUP(K74,clasif_filas!$A$1:$J$39,10,FALSE()) -> No bioeconomía
A75: BRAof074 | B75: ATF01 | C75: =VLOOKUP(B75, AT_FILAS!$A$2:$C$8,2,FALSE()) -> Producción | D75: =VLOOKUP(B75, AT_FILAS!$A$2:$C$8,3,FALSE()) -> P1 | E75: 26003 | F75: Material eletrônico e equip. de comunicações | G75: No bioeconomía | H75: 4 | I75: No bioeconomía | J75: No bioeconomía | K75: 41-49 | L75: =VLOOKUP(K75,clasif_filas!$A$1:$J$39,2,FALSE()) -> Metales, Maquianria, equipos y transporte | M75: =VLOOKUP(K75,clasif_filas!$A$1:$J$39,3,FALSE()) -> 41-49 | N75: =VLOOKUP(K75,clasif_filas!$A$1:$J$39,4,FALSE()) -> Metales, Maquianria, equipos y transporte | O75: =VLOOKUP(K75,clasif_filas!$A$1:$J$39,5,FALSE()) -> 99 | P75: =VLOOKUP(K75,clasif_filas!$A$1:$J$39,6,FALSE()) -> No Bioeconomía | Q75: =VLOOKUP(K75,clasif_filas!$A$1:$J$39,7,FALSE()) -> 4 | R75: =VLOOKUP(K75,clasif_filas!$A$1:$J$39,8,FALSE()) -> Productos metálicos, maquinaria y equipo | S75: =VLOOKUP(K75,clasif_filas!$A$1:$J$39,9,FALSE()) -> 3 | T75: =VLOOKUP(K75,clasif_filas!$A$1:$J$39,10,FALSE()) -> No bioeconomía
A76: BRAof075 | B76: ATF01 | C76: =VLOOKUP(B76, AT_FILAS!$A$2:$C$8,2,FALSE()) -> Producción | D76: =VLOOKUP(B76, AT_FILAS!$A$2:$C$8,3,FALSE()) -> P1 | E76: 26004 | F76: Equip. de medida, teste e controle, ópticos e eletromédicos | G76: No bioeconomía | H76: 4 | I76: No bioeconomía | J76: No bioeconomía | K76: 41-49 | L76: =VLOOKUP(K76,clasif_filas!$A$1:$J$39,2,FALSE()) -> Metales, Maquianria, equipos y transporte | M76: =VLOOKUP(K76,clasif_filas!$A$1:$J$39,3,FALSE()) -> 41-49 | N76: =VLOOKUP(K76,clasif_filas!$A$1:$J$39,4,FALSE()) -> Metales, Maquianria, equipos y transporte | O76: =VLOOKUP(K76,clasif_filas!$A$1:$J$39,5,FALSE()) -> 99 | P76: =VLOOKUP(K76,clasif_filas!$A$1:$J$39,6,FALSE()) -> No Bioeconomía | Q76: =VLOOKUP(K76,clasif_filas!$A$1:$J$39,7,FALSE()) -> 4 | R76: =VLOOKUP(K76,clasif_filas!$A$1:$J$39,8,FALSE()) -> Productos metálicos, maquinaria y equipo | S76: =VLOOKUP(K76,clasif_filas!$A$1:$J$39,9,FALSE()) -> 3 | T76: =VLOOKUP(K76,clasif_filas!$A$1:$J$39,10,FALSE()) -> No bioeconomía
A77: BRAof076 | B77: ATF01 | C77: =VLOOKUP(B77, AT_FILAS!$A$2:$C$8,2,FALSE()) -> Producción | D77: =VLOOKUP(B77, AT_FILAS!$A$2:$C$8,3,FALSE()) -> P1 | E77: 27001 | F77: Máquinas, aparelhos e materiais elétricos | G77: No bioeconomía | H77: 4 | I77: No bioeconomía | J77: No bioeconomía | K77: 41-49 | L77: =VLOOKUP(K77,clasif_filas!$A$1:$J$39,2,FALSE()) -> Metales, Maquianria, equipos y transporte | M77: =VLOOKUP(K77,clasif_filas!$A$1:$J$39,3,FALSE()) -> 41-49 | N77: =VLOOKUP(K77,clasif_filas!$A$1:$J$39,4,FALSE()) -> Metales, Maquianria, equipos y transporte | O77: =VLOOKUP(K77,clasif_filas!$A$1:$J$39,5,FALSE()) -> 99 | P77: =VLOOKUP(K77,clasif_filas!$A$1:$J$39,6,FALSE()) -> No Bioeconomía | Q77: =VLOOKUP(K77,clasif_filas!$A$1:$J$39,7,FALSE()) -> 4 | R77: =VLOOKUP(K77,clasif_filas!$A$1:$J$39,8,FALSE()) -> Productos metálicos, maquinaria y equipo | S77: =VLOOKUP(K77,clasif_filas!$A$1:$J$39,9,FALSE()) -> 3 | T77: =VLOOKUP(K77,clasif_filas!$A$1:$J$39,10,FALSE()) -> No bioeconomía
A78: BRAof077 | B78: ATF01 | C78: =VLOOKUP(B78, AT_FILAS!$A$2:$C$8,2,FALSE()) -> Producción | D78: =VLOOKUP(B78, AT_FILAS!$A$2:$C$8,3,FALSE()) -> P1 | E78: 27002 | F78: Eletrodomésticos | G78: No bioeconomía | H78: 4 | I78: No bioeconomía | J78: No bioeconomía | K78: 41-49 | L78: =VLOOKUP(K78,clasif_filas!$A$1:$J$39,2,FALSE()) -> Metales, Maquianria, equipos y transporte | M78: =VLOOKUP(K78,clasif_filas!$A$1:$J$39,3,FALSE()) -> 41-49 | N78: =VLOOKUP(K78,clasif_filas!$A$1:$J$39,4,FALSE()) -> Metales, Maquianria, equipos y transporte | O78: =VLOOKUP(K78,clasif_filas!$A$1:$J$39,5,FALSE()) -> 99 | P78: =VLOOKUP(K78,clasif_filas!$A$1:$J$39,6,FALSE()) -> No Bioeconomía | Q78: =VLOOKUP(K78,clasif_filas!$A$1:$J$39,7,FALSE()) -> 4 | R78: =VLOOKUP(K78,clasif_filas!$A$1:$J$39,8,FALSE()) -> Productos metálicos, maquinaria y equipo | S78: =VLOOKUP(K78,clasif_filas!$A$1:$J$39,9,FALSE()) -> 3 | T78: =VLOOKUP(K78,clasif_filas!$A$1:$J$39,10,FALSE()) -> No bioeconomía
A79: BRAof078 | B79: ATF01 | C79: =VLOOKUP(B79, AT_FILAS!$A$2:$C$8,2,FALSE()) -> Producción | D79: =VLOOKUP(B79, AT_FILAS!$A$2:$C$8,3,FALSE()) -> P1 | E79: 28001 | F79: Tratores e outras máquinas agrícolas | G79: No bioeconomía | H79: 4 | I79: No bioeconomía | J79: No bioeconomía | K79: 41-49 | L79: =VLOOKUP(K79,clasif_filas!$A$1:$J$39,2,FALSE()) -> Metales, Maquianria, equipos y transporte | M79: =VLOOKUP(K79,clasif_filas!$A$1:$J$39,3,FALSE()) -> 41-49 | N79: =VLOOKUP(K79,clasif_filas!$A$1:$J$39,4,FALSE()) -> Metales, Maquianria, equipos y transporte | O79: =VLOOKUP(K79,clasif_filas!$A$1:$J$39,5,FALSE()) -> 99 | P79: =VLOOKUP(K79,clasif_filas!$A$1:$J$39,6,FALSE()) -> No Bioeconomía | Q79: =VLOOKUP(K79,clasif_filas!$A$1:$J$39,7,FALSE()) -> 4 | R79: =VLOOKUP(K79,clasif_filas!$A$1:$J$39,8,FALSE()) -> Productos metálicos, maquinaria y equipo | S79: =VLOOKUP(K79,clasif_filas!$A$1:$J$39,9,FALSE()) -> 3 | T79: =VLOOKUP(K79,clasif_filas!$A$1:$J$39,10,FALSE()) -> No bioeconomía
A80: BRAof079 | B80: ATF01 | C80: =VLOOKUP(B80, AT_FILAS!$A$2:$C$8,2,FALSE()) -> Producción | D80: =VLOOKUP(B80, AT_FILAS!$A$2:$C$8,3,FALSE()) -> P1 | E80: 28002 | F80: Máquinas para a extração mineral e a construção | G80: No bioeconomía | H80: 4 | I80: No bioeconomía | J80: No bioeconomía | K80: 41-49 | L80: =VLOOKUP(K80,clasif_filas!$A$1:$J$39,2,FALSE()) -> Metales, Maquianria, equipos y transporte | M80: =VLOOKUP(K80,clasif_filas!$A$1:$J$39,3,FALSE()) -> 41-49 | N80: =VLOOKUP(K80,clasif_filas!$A$1:$J$39,4,FALSE()) -> Metales, Maquianria, equipos y transporte | O80: =VLOOKUP(K80,clasif_filas!$A$1:$J$39,5,FALSE()) -> 99 | P80: =VLOOKUP(K80,clasif_filas!$A$1:$J$39,6,FALSE()) -> No Bioeconomía | Q80: =VLOOKUP(K80,clasif_filas!$A$1:$J$39,7,FALSE()) -> 4 | R80: =VLOOKUP(K80,clasif_filas!$A$1:$J$39,8,FALSE()) -> Productos metálicos, maquinaria y equipo | S80: =VLOOKUP(K80,clasif_filas!$A$1:$J$39,9,FALSE()) -> 3 | T80: =VLOOKUP(K80,clasif_filas!$A$1:$J$39,10,FALSE()) -> No bioeconomía
A81: BRAof080 | B81: ATF01 | C81: =VLOOKUP(B81, AT_FILAS!$A$2:$C$8,2,FALSE()) -> Producción | D81: =VLOOKUP(B81, AT_FILAS!$A$2:$C$8,3,FALSE()) -> P1 | E81: 28003 | F81: Outras máquinas e equipamentos mecânicos | G81: No bioeconomía | H81: 4 | I81: No bioeconomía | J81: No bioeconomía | K81: 41-49 | L81: =VLOOKUP(K81,clasif_filas!$A$1:$J$39,2,FALSE()) -> Metales, Maquianria, equipos y transporte | M81: =VLOOKUP(K81,clasif_filas!$A$1:$J$39,3,FALSE()) -> 41-49 | N81: =VLOOKUP(K81,clasif_filas!$A$1:$J$39,4,FALSE()) -> Metales, Maquianria, equipos y transporte | O81: =VLOOKUP(K81,clasif_filas!$A$1:$J$39,5,FALSE()) -> 99 | P81: =VLOOKUP(K81,clasif_filas!$A$1:$J$39,6,FALSE()) -> No Bioeconomía | Q81: =VLOOKUP(K81,clasif_filas!$A$1:$J$39,7,FALSE()) -> 4 | R81: =VLOOKUP(K81,clasif_filas!$A$1:$J$39,8,FALSE()) -> Productos metálicos, maquinaria y equipo | S81: =VLOOKUP(K81,clasif_filas!$A$1:$J$39,9,FALSE()) -> 3 | T81: =VLOOKUP(K81,clasif_filas!$A$1:$J$39,10,FALSE()) -> No bioeconomía
... A88: BRAof087 | B88: ATF01 | C88: =VLOOKUP(B88, AT_FILAS!$A$2:$C$8,2,FALSE()) -> Producción | D88: =VLOOKUP(B88, AT_FILAS!$A$2:$C$8,3,FALSE()) -> P1 | E88: 33001 | F88: Manutenção, reparação e instalação de máquinas e equipamentos | G88: No bioeconomía | H88: 4 | I88: No bioeconomía | J88: No bioeconomía | K88: 41-49 | L88: =VLOOKUP(K88,clasif_filas!$A$1:$J$39,2,FALSE()) -> Metales, Maquianria, equipos y transporte | M88: =VLOOKUP(K88,clasif_filas!$A$1:$J$39,3,FALSE()) -> 41-49 | N88: =VLOOKUP(K88,clasif_filas!$A$1:$J$39,4,FALSE()) -> Metales, Maquianria, equipos y transporte | O88: =VLOOKUP(K88,clasif_filas!$A$1:$J$39,5,FALSE()) -> 99 | P88: =VLOOKUP(K88,clasif_filas!$A$1:$J$39,6,FALSE()) -> No Bioeconomía | Q88: =VLOOKUP(K88,clasif_filas!$A$1:$J$39,7,FALSE()) -> 4 | R88: =VLOOKUP(K88,clasif_filas!$A$1:$J$39,8,FALSE()) -> Productos metálicos, maquinaria y equipo | S88: =VLOOKUP(K88,clasif_filas!$A$1:$J$39,9,FALSE()) -> 3 | T88: =VLOOKUP(K88,clasif_filas!$A$1:$J$39,10,FALSE()) -> No bioeconomía
A89: BRAof088 | B89: ATF01 | C89: =VLOOKUP(B89, AT_FILAS!$A$2:$C$8,2,FALSE()) -> Producción | D89: =VLOOKUP(B89, AT_FILAS!$A$2:$C$8,3,FALSE()) -> P1 | E89: 35001 | F89: Eletricidade, gás e outras utilidades | G89: Agua | H89: 1 | I89: Bioeconomía de productos básicos | J89: Materias primas | K89: 17.5 | L89: =VLOOKUP(K89,clasif_filas!$A$1:$J$39,2,FALSE()) -> Electricidad y agua | M89: =VLOOKUP(K89,clasif_filas!$A$1:$J$39,3,FALSE()) -> 17.5 | N89: =VLOOKUP(K89,clasif_filas!$A$1:$J$39,4,FALSE()) -> Electricidad y agua | O89: =VLOOKUP(K89,clasif_filas!$A$1:$J$39,5,FALSE()) -> 6 | P89: =VLOOKUP(K89,clasif_filas!$A$1:$J$39,6,FALSE()) -> Conocimiento, procesos y servicios relacionados | Q89: =VLOOKUP(K89,clasif_filas!$A$1:$J$39,7,FALSE()) -> 1 | R89: =VLOOKUP(K89,clasif_filas!$A$1:$J$39,8,FALSE()) -> Minerales; electricidad, gas y agua | S89: =VLOOKUP(K89,clasif_filas!$A$1:$J$39,9,FALSE()) -> 2 | T89: =VLOOKUP(K89,clasif_filas!$A$1:$J$39,10,FALSE()) -> Bioeconomía extendida
A90: BRAof089 | B90: ATF01 | C90: =VLOOKUP(B90, AT_FILAS!$A$2:$C$8,2,FALSE()) -> Producción | D90: =VLOOKUP(B90, AT_FILAS!$A$2:$C$8,3,FALSE()) -> P1 | E90: 36801 | F90: Água, esgoto, reciclagem e gestão de resíduos | G90: Productos agricolas_Residuos | H90: 1 | I90: Bioeconomía de productos básicos | J90: Productos agropecuarios | K90: 94 | L90: =VLOOKUP(K90,clasif_filas!$A$1:$J$39,2,FALSE()) -> Servicios de alcantarillado, recolección, tratamiento y disposición de desechos y otros servicios de saneamiento ambiental | M90: =VLOOKUP(K90,clasif_filas!$A$1:$J$39,3,FALSE()) -> 94 | N90: =VLOOKUP(K90,clasif_filas!$A$1:$J$39,4,FALSE()) -> Servicios de alcantarillado, recolección, tratamiento y disposición de desechos y otros servicios de saneamiento ambiental | O90: =VLOOKUP(K90,clasif_filas!$A$1:$J$39,5,FALSE()) -> 4 | P90: =VLOOKUP(K90,clasif_filas!$A$1:$J$39,6,FALSE()) -> Biomasa residual en los sectores agropecuario, pesca y acuacultura, forestal y agroindustrial | Q90: =VLOOKUP(K90,clasif_filas!$A$1:$J$39,7,FALSE()) -> 9 | R90: =VLOOKUP(K90,clasif_filas!$A$1:$J$39,8,FALSE()) -> Servicios para la comunidad, sociales y personales | S90: =VLOOKUP(K90,clasif_filas!$A$1:$J$39,9,FALSE()) -> 2 | T90: =VLOOKUP(K90,clasif_filas!$A$1:$J$39,10,FALSE()) -> Bioeconomía extendida
A91: BRAof090 | B91: ATF01 | C91: =VLOOKUP(B91, AT_FILAS!$A$2:$C$8,2,FALSE()) -> Producción | D91: =VLOOKUP(B91, AT_FILAS!$A$2:$C$8,3,FALSE()) -> P1 | E91: 41801 | F91: Edificações | G91: No bioeconomía | H91: 4 | I91: No bioeconomía | J91: No bioeconomía | K91: 5 | L91: =VLOOKUP(K91,clasif_filas!$A$1:$J$39,2,FALSE()) -> Construcciones y servicios de construcción | M91: =VLOOKUP(K91,clasif_filas!$A$1:$J$39,3,FALSE()) -> 5 | N91: =VLOOKUP(K91,clasif_filas!$A$1:$J$39,4,FALSE()) -> Construcciones y servicios de construcción | O91: =VLOOKUP(K91,clasif_filas!$A$1:$J$39,5,FALSE()) -> 99 | P91: =VLOOKUP(K91,clasif_filas!$A$1:$J$39,6,FALSE()) -> No Bioeconomía | Q91: =VLOOKUP(K91,clasif_filas!$A$1:$J$39,7,FALSE()) -> 5 | R91: =VLOOKUP(K91,clasif_filas!$A$1:$J$39,8,FALSE()) -> Construcciones y servicios de construcción | S91: =VLOOKUP(K91,clasif_filas!$A$1:$J$39,9,FALSE()) -> 3 | T91: =VLOOKUP(K91,clasif_filas!$A$1:$J$39,10,FALSE()) -> No bioeconomía
A92: BRAof091 | B92: ATF01 | C92: =VLOOKUP(B92, AT_FILAS!$A$2:$C$8,2,FALSE()) -> Producción | D92: =VLOOKUP(B92, AT_FILAS!$A$2:$C$8,3,FALSE()) -> P1 | E92: 41802 | F92: Obras de infra-estrutura | G92: No bioeconomía | H92: 4 | I92: No bioeconomía | J92: No bioeconomía | K92: 5 | L92: =VLOOKUP(K92,clasif_filas!$A$1:$J$39,2,FALSE()) -> Construcciones y servicios de construcción | M92: =VLOOKUP(K92,clasif_filas!$A$1:$J$39,3,FALSE()) -> 5 | N92: =VLOOKUP(K92,clasif_filas!$A$1:$J$39,4,FALSE()) -> Construcciones y servicios de construcción | O92: =VLOOKUP(K92,clasif_filas!$A$1:$J$39,5,FALSE()) -> 99 | P92: =VLOOKUP(K92,clasif_filas!$A$1:$J$39,6,FALSE()) -> No Bioeconomía | Q92: =VLOOKUP(K92,clasif_filas!$A$1:$J$39,7,FALSE()) -> 5 | R92: =VLOOKUP(K92,clasif_filas!$A$1:$J$39,8,FALSE()) -> Construcciones y servicios de construcción | S92: =VLOOKUP(K92,clasif_filas!$A$1:$J$39,9,FALSE()) -> 3 | T92: =VLOOKUP(K92,clasif_filas!$A$1:$J$39,10,FALSE()) -> No bioeconomía
A93: BRAof092 | B93: ATF01 | C93: =VLOOKUP(B93, AT_FILAS!$A$2:$C$8,2,FALSE()) -> Producción | D93: =VLOOKUP(B93, AT_FILAS!$A$2:$C$8,3,FALSE()) -> P1 | E93: 41803 | F93: Serviços especializados para construção | G93: No bioeconomía | H93: 4 | I93: No bioeconomía | J93: No bioeconomía | K93: 5 | L93: =VLOOKUP(K93,clasif_filas!$A$1:$J$39,2,FALSE()) -> Construcciones y servicios de construcción | M93: =VLOOKUP(K93,clasif_filas!$A$1:$J$39,3,FALSE()) -> 5 | N93: =VLOOKUP(K93,clasif_filas!$A$1:$J$39,4,FALSE()) -> Construcciones y servicios de construcción | O93: =VLOOKUP(K93,clasif_filas!$A$1:$J$39,5,FALSE()) -> 99 | P93: =VLOOKUP(K93,clasif_filas!$A$1:$J$39,6,FALSE()) -> No Bioeconomía | Q93: =VLOOKUP(K93,clasif_filas!$A$1:$J$39,7,FALSE()) -> 5 | R93: =VLOOKUP(K93,clasif_filas!$A$1:$J$39,8,FALSE()) -> Construcciones y servicios de construcción | S93: =VLOOKUP(K93,clasif_filas!$A$1:$J$39,9,FALSE()) -> 3 | T93: =VLOOKUP(K93,clasif_filas!$A$1:$J$39,10,FALSE()) -> No bioeconomía
A94: BRAof093 | B94: ATF01 | C94: =VLOOKUP(B94, AT_FILAS!$A$2:$C$8,2,FALSE()) -> Producción | D94: =VLOOKUP(B94, AT_FILAS!$A$2:$C$8,3,FALSE()) -> P1 | E94: 45001 | F94: Comércio e reparação de veículos | G94: No bioeconomía | H94: 4 | I94: No bioeconomía | J94: No bioeconomía | K94: 6 | L94: =VLOOKUP(K94,clasif_filas!$A$1:$J$39,2,FALSE()) -> Otros servicios | M94: =VLOOKUP(K94,clasif_filas!$A$1:$J$39,3,FALSE()) -> 6 | N94: =VLOOKUP(K94,clasif_filas!$A$1:$J$39,4,FALSE()) -> Otros servicios | O94: =VLOOKUP(K94,clasif_filas!$A$1:$J$39,5,FALSE()) -> 99 | P94: =VLOOKUP(K94,clasif_filas!$A$1:$J$39,6,FALSE()) -> No Bioeconomía | Q94: =VLOOKUP(K94,clasif_filas!$A$1:$J$39,7,FALSE()) -> 6 | R94: =VLOOKUP(K94,clasif_filas!$A$1:$J$39,8,FALSE()) -> Servicios comerciales de distribución; alojamiento, servicios de suministro de comidas y bebidas; servicios de transporte; y servicios de distribución de electricidad, gas y agua | S94: =VLOOKUP(K94,clasif_filas!$A$1:$J$39,9,FALSE()) -> 3 | T94: =VLOOKUP(K94,clasif_filas!$A$1:$J$39,10,FALSE()) -> No bioeconomía
A95: BRAof094 | B95: ATF01 | C95: =VLOOKUP(B95, AT_FILAS!$A$2:$C$8,2,FALSE()) -> Producción | D95: =VLOOKUP(B95, AT_FILAS!$A$2:$C$8,3,FALSE()) -> P1 | E95: 46801 | F95: Comércio por atacado e a varejo, exceto veículos automotores | G95: No bioeconomía | H95: 4 | I95: No bioeconomía | J95: No bioeconomía | K95: 6 | L95: =VLOOKUP(K95,clasif_filas!$A$1:$J$39,2,FALSE()) -> Otros servicios | M95: =VLOOKUP(K95,clasif_filas!$A$1:$J$39,3,FALSE()) -> 6 | N95: =VLOOKUP(K95,clasif_filas!$A$1:$J$39,4,FALSE()) -> Otros servicios | O95: =VLOOKUP(K95,clasif_filas!$A$1:$J$39,5,FALSE()) -> 99 | P95: =VLOOKUP(K95,clasif_filas!$A$1:$J$39,6,FALSE()) -> No Bioeconomía | Q95: =VLOOKUP(K95,clasif_filas!$A$1:$J$39,7,FALSE()) -> 6 | R95: =VLOOKUP(K95,clasif_filas!$A$1:$J$39,8,FALSE()) -> Servicios comerciales de distribución; alojamiento, servicios de suministro de comidas y bebidas; servicios de transporte; y servicios de distribución de electricidad, gas y agua | S95: =VLOOKUP(K95,clasif_filas!$A$1:$J$39,9,FALSE()) -> 3 | T95: =VLOOKUP(K95,clasif_filas!$A$1:$J$39,10,FALSE()) -> No bioeconomía
A96: BRAof095 | B96: ATF01 | C96: =VLOOKUP(B96, AT_FILAS!$A$2:$C$8,2,FALSE()) -> Producción | D96: =VLOOKUP(B96, AT_FILAS!$A$2:$C$8,3,FALSE()) -> P1 | E96: 49001 | F96: Transporte terrestre de carga | G96: No bioeconomía | H96: 4 | I96: No bioeconomía | J96: No bioeconomía | K96: 6 | L96: =VLOOKUP(K96,clasif_filas!$A$1:$J$39,2,FALSE()) -> Otros servicios | M96: =VLOOKUP(K96,clasif_filas!$A$1:$J$39,3,FALSE()) -> 6 | N96: =VLOOKUP(K96,clasif_filas!$A$1:$J$39,4,FALSE()) -> Otros servicios | O96: =VLOOKUP(K96,clasif_filas!$A$1:$J$39,5,FALSE()) -> 99 | P96: =VLOOKUP(K96,clasif_filas!$A$1:$J$39,6,FALSE()) -> No Bioeconomía | Q96: =VLOOKUP(K96,clasif_filas!$A$1:$J$39,7,FALSE()) -> 6 | R96: =VLOOKUP(K96,clasif_filas!$A$1:$J$39,8,FALSE()) -> Servicios comerciales de distribución; alojamiento, servicios de suministro de comidas y bebidas; servicios de transporte; y servicios de distribución de electricidad, gas y agua | S96: =VLOOKUP(K96,clasif_filas!$A$1:$J$39,9,FALSE()) -> 3 | T96: =VLOOKUP(K96,clasif_filas!$A$1:$J$39,10,FALSE()) -> No bioeconomía
A97: BRAof096 | B97: ATF01 | C97: =VLOOKUP(B97, AT_FILAS!$A$2:$C$8,2,FALSE()) -> Producción | D97: =VLOOKUP(B97, AT_FILAS!$A$2:$C$8,3,FALSE()) -> P1 | E97: 49002 | F97: Transporte terrestre de passageiros | G97: No bioeconomía | H97: 4 | I97: No bioeconomía | J97: No bioeconomía | K97: 6 | L97: =VLOOKUP(K97,clasif_filas!$A$1:$J$39,2,FALSE()) -> Otros servicios | M97: =VLOOKUP(K97,clasif_filas!$A$1:$J$39,3,FALSE()) -> 6 | N97: =VLOOKUP(K97,clasif_filas!$A$1:$J$39,4,FALSE()) -> Otros servicios | O97: =VLOOKUP(K97,clasif_filas!$A$1:$J$39,5,FALSE()) -> 99 | P97: =VLOOKUP(K97,clasif_filas!$A$1:$J$39,6,FALSE()) -> No Bioeconomía | Q97: =VLOOKUP(K97,clasif_filas!$A$1:$J$39,7,FALSE()) -> 6 | R97: =VLOOKUP(K97,clasif_filas!$A$1:$J$39,8,FALSE()) -> Servicios comerciales de distribución; alojamiento, servicios de suministro de comidas y bebidas; servicios de transporte; y servicios de distribución de electricidad, gas y agua | S97: =VLOOKUP(K97,clasif_filas!$A$1:$J$39,9,FALSE()) -> 3 | T97: =VLOOKUP(K97,clasif_filas!$A$1:$J$39,10,FALSE()) -> No bioeconomía
A98: BRAof097 | B98: ATF01 | C98: =VLOOKUP(B98, AT_FILAS!$A$2:$C$8,2,FALSE()) -> Producción | D98: =VLOOKUP(B98, AT_FILAS!$A$2:$C$8,3,FALSE()) -> P1 | E98: 50001 | F98: Transporte aquaviário | G98: No bioeconomía | H98: 4 | I98: No bioeconomía | J98: No bioeconomía | K98: 6 | L98: =VLOOKUP(K98,clasif_filas!$A$1:$J$39,2,FALSE()) -> Otros servicios | M98: =VLOOKUP(K98,clasif_filas!$A$1:$J$39,3,FALSE()) -> 6 | N98: =VLOOKUP(K98,clasif_filas!$A$1:$J$39,4,FALSE()) -> Otros servicios | O98: =VLOOKUP(K98,clasif_filas!$A$1:$J$39,5,FALSE()) -> 99 | P98: =VLOOKUP(K98,clasif_filas!$A$1:$J$39,6,FALSE()) -> No Bioeconomía | Q98: =VLOOKUP(K98,clasif_filas!$A$1:$J$39,7,FALSE()) -> 6 | R98: =VLOOKUP(K98,clasif_filas!$A$1:$J$39,8,FALSE()) -> Servicios comerciales de distribución; alojamiento, servicios de suministro de comidas y bebidas; servicios de transporte; y servicios de distribución de electricidad, gas y agua | S98: =VLOOKUP(K98,clasif_filas!$A$1:$J$39,9,FALSE()) -> 3 | T98: =VLOOKUP(K98,clasif_filas!$A$1:$J$39,10,FALSE()) -> No bioeconomía
A99: BRAof098 | B99: ATF01 | C99: =VLOOKUP(B99, AT_FILAS!$A$2:$C$8,2,FALSE()) -> Producción | D99: =VLOOKUP(B99, AT_FILAS!$A$2:$C$8,3,FALSE()) -> P1 | E99: 51001 | F99: Transporte aéreo | G99: No bioeconomía | H99: 4 | I99: No bioeconomía | J99: No bioeconomía | K99: 6 | L99: =VLOOKUP(K99,clasif_filas!$A$1:$J$39,2,FALSE()) -> Otros servicios | M99: =VLOOKUP(K99,clasif_filas!$A$1:$J$39,3,FALSE()) -> 6 | N99: =VLOOKUP(K99,clasif_filas!$A$1:$J$39,4,FALSE()) -> Otros servicios | O99: =VLOOKUP(K99,clasif_filas!$A$1:$J$39,5,FALSE()) -> 99 | P99: =VLOOKUP(K99,clasif_filas!$A$1:$J$39,6,FALSE()) -> No Bioeconomía | Q99: =VLOOKUP(K99,clasif_filas!$A$1:$J$39,7,FALSE()) -> 6 | R99: =VLOOKUP(K99,clasif_filas!$A$1:$J$39,8,FALSE()) -> Servicios comerciales de distribución; alojamiento, servicios de suministro de comidas y bebidas; servicios de transporte; y servicios de distribución de electricidad, gas y agua | S99: =VLOOKUP(K99,clasif_filas!$A$1:$J$39,9,FALSE()) -> 3 | T99: =VLOOKUP(K99,clasif_filas!$A$1:$J$39,10,FALSE()) -> No bioeconomía
A100: BRAof099 | B100: ATF01 | C100: =VLOOKUP(B100, AT_FILAS!$A$2:$C$8,2,FALSE()) -> Producción | D100: =VLOOKUP(B100, AT_FILAS!$A$2:$C$8,3,FALSE()) -> P1 | E100: 52801 | F100: Armazenamento e serviços auxiliares aos transportes | G100: No bioeconomía | H100: 4 | I100: No bioeconomía | J100: No bioeconomía | K100: 6 | L100: =VLOOKUP(K100,clasif_filas!$A$1:$J$39,2,FALSE()) -> Otros servicios | M100: =VLOOKUP(K100,clasif_filas!$A$1:$J$39,3,FALSE()) -> 6 | N100: =VLOOKUP(K100,clasif_filas!$A$1:$J$39,4,FALSE()) -> Otros servicios | O100: =VLOOKUP(K100,clasif_filas!$A$1:$J$39,5,FALSE()) -> 99 | P100: =VLOOKUP(K100,clasif_filas!$A$1:$J$39,6,FALSE()) -> No Bioeconomía | Q100: =VLOOKUP(K100,clasif_filas!$A$1:$J$39,7,FALSE()) -> 6 | R100: =VLOOKUP(K100,clasif_filas!$A$1:$J$39,8,FALSE()) -> Servicios comerciales de distribución; alojamiento, servicios de suministro de comidas y bebidas; servicios de transporte; y servicios de distribución de electricidad, gas y agua | S100: =VLOOKUP(K100,clasif_filas!$A$1:$J$39,9,FALSE()) -> 3 | T100: =VLOOKUP(K100,clasif_filas!$A$1:$J$39,10,FALSE()) -> No bioeconomía
... A197: BRAuf068 | B197: ATF02 | C197: =VLOOKUP(B197, AT_FILAS!$A$2:$C$8,2,FALSE()) -> Consumo intermedio | D197: =VLOOKUP(B197, AT_FILAS!$A$2:$C$8,3,FALSE()) -> P2 | E197: 24912 | F197: Semi-acabacados, laminados planos, longos e tubos de aço | G197: No bioeconomía | H197: 4 | I197: No bioeconomía | J197: No bioeconomía | K197: 38 | L197: =VLOOKUP(K197,clasif_filas!$A$1:$J$39,2,FALSE()) -> Muebles; otros bienes transportables n.c.p. | M197: =VLOOKUP(K197,clasif_filas!$A$1:$J$39,3,FALSE()) -> 38 | N197: =VLOOKUP(K197,clasif_filas!$A$1:$J$39,4,FALSE()) -> Muebles; otros bienes transportables n.c.p. | O197: =VLOOKUP(K197,clasif_filas!$A$1:$J$39,5,FALSE()) -> 99 | P197: =VLOOKUP(K197,clasif_filas!$A$1:$J$39,6,FALSE()) -> No Bioeconomía | Q197: =VLOOKUP(K197,clasif_filas!$A$1:$J$39,7,FALSE()) -> 3 | R197: =VLOOKUP(K197,clasif_filas!$A$1:$J$39,8,FALSE()) -> Otros bienes transportables, excepto productos metálicos, maquinaria y equipo | S197: =VLOOKUP(K197,clasif_filas!$A$1:$J$39,9,FALSE()) -> 3 | T197: =VLOOKUP(K197,clasif_filas!$A$1:$J$39,10,FALSE()) -> No bioeconomía
A198: BRAuf069 | B198: ATF02 | C198: =VLOOKUP(B198, AT_FILAS!$A$2:$C$8,2,FALSE()) -> Consumo intermedio | D198: =VLOOKUP(B198, AT_FILAS!$A$2:$C$8,3,FALSE()) -> P2 | E198: 24921 | F198: Produtos da metalurgia de metais não-ferrosos | G198: No bioeconomía | H198: 4 | I198: No bioeconomía | J198: No bioeconomía | K198: 41-49 | L198: =VLOOKUP(K198,clasif_filas!$A$1:$J$39,2,FALSE()) -> Metales, Maquianria, equipos y transporte | M198: =VLOOKUP(K198,clasif_filas!$A$1:$J$39,3,FALSE()) -> 41-49 | N198: =VLOOKUP(K198,clasif_filas!$A$1:$J$39,4,FALSE()) -> Metales, Maquianria, equipos y transporte | O198: =VLOOKUP(K198,clasif_filas!$A$1:$J$39,5,FALSE()) -> 99 | P198: =VLOOKUP(K198,clasif_filas!$A$1:$J$39,6,FALSE()) -> No Bioeconomía | Q198: =VLOOKUP(K198,clasif_filas!$A$1:$J$39,7,FALSE()) -> 4 | R198: =VLOOKUP(K198,clasif_filas!$A$1:$J$39,8,FALSE()) -> Productos metálicos, maquinaria y equipo | S198: =VLOOKUP(K198,clasif_filas!$A$1:$J$39,9,FALSE()) -> 3 | T198: =VLOOKUP(K198,clasif_filas!$A$1:$J$39,10,FALSE()) -> No bioeconomía
A199: BRAuf070 | B199: ATF02 | C199: =VLOOKUP(B199, AT_FILAS!$A$2:$C$8,2,FALSE()) -> Consumo intermedio | D199: =VLOOKUP(B199, AT_FILAS!$A$2:$C$8,3,FALSE()) -> P2 | E199: 24922 | F199: Peças fundidas de aço e de metais não ferrosos | G199: No bioeconomía | H199: 4 | I199: No bioeconomía | J199: No bioeconomía | K199: 41-49 | L199: =VLOOKUP(K199,clasif_filas!$A$1:$J$39,2,FALSE()) -> Metales, Maquianria, equipos y transporte | M199: =VLOOKUP(K199,clasif_filas!$A$1:$J$39,3,FALSE()) -> 41-49 | N199: =VLOOKUP(K199,clasif_filas!$A$1:$J$39,4,FALSE()) -> Metales, Maquianria, equipos y transporte | O199: =VLOOKUP(K199,clasif_filas!$A$1:$J$39,5,FALSE()) -> 99 | P199: =VLOOKUP(K199,clasif_filas!$A$1:$J$39,6,FALSE()) -> No Bioeconomía | Q199: =VLOOKUP(K199,clasif_filas!$A$1:$J$39,7,FALSE()) -> 4 | R199: =VLOOKUP(K199,clasif_filas!$A$1:$J$39,8,FALSE()) -> Productos metálicos, maquinaria y equipo | S199: =VLOOKUP(K199,clasif_filas!$A$1:$J$39,9,FALSE()) -> 3 | T199: =VLOOKUP(K199,clasif_filas!$A$1:$J$39,10,FALSE()) -> No bioeconomía
A200: BRAuf071 | B200: ATF02 | C200: =VLOOKUP(B200, AT_FILAS!$A$2:$C$8,2,FALSE()) -> Consumo intermedio | D200: =VLOOKUP(B200, AT_FILAS!$A$2:$C$8,3,FALSE()) -> P2 | E200: 25001 | F200: Produtos de metal, excl. máquinas e equipamentos | G200: No bioeconomía | H200: 4 | I200: No bioeconomía | J200: No bioeconomía | K200: 41-49 | L200: =VLOOKUP(K200,clasif_filas!$A$1:$J$39,2,FALSE()) -> Metales, Maquianria, equipos y transporte | M200: =VLOOKUP(K200,clasif_filas!$A$1:$J$39,3,FALSE()) -> 41-49 | N200: =VLOOKUP(K200,clasif_filas!$A$1:$J$39,4,FALSE()) -> Metales, Maquianria, equipos y transporte | O200: =VLOOKUP(K200,clasif_filas!$A$1:$J$39,5,FALSE()) -> 99 | P200: =VLOOKUP(K200,clasif_filas!$A$1:$J$39,6,FALSE()) -> No Bioeconomía | Q200: =VLOOKUP(K200,clasif_filas!$A$1:$J$39,7,FALSE()) -> 4 | R200: =VLOOKUP(K200,clasif_filas!$A$1:$J$39,8,FALSE()) -> Productos metálicos, maquinaria y equipo | S200: =VLOOKUP(K200,clasif_filas!$A$1:$J$39,9,FALSE()) -> 3 | T200: =VLOOKUP(K200,clasif_filas!$A$1:$J$39,10,FALSE()) -> No bioeconomía
A201: BRAuf072 | B201: ATF02 | C201: =VLOOKUP(B201, AT_FILAS!$A$2:$C$8,2,FALSE()) -> Consumo intermedio | D201: =VLOOKUP(B201, AT_FILAS!$A$2:$C$8,3,FALSE()) -> P2 | E201: 26001 | F201: Componentes eletrônicos | G201: No bioeconomía | H201: 4 | I201: No bioeconomía | J201: No bioeconomía | K201: 41-49 | L201: =VLOOKUP(K201,clasif_filas!$A$1:$J$39,2,FALSE()) -> Metales, Maquianria, equipos y transporte | M201: =VLOOKUP(K201,clasif_filas!$A$1:$J$39,3,FALSE()) -> 41-49 | N201: =VLOOKUP(K201,clasif_filas!$A$1:$J$39,4,FALSE()) -> Metales, Maquianria, equipos y transporte | O201: =VLOOKUP(K201,clasif_filas!$A$1:$J$39,5,FALSE()) -> 99 | P201: =VLOOKUP(K201,clasif_filas!$A$1:$J$39,6,FALSE()) -> No Bioeconomía | Q201: =VLOOKUP(K201,clasif_filas!$A$1:$J$39,7,FALSE()) -> 4 | R201: =VLOOKUP(K201,clasif_filas!$A$1:$J$39,8,FALSE()) -> Productos metálicos, maquinaria y equipo | S201: =VLOOKUP(K201,clasif_filas!$A$1:$J$39,9,FALSE()) -> 3 | T201: =VLOOKUP(K201,clasif_filas!$A$1:$J$39,10,FALSE()) -> No bioeconomía
A202: BRAuf073 | B202: ATF02 | C202: =VLOOKUP(B202, AT_FILAS!$A$2:$C$8,2,FALSE()) -> Consumo intermedio | D202: =VLOOKUP(B202, AT_FILAS!$A$2:$C$8,3,FALSE()) -> P2 | E202: 26002 | F202: Máquinas para escritório e equip. de informática | G202: No bioeconomía | H202: 4 | I202: No bioeconomía | J202: No bioeconomía | K202: 41-49 | L202: =VLOOKUP(K202,clasif_filas!$A$1:$J$39,2,FALSE()) -> Metales, Maquianria, equipos y transporte | M202: =VLOOKUP(K202,clasif_filas!$A$1:$J$39,3,FALSE()) -> 41-49 | N202: =VLOOKUP(K202,clasif_filas!$A$1:$J$39,4,FALSE()) -> Metales, Maquianria, equipos y transporte | O202: =VLOOKUP(K202,clasif_filas!$A$1:$J$39,5,FALSE()) -> 99 | P202: =VLOOKUP(K202,clasif_filas!$A$1:$J$39,6,FALSE()) -> No Bioeconomía | Q202: =VLOOKUP(K202,clasif_filas!$A$1:$J$39,7,FALSE()) -> 4 | R202: =VLOOKUP(K202,clasif_filas!$A$1:$J$39,8,FALSE()) -> Productos metálicos, maquinaria y equipo | S202: =VLOOKUP(K202,clasif_filas!$A$1:$J$39,9,FALSE()) -> 3 | T202: =VLOOKUP(K202,clasif_filas!$A$1:$J$39,10,FALSE()) -> No bioeconomía
A203: BRAuf074 | B203: ATF02 | C203: =VLOOKUP(B203, AT_FILAS!$A$2:$C$8,2,FALSE()) -> Consumo intermedio | D203: =VLOOKUP(B203, AT_FILAS!$A$2:$C$8,3,FALSE()) -> P2 | E203: 26003 | F203: Material eletrônico e equip. de comunicações | G203: No bioeconomía | H203: 4 | I203: No bioeconomía | J203: No bioeconomía | K203: 41-49 | L203: =VLOOKUP(K203,clasif_filas!$A$1:$J$39,2,FALSE()) -> Metales, Maquianria, equipos y transporte | M203: =VLOOKUP(K203,clasif_filas!$A$1:$J$39,3,FALSE()) -> 41-49 | N203: =VLOOKUP(K203,clasif_filas!$A$1:$J$39,4,FALSE()) -> Metales, Maquianria, equipos y transporte | O203: =VLOOKUP(K203,clasif_filas!$A$1:$J$39,5,FALSE()) -> 99 | P203: =VLOOKUP(K203,clasif_filas!$A$1:$J$39,6,FALSE()) -> No Bioeconomía | Q203: =VLOOKUP(K203,clasif_filas!$A$1:$J$39,7,FALSE()) -> 4 | R203: =VLOOKUP(K203,clasif_filas!$A$1:$J$39,8,FALSE()) -> Productos metálicos, maquinaria y equipo | S203: =VLOOKUP(K203,clasif_filas!$A$1:$J$39,9,FALSE()) -> 3 | T203: =VLOOKUP(K203,clasif_filas!$A$1:$J$39,10,FALSE()) -> No bioeconomía
A204: BRAuf075 | B204: ATF02 | C204: =VLOOKUP(B204, AT_FILAS!$A$2:$C$8,2,FALSE()) -> Consumo intermedio | D204: =VLOOKUP(B204, AT_FILAS!$A$2:$C$8,3,FALSE()) -> P2 | E204: 26004 | F204: Equip. de medida, teste e controle, ópticos e eletromédicos | G204: No bioeconomía | H204: 4 | I204: No bioeconomía | J204: No bioeconomía | K204: 41-49 | L204: =VLOOKUP(K204,clasif_filas!$A$1:$J$39,2,FALSE()) -> Metales, Maquianria, equipos y transporte | M204: =VLOOKUP(K204,clasif_filas!$A$1:$J$39,3,FALSE()) -> 41-49 | N204: =VLOOKUP(K204,clasif_filas!$A$1:$J$39,4,FALSE()) -> Metales, Maquianria, equipos y transporte | O204: =VLOOKUP(K204,clasif_filas!$A$1:$J$39,5,FALSE()) -> 99 | P204: =VLOOKUP(K204,clasif_filas!$A$1:$J$39,6,FALSE()) -> No Bioeconomía | Q204: =VLOOKUP(K204,clasif_filas!$A$1:$J$39,7,FALSE()) -> 4 | R204: =VLOOKUP(K204,clasif_filas!$A$1:$J$39,8,FALSE()) -> Productos metálicos, maquinaria y equipo | S204: =VLOOKUP(K204,clasif_filas!$A$1:$J$39,9,FALSE()) -> 3 | T204: =VLOOKUP(K204,clasif_filas!$A$1:$J$39,10,FALSE()) -> No bioeconomía
A205: BRAuf076 | B205: ATF02 | C205: =VLOOKUP(B205, AT_FILAS!$A$2:$C$8,2,FALSE()) -> Consumo intermedio | D205: =VLOOKUP(B205, AT_FILAS!$A$2:$C$8,3,FALSE()) -> P2 | E205: 27001 | F205: Máquinas, aparelhos e materiais elétricos | G205: No bioeconomía | H205: 4 | I205: No bioeconomía | J205: No bioeconomía | K205: 41-49 | L205: =VLOOKUP(K205,clasif_filas!$A$1:$J$39,2,FALSE()) -> Metales, Maquianria, equipos y transporte | M205: =VLOOKUP(K205,clasif_filas!$A$1:$J$39,3,FALSE()) -> 41-49 | N205: =VLOOKUP(K205,clasif_filas!$A$1:$J$39,4,FALSE()) -> Metales, Maquianria, equipos y transporte | O205: =VLOOKUP(K205,clasif_filas!$A$1:$J$39,5,FALSE()) -> 99 | P205: =VLOOKUP(K205,clasif_filas!$A$1:$J$39,6,FALSE()) -> No Bioeconomía | Q205: =VLOOKUP(K205,clasif_filas!$A$1:$J$39,7,FALSE()) -> 4 | R205: =VLOOKUP(K205,clasif_filas!$A$1:$J$39,8,FALSE()) -> Productos metálicos, maquinaria y equipo | S205: =VLOOKUP(K205,clasif_filas!$A$1:$J$39,9,FALSE()) -> 3 | T205: =VLOOKUP(K205,clasif_filas!$A$1:$J$39,10,FALSE()) -> No bioeconomía
A206: BRAuf077 | B206: ATF02 | C206: =VLOOKUP(B206, AT_FILAS!$A$2:$C$8,2,FALSE()) -> Consumo intermedio | D206: =VLOOKUP(B206, AT_FILAS!$A$2:$C$8,3,FALSE()) -> P2 | E206: 27002 | F206: Eletrodomésticos | G206: No bioeconomía | H206: 4 | I206: No bioeconomía | J206: No bioeconomía | K206: 41-49 | L206: =VLOOKUP(K206,clasif_filas!$A$1:$J$39,2,FALSE()) -> Metales, Maquianria, equipos y transporte | M206: =VLOOKUP(K206,clasif_filas!$A$1:$J$39,3,FALSE()) -> 41-49 | N206: =VLOOKUP(K206,clasif_filas!$A$1:$J$39,4,FALSE()) -> Metales, Maquianria, equipos y transporte | O206: =VLOOKUP(K206,clasif_filas!$A$1:$J$39,5,FALSE()) -> 99 | P206: =VLOOKUP(K206,clasif_filas!$A$1:$J$39,6,FALSE()) -> No Bioeconomía | Q206: =VLOOKUP(K206,clasif_filas!$A$1:$J$39,7,FALSE()) -> 4 | R206: =VLOOKUP(K206,clasif_filas!$A$1:$J$39,8,FALSE()) -> Productos metálicos, maquinaria y equipo | S206: =VLOOKUP(K206,clasif_filas!$A$1:$J$39,9,FALSE()) -> 3 | T206: =VLOOKUP(K206,clasif_filas!$A$1:$J$39,10,FALSE()) -> No bioeconomía
A207: BRAuf078 | B207: ATF02 | C207: =VLOOKUP(B207, AT_FILAS!$A$2:$C$8,2,FALSE()) -> Consumo intermedio | D207: =VLOOKUP(B207, AT_FILAS!$A$2:$C$8,3,FALSE()) -> P2 | E207: 28001 | F207: Tratores e outras máquinas agrícolas | G207: No bioeconomía | H207: 4 | I207: No bioeconomía | J207: No bioeconomía | K207: 41-49 | L207: =VLOOKUP(K207,clasif_filas!$A$1:$J$39,2,FALSE()) -> Metales, Maquianria, equipos y transporte | M207: =VLOOKUP(K207,clasif_filas!$A$1:$J$39,3,FALSE()) -> 41-49 | N207: =VLOOKUP(K207,clasif_filas!$A$1:$J$39,4,FALSE()) -> Metales, Maquianria, equipos y transporte | O207: =VLOOKUP(K207,clasif_filas!$A$1:$J$39,5,FALSE()) -> 99 | P207: =VLOOKUP(K207,clasif_filas!$A$1:$J$39,6,FALSE()) -> No Bioeconomía | Q207: =VLOOKUP(K207,clasif_filas!$A$1:$J$39,7,FALSE()) -> 4 | R207: =VLOOKUP(K207,clasif_filas!$A$1:$J$39,8,FALSE()) -> Productos metálicos, maquinaria y equipo | S207: =VLOOKUP(K207,clasif_filas!$A$1:$J$39,9,FALSE()) -> 3 | T207: =VLOOKUP(K207,clasif_filas!$A$1:$J$39,10,FALSE()) -> No bioeconomía
A208: BRAuf079 | B208: ATF02 | C208: =VLOOKUP(B208, AT_FILAS!$A$2:$C$8,2,FALSE()) -> Consumo intermedio | D208: =VLOOKUP(B208, AT_FILAS!$A$2:$C$8,3,FALSE()) -> P2 | E208: 28002 | F208: Máquinas para a extração mineral e a construção | G208: No bioeconomía | H208: 4 | I208: No bioeconomía | J208: No bioeconomía | K208: 41-49 | L208: =VLOOKUP(K208,clasif_filas!$A$1:$J$39,2,FALSE()) -> Metales, Maquianria, equipos y transporte | M208: =VLOOKUP(K208,clasif_filas!$A$1:$J$39,3,FALSE()) -> 41-49 | N208: =VLOOKUP(K208,clasif_filas!$A$1:$J$39,4,FALSE()) -> Metales, Maquianria, equipos y transporte | O208: =VLOOKUP(K208,clasif_filas!$A$1:$J$39,5,FALSE()) -> 99 | P208: =VLOOKUP(K208,clasif_filas!$A$1:$J$39,6,FALSE()) -> No Bioeconomía | Q208: =VLOOKUP(K208,clasif_filas!$A$1:$J$39,7,FALSE()) -> 4 | R208: =VLOOKUP(K208,clasif_filas!$A$1:$J$39,8,FALSE()) -> Productos metálicos, maquinaria y equipo | S208: =VLOOKUP(K208,clasif_filas!$A$1:$J$39,9,FALSE()) -> 3 | T208: =VLOOKUP(K208,clasif_filas!$A$1:$J$39,10,FALSE()) -> No bioeconomía
A209: BRAuf080 | B209: ATF02 | C209: =VLOOKUP(B209, AT_FILAS!$A$2:$C$8,2,FALSE()) -> Consumo intermedio | D209: =VLOOKUP(B209, AT_FILAS!$A$2:$C$8,3,FALSE()) -> P2 | E209: 28003 | F209: Outras máquinas e equipamentos mecânicos | G209: No bioeconomía | H209: 4 | I209: No bioeconomía | J209: No bioeconomía | K209: 41-49 | L209: =VLOOKUP(K209,clasif_filas!$A$1:$J$39,2,FALSE()) -> Metales, Maquianria, equipos y transporte | M209: =VLOOKUP(K209,clasif_filas!$A$1:$J$39,3,FALSE()) -> 41-49 | N209: =VLOOKUP(K209,clasif_filas!$A$1:$J$39,4,FALSE()) -> Metales, Maquianria, equipos y transporte | O209: =VLOOKUP(K209,clasif_filas!$A$1:$J$39,5,FALSE()) -> 99 | P209: =VLOOKUP(K209,clasif_filas!$A$1:$J$39,6,FALSE()) -> No Bioeconomía | Q209: =VLOOKUP(K209,clasif_filas!$A$1:$J$39,7,FALSE()) -> 4 | R209: =VLOOKUP(K209,clasif_filas!$A$1:$J$39,8,FALSE()) -> Productos metálicos, maquinaria y equipo | S209: =VLOOKUP(K209,clasif_filas!$A$1:$J$39,9,FALSE()) -> 3 | T209: =VLOOKUP(K209,clasif_filas!$A$1:$J$39,10,FALSE()) -> No bioeconomía
... A216: BRAuf087 | B216: ATF02 | C216: =VLOOKUP(B216, AT_FILAS!$A$2:$C$8,2,FALSE()) -> Consumo intermedio | D216: =VLOOKUP(B216, AT_FILAS!$A$2:$C$8,3,FALSE()) -> P2 | E216: 33001 | F216: Manutenção, reparação e instalação de máquinas e equipamentos | G216: No bioeconomía | H216: 4 | I216: No bioeconomía | J216: No bioeconomía | K216: 41-49 | L216: =VLOOKUP(K216,clasif_filas!$A$1:$J$39,2,FALSE()) -> Metales, Maquianria, equipos y transporte | M216: =VLOOKUP(K216,clasif_filas!$A$1:$J$39,3,FALSE()) -> 41-49 | N216: =VLOOKUP(K216,clasif_filas!$A$1:$J$39,4,FALSE()) -> Metales, Maquianria, equipos y transporte | O216: =VLOOKUP(K216,clasif_filas!$A$1:$J$39,5,FALSE()) -> 99 | P216: =VLOOKUP(K216,clasif_filas!$A$1:$J$39,6,FALSE()) -> No Bioeconomía | Q216: =VLOOKUP(K216,clasif_filas!$A$1:$J$39,7,FALSE()) -> 4 | R216: =VLOOKUP(K216,clasif_filas!$A$1:$J$39,8,FALSE()) -> Productos metálicos, maquinaria y equipo | S216: =VLOOKUP(K216,clasif_filas!$A$1:$J$39,9,FALSE()) -> 3 | T216: =VLOOKUP(K216,clasif_filas!$A$1:$J$39,10,FALSE()) -> No bioeconomía
A217: BRAuf088 | B217: ATF02 | C217: =VLOOKUP(B217, AT_FILAS!$A$2:$C$8,2,FALSE()) -> Consumo intermedio | D217: =VLOOKUP(B217, AT_FILAS!$A$2:$C$8,3,FALSE()) -> P2 | E217: 35001 | F217: Eletricidade, gás e outras utilidades | G217: Agua | H217: 1 | I217: Bioeconomía de productos básicos | J217: Materias primas | K217: 17.5 | L217: =VLOOKUP(K217,clasif_filas!$A$1:$J$39,2,FALSE()) -> Electricidad y agua | M217: =VLOOKUP(K217,clasif_filas!$A$1:$J$39,3,FALSE()) -> 17.5 | N217: =VLOOKUP(K217,clasif_filas!$A$1:$J$39,4,FALSE()) -> Electricidad y agua | O217: =VLOOKUP(K217,clasif_filas!$A$1:$J$39,5,FALSE()) -> 6 | P217: =VLOOKUP(K217,clasif_filas!$A$1:$J$39,6,FALSE()) -> Conocimiento, procesos y servicios relacionados | Q217: =VLOOKUP(K217,clasif_filas!$A$1:$J$39,7,FALSE()) -> 1 | R217: =VLOOKUP(K217,clasif_filas!$A$1:$J$39,8,FALSE()) -> Minerales; electricidad, gas y agua | S217: =VLOOKUP(K217,clasif_filas!$A$1:$J$39,9,FALSE()) -> 2 | T217: =VLOOKUP(K217,clasif_filas!$A$1:$J$39,10,FALSE()) -> Bioeconomía extendida
A218: BRAuf089 | B218: ATF02 | C218: =VLOOKUP(B218, AT_FILAS!$A$2:$C$8,2,FALSE()) -> Consumo intermedio | D218: =VLOOKUP(B218, AT_FILAS!$A$2:$C$8,3,FALSE()) -> P2 | E218: 36801 | F218: Água, esgoto, reciclagem e gestão de resíduos | G218: Productos agricolas_Residuos | H218: 1 | I218: Bioeconomía de productos básicos | J218: Productos agropecuarios | K218: 94 | L218: =VLOOKUP(K218,clasif_filas!$A$1:$J$39,2,FALSE()) -> Servicios de alcantarillado, recolección, tratamiento y disposición de desechos y otros servicios de saneamiento ambiental | M218: =VLOOKUP(K218,clasif_filas!$A$1:$J$39,3,FALSE()) -> 94 | N218: =VLOOKUP(K218,clasif_filas!$A$1:$J$39,4,FALSE()) -> Servicios de alcantarillado, recolección, tratamiento y disposición de desechos y otros servicios de saneamiento ambiental | O218: =VLOOKUP(K218,clasif_filas!$A$1:$J$39,5,FALSE()) -> 4 | P218: =VLOOKUP(K218,clasif_filas!$A$1:$J$39,6,FALSE()) -> Biomasa residual en los sectores agropecuario, pesca y acuacultura, forestal y agroindustrial | Q218: =VLOOKUP(K218,clasif_filas!$A$1:$J$39,7,FALSE()) -> 9 | R218: =VLOOKUP(K218,clasif_filas!$A$1:$J$39,8,FALSE()) -> Servicios para la comunidad, sociales y personales | S218: =VLOOKUP(K218,clasif_filas!$A$1:$J$39,9,FALSE()) -> 2 | T218: =VLOOKUP(K218,clasif_filas!$A$1:$J$39,10,FALSE()) -> Bioeconomía extendida
A219: BRAuf090 | B219: ATF02 | C219: =VLOOKUP(B219, AT_FILAS!$A$2:$C$8,2,FALSE()) -> Consumo intermedio | D219: =VLOOKUP(B219, AT_FILAS!$A$2:$C$8,3,FALSE()) -> P2 | E219: 41801 | F219: Edificações | G219: No bioeconomía | H219: 4 | I219: No bioeconomía | J219: No bioeconomía | K219: 5 | L219: =VLOOKUP(K219,clasif_filas!$A$1:$J$39,2,FALSE()) -> Construcciones y servicios de construcción | M219: =VLOOKUP(K219,clasif_filas!$A$1:$J$39,3,FALSE()) -> 5 | N219: =VLOOKUP(K219,clasif_filas!$A$1:$J$39,4,FALSE()) -> Construcciones y servicios de construcción | O219: =VLOOKUP(K219,clasif_filas!$A$1:$J$39,5,FALSE()) -> 99 | P219: =VLOOKUP(K219,clasif_filas!$A$1:$J$39,6,FALSE()) -> No Bioeconomía | Q219: =VLOOKUP(K219,clasif_filas!$A$1:$J$39,7,FALSE()) -> 5 | R219: =VLOOKUP(K219,clasif_filas!$A$1:$J$39,8,FALSE()) -> Construcciones y servicios de construcción | S219: =VLOOKUP(K219,clasif_filas!$A$1:$J$39,9,FALSE()) -> 3 | T219: =VLOOKUP(K219,clasif_filas!$A$1:$J$39,10,FALSE()) -> No bioeconomía
A220: BRAuf091 | B220: ATF02 | C220: =VLOOKUP(B220, AT_FILAS!$A$2:$C$8,2,FALSE()) -> Consumo intermedio | D220: =VLOOKUP(B220, AT_FILAS!$A$2:$C$8,3,FALSE()) -> P2 | E220: 41802 | F220: Obras de infra-estrutura | G220: No bioeconomía | H220: 4 | I220: No bioeconomía | J220: No bioeconomía | K220: 5 | L220: =VLOOKUP(K220,clasif_filas!$A$1:$J$39,2,FALSE()) -> Construcciones y servicios de construcción | M220: =VLOOKUP(K220,clasif_filas!$A$1:$J$39,3,FALSE()) -> 5 | N220: =VLOOKUP(K220,clasif_filas!$A$1:$J$39,4,FALSE()) -> Construcciones y servicios de construcción | O220: =VLOOKUP(K220,clasif_filas!$A$1:$J$39,5,FALSE()) -> 99 | P220: =VLOOKUP(K220,clasif_filas!$A$1:$J$39,6,FALSE()) -> No Bioeconomía | Q220: =VLOOKUP(K220,clasif_filas!$A$1:$J$39,7,FALSE()) -> 5 | R220: =VLOOKUP(K220,clasif_filas!$A$1:$J$39,8,FALSE()) -> Construcciones y servicios de construcción | S220: =VLOOKUP(K220,clasif_filas!$A$1:$J$39,9,FALSE()) -> 3 | T220: =VLOOKUP(K220,clasif_filas!$A$1:$J$39,10,FALSE()) -> No bioeconomía
A221: BRAuf092 | B221: ATF02 | C221: =VLOOKUP(B221, AT_FILAS!$A$2:$C$8,2,FALSE()) -> Consumo intermedio | D221: =VLOOKUP(B221, AT_FILAS!$A$2:$C$8,3,FALSE()) -> P2 | E221: 41803 | F221: Serviços especializados para construção | G221: No bioeconomía | H221: 4 | I221: No bioeconomía | J221: No bioeconomía | K221: 5 | L221: =VLOOKUP(K221,clasif_filas!$A$1:$J$39,2,FALSE()) -> Construcciones y servicios de construcción | M221: =VLOOKUP(K221,clasif_filas!$A$1:$J$39,3,FALSE()) -> 5 | N221: =VLOOKUP(K221,clasif_filas!$A$1:$J$39,4,FALSE()) -> Construcciones y servicios de construcción | O221: =VLOOKUP(K221,clasif_filas!$A$1:$J$39,5,FALSE()) -> 99 | P221: =VLOOKUP(K221,clasif_filas!$A$1:$J$39,6,FALSE()) -> No Bioeconomía | Q221: =VLOOKUP(K221,clasif_filas!$A$1:$J$39,7,FALSE()) -> 5 | R221: =VLOOKUP(K221,clasif_filas!$A$1:$J$39,8,FALSE()) -> Construcciones y servicios de construcción | S221: =VLOOKUP(K221,clasif_filas!$A$1:$J$39,9,FALSE()) -> 3 | T221: =VLOOKUP(K221,clasif_filas!$A$1:$J$39,10,FALSE()) -> No bioeconomía
A222: BRAuf093 | B222: ATF02 | C222: =VLOOKUP(B222, AT_FILAS!$A$2:$C$8,2,FALSE()) -> Consumo intermedio | D222: =VLOOKUP(B222, AT_FILAS!$A$2:$C$8,3,FALSE()) -> P2 | E222: 45001 | F222: Comércio e reparação de veículos | G222: No bioeconomía | H222: 4 | I222: No bioeconomía | J222: No bioeconomía | K222: 6 | L222: =VLOOKUP(K222,clasif_filas!$A$1:$J$39,2,FALSE()) -> Otros servicios | M222: =VLOOKUP(K222,clasif_filas!$A$1:$J$39,3,FALSE()) -> 6 | N222: =VLOOKUP(K222,clasif_filas!$A$1:$J$39,4,FALSE()) -> Otros servicios | O222: =VLOOKUP(K222,clasif_filas!$A$1:$J$39,5,FALSE()) -> 99 | P222: =VLOOKUP(K222,clasif_filas!$A$1:$J$39,6,FALSE()) -> No Bioeconomía | Q222: =VLOOKUP(K222,clasif_filas!$A$1:$J$39,7,FALSE()) -> 6 | R222: =VLOOKUP(K222,clasif_filas!$A$1:$J$39,8,FALSE()) -> Servicios comerciales de distribución; alojamiento, servicios de suministro de comidas y bebidas; servicios de transporte; y servicios de distribución de electricidad, gas y agua | S222: =VLOOKUP(K222,clasif_filas!$A$1:$J$39,9,FALSE()) -> 3 | T222: =VLOOKUP(K222,clasif_filas!$A$1:$J$39,10,FALSE()) -> No bioeconomía
A223: BRAuf094 | B223: ATF02 | C223: =VLOOKUP(B223, AT_FILAS!$A$2:$C$8,2,FALSE()) -> Consumo intermedio | D223: =VLOOKUP(B223, AT_FILAS!$A$2:$C$8,3,FALSE()) -> P2 | E223: 46801 | F223: Comércio por atacado e a varejo, exceto veículos automotores | G223: No bioeconomía | H223: 4 | I223: No bioeconomía | J223: No bioeconomía | K223: 6 | L223: =VLOOKUP(K223,clasif_filas!$A$1:$J$39,2,FALSE()) -> Otros servicios | M223: =VLOOKUP(K223,clasif_filas!$A$1:$J$39,3,FALSE()) -> 6 | N223: =VLOOKUP(K223,clasif_filas!$A$1:$J$39,4,FALSE()) -> Otros servicios | O223: =VLOOKUP(K223,clasif_filas!$A$1:$J$39,5,FALSE()) -> 99 | P223: =VLOOKUP(K223,clasif_filas!$A$1:$J$39,6,FALSE()) -> No Bioeconomía | Q223: =VLOOKUP(K223,clasif_filas!$A$1:$J$39,7,FALSE()) -> 6 | R223: =VLOOKUP(K223,clasif_filas!$A$1:$J$39,8,FALSE()) -> Servicios comerciales de distribución; alojamiento, servicios de suministro de comidas y bebidas; servicios de transporte; y servicios de distribución de electricidad, gas y agua | S223: =VLOOKUP(K223,clasif_filas!$A$1:$J$39,9,FALSE()) -> 3 | T223: =VLOOKUP(K223,clasif_filas!$A$1:$J$39,10,FALSE()) -> No bioeconomía
A224: BRAuf095 | B224: ATF02 | C224: =VLOOKUP(B224, AT_FILAS!$A$2:$C$8,2,FALSE()) -> Consumo intermedio | D224: =VLOOKUP(B224, AT_FILAS!$A$2:$C$8,3,FALSE()) -> P2 | E224: 49001 | F224: Transporte terrestre de carga | G224: No bioeconomía | H224: 4 | I224: No bioeconomía | J224: No bioeconomía | K224: 6 | L224: =VLOOKUP(K224,clasif_filas!$A$1:$J$39,2,FALSE()) -> Otros servicios | M224: =VLOOKUP(K224,clasif_filas!$A$1:$J$39,3,FALSE()) -> 6 | N224: =VLOOKUP(K224,clasif_filas!$A$1:$J$39,4,FALSE()) -> Otros servicios | O224: =VLOOKUP(K224,clasif_filas!$A$1:$J$39,5,FALSE()) -> 99 | P224: =VLOOKUP(K224,clasif_filas!$A$1:$J$39,6,FALSE()) -> No Bioeconomía | Q224: =VLOOKUP(K224,clasif_filas!$A$1:$J$39,7,FALSE()) -> 6 | R224: =VLOOKUP(K224,clasif_filas!$A$1:$J$39,8,FALSE()) -> Servicios comerciales de distribución; alojamiento, servicios de suministro de comidas y bebidas; servicios de transporte; y servicios de distribución de electricidad, gas y agua | S224: =VLOOKUP(K224,clasif_filas!$A$1:$J$39,9,FALSE()) -> 3 | T224: =VLOOKUP(K224,clasif_filas!$A$1:$J$39,10,FALSE()) -> No bioeconomía
A225: BRAuf096 | B225: ATF02 | C225: =VLOOKUP(B225, AT_FILAS!$A$2:$C$8,2,FALSE()) -> Consumo intermedio | D225: =VLOOKUP(B225, AT_FILAS!$A$2:$C$8,3,FALSE()) -> P2 | E225: 49002 | F225: Transporte terrestre de passageiros | G225: No bioeconomía | H225: 4 | I225: No bioeconomía | J225: No bioeconomía | K225: 6 | L225: =VLOOKUP(K225,clasif_filas!$A$1:$J$39,2,FALSE()) -> Otros servicios | M225: =VLOOKUP(K225,clasif_filas!$A$1:$J$39,3,FALSE()) -> 6 | N225: =VLOOKUP(K225,clasif_filas!$A$1:$J$39,4,FALSE()) -> Otros servicios | O225: =VLOOKUP(K225,clasif_filas!$A$1:$J$39,5,FALSE()) -> 99 | P225: =VLOOKUP(K225,clasif_filas!$A$1:$J$39,6,FALSE()) -> No Bioeconomía | Q225: =VLOOKUP(K225,clasif_filas!$A$1:$J$39,7,FALSE()) -> 6 | R225: =VLOOKUP(K225,clasif_filas!$A$1:$J$39,8,FALSE()) -> Servicios comerciales de distribución; alojamiento, servicios de suministro de comidas y bebidas; servicios de transporte; y servicios de distribución de electricidad, gas y agua | S225: =VLOOKUP(K225,clasif_filas!$A$1:$J$39,9,FALSE()) -> 3 | T225: =VLOOKUP(K225,clasif_filas!$A$1:$J$39,10,FALSE()) -> No bioeconomía
A226: BRAuf097 | B226: ATF02 | C226: =VLOOKUP(B226, AT_FILAS!$A$2:$C$8,2,FALSE()) -> Consumo intermedio | D226: =VLOOKUP(B226, AT_FILAS!$A$2:$C$8,3,FALSE()) -> P2 | E226: 50001 | F226: Transporte aquaviário | G226: No bioeconomía | H226: 4 | I226: No bioeconomía | J226: No bioeconomía | K226: 6 | L226: =VLOOKUP(K226,clasif_filas!$A$1:$J$39,2,FALSE()) -> Otros servicios | M226: =VLOOKUP(K226,clasif_filas!$A$1:$J$39,3,FALSE()) -> 6 | N226: =VLOOKUP(K226,clasif_filas!$A$1:$J$39,4,FALSE()) -> Otros servicios | O226: =VLOOKUP(K226,clasif_filas!$A$1:$J$39,5,FALSE()) -> 99 | P226: =VLOOKUP(K226,clasif_filas!$A$1:$J$39,6,FALSE()) -> No Bioeconomía | Q226: =VLOOKUP(K226,clasif_filas!$A$1:$J$39,7,FALSE()) -> 6 | R226: =VLOOKUP(K226,clasif_filas!$A$1:$J$39,8,FALSE()) -> Servicios comerciales de distribución; alojamiento, servicios de suministro de comidas y bebidas; servicios de transporte; y servicios de distribución de electricidad, gas y agua | S226: =VLOOKUP(K226,clasif_filas!$A$1:$J$39,9,FALSE()) -> 3 | T226: =VLOOKUP(K226,clasif_filas!$A$1:$J$39,10,FALSE()) -> No bioeconomía
A227: BRAuf098 | B227: ATF02 | C227: =VLOOKUP(B227, AT_FILAS!$A$2:$C$8,2,FALSE()) -> Consumo intermedio | D227: =VLOOKUP(B227, AT_FILAS!$A$2:$C$8,3,FALSE()) -> P2 | E227: 51001 | F227: Transporte aéreo | G227: No bioeconomía | H227: 4 | I227: No bioeconomía | J227: No bioeconomía | K227: 6 | L227: =VLOOKUP(K227,clasif_filas!$A$1:$J$39,2,FALSE()) -> Otros servicios | M227: =VLOOKUP(K227,clasif_filas!$A$1:$J$39,3,FALSE()) -> 6 | N227: =VLOOKUP(K227,clasif_filas!$A$1:$J$39,4,FALSE()) -> Otros servicios | O227: =VLOOKUP(K227,clasif_filas!$A$1:$J$39,5,FALSE()) -> 99 | P227: =VLOOKUP(K227,clasif_filas!$A$1:$J$39,6,FALSE()) -> No Bioeconomía | Q227: =VLOOKUP(K227,clasif_filas!$A$1:$J$39,7,FALSE()) -> 6 | R227: =VLOOKUP(K227,clasif_filas!$A$1:$J$39,8,FALSE()) -> Servicios comerciales de distribución; alojamiento, servicios de suministro de comidas y bebidas; servicios de transporte; y servicios de distribución de electricidad, gas y agua | S227: =VLOOKUP(K227,clasif_filas!$A$1:$J$39,9,FALSE()) -> 3 | T227: =VLOOKUP(K227,clasif_filas!$A$1:$J$39,10,FALSE()) -> No bioeconomía
A228: BRAuf099 | B228: ATF02 | C228: =VLOOKUP(B228, AT_FILAS!$A$2:$C$8,2,FALSE()) -> Consumo intermedio | D228: =VLOOKUP(B228, AT_FILAS!$A$2:$C$8,3,FALSE()) -> P2 | E228: 52801 | F228: Armazenamento e serviços auxiliares aos transportes | G228: No bioeconomía | H228: 4 | I228: No bioeconomía | J228: No bioeconomía | K228: 6 | L228: =VLOOKUP(K228,clasif_filas!$A$1:$J$39,2,FALSE()) -> Otros servicios | M228: =VLOOKUP(K228,clasif_filas!$A$1:$J$39,3,FALSE()) -> 6 | N228: =VLOOKUP(K228,clasif_filas!$A$1:$J$39,4,FALSE()) -> Otros servicios | O228: =VLOOKUP(K228,clasif_filas!$A$1:$J$39,5,FALSE()) -> 99 | P228: =VLOOKUP(K228,clasif_filas!$A$1:$J$39,6,FALSE()) -> No Bioeconomía | Q228: =VLOOKUP(K228,clasif_filas!$A$1:$J$39,7,FALSE()) -> 6 | R228: =VLOOKUP(K228,clasif_filas!$A$1:$J$39,8,FALSE()) -> Servicios comerciales de distribución; alojamiento, servicios de suministro de comidas y bebidas; servicios de transporte; y servicios de distribución de electricidad, gas y agua | S228: =VLOOKUP(K228,clasif_filas!$A$1:$J$39,9,FALSE()) -> 3 | T228: =VLOOKUP(K228,clasif_filas!$A$1:$J$39,10,FALSE()) -> No bioeconomía
... A257: BRAuf128 | B257: ATF02 | C257: =VLOOKUP(B257, AT_FILAS!$A$2:$C$8,2,FALSE()) -> Consumo intermedio | D257: =VLOOKUP(B257, AT_FILAS!$A$2:$C$8,3,FALSE()) -> P2 | E257: 97001 | F257: Serviços domésticos | G257: No bioeconomía | H257: 4 | I257: No bioeconomía | J257: No bioeconomía | K257: 6 | L257: =VLOOKUP(K257,clasif_filas!$A$1:$J$39,2,FALSE()) -> Otros servicios | M257: =VLOOKUP(K257,clasif_filas!$A$1:$J$39,3,FALSE()) -> 6 | N257: =VLOOKUP(K257,clasif_filas!$A$1:$J$39,4,FALSE()) -> Otros servicios | O257: =VLOOKUP(K257,clasif_filas!$A$1:$J$39,5,FALSE()) -> 99 | P257: =VLOOKUP(K257,clasif_filas!$A$1:$J$39,6,FALSE()) -> No Bioeconomía | Q257: =VLOOKUP(K257,clasif_filas!$A$1:$J$39,7,FALSE()) -> 6 | R257: =VLOOKUP(K257,clasif_filas!$A$1:$J$39,8,FALSE()) -> Servicios comerciales de distribución; alojamiento, servicios de suministro de comidas y bebidas; servicios de transporte; y servicios de distribución de electricidad, gas y agua | S257: =VLOOKUP(K257,clasif_filas!$A$1:$J$39,9,FALSE()) -> 3 | T257: =VLOOKUP(K257,clasif_filas!$A$1:$J$39,10,FALSE()) -> No bioeconomía
A258: BRAvf001 | B258: ATF06 | C258: =VLOOKUP(B258, AT_FILAS!$A$2:$C$8,2,FALSE()) -> Valor Agregado | D258: =VLOOKUP(B258, AT_FILAS!$A$2:$C$8,3,FALSE()) -> - | E258: - | F258: Valor adicionado bruto ( PIB ) | G258: - | H258: - | I258: - | J258: - | K258: - | L258: - | M258: - | N258: - | O258: - | P258: - | Q258: - | R258: - | S258: - | T258: -

Sheet Base_filas
A1: Nom_Loc_Prod_BRA | B1: Cód_Div_CPC_3 | C1: División CPC_3 | D1: Cód_Div_CPC_2 | E1: División CPC_2 | F1: Cod. Elem. Def. Bioeconomía | G1: Tipo de elemento | H1: Código CPC | I1: Elemento CPC | J1: Código Bioeconomía | K1: Clasificación Bioeconomí
A2: Arroz, trigo e outros cereais | B2: 1 | C2: =VLOOKUP(B2,clasif_filas!$A$1:$J$39,2,FALSE()) -> Productos de la agricultura, la horticultura y la jardinería comercial | D2: =VLOOKUP(B2,clasif_filas!$A$1:$J$39,3,FALSE()) -> 1 | E2: =VLOOKUP(B2,clasif_filas!$A$1:$J$39,4,FALSE()) -> Productos de la agricultura, la horticultura y la jardinería comercial | F2: =VLOOKUP(B2,clasif_filas!$A$1:$J$39,5,FALSE()) -> 1 | G2: =VLOOKUP(B2,clasif_filas!$A$1:$J$39,6,FALSE()) -> Biomasa que se cultiva para producir alimentos, forrajes, fibras y energía | H2: =VLOOKUP(B2,clasif_filas!$A$1:$J$39,7,FALSE()) -> 0 | I2: =VLOOKUP(B2,clasif_filas!$A$1:$J$39,8,FALSE()) -> Productos de la agricultura, la silvicultura yla pesca | J2: =VLOOKUP(B2,clasif_filas!$A$1:$J$39,9,FALSE()) -> 1 | K2: =VLOOKUP(B2,clasif_filas!$A$1:$J$39,10,FALSE()) -> Bioeconomía
A3: Milho em grão | B3: 1 | C3: =VLOOKUP(B3,clasif_filas!$A$1:$J$39,2,FALSE()) -> Productos de la agricultura, la horticultura y la jardinería comercial | D3: =VLOOKUP(B3,clasif_filas!$A$1:$J$39,3,FALSE()) -> 1 | E3: =VLOOKUP(B3,clasif_filas!$A$1:$J$39,4,FALSE()) -> Productos de la agricultura, la horticultura y la jardinería comercial | F3: =VLOOKUP(B3,clasif_filas!$A$1:$J$39,5,FALSE()) -> 1 | G3: =VLOOKUP(B3,clasif_filas!$A$1:$J$39,6,FALSE()) -> Biomasa que se cultiva para producir alimentos, forrajes, fibras y energía | H3: =VLOOKUP(B3,clasif_filas!$A$1:$J$39,7,FALSE()) -> 0 | I3: =VLOOKUP(B3,clasif_filas!$A$1:$J$39,8,FALSE()) -> Productos de la agricultura, la silvicultura yla pesca | J3: =VLOOKUP(B3,clasif_filas!$A$1:$J$39,9,FALSE()) -> 1 | K3: =VLOOKUP(B3,clasif_filas!$A$1:$J$39,10,FALSE()) -> Bioeconomía
A4: Algodão herbáceo, outras fibras da lav. temporária | B4: 1 | C4: =VLOOKUP(B4,clasif_filas!$A$1:$J$39,2,FALSE()) -> Productos de la agricultura, la horticultura y la jardinería comercial | D4: =VLOOKUP(B4,clasif_filas!$A$1:$J$39,3,FALSE()) -> 1 | E4: =VLOOKUP(B4,clasif_filas!$A$1:$J$39,4,FALSE()) -> Productos de la agricultura, la horticultura y la jardinería comercial | F4: =VLOOKUP(B4,clasif_filas!$A$1:$J$39,5,FALSE()) -> 1 | G4: =VLOOKUP(B4,clasif_filas!$A$1:$J$39,6,FALSE()) -> Biomasa que se cultiva para producir alimentos, forrajes, fibras y energía | H4: =VLOOKUP(B4,clasif_filas!$A$1:$J$39,7,FALSE()) -> 0 | I4: =VLOOKUP(B4,clasif_filas!$A$1:$J$39,8,FALSE()) -> Productos de la agricultura, la silvicultura yla pesca | J4: =VLOOKUP(B4,clasif_filas!$A$1:$J$39,9,FALSE()) -> 1 | K4: =VLOOKUP(B4,clasif_filas!$A$1:$J$39,10,FALSE()) -> Bioeconomía
A5: Cana-de-açúcar | B5: 1 | C5: =VLOOKUP(B5,clasif_filas!$A$1:$J$39,2,FALSE()) -> Productos de la agricultura, la horticultura y la jardinería comercial | D5: =VLOOKUP(B5,clasif_filas!$A$1:$J$39,3,FALSE()) -> 1 | E5: =VLOOKUP(B5,clasif_filas!$A$1:$J$39,4,FALSE()) -> Productos de la agricultura, la horticultura y la jardinería comercial | F5: =VLOOKUP(B5,clasif_filas!$A$1:$J$39,5,FALSE()) -> 1 | G5: =VLOOKUP(B5,clasif_filas!$A$1:$J$39,6,FALSE()) -> Biomasa que se cultiva para producir alimentos, forrajes, fibras y energía | H5: =VLOOKUP(B5,clasif_filas!$A$1:$J$39,7,FALSE()) -> 0 | I5: =VLOOKUP(B5,clasif_filas!$A$1:$J$39,8,FALSE()) -> Productos de la agricultura, la silvicultura yla pesca | J5: =VLOOKUP(B5,clasif_filas!$A$1:$J$39,9,FALSE()) -> 1 | K5: =VLOOKUP(B5,clasif_filas!$A$1:$J$39,10,FALSE()) -> Bioeconomía
A6: Soja em grão | B6: 1 | C6: =VLOOKUP(B6,clasif_filas!$A$1:$J$39,2,FALSE()) -> Productos de la agricultura, la horticultura y la jardinería comercial | D6: =VLOOKUP(B6,clasif_filas!$A$1:$J$39,3,FALSE()) -> 1 | E6: =VLOOKUP(B6,clasif_filas!$A$1:$J$39,4,FALSE()) -> Productos de la agricultura, la horticultura y la jardinería comercial | F6: =VLOOKUP(B6,clasif_filas!$A$1:$J$39,5,FALSE()) -> 1 | G6: =VLOOKUP(B6,clasif_filas!$A$1:$J$39,6,FALSE()) -> Biomasa que se cultiva para producir alimentos, forrajes, fibras y energía | H6: =VLOOKUP(B6,clasif_filas!$A$1:$J$39,7,FALSE()) -> 0 | I6: =VLOOKUP(B6,clasif_filas!$A$1:$J$39,8,FALSE()) -> Productos de la agricultura, la silvicultura yla pesca | J6: =VLOOKUP(B6,clasif_filas!$A$1:$J$39,9,FALSE()) -> 1 | K6: =VLOOKUP(B6,clasif_filas!$A$1:$J$39,10,FALSE()) -> Bioeconomía
A7: Outros produtos e serviços da lavoura temporária | B7: 1 | C7: =VLOOKUP(B7,clasif_filas!$A$1:$J$39,2,FALSE()) -> Productos de la agricultura, la horticultura y la jardinería comercial | D7: =VLOOKUP(B7,clasif_filas!$A$1:$J$39,3,FALSE()) -> 1 | E7: =VLOOKUP(B7,clasif_filas!$A$1:$J$39,4,FALSE()) -> Productos de la agricultura, la horticultura y la jardinería comercial | F7: =VLOOKUP(B7,clasif_filas!$A$1:$J$39,5,FALSE()) -> 1 | G7: =VLOOKUP(B7,clasif_filas!$A$1:$J$39,6,FALSE()) -> Biomasa que se cultiva para producir alimentos, forrajes, fibras y energía | H7: =VLOOKUP(B7,clasif_filas!$A$1:$J$39,7,FALSE()) -> 0 | I7: =VLOOKUP(B7,clasif_filas!$A$1:$J$39,8,FALSE()) -> Productos de la agricultura, la silvicultura yla pesca | J7: =VLOOKUP(B7,clasif_filas!$A$1:$J$39,9,FALSE()) -> 1 | K7: =VLOOKUP(B7,clasif_filas!$A$1:$J$39,10,FALSE()) -> Bioeconomía
A8: Laranja | B8: 1 | C8: =VLOOKUP(B8,clasif_filas!$A$1:$J$39,2,FALSE()) -> Productos de la agricultura, la horticultura y la jardinería comercial | D8: =VLOOKUP(B8,clasif_filas!$A$1:$J$39,3,FALSE()) -> 1 | E8: =VLOOKUP(B8,clasif_filas!$A$1:$J$39,4,FALSE()) -> Productos de la agricultura, la horticultura y la jardinería comercial | F8: =VLOOKUP(B8,clasif_filas!$A$1:$J$39,5,FALSE()) -> 1 | G8: =VLOOKUP(B8,clasif_filas!$A$1:$J$39,6,FALSE()) -> Biomasa que se cultiva para producir alimentos, forrajes, fibras y energía | H8: =VLOOKUP(B8,clasif_filas!$A$1:$J$39,7,FALSE()) -> 0 | I8: =VLOOKUP(B8,clasif_filas!$A$1:$J$39,8,FALSE()) -> Productos de la agricultura, la silvicultura yla pesca | J8: =VLOOKUP(B8,clasif_filas!$A$1:$J$39,9,FALSE()) -> 1 | K8: =VLOOKUP(B8,clasif_filas!$A$1:$J$39,10,FALSE()) -> Bioeconomía
A9: Café em grão | B9: 1 | C9: =VLOOKUP(B9,clasif_filas!$A$1:$J$39,2,FALSE()) -> Productos de la agricultura, la horticultura y la jardinería comercial | D9: =VLOOKUP(B9,clasif_filas!$A$1:$J$39,3,FALSE()) -> 1 | E9: =VLOOKUP(B9,clasif_filas!$A$1:$J$39,4,FALSE()) -> Productos de la agricultura, la horticultura y la jardinería comercial | F9: =VLOOKUP(B9,clasif_filas!$A$1:$J$39,5,FALSE()) -> 1 | G9: =VLOOKUP(B9,clasif_filas!$A$1:$J$39,6,FALSE()) -> Biomasa que se cultiva para producir alimentos, forrajes, fibras y energía | H9: =VLOOKUP(B9,clasif_filas!$A$1:$J$39,7,FALSE()) -> 0 | I9: =VLOOKUP(B9,clasif_filas!$A$1:$J$39,8,FALSE()) -> Productos de la agricultura, la silvicultura yla pesca | J9: =VLOOKUP(B9,clasif_filas!$A$1:$J$39,9,FALSE()) -> 1 | K9: =VLOOKUP(B9,clasif_filas!$A$1:$J$39,10,FALSE()) -> Bioeconomía
A10: Outros produtos da lavoura permanente | B10: 1 | C10: =VLOOKUP(B10,clasif_filas!$A$1:$J$39,2,FALSE()) -> Productos de la agricultura, la horticultura y la jardinería comercial | D10: =VLOOKUP(B10,clasif_filas!$A$1:$J$39,3,FALSE()) -> 1 | E10: =VLOOKUP(B10,clasif_filas!$A$1:$J$39,4,FALSE()) -> Productos de la agricultura, la horticultura y la jardinería comercial | F10: =VLOOKUP(B10,clasif_filas!$A$1:$J$39,5,FALSE()) -> 1 | G10: =VLOOKUP(B10,clasif_filas!$A$1:$J$39,6,FALSE()) -> Biomasa que se cultiva para producir alimentos, forrajes, fibras y energía | H10: =VLOOKUP(B10,clasif_filas!$A$1:$J$39,7,FALSE()) -> 0 | I10: =VLOOKUP(B10,clasif_filas!$A$1:$J$39,8,FALSE()) -> Productos de la agricultura, la silvicultura yla pesca | J10: =VLOOKUP(B10,clasif_filas!$A$1:$J$39,9,FALSE()) -> 1 | K10: =VLOOKUP(B10,clasif_filas!$A$1:$J$39,10,FALSE()) -> Bioeconomía
A11: Bovinos e outros animais vivos, prods. animal, caça e serv. | B11: 2 | C11: =VLOOKUP(B11,clasif_filas!$A$1:$J$39,2,FALSE()) -> Animales vivos y productos animales (excepto la carne) | D11: =VLOOKUP(B11,clasif_filas!$A$1:$J$39,3,FALSE()) -> 2 | E11: =VLOOKUP(B11,clasif_filas!$A$1:$J$39,4,FALSE()) -> Animales vivos y productos animales (excepto la carne) | F11: =VLOOKUP(B11,clasif_filas!$A$1:$J$39,5,FALSE()) -> 1 | G11: =VLOOKUP(B11,clasif_filas!$A$1:$J$39,6,FALSE()) -> Biomasa que se cultiva para producir alimentos, forrajes, fibras y energía | H11: =VLOOKUP(B11,clasif_filas!$A$1:$J$39,7,FALSE()) -> 0 | I11: =VLOOKUP(B11,clasif_filas!$A$1:$J$39,8,FALSE()) -> Productos de la agricultura, la silvicultura yla pesca | J11: =VLOOKUP(B11,clasif_filas!$A$1:$J$39,9,FALSE()) -> 1 | K11: =VLOOKUP(B11,clasif_filas!$A$1:$J$39,10,FALSE()) -> Bioeconomía
A12: Leite de vaca e de outros animais | B12: 2 | C12: =VLOOKUP(B12,clasif_filas!$A$1:$J$39,2,FALSE()) -> Animales vivos y productos animales (excepto la carne) | D12: =VLOOKUP(B12,clasif_filas!$A$1:$J$39,3,FALSE()) -> 2 | E12: =VLOOKUP(B12,clasif_filas!$A$1:$J$39,4,FALSE()) -> Animales vivos y productos animales (excepto la carne) | F12: =VLOOKUP(B12,clasif_filas!$A$1:$J$39,5,FALSE()) -> 1 | G12: =VLOOKUP(B12,clasif_filas!$A$1:$J$39,6,FALSE()) -> Biomasa que se cultiva para producir alimentos, forrajes, fibras y energía | H12: =VLOOKUP(B12,clasif_filas!$A$1:$J$39,7,FALSE()) -> 0 | I12: =VLOOKUP(B12,clasif_filas!$A$1:$J$39,8,FALSE()) -> Productos de la agricultura, la silvicultura yla pesca | J12: =VLOOKUP(B12,clasif_filas!$A$1:$J$39,9,FALSE()) -> 1 | K12: =VLOOKUP(B12,clasif_filas!$A$1:$J$39,10,FALSE()) -> Bioeconomía
A13: Suínos | B13: 2 | C13: =VLOOKUP(B13,clasif_filas!$A$1:$J$39,2,FALSE()) -> Animales vivos y productos animales (excepto la carne) | D13: =VLOOKUP(B13,clasif_filas!$A$1:$J$39,3,FALSE()) -> 2 | E13: =VLOOKUP(B13,clasif_filas!$A$1:$J$39,4,FALSE()) -> Animales vivos y productos animales (excepto la carne) | F13: =VLOOKUP(B13,clasif_filas!$A$1:$J$39,5,FALSE()) -> 1 | G13: =VLOOKUP(B13,clasif_filas!$A$1:$J$39,6,FALSE()) -> Biomasa que se cultiva para producir alimentos, forrajes, fibras y energía | H13: =VLOOKUP(B13,clasif_filas!$A$1:$J$39,7,FALSE()) -> 0 | I13: =VLOOKUP(B13,clasif_filas!$A$1:$J$39,8,FALSE()) -> Productos de la agricultura, la silvicultura yla pesca | J13: =VLOOKUP(B13,clasif_filas!$A$1:$J$39,9,FALSE()) -> 1 | K13: =VLOOKUP(B13,clasif_filas!$A$1:$J$39,10,FALSE()) -> Bioeconomía
... A69: Semi-acabacados, laminados planos, longos e tubos de aço | B69: 38 | C69: =VLOOKUP(B69,clasif_filas!$A$1:$J$39,2,FALSE()) -> Muebles; otros bienes transportables n.c.p. | D69: =VLOOKUP(B69,clasif_filas!$A$1:$J$39,3,FALSE()) -> 38 | E69: =VLOOKUP(B69,clasif_filas!$A$1:$J$39,4,FALSE()) -> Muebles; otros bienes transportables n.c.p. | F69: =VLOOKUP(B69,clasif_filas!$A$1:$J$39,5,FALSE()) -> 99 | G69: =VLOOKUP(B69,clasif_filas!$A$1:$J$39,6,FALSE()) -> No Bioeconomía | H69: =VLOOKUP(B69,clasif_filas!$A$1:$J$39,7,FALSE()) -> 3 | I69: =VLOOKUP(B69,clasif_filas!$A$1:$J$39,8,FALSE()) -> Otros bienes transportables, excepto productos metálicos, maquinaria y equipo | J69: =VLOOKUP(B69,clasif_filas!$A$1:$J$39,9,FALSE()) -> 3 | K69: =VLOOKUP(B69,clasif_filas!$A$1:$J$39,10,FALSE()) -> No bioeconomía
A70: Produtos da metalurgia de metais não-ferrosos | B70: 41-49 | C70: =VLOOKUP(B70,clasif_filas!$A$1:$J$39,2,FALSE()) -> Metales, Maquianria, equipos y transporte | D70: =VLOOKUP(B70,clasif_filas!$A$1:$J$39,3,FALSE()) -> 41-49 | E70: =VLOOKUP(B70,clasif_filas!$A$1:$J$39,4,FALSE()) -> Metales, Maquianria, equipos y transporte | F70: =VLOOKUP(B70,clasif_filas!$A$1:$J$39,5,FALSE()) -> 99 | G70: =VLOOKUP(B70,clasif_filas!$A$1:$J$39,6,FALSE()) -> No Bioeconomía | H70: =VLOOKUP(B70,clasif_filas!$A$1:$J$39,7,FALSE()) -> 4 | I70: =VLOOKUP(B70,clasif_filas!$A$1:$J$39,8,FALSE()) -> Productos metálicos, maquinaria y equipo | J70: =VLOOKUP(B70,clasif_filas!$A$1:$J$39,9,FALSE()) -> 3 | K70: =VLOOKUP(B70,clasif_filas!$A$1:$J$39,10,FALSE()) -> No bioeconomía
A71: Peças fundidas de aço e de metais não ferrosos | B71: 41-49 | C71: =VLOOKUP(B71,clasif_filas!$A$1:$J$39,2,FALSE()) -> Metales, Maquianria, equipos y transporte | D71: =VLOOKUP(B71,clasif_filas!$A$1:$J$39,3,FALSE()) -> 41-49 | E71: =VLOOKUP(B71,clasif_filas!$A$1:$J$39,4,FALSE()) -> Metales, Maquianria, equipos y transporte | F71: =VLOOKUP(B71,clasif_filas!$A$1:$J$39,5,FALSE()) -> 99 | G71: =VLOOKUP(B71,clasif_filas!$A$1:$J$39,6,FALSE()) -> No Bioeconomía | H71: =VLOOKUP(B71,clasif_filas!$A$1:$J$39,7,FALSE()) -> 4 | I71: =VLOOKUP(B71,clasif_filas!$A$1:$J$39,8,FALSE()) -> Productos metálicos, maquinaria y equipo | J71: =VLOOKUP(B71,clasif_filas!$A$1:$J$39,9,FALSE()) -> 3 | K71: =VLOOKUP(B71,clasif_filas!$A$1:$J$39,10,FALSE()) -> No bioeconomía
A72: Produtos de metal, excl. máquinas e equipamentos | B72: 41-49 | C72: =VLOOKUP(B72,clasif_filas!$A$1:$J$39,2,FALSE()) -> Metales, Maquianria, equipos y transporte | D72: =VLOOKUP(B72,clasif_filas!$A$1:$J$39,3,FALSE()) -> 41-49 | E72: =VLOOKUP(B72,clasif_filas!$A$1:$J$39,4,FALSE()) -> Metales, Maquianria, equipos y transporte | F72: =VLOOKUP(B72,clasif_filas!$A$1:$J$39,5,FALSE()) -> 99 | G72: =VLOOKUP(B72,clasif_filas!$A$1:$J$39,6,FALSE()) -> No Bioeconomía | H72: =VLOOKUP(B72,clasif_filas!$A$1:$J$39,7,FALSE()) -> 4 | I72: =VLOOKUP(B72,clasif_filas!$A$1:$J$39,8,FALSE()) -> Productos metálicos, maquinaria y equipo | J72: =VLOOKUP(B72,clasif_filas!$A$1:$J$39,9,FALSE()) -> 3 | K72: =VLOOKUP(B72,clasif_filas!$A$1:$J$39,10,FALSE()) -> No bioeconomía
A73: Componentes eletrônicos | B73: 41-49 | C73: =VLOOKUP(B73,clasif_filas!$A$1:$J$39,2,FALSE()) -> Metales, Maquianria, equipos y transporte | D73: =VLOOKUP(B73,clasif_filas!$A$1:$J$39,3,FALSE()) -> 41-49 | E73: =VLOOKUP(B73,clasif_filas!$A$1:$J$39,4,FALSE()) -> Metales, Maquianria, equipos y transporte | F73: =VLOOKUP(B73,clasif_filas!$A$1:$J$39,5,FALSE()) -> 99 | G73: =VLOOKUP(B73,clasif_filas!$A$1:$J$39,6,FALSE()) -> No Bioeconomía | H73: =VLOOKUP(B73,clasif_filas!$A$1:$J$39,7,FALSE()) -> 4 | I73: =VLOOKUP(B73,clasif_filas!$A$1:$J$39,8,FALSE()) -> Productos metálicos, maquinaria y equipo | J73: =VLOOKUP(B73,clasif_filas!$A$1:$J$39,9,FALSE()) -> 3 | K73: =VLOOKUP(B73,clasif_filas!$A$1:$J$39,10,FALSE()) -> No bioeconomía
A74: Máquinas para escritório e equip. de informática | B74: 41-49 | C74: =VLOOKUP(B74,clasif_filas!$A$1:$J$39,2,FALSE()) -> Metales, Maquianria, equipos y transporte | D74: =VLOOKUP(B74,clasif_filas!$A$1:$J$39,3,FALSE()) -> 41-49 | E74: =VLOOKUP(B74,clasif_filas!$A$1:$J$39,4,FALSE()) -> Metales, Maquianria, equipos y transporte | F74: =VLOOKUP(B74,clasif_filas!$A$1:$J$39,5,FALSE()) -> 99 | G74: =VLOOKUP(B74,clasif_filas!$A$1:$J$39,6,FALSE()) -> No Bioeconomía | H74: =VLOOKUP(B74,clasif_filas!$A$1:$J$39,7,FALSE()) -> 4 | I74: =VLOOKUP(B74,clasif_filas!$A$1:$J$39,8,FALSE()) -> Productos metálicos, maquinaria y equipo | J74: =VLOOKUP(B74,clasif_filas!$A$1:$J$39,9,FALSE()) -> 3 | K74: =VLOOKUP(B74,clasif_filas!$A$1:$J$39,10,FALSE()) -> No bioeconomía
A75: Material eletrônico e equip. de comunicações | B75: 41-49 | C75: =VLOOKUP(B75,clasif_filas!$A$1:$J$39,2,FALSE()) -> Metales, Maquianria, equipos y transporte | D75: =VLOOKUP(B75,clasif_filas!$A$1:$J$39,3,FALSE()) -> 41-49 | E75: =VLOOKUP(B75,clasif_filas!$A$1:$J$39,4,FALSE()) -> Metales, Maquianria, equipos y transporte | F75: =VLOOKUP(B75,clasif_filas!$A$1:$J$39,5,FALSE()) -> 99 | G75: =VLOOKUP(B75,clasif_filas!$A$1:$J$39,6,FALSE()) -> No Bioeconomía | H75: =VLOOKUP(B75,clasif_filas!$A$1:$J$39,7,FALSE()) -> 4 | I75: =VLOOKUP(B75,clasif_filas!$A$1:$J$39,8,FALSE()) -> Productos metálicos, maquinaria y equipo | J75: =VLOOKUP(B75,clasif_filas!$A$1:$J$39,9,FALSE()) -> 3 | K75: =VLOOKUP(B75,clasif_filas!$A$1:$J$39,10,FALSE()) -> No bioeconomía
A76: Equip. de medida, teste e controle, ópticos e eletromédicos | B76: 41-49 | C76: =VLOOKUP(B76,clasif_filas!$A$1:$J$39,2,FALSE()) -> Metales, Maquianria, equipos y transporte | D76: =VLOOKUP(B76,clasif_filas!$A$1:$J$39,3,FALSE()) -> 41-49 | E76: =VLOOKUP(B76,clasif_filas!$A$1:$J$39,4,FALSE()) -> Metales, Maquianria, equipos y transporte | F76: =VLOOKUP(B76,clasif_filas!$A$1:$J$39,5,FALSE()) -> 99 | G76: =VLOOKUP(B76,clasif_filas!$A$1:$J$39,6,FALSE()) -> No Bioeconomía | H76: =VLOOKUP(B76,clasif_filas!$A$1:$J$39,7,FALSE()) -> 4 | I76: =VLOOKUP(B76,clasif_filas!$A$1:$J$39,8,FALSE()) -> Productos metálicos, maquinaria y equipo | J76: =VLOOKUP(B76,clasif_filas!$A$1:$J$39,9,FALSE()) -> 3 | K76: =VLOOKUP(B76,clasif_filas!$A$1:$J$39,10,FALSE()) -> No bioeconomía
A77: Máquinas, aparelhos e materiais elétricos | B77: 41-49 | C77: =VLOOKUP(B77,clasif_filas!$A$1:$J$39,2,FALSE()) -> Metales, Maquianria, equipos y transporte | D77: =VLOOKUP(B77,clasif_filas!$A$1:$J$39,3,FALSE()) -> 41-49 | E77: =VLOOKUP(B77,clasif_filas!$A$1:$J$39,4,FALSE()) -> Metales, Maquianria, equipos y transporte | F77: =VLOOKUP(B77,clasif_filas!$A$1:$J$39,5,FALSE()) -> 99 | G77: =VLOOKUP(B77,clasif_filas!$A$1:$J$39,6,FALSE()) -> No Bioeconomía | H77: =VLOOKUP(B77,clasif_filas!$A$1:$J$39,7,FALSE()) -> 4 | I77: =VLOOKUP(B77,clasif_filas!$A$1:$J$39,8,FALSE()) -> Productos metálicos, maquinaria y equipo | J77: =VLOOKUP(B77,clasif_filas!$A$1:$J$39,9,FALSE()) -> 3 | K77: =VLOOKUP(B77,clasif_filas!$A$1:$J$39,10,FALSE()) -> No bioeconomía
A78: Eletrodomésticos | B78: 41-49 | C78: =VLOOKUP(B78,clasif_filas!$A$1:$J$39,2,FALSE()) -> Metales, Maquianria, equipos y transporte | D78: =VLOOKUP(B78,clasif_filas!$A$1:$J$39,3,FALSE()) -> 41-49 | E78: =VLOOKUP(B78,clasif_filas!$A$1:$J$39,4,FALSE()) -> Metales, Maquianria, equipos y transporte | F78: =VLOOKUP(B78,clasif_filas!$A$1:$J$39,5,FALSE()) -> 99 | G78: =VLOOKUP(B78,clasif_filas!$A$1:$J$39,6,FALSE()) -> No Bioeconomía | H78: =VLOOKUP(B78,clasif_filas!$A$1:$J$39,7,FALSE()) -> 4 | I78: =VLOOKUP(B78,clasif_filas!$A$1:$J$39,8,FALSE()) -> Productos metálicos, maquinaria y equipo | J78: =VLOOKUP(B78,clasif_filas!$A$1:$J$39,9,FALSE()) -> 3 | K78: =VLOOKUP(B78,clasif_filas!$A$1:$J$39,10,FALSE()) -> No bioeconomía
A79: Tratores e outras máquinas agrícolas | B79: 41-49 | C79: =VLOOKUP(B79,clasif_filas!$A$1:$J$39,2,FALSE()) -> Metales, Maquianria, equipos y transporte | D79: =VLOOKUP(B79,clasif_filas!$A$1:$J$39,3,FALSE()) -> 41-49 | E79: =VLOOKUP(B79,clasif_filas!$A$1:$J$39,4,FALSE()) -> Metales, Maquianria, equipos y transporte | F79: =VLOOKUP(B79,clasif_filas!$A$1:$J$39,5,FALSE()) -> 99 | G79: =VLOOKUP(B79,clasif_filas!$A$1:$J$39,6,FALSE()) -> No Bioeconomía | H79: =VLOOKUP(B79,clasif_filas!$A$1:$J$39,7,FALSE()) -> 4 | I79: =VLOOKUP(B79,clasif_filas!$A$1:$J$39,8,FALSE()) -> Productos metálicos, maquinaria y equipo | J79: =VLOOKUP(B79,clasif_filas!$A$1:$J$39,9,FALSE()) -> 3 | K79: =VLOOKUP(B79,clasif_filas!$A$1:$J$39,10,FALSE()) -> No bioeconomía
A80: Máquinas para a extração mineral e a construção | B80: 41-49 | C80: =VLOOKUP(B80,clasif_filas!$A$1:$J$39,2,FALSE()) -> Metales, Maquianria, equipos y transporte | D80: =VLOOKUP(B80,clasif_filas!$A$1:$J$39,3,FALSE()) -> 41-49 | E80: =VLOOKUP(B80,clasif_filas!$A$1:$J$39,4,FALSE()) -> Metales, Maquianria, equipos y transporte | F80: =VLOOKUP(B80,clasif_filas!$A$1:$J$39,5,FALSE()) -> 99 | G80: =VLOOKUP(B80,clasif_filas!$A$1:$J$39,6,FALSE()) -> No Bioeconomía | H80: =VLOOKUP(B80,clasif_filas!$A$1:$J$39,7,FALSE()) -> 4 | I80: =VLOOKUP(B80,clasif_filas!$A$1:$J$39,8,FALSE()) -> Productos metálicos, maquinaria y equipo | J80: =VLOOKUP(B80,clasif_filas!$A$1:$J$39,9,FALSE()) -> 3 | K80: =VLOOKUP(B80,clasif_filas!$A$1:$J$39,10,FALSE()) -> No bioeconomía
A81: Outras máquinas e equipamentos mecânicos | B81: 41-49 | C81: =VLOOKUP(B81,clasif_filas!$A$1:$J$39,2,FALSE()) -> Metales, Maquianria, equipos y transporte | D81: =VLOOKUP(B81,clasif_filas!$A$1:$J$39,3,FALSE()) -> 41-49 | E81: =VLOOKUP(B81,clasif_filas!$A$1:$J$39,4,FALSE()) -> Metales, Maquianria, equipos y transporte | F81: =VLOOKUP(B81,clasif_filas!$A$1:$J$39,5,FALSE()) -> 99 | G81: =VLOOKUP(B81,clasif_filas!$A$1:$J$39,6,FALSE()) -> No Bioeconomía | H81: =VLOOKUP(B81,clasif_filas!$A$1:$J$39,7,FALSE()) -> 4 | I81: =VLOOKUP(B81,clasif_filas!$A$1:$J$39,8,FALSE()) -> Productos metálicos, maquinaria y equipo | J81: =VLOOKUP(B81,clasif_filas!$A$1:$J$39,9,FALSE()) -> 3 | K81: =VLOOKUP(B81,clasif_filas!$A$1:$J$39,10,FALSE()) -> No bioeconomía
... A88: Manutenção, reparação e instalação de máquinas e equipamentos | B88: 41-49 | C88: =VLOOKUP(B88,clasif_filas!$A$1:$J$39,2,FALSE()) -> Metales, Maquianria, equipos y transporte | D88: =VLOOKUP(B88,clasif_filas!$A$1:$J$39,3,FALSE()) -> 41-49 | E88: =VLOOKUP(B88,clasif_filas!$A$1:$J$39,4,FALSE()) -> Metales, Maquianria, equipos y transporte | F88: =VLOOKUP(B88,clasif_filas!$A$1:$J$39,5,FALSE()) -> 99 | G88: =VLOOKUP(B88,clasif_filas!$A$1:$J$39,6,FALSE()) -> No Bioeconomía | H88: =VLOOKUP(B88,clasif_filas!$A$1:$J$39,7,FALSE()) -> 4 | I88: =VLOOKUP(B88,clasif_filas!$A$1:$J$39,8,FALSE()) -> Productos metálicos, maquinaria y equipo | J88: =VLOOKUP(B88,clasif_filas!$A$1:$J$39,9,FALSE()) -> 3 | K88: =VLOOKUP(B88,clasif_filas!$A$1:$J$39,10,FALSE()) -> No bioeconomía
A89: Eletricidade, gás e outras utilidades | B89: 17.5 | C89: =VLOOKUP(B89,clasif_filas!$A$1:$J$39,2,FALSE()) -> Electricidad y agua | D89: =VLOOKUP(B89,clasif_filas!$A$1:$J$39,3,FALSE()) -> 17.5 | E89: =VLOOKUP(B89,clasif_filas!$A$1:$J$39,4,FALSE()) -> Electricidad y agua | F89: =VLOOKUP(B89,clasif_filas!$A$1:$J$39,5,FALSE()) -> 6 | G89: =VLOOKUP(B89,clasif_filas!$A$1:$J$39,6,FALSE()) -> Conocimiento, procesos y servicios relacionados | H89: =VLOOKUP(B89,clasif_filas!$A$1:$J$39,7,FALSE()) -> 1 | I89: =VLOOKUP(B89,clasif_filas!$A$1:$J$39,8,FALSE()) -> Minerales; electricidad, gas y agua | J89: =VLOOKUP(B89,clasif_filas!$A$1:$J$39,9,FALSE()) -> 2 | K89: =VLOOKUP(B89,clasif_filas!$A$1:$J$39,10,FALSE()) -> Bioeconomía extendida
A90: Água, esgoto, reciclagem e gestão de resíduos | B90: 94 | C90: =VLOOKUP(B90,clasif_filas!$A$1:$J$39,2,FALSE()) -> Servicios de alcantarillado, recolección, tratamiento y disposición de desechos y otros servicios de saneamiento ambiental | D90: =VLOOKUP(B90,clasif_filas!$A$1:$J$39,3,FALSE()) -> 94 | E90: =VLOOKUP(B90,clasif_filas!$A$1:$J$39,4,FALSE()) -> Servicios de alcantarillado, recolección, tratamiento y disposición de desechos y otros servicios de saneamiento ambiental | F90: =VLOOKUP(B90,clasif_filas!$A$1:$J$39,5,FALSE()) -> 4 | G90: =VLOOKUP(B90,clasif_filas!$A$1:$J$39,6,FALSE()) -> Biomasa residual en los sectores agropecuario, pesca y acuacultura, forestal y agroindustrial | H90: =VLOOKUP(B90,clasif_filas!$A$1:$J$39,7,FALSE()) -> 9 | I90: =VLOOKUP(B90,clasif_filas!$A$1:$J$39,8,FALSE()) -> Servicios para la comunidad, sociales y personales | J90: =VLOOKUP(B90,clasif_filas!$A$1:$J$39,9,FALSE()) -> 2 | K90: =VLOOKUP(B90,clasif_filas!$A$1:$J$39,10,FALSE()) -> Bioeconomía extendida
A91: Edificações | B91: 5 | C91: =VLOOKUP(B91,clasif_filas!$A$1:$J$39,2,FALSE()) -> Construcciones y servicios de construcción | D91: =VLOOKUP(B91,clasif_filas!$A$1:$J$39,3,FALSE()) -> 5 | E91: =VLOOKUP(B91,clasif_filas!$A$1:$J$39,4,FALSE()) -> Construcciones y servicios de construcción | F91: =VLOOKUP(B91,clasif_filas!$A$1:$J$39,5,FALSE()) -> 99 | G91: =VLOOKUP(B91,clasif_filas!$A$1:$J$39,6,FALSE()) -> No Bioeconomía | H91: =VLOOKUP(B91,clasif_filas!$A$1:$J$39,7,FALSE()) -> 5 | I91: =VLOOKUP(B91,clasif_filas!$A$1:$J$39,8,FALSE()) -> Construcciones y servicios de construcción | J91: =VLOOKUP(B91,clasif_filas!$A$1:$J$39,9,FALSE()) -> 3 | K91: =VLOOKUP(B91,clasif_filas!$A$1:$J$39,10,FALSE()) -> No bioeconomía
A92: Obras de infra-estrutura | B92: 5 | C92: =VLOOKUP(B92,clasif_filas!$A$1:$J$39,2,FALSE()) -> Construcciones y servicios de construcción | D92: =VLOOKUP(B92,clasif_filas!$A$1:$J$39,3,FALSE()) -> 5 | E92: =VLOOKUP(B92,clasif_filas!$A$1:$J$39,4,FALSE()) -> Construcciones y servicios de construcción | F92: =VLOOKUP(B92,clasif_filas!$A$1:$J$39,5,FALSE()) -> 99 | G92: =VLOOKUP(B92,clasif_filas!$A$1:$J$39,6,FALSE()) -> No Bioeconomía | H92: =VLOOKUP(B92,clasif_filas!$A$1:$J$39,7,FALSE()) -> 5 | I92: =VLOOKUP(B92,clasif_filas!$A$1:$J$39,8,FALSE()) -> Construcciones y servicios de construcción | J92: =VLOOKUP(B92,clasif_filas!$A$1:$J$39,9,FALSE()) -> 3 | K92: =VLOOKUP(B92,clasif_filas!$A$1:$J$39,10,FALSE()) -> No bioeconomía
A93: Serviços especializados para construção | B93: 5 | C93: =VLOOKUP(B93,clasif_filas!$A$1:$J$39,2,FALSE()) -> Construcciones y servicios de construcción | D93: =VLOOKUP(B93,clasif_filas!$A$1:$J$39,3,FALSE()) -> 5 | E93: =VLOOKUP(B93,clasif_filas!$A$1:$J$39,4,FALSE()) -> Construcciones y servicios de construcción | F93: =VLOOKUP(B93,clasif_filas!$A$1:$J$39,5,FALSE()) -> 99 | G93: =VLOOKUP(B93,clasif_filas!$A$1:$J$39,6,FALSE()) -> No Bioeconomía | H93: =VLOOKUP(B93,clasif_filas!$A$1:$J$39,7,FALSE()) -> 5 | I93: =VLOOKUP(B93,clasif_filas!$A$1:$J$39,8,FALSE()) -> Construcciones y servicios de construcción | J93: =VLOOKUP(B93,clasif_filas!$A$1:$J$39,9,FALSE()) -> 3 | K93: =VLOOKUP(B93,clasif_filas!$A$1:$J$39,10,FALSE()) -> No bioeconomía
A94: Comércio e reparação de veículos | B94: 6 | C94: =VLOOKUP(B94,clasif_filas!$A$1:$J$39,2,FALSE()) -> Otros servicios | D94: =VLOOKUP(B94,clasif_filas!$A$1:$J$39,3,FALSE()) -> 6 | E94: =VLOOKUP(B94,clasif_filas!$A$1:$J$39,4,FALSE()) -> Otros servicios | F94: =VLOOKUP(B94,clasif_filas!$A$1:$J$39,5,FALSE()) -> 99 | G94: =VLOOKUP(B94,clasif_filas!$A$1:$J$39,6,FALSE()) -> No Bioeconomía | H94: =VLOOKUP(B94,clasif_filas!$A$1:$J$39,7,FALSE()) -> 6 | I94: =VLOOKUP(B94,clasif_filas!$A$1:$J$39,8,FALSE()) -> Servicios comerciales de distribución; alojamiento, servicios de suministro de comidas y bebidas; servicios de transporte; y servicios de distribución de electricidad, gas y agua | J94: =VLOOKUP(B94,clasif_filas!$A$1:$J$39,9,FALSE()) -> 3 | K94: =VLOOKUP(B94,clasif_filas!$A$1:$J$39,10,FALSE()) -> No bioeconomía
A95: Comércio por atacado e a varejo, exceto veículos automotores | B95: 6 | C95: =VLOOKUP(B95,clasif_filas!$A$1:$J$39,2,FALSE()) -> Otros servicios | D95: =VLOOKUP(B95,clasif_filas!$A$1:$J$39,3,FALSE()) -> 6 | E95: =VLOOKUP(B95,clasif_filas!$A$1:$J$39,4,FALSE()) -> Otros servicios | F95: =VLOOKUP(B95,clasif_filas!$A$1:$J$39,5,FALSE()) -> 99 | G95: =VLOOKUP(B95,clasif_filas!$A$1:$J$39,6,FALSE()) -> No Bioeconomía | H95: =VLOOKUP(B95,clasif_filas!$A$1:$J$39,7,FALSE()) -> 6 | I95: =VLOOKUP(B95,clasif_filas!$A$1:$J$39,8,FALSE()) -> Servicios comerciales de distribución; alojamiento, servicios de suministro de comidas y bebidas; servicios de transporte; y servicios de distribución de electricidad, gas y agua | J95: =VLOOKUP(B95,clasif_filas!$A$1:$J$39,9,FALSE()) -> 3 | K95: =VLOOKUP(B95,clasif_filas!$A$1:$J$39,10,FALSE()) -> No bioeconomía
A96: Transporte terrestre de carga | B96: 6 | C96: =VLOOKUP(B96,clasif_filas!$A$1:$J$39,2,FALSE()) -> Otros servicios | D96: =VLOOKUP(B96,clasif_filas!$A$1:$J$39,3,FALSE()) -> 6 | E96: =VLOOKUP(B96,clasif_filas!$A$1:$J$39,4,FALSE()) -> Otros servicios | F96: =VLOOKUP(B96,clasif_filas!$A$1:$J$39,5,FALSE()) -> 99 | G96: =VLOOKUP(B96,clasif_filas!$A$1:$J$39,6,FALSE()) -> No Bioeconomía | H96: =VLOOKUP(B96,clasif_filas!$A$1:$J$39,7,FALSE()) -> 6 | I96: =VLOOKUP(B96,clasif_filas!$A$1:$J$39,8,FALSE()) -> Servicios comerciales de distribución; alojamiento, servicios de suministro de comidas y bebidas; servicios de transporte; y servicios de distribución de electricidad, gas y agua | J96: =VLOOKUP(B96,clasif_filas!$A$1:$J$39,9,FALSE()) -> 3 | K96: =VLOOKUP(B96,clasif_filas!$A$1:$J$39,10,FALSE()) -> No bioeconomía
A97: Transporte terrestre de passageiros | B97: 6 | C97: =VLOOKUP(B97,clasif_filas!$A$1:$J$39,2,FALSE()) -> Otros servicios | D97: =VLOOKUP(B97,clasif_filas!$A$1:$J$39,3,FALSE()) -> 6 | E97: =VLOOKUP(B97,clasif_filas!$A$1:$J$39,4,FALSE()) -> Otros servicios | F97: =VLOOKUP(B97,clasif_filas!$A$1:$J$39,5,FALSE()) -> 99 | G97: =VLOOKUP(B97,clasif_filas!$A$1:$J$39,6,FALSE()) -> No Bioeconomía | H97: =VLOOKUP(B97,clasif_filas!$A$1:$J$39,7,FALSE()) -> 6 | I97: =VLOOKUP(B97,clasif_filas!$A$1:$J$39,8,FALSE()) -> Servicios comerciales de distribución; alojamiento, servicios de suministro de comidas y bebidas; servicios de transporte; y servicios de distribución de electricidad, gas y agua | J97: =VLOOKUP(B97,clasif_filas!$A$1:$J$39,9,FALSE()) -> 3 | K97: =VLOOKUP(B97,clasif_filas!$A$1:$J$39,10,FALSE()) -> No bioeconomía
A98: Transporte aquaviário | B98: 6 | C98: =VLOOKUP(B98,clasif_filas!$A$1:$J$39,2,FALSE()) -> Otros servicios | D98: =VLOOKUP(B98,clasif_filas!$A$1:$J$39,3,FALSE()) -> 6 | E98: =VLOOKUP(B98,clasif_filas!$A$1:$J$39,4,FALSE()) -> Otros servicios | F98: =VLOOKUP(B98,clasif_filas!$A$1:$J$39,5,FALSE()) -> 99 | G98: =VLOOKUP(B98,clasif_filas!$A$1:$J$39,6,FALSE()) -> No Bioeconomía | H98: =VLOOKUP(B98,clasif_filas!$A$1:$J$39,7,FALSE()) -> 6 | I98: =VLOOKUP(B98,clasif_filas!$A$1:$J$39,8,FALSE()) -> Servicios comerciales de distribución; alojamiento, servicios de suministro de comidas y bebidas; servicios de transporte; y servicios de distribución de electricidad, gas y agua | J98: =VLOOKUP(B98,clasif_filas!$A$1:$J$39,9,FALSE()) -> 3 | K98: =VLOOKUP(B98,clasif_filas!$A$1:$J$39,10,FALSE()) -> No bioeconomía
A99: Transporte aéreo | B99: 6 | C99: =VLOOKUP(B99,clasif_filas!$A$1:$J$39,2,FALSE()) -> Otros servicios | D99: =VLOOKUP(B99,clasif_filas!$A$1:$J$39,3,FALSE()) -> 6 | E99: =VLOOKUP(B99,clasif_filas!$A$1:$J$39,4,FALSE()) -> Otros servicios | F99: =VLOOKUP(B99,clasif_filas!$A$1:$J$39,5,FALSE()) -> 99 | G99: =VLOOKUP(B99,clasif_filas!$A$1:$J$39,6,FALSE()) -> No Bioeconomía | H99: =VLOOKUP(B99,clasif_filas!$A$1:$J$39,7,FALSE()) -> 6 | I99: =VLOOKUP(B99,clasif_filas!$A$1:$J$39,8,FALSE()) -> Servicios comerciales de distribución; alojamiento, servicios de suministro de comidas y bebidas; servicios de transporte; y servicios de distribución de electricidad, gas y agua | J99: =VLOOKUP(B99,clasif_filas!$A$1:$J$39,9,FALSE()) -> 3 | K99: =VLOOKUP(B99,clasif_filas!$A$1:$J$39,10,FALSE()) -> No bioeconomía
A100: Armazenamento e serviços auxiliares aos transportes | B100: 6 | C100: =VLOOKUP(B100,clasif_filas!$A$1:$J$39,2,FALSE()) -> Otros servicios | D100: =VLOOKUP(B100,clasif_filas!$A$1:$J$39,3,FALSE()) -> 6 | E100: =VLOOKUP(B100,clasif_filas!$A$1:$J$39,4,FALSE()) -> Otros servicios | F100: =VLOOKUP(B100,clasif_filas!$A$1:$J$39,5,FALSE()) -> 99 | G100: =VLOOKUP(B100,clasif_filas!$A$1:$J$39,6,FALSE()) -> No Bioeconomía | H100: =VLOOKUP(B100,clasif_filas!$A$1:$J$39,7,FALSE()) -> 6 | I100: =VLOOKUP(B100,clasif_filas!$A$1:$J$39,8,FALSE()) -> Servicios comerciales de distribución; alojamiento, servicios de suministro de comidas y bebidas; servicios de transporte; y servicios de distribución de electricidad, gas y agua | J100: =VLOOKUP(B100,clasif_filas!$A$1:$J$39,9,FALSE()) -> 3 | K100: =VLOOKUP(B100,clasif_filas!$A$1:$J$39,10,FALSE()) -> No bioeconomía
... A129: Serviços domésticos | B129: 6 | C129: =VLOOKUP(B129,clasif_filas!$A$1:$J$39,2,FALSE()) -> Otros servicios | D129: =VLOOKUP(B129,clasif_filas!$A$1:$J$39,3,FALSE()) -> 6 | E129: =VLOOKUP(B129,clasif_filas!$A$1:$J$39,4,FALSE()) -> Otros servicios | F129: =VLOOKUP(B129,clasif_filas!$A$1:$J$39,5,FALSE()) -> 99 | G129: =VLOOKUP(B129,clasif_filas!$A$1:$J$39,6,FALSE()) -> No Bioeconomía | H129: =VLOOKUP(B129,clasif_filas!$A$1:$J$39,7,FALSE()) -> 6 | I129: =VLOOKUP(B129,clasif_filas!$A$1:$J$39,8,FALSE()) -> Servicios comerciales de distribución; alojamiento, servicios de suministro de comidas y bebidas; servicios de transporte; y servicios de distribución de electricidad, gas y agua | J129: =VLOOKUP(B129,clasif_filas!$A$1:$J$39,9,FALSE()) -> 3 | K129: =VLOOKUP(B129,clasif_filas!$A$1:$J$39,10,FALSE()) -> No bioeconomía

Sheet clasif_filas
A1: Cód_Div_CPC_3 | B1: División CPC_3 | C1: Cód_Div_CPC_2 | D1: División CPC_2 | E1: Cod. Elem. Def. Bioeconomía | F1: Tipo de elemento | G1: Código CPC | H1: Elemento CPC | I1: Código Bioeconomía | J1: Clasificación Bioeconomí
A2: 1 | B2: Productos de la agricultura, la horticultura y la jardinería comercial | C2: 1 | D2: Productos de la agricultura, la horticultura y la jardinería comercial | E2: 1 | F2: Biomasa que se cultiva para producir alimentos, forrajes, fibras y energía | G2: 0 | H2: Productos de la agricultura, la silvicultura yla pesca | I2: 1 | J2: Bioeconomía
A3: 2 | B3: Animales vivos y productos animales (excepto la carne) | C3: 2 | D3: Animales vivos y productos animales (excepto la carne) | E3: 1 | F3: Biomasa que se cultiva para producir alimentos, forrajes, fibras y energía | G3: 0 | H3: Productos de la agricultura, la silvicultura yla pesca | I3: 1 | J3: Bioeconomía
A4: 3 | B4: Productos forestales y de la tala | C4: 3 | D4: Productos forestales y de la tala | E4: 3 | F4: Biomasa forestal, sobre todo la que se cultiva para su aprovechamiento en las industrias forestal y del papel, y aquella extraída legalmente de ecosistemas naturales | G4: 0 | H4: Productos de la agricultura, la silvicultura yla pesca | I4: 1 | J4: Bioeconomía
A5: 4 | B5: Pescado y otros productos de la pesca | C5: 4 | D5: Pescado y otros productos de la pesca | E5: 2 | F5: Biomasa de los recursos marinos y la producida mediante la acuicultura | G5: 0 | H5: Productos de la agricultura, la silvicultura yla pesca | I5: 1 | J5: Bioeconomía
A6: 11 | B6: Minerales, combustibles y derivados | C6: 11 | D6: Minerales, combustibles y derivados | E6: 99 | F6: No Bioeconomía | G6: 1 | H6: Minerales; electricidad, gas y agua | I6: 3 | J6: No bioeconomía
A7: 17.5 | B7: Electricidad y agua | C7: 17.5 | D7: Electricidad y agua | E7: 6 | F7: Conocimiento, procesos y servicios relacionados | G7: 1 | H7: Minerales; electricidad, gas y agua | I7: 2 | J7: Bioeconomía extendida
A8: 18 | B8: Agua natural | C8: 18 | D8: Agua natural | E8: 6 | F8: Conocimiento, procesos y servicios relacionados | G8: 1 | H8: Minerales; electricidad, gas y agua | I8: 2 | J8: Bioeconomía extendida
A9: 21 | B9: Carne, pescado, frutas, vegetales, aceites y grasas | C9: 21 | D9: Carne, pescado, frutas, vegetales, aceites y grasas | E9: 6 | F9: Conocimiento, procesos y servicios relacionados | G9: 2 | H9: Productos alimenticios, bebidas y tabaco; textiles, prendas de vestir y productos de cuero | I9: 1 | J9: Bioeconomía
A10: 22 | B10: Productos lácteos y productos de huevo | C10: 22 | D10: Productos lácteos y productos de huevo | E10: 6 | F10: Conocimiento, procesos y servicios relacionados | G10: 2 | H10: Productos alimenticios, bebidas y tabaco; textiles, prendas de vestir y productos de cuero | I10: 1 | J10: Bioeconomía
A11: 23 | B11: Productos de molienda, productos con almidón o maicena; otros productos de alimenticios | C11: 23 | D11: Productos de molienda, productos con almidón o maicena; otros productos de alimenticios | E11: 6 | F11: Conocimiento, procesos y servicios relacionados | G11: 2 | H11: Productos alimenticios, bebidas y tabaco; textiles, prendas de vestir y productos de cuero | I11: 1 | J11: Bioeconomía
A12: 24 | B12: Bebidas | C12: 24 | D12: Bebidas | E12: 6 | F12: Conocimiento, procesos y servicios relacionados | G12: 2 | H12: Productos alimenticios, bebidas y tabaco; textiles, prendas de vestir y productos de cuero | I12: 1 | J12: Bioeconomía
A13: 25 | B13: Productos del tabaco | C13: 25 | D13: Productos del tabaco | E13: 6 | F13: Conocimiento, procesos y servicios relacionados | G13: 2 | H13: Productos alimenticios, bebidas y tabaco; textiles, prendas de vestir y productos de cuero | I13: 1 | J13: Bioeconomía
... A30: 39 | B30: Desperdicios o desechos | C30: 39 | D30: Desperdicios o desechos | E30: 4 | F30: Biomasa residual en los sectores agropecuario, pesca y acuacultura, forestal y agroindustrial | G30: 3 | H30: Otros bienes transportables, excepto productos metálicos, maquinaria y equipo | I30: 2 | J30: Bioeconomía extendida
A31: 41-49 | B31: Metales, Maquianria, equipos y transporte | C31: 41-49 | D31: Metales, Maquianria, equipos y transporte | E31: 99 | F31: No Bioeconomía | G31: 4 | H31: Productos metálicos, maquinaria y equipo | I31: 3 | J31: No bioeconomía
A32: 5 | B32: Construcciones y servicios de construcción | C32: 5 | D32: Construcciones y servicios de construcción | E32: 99 | F32: No Bioeconomía | G32: 5 | H32: Construcciones y servicios de construcción | I32: 3 | J32: No bioeconomía
A33: 6 | B33: Otros servicios | C33: 6 | D33: Otros servicios | E33: 99 | F33: No Bioeconomía | G33: 6 | H33: Servicios comerciales de distribución; alojamiento, servicios de suministro de comidas y bebidas; servicios de transporte; y servicios de distribución de electricidad, gas y agua | I33: 3 | J33: No bioeconomía
A34: 63 | B34: Alojamiento, servicios de suministro de comidas y bebidas | C34: 63 | D34: Alojamiento, servicios de suministro de comidas y bebidas | E34: 6 | F34: Conocimiento, procesos y servicios relacionados | G34: 6 | H34: Servicios comerciales de distribución; alojamiento, servicios de suministro de comidas y bebidas; servicios de transporte; y servicios de distribución de electricidad, gas y agua | I34: 2 | J34: Bioeconomía extendida
A35: 69 | B35: Distribución de electricidad, gas y agua (por cuenta propia) | C35: 69 | D35: Distribución de electricidad, gas y agua (por cuenta propia) | E35: 6 | F35: Conocimiento, procesos y servicios relacionados | G35: 6 | H35: Servicios comerciales de distribución; alojamiento, servicios de suministro de comidas y bebidas; servicios de transporte; y servicios de distribución de electricidad, gas y agua | I35: 2 | J35: Bioeconomía extendida
A36: 81 | B36: Servicios de investigación y desarrollo | C36: 81 | D36: Servicios de investigación y desarrollo | E36: 6 | F36: Conocimiento, procesos y servicios relacionados | G36: 8 | H36: Servicios prestados a las empresas y servicios de producción | I36: 2 | J36: Bioeconomía extendida
A37: 83 | B37: Otros servicios profesionales, científicos y técnicos | C37: 83 | D37: Otros servicios profesionales, científicos y técnicos | E37: 6 | F37: Conocimiento, procesos y servicios relacionados | G37: 8 | H37: Servicios prestados a las empresas y servicios de producción | I37: 2 | J37: Bioeconomía extendida
A38: 86 | B38: Servicios de apoyo a la agricultura,la caza, la silvicutura, la pesca, la minería y los servicios públicos | C38: 86 | D38: Servicios de apoyo a la agricultura,la caza, la silvicutura, la pesca, la minería y los servicios públicos | E38: 6 | F38: Conocimiento, procesos y servicios relacionados | G38: 8 | H38: Servicios prestados a las empresas y servicios de producción | I38: 2 | J38: Bioeconomía extendida
A39: 94 | B39: Servicios de alcantarillado, recolección, tratamiento y disposición de desechos y otros servicios de saneamiento ambiental | C39: 94 | D39: Servicios de alcantarillado, recolección, tratamiento y disposición de desechos y otros servicios de saneamiento ambiental | E39: 4 | F39: Biomasa residual en los sectores agropecuario, pesca y acuacultura, forestal y agroindustrial | G39: 9 | H39: Servicios para la comunidad, sociales y personales | I39: 2 | J39: Bioeconomía extendida

Sheet AT_FILAS
A1: Áreas Transaccionales Filas No. | B1: Áreas Transaccionales Filas Descripción | C1: Codigo Transacción Filas
A2: ATF01 | B2: Producción | C2: P1
A3: ATF02 | B3: Consumo intermedio | C3: P2
A4: ATF03 | B4: Ajuste CIF/FOB | C4: CIF
A5: ATF04 | B5: Compras directas en el exterior por residentes | C5: P6
A6: ATF05 | B6: Compras directas en el territorio nacional por no residentes | C6: P7
A7: ATF06 | B7: Valor Agregado | C7: -
A8: ATF07 | B8: Puestos de trabajo | C8: -
